Workbook

Sheet тахлил
A1: table_name | B1: table_schema | C1: =B1&"."&A1 -> table_schema.table_name | D1: Аниқлик киритиш керак | E1: изох | F1: +- | H1: Мавжуд | N1: қидирув 1 | O1: қидирув 2 | P1: Итог
A2: credits | B2: education | C2: =B2&"."&A2 -> education.credits | D2: =IFERROR(VLOOKUP(A2,#REF!,1,0),VLOOKUP(C2,#REF!,1,0)) -> #REF! | E2: delete | F2: - | H2: financial_transactions | N2: =IFERROR(VLOOKUP(H2,A:A,1,0),"") -> financial_transactions | O2: =IFERROR(VLOOKUP(H2,C:C,1,0),"") | P2: =N2&O2 -> financial_transactions
A3: dtm_recommends | B3: education | C3: =B3&"."&A3 -> education.dtm_recommends | D3: =IFERROR(VLOOKUP(A3,#REF!,1,0),VLOOKUP(C3,#REF!,1,0)) -> #REF! | E3: delete | F3: - | H3: dembat_faktura | N3: =IFERROR(VLOOKUP(H3,A:A,1,0),"") -> dembat_faktura | O3: =IFERROR(VLOOKUP(H3,C:C,1,0),"") | P3: =N3&O3 -> dembat_faktura
A4: dtm_transfers | B4: education | C4: =B4&"."&A4 -> education.dtm_transfers | D4: =IFERROR(VLOOKUP(A4,#REF!,1,0),VLOOKUP(C4,#REF!,1,0)) -> #REF! | E4: delete | F4: - | N4: =IFERROR(VLOOKUP(H4,A:A,1,0),"") | O4: =IFERROR(VLOOKUP(H4,C:C,1,0),"") | P4: =N4&O4
A5: hemis_graduates | B5: education | C5: =B5&"."&A5 -> education.hemis_graduates | D5: =IFERROR(VLOOKUP(A5,#REF!,1,0),VLOOKUP(C5,#REF!,1,0)) -> #REF! | E5: delete | F5: - | N5: =IFERROR(VLOOKUP(H5,A:A,1,0),"") | O5: =IFERROR(VLOOKUP(H5,C:C,1,0),"") | P5: =N5&O5
A6: hemis_students | B6: education | C6: =B6&"."&A6 -> education.hemis_students | D6: =IFERROR(VLOOKUP(A6,#REF!,1,0),VLOOKUP(C6,#REF!,1,0)) -> #REF! | E6: delete | F6: - | H6: report_months | N6: =IFERROR(VLOOKUP(H6,A:A,1,0),"") -> report_months | O6: =IFERROR(VLOOKUP(H6,C:C,1,0),"") | P6: =N6&O6 -> report_months
A7: borders | B7: employement | C7: =B7&"."&A7 -> employement.borders | D7: =IFERROR(VLOOKUP(A7,#REF!,1,0),VLOOKUP(C7,#REF!,1,0)) -> #REF! | E7: pagran | F7: - | H7: position_vault | I7: positions_vault | N7: =IFERROR(VLOOKUP(H7,A:A,1,0),"") -> position_vault | O7: =IFERROR(VLOOKUP(H7,C:C,1,0),"") | P7: =N7&O7 -> position_vault
A8: inps | B8: employement | C8: =B8&"."&A8 -> employement.inps | D8: =IFERROR(VLOOKUP(A8,#REF!,1,0),VLOOKUP(C8,#REF!,1,0)) -> #REF! | E8: delete | F8: - | H8: vedemost | N8: =IFERROR(VLOOKUP(H8,A:A,1,0),"") -> vedemost | O8: =IFERROR(VLOOKUP(H8,C:C,1,0),"") | P8: =N8&O8 -> vedemost
A9: mymehnat | B9: employement | C9: =B9&"."&A9 -> employement.mymehnat | D9: =IFERROR(VLOOKUP(A9,#REF!,1,0),VLOOKUP(C9,#REF!,1,0)) -> #REF! | E9: delete | F9: - | N9: =IFERROR(VLOOKUP(H9,A:A,1,0),"") | O9: =IFERROR(VLOOKUP(H9,C:C,1,0),"") | P9: =N9&O9
A10: mymehnat_history | B10: employement | C10: =B10&"."&A10 -> employement.mymehnat_history | D10: =IFERROR(VLOOKUP(A10,#REF!,1,0),VLOOKUP(C10,#REF!,1,0)) -> #REF! | E10: delete | F10: - | H10: student_info | N10: =IFERROR(VLOOKUP(H10,A:A,1,0),"") -> student_info | O10: =IFERROR(VLOOKUP(H10,C:C,1,0),"") | P10: =N10&O10 -> student_info
A11: deaths | B11: minyust | C11: =B11&"."&A11 -> minyust.deaths | D11: =IFERROR(VLOOKUP(A11,#REF!,1,0),VLOOKUP(C11,#REF!,1,0)) -> #REF! | E11: ulganlar | F11: - | N11: =IFERROR(VLOOKUP(H11,A:A,1,0),"") | O11: =IFERROR(VLOOKUP(H11,C:C,1,0),"") | P11: =N11&O11
A12: authorized_funds | B12: minyust | C12: =B12&"."&A12 -> minyust.authorized_funds | D12: =IFERROR(VLOOKUP(A12,#REF!,1,0),VLOOKUP(C12,#REF!,1,0)) -> #REF! | E12: tasisci_history | F12: - | N12: =IFERROR(VLOOKUP(H12,A:A,1,0),"") | O12: =IFERROR(VLOOKUP(H12,C:C,1,0),"") | P12: =N12&O12
A13: birth_extra | B13: minyust | C13: =B13&"."&A13 -> minyust.birth_extra | D13: =IFERROR(VLOOKUP(A13,#REF!,1,0),VLOOKUP(C13,#REF!,1,0)) -> #REF! | E13: delete | F13: - | H13: education.teacher | N13: =IFERROR(VLOOKUP(H13,A:A,1,0),"") | O13: =IFERROR(VLOOKUP(H13,C:C,1,0),"") -> education.teacher | P13: =N13&O13 -> education.teacher
A14: birth_fulled | B14: minyust | C14: =B14&"."&A14 -> minyust.birth_fulled | D14: =IFERROR(VLOOKUP(A14,#REF!,1,0),VLOOKUP(C14,#REF!,1,0)) -> #REF! | E14: tugulish | F14: - | N14: =IFERROR(VLOOKUP(H14,A:A,1,0),"") | O14: =IFERROR(VLOOKUP(H14,C:C,1,0),"") | P14: =N14&O14
A15: death_extra | B15: minyust | C15: =B15&"."&A15 -> minyust.death_extra | D15: =IFERROR(VLOOKUP(A15,#REF!,1,0),VLOOKUP(C15,#REF!,1,0)) -> #REF! | E15: delete | F15: - | N15: =IFERROR(VLOOKUP(H15,A:A,1,0),"") | O15: =IFERROR(VLOOKUP(H15,C:C,1,0),"") | P15: =N15&O15
A16: founders | B16: minyust | C16: =B16&"."&A16 -> minyust.founders | D16: =IFERROR(VLOOKUP(A16,#REF!,1,0),VLOOKUP(C16,#REF!,1,0)) -> #REF! | E16: delete | F16: - | N16: =IFERROR(VLOOKUP(H16,A:A,1,0),"") | O16: =IFERROR(VLOOKUP(H16,C:C,1,0),"") | P16: =N16&O16
A17: half_birth | B17: minyust | C17: =B17&"."&A17 -> minyust.half_birth | D17: =IFERROR(VLOOKUP(A17,#REF!,1,0),VLOOKUP(C17,#REF!,1,0)) -> #REF! | E17: tugulish_davomi | F17: - | N17: =IFERROR(VLOOKUP(H17,A:A,1,0),"") | O17: =IFERROR(VLOOKUP(H17,C:C,1,0),"") | P17: =N17&O17
A18: person | B18: minyust | C18: =B18&"."&A18 -> minyust.person | D18: =IFERROR(VLOOKUP(A18,#REF!,1,0),VLOOKUP(C18,#REF!,1,0)) -> #REF! | E18: pasport | F18: - | H18: customers_jur | I18: customers_phys | N18: =IFERROR(VLOOKUP(H18,A:A,1,0),"") -> customers_jur | O18: =IFERROR(VLOOKUP(H18,C:C,1,0),"") | P18: =N18&O18 -> customers_jur
A19: person_red_passport | B19: minyust | C19: =B19&"."&A19 -> minyust.person_red_passport | D19: =IFERROR(VLOOKUP(A19,#REF!,1,0),VLOOKUP(C19,#REF!,1,0)) -> #REF! | E19: ped_pasport | F19: - | H19: gaz_elektr.meters | N19: =IFERROR(VLOOKUP(H19,A:A,1,0),"") | O19: =IFERROR(VLOOKUP(H19,C:C,1,0),"") -> gaz_elektr.meters | P19: =N19&O19 -> gaz_elektr.meters
A20: Inappsite_appusagemonitoring | B20: public | C20: =B20&"."&A20 -> public.Inappsite_appusagemonitoring | D20: =IFERROR(VLOOKUP(A20,#REF!,1,0),VLOOKUP(C20,#REF!,1,0)) -> #REF! | E20: delete | F20: - | N20: =IFERROR(VLOOKUP(H20,A:A,1,0),"") | O20: =IFERROR(VLOOKUP(H20,C:C,1,0),"") | P20: =N20&O20
A21: conflictofinterests | B21: public | C21: =B21&"."&A21 -> public.conflictofinterests | D21: =IFERROR(VLOOKUP(A21,#REF!,1,0),VLOOKUP(C21,#REF!,1,0)) -> #REF! | E21: delete | F21: - | H21: geo_eco.yer_osti_uchastka | N21: =IFERROR(VLOOKUP(H21,A:A,1,0),"") | O21: =IFERROR(VLOOKUP(H21,C:C,1,0),"") -> geo_eco.yer_osti_uchastka | P21: =N21&O21 -> geo_eco.yer_osti_uchastka
A22: e_qaror | B22: public | C22: =B22&"."&A22 -> public.e_qaror | D22: =IFERROR(VLOOKUP(A22,#REF!,1,0),VLOOKUP(C22,#REF!,1,0)) -> #REF! | E22: delete | F22: - | H22: geo_eco.qazilma_hajmi | N22: =IFERROR(VLOOKUP(H22,A:A,1,0),"") | O22: =IFERROR(VLOOKUP(H22,C:C,1,0),"") -> geo_eco.qazilma_hajmi | P22: =N22&O22 -> geo_eco.qazilma_hajmi
A23: ehf_copy1 | B23: public | C23: =B23&"."&A23 -> public.ehf_copy1 | D23: =IFERROR(VLOOKUP(A23,#REF!,1,0),VLOOKUP(C23,#REF!,1,0)) -> #REF! | E23: delete | F23: - | H23: geo_eco.yer_osti_suv | N23: =IFERROR(VLOOKUP(H23,A:A,1,0),"") | O23: =IFERROR(VLOOKUP(H23,C:C,1,0),"") -> geo_eco.yer_osti_suv | P23: =N23&O23 -> geo_eco.yer_osti_suv
A24: ehf_copy2 | B24: public | C24: =B24&"."&A24 -> public.ehf_copy2 | D24: =IFERROR(VLOOKUP(A24,#REF!,1,0),VLOOKUP(C24,#REF!,1,0)) -> #REF! | E24: delete | F24: - | H24: geo_eco.choraklik_hajm | N24: =IFERROR(VLOOKUP(H24,A:A,1,0),"") | O24: =IFERROR(VLOOKUP(H24,C:C,1,0),"") -> geo_eco.choraklik_hajm | P24: =N24&O24 -> geo_eco.choraklik_hajm
A25: faktura_2022-2023 | B25: public | C25: =B25&"."&A25 -> public.faktura_2022-2023 | D25: =IFERROR(VLOOKUP(A25,#REF!,1,0),VLOOKUP(C25,#REF!,1,0)) -> #REF! | E25: delete | F25: - | N25: =IFERROR(VLOOKUP(H25,A:A,1,0),"") | O25: =IFERROR(VLOOKUP(H25,C:C,1,0),"") | P25: =N25&O25
A26: newtable | B26: public | C26: =B26&"."&A26 -> public.newtable | D26: =IFERROR(VLOOKUP(A26,#REF!,1,0),VLOOKUP(C26,#REF!,1,0)) -> #REF! | E26: delete | F26: - | N26: =IFERROR(VLOOKUP(H26,A:A,1,0),"") | O26: =IFERROR(VLOOKUP(H26,C:C,1,0),"") | P26: =N26&O26
A27: opendata.api.eqaror | B27: public | C27: =B27&"."&A27 -> public.opendata.api.eqaror | D27: =IFERROR(VLOOKUP(A27,#REF!,1,0),VLOOKUP(C27,#REF!,1,0)) -> #REF! | E27: delete | F27: - | N27: =IFERROR(VLOOKUP(H27,A:A,1,0),"") | O27: =IFERROR(VLOOKUP(H27,C:C,1,0),"") | P27: =N27&O27
A28: opendata.api.history | B28: public | C28: =B28&"."&A28 -> public.opendata.api.history | D28: =IFERROR(VLOOKUP(A28,#REF!,1,0),VLOOKUP(C28,#REF!,1,0)) -> #REF! | E28: delete | F28: - | N28: =IFERROR(VLOOKUP(H28,A:A,1,0),"") | O28: =IFERROR(VLOOKUP(H28,C:C,1,0),"") | P28: =N28&O28
A29: opendata.api.users | B29: public | C29: =B29&"."&A29 -> public.opendata.api.users | D29: =IFERROR(VLOOKUP(A29,#REF!,1,0),VLOOKUP(C29,#REF!,1,0)) -> #REF! | E29: delete | F29: - | N29: =IFERROR(VLOOKUP(H29,A:A,1,0),"") | O29: =IFERROR(VLOOKUP(H29,C:C,1,0),"") | P29: =N29&O29
A30: opendata.region.data | B30: public | C30: =B30&"."&A30 -> public.opendata.region.data | D30: =IFERROR(VLOOKUP(A30,#REF!,1,0),VLOOKUP(C30,#REF!,1,0)) -> #REF! | E30: delete | F30: - | N30: =IFERROR(VLOOKUP(H30,A:A,1,0),"") | O30: =IFERROR(VLOOKUP(H30,C:C,1,0),"") | P30: =N30&O30
A31: opendata.region.users | B31: public | C31: =B31&"."&A31 -> public.opendata.region.users | D31: =IFERROR(VLOOKUP(A31,#REF!,1,0),VLOOKUP(C31,#REF!,1,0)) -> #REF! | E31: delete | F31: - | N31: =IFERROR(VLOOKUP(H31,A:A,1,0),"") | O31: =IFERROR(VLOOKUP(H31,C:C,1,0),"") | P31: =N31&O31
A32: paragraph | B32: public | C32: =B32&"."&A32 -> public.paragraph | D32: =IFERROR(VLOOKUP(A32,#REF!,1,0),VLOOKUP(C32,#REF!,1,0)) -> #REF! | E32: delete | F32: - | N32: =IFERROR(VLOOKUP(H32,A:A,1,0),"") | O32: =IFERROR(VLOOKUP(H32,C:C,1,0),"") | P32: =N32&O32
A33: soliq_oylik | B33: public | C33: =B33&"."&A33 -> public.soliq_oylik | D33: =IFERROR(VLOOKUP(A33,#REF!,1,0),VLOOKUP(C33,#REF!,1,0)) -> #REF! | E33: delete | F33: - | N33: =IFERROR(VLOOKUP(H33,A:A,1,0),"") | O33: =IFERROR(VLOOKUP(H33,C:C,1,0),"") | P33: =N33&O33
A34: soliq_token | B34: public | C34: =B34&"."&A34 -> public.soliq_token | D34: =IFERROR(VLOOKUP(A34,#REF!,1,0),VLOOKUP(C34,#REF!,1,0)) -> #REF! | E34: delete | F34: - | H34: qurilish.object_pudrat | N34: =IFERROR(VLOOKUP(H34,A:A,1,0),"") | O34: =IFERROR(VLOOKUP(H34,C:C,1,0),"") -> qurilish.object_pudrat | P34: =N34&O34 -> qurilish.object_pudrat
A35: tax_ehf2022 | B35: public | C35: =B35&"."&A35 -> public.tax_ehf2022 | D35: =IFERROR(VLOOKUP(A35,#REF!,1,0),VLOOKUP(C35,#REF!,1,0)) -> #REF! | E35: delete | F35: - | H35: qurilish.object_loyiha | N35: =IFERROR(VLOOKUP(H35,A:A,1,0),"") | O35: =IFERROR(VLOOKUP(H35,C:C,1,0),"") -> qurilish.object_loyiha | P35: =N35&O35 -> qurilish.object_loyiha
A36: tax_salary | B36: public | C36: =B36&"."&A36 -> public.tax_salary | D36: =IFERROR(VLOOKUP(A36,#REF!,1,0),VLOOKUP(C36,#REF!,1,0)) -> #REF! | E36: delete | F36: - | H36: qurilish.object_winner_pudrat | N36: =IFERROR(VLOOKUP(H36,A:A,1,0),"") | O36: =IFERROR(VLOOKUP(H36,C:C,1,0),"") -> qurilish.object_winner_pudrat | P36: =N36&O36 -> qurilish.object_winner_pudrat
A37: tax_shot_faktura | B37: public | C37: =B37&"."&A37 -> public.tax_shot_faktura | D37: =IFERROR(VLOOKUP(A37,#REF!,1,0),VLOOKUP(C37,#REF!,1,0)) -> #REF! | E37: delete | F37: - | H37: qurilish.object_pudrat_data | N37: =IFERROR(VLOOKUP(H37,A:A,1,0),"") | O37: =IFERROR(VLOOKUP(H37,C:C,1,0),"") -> qurilish.object_pudrat_data | P37: =N37&O37 -> qurilish.object_pudrat_data
A38: uzasbo_soliq | B38: public | C38: =B38&"."&A38 -> public.uzasbo_soliq | D38: =IFERROR(VLOOKUP(A38,#REF!,1,0),VLOOKUP(C38,#REF!,1,0)) -> #REF! | E38: delete | F38: - | H38: qurilish.object_winner_loyiha | N38: =IFERROR(VLOOKUP(H38,A:A,1,0),"") | O38: =IFERROR(VLOOKUP(H38,C:C,1,0),"") -> qurilish.object_winner_loyiha | P38: =N38&O38 -> qurilish.object_winner_loyiha
A39: sql_parts | B39: information_schema | C39: =B39&"."&A39 -> information_schema.sql_parts | D39: =IFERROR(VLOOKUP(A39,#REF!,1,0),VLOOKUP(C39,#REF!,1,0)) -> #REF! | E39: delete | F39: - | H39: agrosanoat_data | I39: ichki_ishlar_yol | J39: mehnat_vazirligi | K39: organization | L39: organization_detail | M39: sanoat_xavfsizligi | N39: =IFERROR(VLOOKUP(H39,A:A,1,0),"") -> agrosanoat_data | O39: =IFERROR(VLOOKUP(H39,C:C,1,0),"") | P39: =N39&O39 -> agrosanoat_data
A40: sql_implementation_info | B40: information_schema | C40: =B40&"."&A40 -> information_schema.sql_implementation_info | D40: =IFERROR(VLOOKUP(A40,#REF!,1,0),VLOOKUP(C40,#REF!,1,0)) -> #REF! | E40: delete | F40: - | H40: qurilish.object_loyiha_ekspertiza | N40: =IFERROR(VLOOKUP(H40,A:A,1,0),"") | O40: =IFERROR(VLOOKUP(H40,C:C,1,0),"") -> qurilish.object_loyiha_ekspertiza | P40: =N40&O40 -> qurilish.object_loyiha_ekspertiza
A41: sql_features | B41: information_schema | C41: =B41&"."&A41 -> information_schema.sql_features | D41: =IFERROR(VLOOKUP(A41,#REF!,1,0),VLOOKUP(C41,#REF!,1,0)) -> #REF! | E41: delete | F41: - | H41: qurilish.object_gasn_data | N41: =IFERROR(VLOOKUP(H41,A:A,1,0),"") | O41: =IFERROR(VLOOKUP(H41,C:C,1,0),"") -> qurilish.object_gasn_data | P41: =N41&O41 -> qurilish.object_gasn_data
A42: sql_sizing | B42: information_schema | C42: =B42&"."&A42 -> information_schema.sql_sizing | D42: =IFERROR(VLOOKUP(A42,#REF!,1,0),VLOOKUP(C42,#REF!,1,0)) -> #REF! | E42: delete | F42: - | N42: =IFERROR(VLOOKUP(H42,A:A,1,0),"") | O42: =IFERROR(VLOOKUP(H42,C:C,1,0),"") | P42: =N42&O42
A43: cattle_ranching | B43: subsidy | C43: =B43&"."&A43 -> subsidy.cattle_ranching | D43: =IFERROR(VLOOKUP(A43,#REF!,1,0),VLOOKUP(C43,#REF!,1,0)) -> #REF! | E43: delete | F43: - | N43: =IFERROR(VLOOKUP(H43,A:A,1,0),"") | O43: =IFERROR(VLOOKUP(H43,C:C,1,0),"") | P43: =N43&O43
A44: temp_pinfl | B44: minyust | C44: =B44&"."&A44 -> minyust.temp_pinfl | D44: =IFERROR(VLOOKUP(A44,#REF!,1,0),VLOOKUP(C44,#REF!,1,0)) -> #REF! | E44: delete | F44: - | N44: =IFERROR(VLOOKUP(H44,A:A,1,0),"") | O44: =IFERROR(VLOOKUP(H44,C:C,1,0),"") | P44: =N44&O44
A45: chemical | B45: subsidy | C45: =B45&"."&A45 -> subsidy.chemical | D45: =IFERROR(VLOOKUP(A45,#REF!,1,0),VLOOKUP(C45,#REF!,1,0)) -> #REF! | E45: delete | F45: - | H45: public.gos_active_reestr | N45: =IFERROR(VLOOKUP(H45,A:A,1,0),"") | O45: =IFERROR(VLOOKUP(H45,C:C,1,0),"") -> public.gos_active_reestr | P45: =N45&O45 -> public.gos_active_reestr
A46: cocoon | B46: subsidy | C46: =B46&"."&A46 -> subsidy.cocoon | D46: =IFERROR(VLOOKUP(A46,#REF!,1,0),VLOOKUP(C46,#REF!,1,0)) -> #REF! | E46: delete | F46: - | N46: =IFERROR(VLOOKUP(H46,A:A,1,0),"") | O46: =IFERROR(VLOOKUP(H46,C:C,1,0),"") | P46: =N46&O46
A47: horticulture | B47: subsidy | C47: =B47&"."&A47 -> subsidy.horticulture | D47: =IFERROR(VLOOKUP(A47,#REF!,1,0),VLOOKUP(C47,#REF!,1,0)) -> #REF! | E47: delete | F47: - | N47: =IFERROR(VLOOKUP(H47,A:A,1,0),"") | O47: =IFERROR(VLOOKUP(H47,C:C,1,0),"") | P47: =N47&O47
A48: insurance | B48: subsidy | C48: =B48&"."&A48 -> subsidy.insurance | D48: =IFERROR(VLOOKUP(A48,#REF!,1,0),VLOOKUP(C48,#REF!,1,0)) -> #REF! | E48: delete | F48: - | N48: =IFERROR(VLOOKUP(H48,A:A,1,0),"") | O48: =IFERROR(VLOOKUP(H48,C:C,1,0),"") | P48: =N48&O48
A49: skins | B49: subsidy | C49: =B49&"."&A49 -> subsidy.skins | D49: =IFERROR(VLOOKUP(A49,#REF!,1,0),VLOOKUP(C49,#REF!,1,0)) -> #REF! | E49: delete | F49: - | N49: =IFERROR(VLOOKUP(H49,A:A,1,0),"") | O49: =IFERROR(VLOOKUP(H49,C:C,1,0),"") | P49: =N49&O49
A50: transports | B50: subsidy | C50: =B50&"."&A50 -> subsidy.transports | D50: =IFERROR(VLOOKUP(A50,#REF!,1,0),VLOOKUP(C50,#REF!,1,0)) -> #REF! | E50: delete | F50: - | N50: =IFERROR(VLOOKUP(H50,A:A,1,0),"") | O50: =IFERROR(VLOOKUP(H50,C:C,1,0),"") | P50: =N50&O50
A51: veterans | B51: subsidy | C51: =B51&"."&A51 -> subsidy.veterans | D51: =IFERROR(VLOOKUP(A51,#REF!,1,0),VLOOKUP(C51,#REF!,1,0)) -> #REF! | E51: delete | F51: - | N51: =IFERROR(VLOOKUP(H51,A:A,1,0),"") | O51: =IFERROR(VLOOKUP(H51,C:C,1,0),"") | P51: =N51&O51
A52: water_managments | B52: subsidy | C52: =B52&"."&A52 -> subsidy.water_managments | D52: =IFERROR(VLOOKUP(A52,#REF!,1,0),VLOOKUP(C52,#REF!,1,0)) -> #REF! | E52: delete | F52: - | N52: =IFERROR(VLOOKUP(H52,A:A,1,0),"") | O52: =IFERROR(VLOOKUP(H52,C:C,1,0),"") | P52: =N52&O52
A53: winemaking | B53: subsidy | C53: =B53&"."&A53 -> subsidy.winemaking | D53: =IFERROR(VLOOKUP(A53,#REF!,1,0),VLOOKUP(C53,#REF!,1,0)) -> #REF! | E53: delete | F53: - | N53: =IFERROR(VLOOKUP(H53,A:A,1,0),"") | O53: =IFERROR(VLOOKUP(H53,C:C,1,0),"") | P53: =N53&O53
A54: women | B54: subsidy | C54: =B54&"."&A54 -> subsidy.women | D54: =IFERROR(VLOOKUP(A54,#REF!,1,0),VLOOKUP(C54,#REF!,1,0)) -> #REF! | E54: delete | F54: - | N54: =IFERROR(VLOOKUP(H54,A:A,1,0),"") | O54: =IFERROR(VLOOKUP(H54,C:C,1,0),"") | P54: =N54&O54
A55: bank_overall1 | B55: tax | C55: =B55&"."&A55 -> tax.bank_overall1 | D55: =IFERROR(VLOOKUP(A55,#REF!,1,0),VLOOKUP(C55,#REF!,1,0)) -> #REF! | E55: delete | F55: - | H55: phys_subsidies_list | N55: =IFERROR(VLOOKUP(H55,A:A,1,0),"") -> phys_subsidies_list | O55: =IFERROR(VLOOKUP(H55,C:C,1,0),"") | P55: =N55&O55 -> phys_subsidies_list
A56: bank_overall2 | B56: tax | C56: =B56&"."&A56 -> tax.bank_overall2 | D56: =IFERROR(VLOOKUP(A56,#REF!,1,0),VLOOKUP(C56,#REF!,1,0)) -> #REF! | E56: delete | F56: - | H56: yur_subsidies_list | N56: =IFERROR(VLOOKUP(H56,A:A,1,0),"") -> yur_subsidies_list | O56: =IFERROR(VLOOKUP(H56,C:C,1,0),"") | P56: =N56&O56 -> yur_subsidies_list
A57: factures | B57: tax | C57: =B57&"."&A57 -> tax.factures | D57: =IFERROR(VLOOKUP(A57,#REF!,1,0),VLOOKUP(C57,#REF!,1,0)) -> #REF! | E57: delete | F57: - | H57: unemployment_list | N57: =IFERROR(VLOOKUP(H57,A:A,1,0),"") -> unemployment_list | O57: =IFERROR(VLOOKUP(H57,C:C,1,0),"") | P57: =N57&O57 -> unemployment_list
A58: kadastr_informations | B58: tax | C58: =B58&"."&A58 -> tax.kadastr_informations | D58: =IFERROR(VLOOKUP(A58,#REF!,1,0),VLOOKUP(C58,#REF!,1,0)) -> #REF! | E58: kadastr | F58: - | H58: employement.malakani_baholash_markazi | N58: =IFERROR(VLOOKUP(H58,A:A,1,0),"") | O58: =IFERROR(VLOOKUP(H58,C:C,1,0),"") -> employement.malakani_baholash_markazi | P58: =N58&O58 -> employement.malakani_baholash_markazi
A59: legal_entities | B59: tax | C59: =B59&"."&A59 -> tax.legal_entities | D59: =IFERROR(VLOOKUP(A59,#REF!,1,0),VLOOKUP(C59,#REF!,1,0)) -> #REF! | E59: np1 | F59: - | H59: employee_history | N59: =IFERROR(VLOOKUP(H59,A:A,1,0),"") -> employee_history | O59: =IFERROR(VLOOKUP(H59,C:C,1,0),"") | P59: =N59&O59 -> employee_history
A60: legal_entities_detailed | B60: tax | C60: =B60&"."&A60 -> tax.legal_entities_detailed | D60: =IFERROR(VLOOKUP(A60,#REF!,1,0),VLOOKUP(C60,#REF!,1,0)) -> #REF! | E60: np1 | F60: - | H60: employement.yaqin_qarindosh | N60: =IFERROR(VLOOKUP(H60,A:A,1,0),"") | O60: =IFERROR(VLOOKUP(H60,C:C,1,0),"") -> employement.yaqin_qarindosh | P60: =N60&O60 -> employement.yaqin_qarindosh
A61: nedra_tax_reports | B61: tax | C61: =B61&"."&A61 -> tax.nedra_tax_reports | D61: =IFERROR(VLOOKUP(A61,#REF!,1,0),VLOOKUP(C61,#REF!,1,0)) -> #REF! | E61: delete | F61: - | H61: employement.personal_info | N61: =IFERROR(VLOOKUP(H61,A:A,1,0),"") | O61: =IFERROR(VLOOKUP(H61,C:C,1,0),"") -> employement.personal_info | P61: =N61&O61 -> employement.personal_info
A62: sp_pinfl_stir | B62: tax | C62: =B62&"."&A62 -> tax.sp_pinfl_stir | D62: =IFERROR(VLOOKUP(A62,#REF!,1,0),VLOOKUP(C62,#REF!,1,0)) -> #REF! | E62: soliq_inn_pinfl | F62: - | H62: employement.mehnat_daftar | N62: =IFERROR(VLOOKUP(H62,A:A,1,0),"") | O62: =IFERROR(VLOOKUP(H62,C:C,1,0),"") -> employement.mehnat_daftar | P62: =N62&O62 -> employement.mehnat_daftar
A63: tax_reports | B63: tax | C63: =B63&"."&A63 -> tax.tax_reports | D63: =IFERROR(VLOOKUP(A63,#REF!,1,0),VLOOKUP(C63,#REF!,1,0)) -> #REF! | E63: delete | F63: - | H63: public_workers_list | N63: =IFERROR(VLOOKUP(H63,A:A,1,0),"") -> public_workers_list | O63: =IFERROR(VLOOKUP(H63,C:C,1,0),"") | P63: =N63&O63 -> public_workers_list
A64: tax_reports_list | B64: tax | C64: =B64&"."&A64 -> tax.tax_reports_list | D64: =IFERROR(VLOOKUP(A64,#REF!,1,0),VLOOKUP(C64,#REF!,1,0)) -> #REF! | E64: delete | F64: - | H64: subsidy.kasbga_yun_fuqaro | N64: =IFERROR(VLOOKUP(H64,A:A,1,0),"") | O64: =IFERROR(VLOOKUP(H64,C:C,1,0),"") -> subsidy.kasbga_yun_fuqaro | P64: =N64&O64 -> subsidy.kasbga_yun_fuqaro
A65: borders_service | B65: uzasbo | C65: =B65&"."&A65 -> uzasbo.borders_service | D65: =IFERROR(VLOOKUP(A65,#REF!,1,0),VLOOKUP(C65,#REF!,1,0)) -> #REF! | E65: pagran_svod | F65: - | H65: employement.hunarmand | N65: =IFERROR(VLOOKUP(H65,A:A,1,0),"") | O65: =IFERROR(VLOOKUP(H65,C:C,1,0),"") -> employement.hunarmand | P65: =N65&O65 -> employement.hunarmand
A66: tax_report | B66: temp | C66: =B66&"."&A66 -> temp.tax_report | D66: =IFERROR(VLOOKUP(A66,#REF!,1,0),VLOOKUP(C66,#REF!,1,0)) -> #REF! | H66: employement.turists | N66: =IFERROR(VLOOKUP(H66,A:A,1,0),"") | O66: =IFERROR(VLOOKUP(H66,C:C,1,0),"") -> employement.turists | P66: =N66&O66 -> employement.turists
A67: accounts_organizations | B67: uzasbo | C67: =B67&"."&A67 -> uzasbo.accounts_organizations | D67: =IFERROR(VLOOKUP(A67,#REF!,1,0),VLOOKUP(C67,#REF!,1,0)) -> #REF! | E67: delete | F67: - | H67: tartibga_solish.e_accreditation | N67: =IFERROR(VLOOKUP(H67,A:A,1,0),"") | O67: =IFERROR(VLOOKUP(H67,C:C,1,0),"") -> tartibga_solish.e_accreditation | P67: =N67&O67 -> tartibga_solish.e_accreditation
A68: accrual_inn_lists | B68: uzasbo | C68: =B68&"."&A68 -> uzasbo.accrual_inn_lists | D68: =IFERROR(VLOOKUP(A68,#REF!,1,0),VLOOKUP(C68,#REF!,1,0)) -> #REF! | E68: delete | F68: - | N68: =IFERROR(VLOOKUP(H68,A:A,1,0),"") | O68: =IFERROR(VLOOKUP(H68,C:C,1,0),"") | P68: =N68&O68
A69: accruals | B69: uzasbo | C69: =B69&"."&A69 -> uzasbo.accruals | D69: =IFERROR(VLOOKUP(A69,#REF!,1,0),VLOOKUP(C69,#REF!,1,0)) -> #REF! | E69: delete | F69: - | H69: cooperation.product | N69: =IFERROR(VLOOKUP(H69,A:A,1,0),"") | O69: =IFERROR(VLOOKUP(H69,C:C,1,0),"") -> cooperation.product | P69: =N69&O69 -> cooperation.product
A70: my_works | B70: uzasbo | C70: =B70&"."&A70 -> uzasbo.my_works | D70: =IFERROR(VLOOKUP(A70,#REF!,1,0),VLOOKUP(C70,#REF!,1,0)) -> #REF! | E70: delete | F70: - | H70: cooperation.companies | N70: =IFERROR(VLOOKUP(H70,A:A,1,0),"") | O70: =IFERROR(VLOOKUP(H70,C:C,1,0),"") -> cooperation.companies | P70: =N70&O70 -> cooperation.companies
A71: positions_vault | B71: uzasbo | C71: =B71&"."&A71 -> uzasbo.positions_vault | D71: =IFERROR(VLOOKUP(A71,#REF!,1,0),VLOOKUP(C71,#REF!,1,0)) -> #REF! | H71: cooperation.contract | N71: =IFERROR(VLOOKUP(H71,A:A,1,0),"") | O71: =IFERROR(VLOOKUP(H71,C:C,1,0),"") -> cooperation.contract | P71: =N71&O71 -> cooperation.contract
A72: report_months | B72: uzasbo | C72: =B72&"."&A72 -> uzasbo.report_months | D72: =IFERROR(VLOOKUP(A72,#REF!,1,0),VLOOKUP(C72,#REF!,1,0)) -> #REF! | H72: subsidy.credits | N72: =IFERROR(VLOOKUP(H72,A:A,1,0),"") | O72: =IFERROR(VLOOKUP(H72,C:C,1,0),"") -> subsidy.credits | P72: =N72&O72 -> subsidy.credits
A73: sp_organizations_bill | B73: uzasbo | C73: =B73&"."&A73 -> uzasbo.sp_organizations_bill | D73: =IFERROR(VLOOKUP(A73,#REF!,1,0),VLOOKUP(C73,#REF!,1,0)) -> #REF! | E73: spravochnik | F73: - | N73: =IFERROR(VLOOKUP(H73,A:A,1,0),"") | O73: =IFERROR(VLOOKUP(H73,C:C,1,0),"") | P73: =N73&O73
A74: sp_orgs | B74: uzasbo | C74: =B74&"."&A74 -> uzasbo.sp_orgs | D74: =IFERROR(VLOOKUP(A74,#REF!,1,0),VLOOKUP(C74,#REF!,1,0)) -> #REF! | E74: spravochnik | F74: - | H74: birja.xt_tender_selection | N74: =IFERROR(VLOOKUP(H74,A:A,1,0),"") | O74: =IFERROR(VLOOKUP(H74,C:C,1,0),"") -> birja.xt_tender_selection | P74: =N74&O74 -> birja.xt_tender_selection
A75: sp_positions | B75: uzasbo | C75: =B75&"."&A75 -> uzasbo.sp_positions | D75: =IFERROR(VLOOKUP(A75,#REF!,1,0),VLOOKUP(C75,#REF!,1,0)) -> #REF! | E75: spravochnik | F75: - | H75: birja.xt_agreement_members | N75: =IFERROR(VLOOKUP(H75,A:A,1,0),"") | O75: =IFERROR(VLOOKUP(H75,C:C,1,0),"") -> birja.xt_agreement_members | P75: =N75&O75 -> birja.xt_agreement_members
A76: sp_regions | B76: uzasbo | C76: =B76&"."&A76 -> uzasbo.sp_regions | D76: =IFERROR(VLOOKUP(A76,#REF!,1,0),VLOOKUP(C76,#REF!,1,0)) -> #REF! | E76: spravochnik | F76: - | H76: birja.xt_request_reduction | N76: =IFERROR(VLOOKUP(H76,A:A,1,0),"") | O76: =IFERROR(VLOOKUP(H76,C:C,1,0),"") -> birja.xt_request_reduction | P76: =N76&O76 -> birja.xt_request_reduction
A77: statements | B77: uzasbo | C77: =B77&"."&A77 -> uzasbo.statements | D77: =IFERROR(VLOOKUP(A77,#REF!,1,0),VLOOKUP(C77,#REF!,1,0)) -> #REF! | E77: delete | F77: - | N77: =IFERROR(VLOOKUP(H77,A:A,1,0),"") | O77: =IFERROR(VLOOKUP(H77,C:C,1,0),"") | P77: =N77&O77
A78: sp_ministry | B78: uzasbo | C78: =B78&"."&A78 -> uzasbo.sp_ministry | D78: =IFERROR(VLOOKUP(A78,#REF!,1,0),VLOOKUP(C78,#REF!,1,0)) -> #REF! | E78: spravochnik | F78: - | H78: birja.e_protocol | N78: =IFERROR(VLOOKUP(H78,A:A,1,0),"") | O78: =IFERROR(VLOOKUP(H78,C:C,1,0),"") -> birja.e_protocol | P78: =N78&O78 -> birja.e_protocol
A79: users | B79: uzasbo | C79: =B79&"."&A79 -> uzasbo.users | D79: =IFERROR(VLOOKUP(A79,#REF!,1,0),VLOOKUP(C79,#REF!,1,0)) -> #REF! | E79: delete | F79: - | H79: birja.directs | N79: =IFERROR(VLOOKUP(H79,A:A,1,0),"") | O79: =IFERROR(VLOOKUP(H79,C:C,1,0),"") -> birja.directs | P79: =N79&O79 -> birja.directs
A80: uzasbo_oylik | B80: uzasbo | C80: =B80&"."&A80 -> uzasbo.uzasbo_oylik | D80: =IFERROR(VLOOKUP(A80,#REF!,1,0),VLOOKUP(C80,#REF!,1,0)) -> #REF! | E80: delete | F80: - | H80: birja.trades | N80: =IFERROR(VLOOKUP(H80,A:A,1,0),"") | O80: =IFERROR(VLOOKUP(H80,C:C,1,0),"") -> birja.trades | P80: =N80&O80 -> birja.trades
A81: info_organization_state | B81: uzasbo | C81: =B81&"."&A81 -> uzasbo.info_organization_state | D81: =IFERROR(VLOOKUP(A81,#REF!,1,0),VLOOKUP(C81,#REF!,1,0)) -> #REF! | E81: UzAsbo Organizatsiyalar ro'yxati | F81: + | N81: =IFERROR(VLOOKUP(H81,A:A,1,0),"") | O81: =IFERROR(VLOOKUP(H81,C:C,1,0),"") | P81: =N81&O81
A82: position_vault | B82: uzasbo | C82: =B82&"."&A82 -> uzasbo.position_vault | D82: =IFERROR(VLOOKUP(A82,#REF!,1,0),VLOOKUP(C82,#REF!,1,0)) -> #REF! | N82: =IFERROR(VLOOKUP(H82,A:A,1,0),"") | O82: =IFERROR(VLOOKUP(H82,C:C,1,0),"") | P82: =N82&O82
A83: financial_transactions | B83: uzasbo | C83: =B83&"."&A83 -> uzasbo.financial_transactions | D83: =IFERROR(VLOOKUP(A83,#REF!,1,0),VLOOKUP(C83,#REF!,1,0)) -> #REF! | N83: =IFERROR(VLOOKUP(H83,A:A,1,0),"") | O83: =IFERROR(VLOOKUP(H83,C:C,1,0),"") | P83: =N83&O83
A84: temp_lavozim_pinfl | B84: minyust | C84: =B84&"."&A84 -> minyust.temp_lavozim_pinfl | D84: =IFERROR(VLOOKUP(A84,#REF!,1,0),VLOOKUP(C84,#REF!,1,0)) -> #REF! | E84: delete | F84: - | N84: =IFERROR(VLOOKUP(H84,A:A,1,0),"") | O84: =IFERROR(VLOOKUP(H84,C:C,1,0),"") | P84: =N84&O84
A85: phys_subsidies_list | B85: subsidy | C85: =B85&"."&A85 -> subsidy.phys_subsidies_list | D85: =IFERROR(VLOOKUP(A85,#REF!,1,0),VLOOKUP(C85,#REF!,1,0)) -> #REF! | H85: minyust.relative_person_info | N85: =IFERROR(VLOOKUP(H85,A:A,1,0),"") | O85: =IFERROR(VLOOKUP(H85,C:C,1,0),"") -> minyust.relative_person_info | P85: =N85&O85 -> minyust.relative_person_info
A86: dembat_faktura | B86: uzasbo | C86: =B86&"."&A86 -> uzasbo.dembat_faktura | D86: =IFERROR(VLOOKUP(A86,#REF!,1,0),VLOOKUP(C86,#REF!,1,0)) -> #REF! | N86: =IFERROR(VLOOKUP(H86,A:A,1,0),"") | O86: =IFERROR(VLOOKUP(H86,C:C,1,0),"") | P86: =N86&O86
A87: unemployment_list | B87: subsidy | C87: =B87&"."&A87 -> subsidy.unemployment_list | D87: =IFERROR(VLOOKUP(A87,#REF!,1,0),VLOOKUP(C87,#REF!,1,0)) -> #REF! | N87: =IFERROR(VLOOKUP(H87,A:A,1,0),"") | O87: =IFERROR(VLOOKUP(H87,C:C,1,0),"") | P87: =N87&O87
A88: info_organizations | B88: uzasbo | C88: =B88&"."&A88 -> uzasbo.info_organizations | D88: =IFERROR(VLOOKUP(A88,#REF!,1,0),VLOOKUP(C88,#REF!,1,0)) -> #REF! | E88: KERAK | F88: + | H88: minyust.relative_person_info | N88: =IFERROR(VLOOKUP(H88,A:A,1,0),"") | O88: =IFERROR(VLOOKUP(H88,C:C,1,0),"") -> minyust.relative_person_info | P88: =N88&O88 -> minyust.relative_person_info
A89: conflictofinterests_ready | B89: public | C89: =B89&"."&A89 -> public.conflictofinterests_ready | D89: =IFERROR(VLOOKUP(A89,#REF!,1,0),VLOOKUP(C89,#REF!,1,0)) -> #REF! | E89: delete | F89: - | N89: =IFERROR(VLOOKUP(H89,A:A,1,0),"") | O89: =IFERROR(VLOOKUP(H89,C:C,1,0),"") | P89: =N89&O89
A90: get_experiences | B90: subsidy | C90: =B90&"."&A90 -> subsidy.get_experiences | D90: =IFERROR(VLOOKUP(A90,#REF!,1,0),VLOOKUP(C90,#REF!,1,0)) -> #REF! | E90: QANDAY TABLE EKANLIGI NOMALUM | F90: + | N90: =IFERROR(VLOOKUP(H90,A:A,1,0),"") | O90: =IFERROR(VLOOKUP(H90,C:C,1,0),"") | P90: =N90&O90
A91: student_info | B91: education | C91: =B91&"."&A91 -> education.student_info | D91: =IFERROR(VLOOKUP(A91,#REF!,1,0),VLOOKUP(C91,#REF!,1,0)) -> #REF! | N91: =IFERROR(VLOOKUP(H91,A:A,1,0),"") | O91: =IFERROR(VLOOKUP(H91,C:C,1,0),"") | P91: =N91&O91
A92: vedemost | B92: uzasbo | C92: =B92&"."&A92 -> uzasbo.vedemost | D92: =IFERROR(VLOOKUP(A92,#REF!,1,0),VLOOKUP(C92,#REF!,1,0)) -> #REF! | N92: =IFERROR(VLOOKUP(H92,A:A,1,0),"") | O92: =IFERROR(VLOOKUP(H92,C:C,1,0),"") | P92: =N92&O92
A93: tax_qum_shagal | B93: geo_eco | C93: =B93&"."&A93 -> geo_eco.tax_qum_shagal | D93: =IFERROR(VLOOKUP(A93,#REF!,1,0),VLOOKUP(C93,#REF!,1,0)) -> #REF! | E93: Qum ShAg'al exceldan export qilingan | F93: + | N93: =IFERROR(VLOOKUP(H93,A:A,1,0),"") | O93: =IFERROR(VLOOKUP(H93,C:C,1,0),"") | P93: =N93&O93
A94: employee_history | B94: employement | C94: =B94&"."&A94 -> employement.employee_history | D94: =IFERROR(VLOOKUP(A94,#REF!,1,0),VLOOKUP(C94,#REF!,1,0)) -> #REF! | N94: =IFERROR(VLOOKUP(H94,A:A,1,0),"") | O94: =IFERROR(VLOOKUP(H94,C:C,1,0),"") | P94: =N94&O94
A95: yur_subsidies_list | B95: subsidy | C95: =B95&"."&A95 -> subsidy.yur_subsidies_list | D95: =IFERROR(VLOOKUP(A95,#REF!,1,0),VLOOKUP(C95,#REF!,1,0)) -> #REF! | N95: =IFERROR(VLOOKUP(H95,A:A,1,0),"") | O95: =IFERROR(VLOOKUP(H95,C:C,1,0),"") | P95: =N95&O95
A96: agricultures | B96: subsidy | C96: =B96&"."&A96 -> subsidy.agricultures | D96: =IFERROR(VLOOKUP(A96,#REF!,1,0),VLOOKUP(C96,#REF!,1,0)) -> #REF! | N96: =IFERROR(VLOOKUP(H96,A:A,1,0),"") | O96: =IFERROR(VLOOKUP(H96,C:C,1,0),"") | P96: =N96&O96
A97: export | B97: bojxona | C97: =B97&"."&A97 -> bojxona.export | D97: =IFERROR(VLOOKUP(A97,#REF!,1,0),VLOOKUP(C97,#REF!,1,0)) -> #REF! | N97: =IFERROR(VLOOKUP(H97,A:A,1,0),"") | O97: =IFERROR(VLOOKUP(H97,C:C,1,0),"") | P97: =N97&O97
A98: import_data | B98: bojxona | C98: =B98&"."&A98 -> bojxona.import_data | D98: =IFERROR(VLOOKUP(A98,#REF!,1,0),VLOOKUP(C98,#REF!,1,0)) -> #REF! | N98: =IFERROR(VLOOKUP(H98,A:A,1,0),"") | O98: =IFERROR(VLOOKUP(H98,C:C,1,0),"") | P98: =N98&O98
A99: extra_salary | B99: soliq | C99: =B99&"."&A99 -> soliq.extra_salary | D99: =IFERROR(VLOOKUP(A99,#REF!,1,0),VLOOKUP(C99,#REF!,1,0)) -> #REF! | E99: Soliq Extra salary | F99: + | N99: =IFERROR(VLOOKUP(H99,A:A,1,0),"") | O99: =IFERROR(VLOOKUP(H99,C:C,1,0),"") | P99: =N99&O99
A100: payments | B100: bojxona | C100: =B100&"."&A100 -> bojxona.payments | D100: =IFERROR(VLOOKUP(A100,#REF!,1,0),VLOOKUP(C100,#REF!,1,0)) -> #REF! | E100: BOJXONA To'lov | F100: + | N100: =IFERROR(VLOOKUP(H100,A:A,1,0),"") | O100: =IFERROR(VLOOKUP(H100,C:C,1,0),"") | P100: =N100&O100
...

Sheet Микросервис (2025-05-24)
A1: Микросервислар орқали кунлик, ойлик ва чораклик жамланадиган маълумотлар
A3: Т/р | B3: Маълумот эгаси ҳамда унинг таркиби | C3: Маълумот олиш усули тўғрисида таклиф | D3: ҳолати | E3: Маълумот жамлаш (кунлик, ойлик, чораклик) | F3: Интеграция ҳолати (1-якунланган, 2-давом этмоқда) | G3: API | H3: Базадаги номи | J3: URL | K3: Вазирдик ва идора номи | L3: Маълумот номи | M3: Таблица номи | N3: Таблицада одам тили
B4: 1. Адлия
A5: =MAX(A$2:A4)+1 -> 1 | B5: Yaqin qarindoshlar | D5: 1 | E5: ойлик | H5: minyust.relative_person_info
A6: =MAX(A$2:A5)+1 -> 2 | B6: Bank xodimlarini yaqin qarindoshlarini yig'ish | D6: 1 | E6: ойлик | H6: minyust.relative_person_info
B7: 2. УзАСБО ДТ
A8: =MAX(A$2:A7)+1 -> 3 | B8: Uzasbo G'azna Faktura | D8: 1 | E8: кунлик | H8: uzasbo.gazna_faktura
A9: =MAX(A$2:A8)+1 -> 4 | B9: Lavozimlarni olish | D9: 1 | E9: ойлик | H9: uzasbo.position_vault | J9: http://10.190.4.11/inps/api/UzRXP/GetSqlQuery
A10: =MAX(A$2:A9)+1 -> 5 | B10: Dembat Faktura | D10: 1 | E10: ойлик | H10: uzasbo.dembat_faktura
A11: =MAX(A$2:A10)+1 -> 6 | B11: Uzasbo ish haqqi | D11: 1 | E11: сўровга асосан | H11: uzasbo.report_months | J11: http://10.190.4.11/inps/api/UzRXP/GetSqlQuery
A12: =MAX(A$2:A11)+1 -> 7 | B12: Dembat Smeta | D12: 1 | E12: кунлик | H12: uzasbo.dembat_smeta
A13: =MAX(A$2:A12)+1 -> 8 | B13: Asosiy Smeta | D13: 1 | E13: ойлик | H13: uzasbo.main_smeta
A14: =MAX(A$2:A13)+1 -> 9 | B14: Vedemost | D14: 1 | E14: сўровга асосан | H14: uzasbo.vedemost | J14: http://10.190.4.11/inps/api/UzRXP/GetSqlQuery
A15: =MAX(A$2:A14)+1 -> 10 | B15: Dembat shartnomalar | D15: 1 | E15: кунлик | H15: uzasbo.financial_transactions
A16: =MAX(A$2:A15)+1 -> 11 | B16: Organizatsiyalar | D16: 1 | E16: ойлик | H16: uzasbo.info_organizations | J16: http://10.190.4.11/inps/api/UzRXP/GetSqlQuery
A17: =MAX(A$2:A16)+1 -> 12 | B17: Position Svod | D17: 1 | E17: ойлик | H17: uzasbo.positions_vault
A18: =MAX(A$2:A17)+1 -> 13 | B18: bittadan inn yuborib Uzasbo Oylik olish | D18: 1 | E18: сўровга асосан | H18: uzasbo.report_months | J18: http://10.190.4.11/inps/api/UzRXP/GetSqlQuery
A19: =MAX(A$2:A18)+1 -> 14 | B19: Taxlil uchun Ish xaqqini tayorlash | D19: 1 | E19: сўровга асосан | H19: uzasbo.report_months_last
B20: 3. Субсидия
A21: =MAX(A$2:A20)+1 -> 15 | B21: Корхона ва ташкилотларда умумий иш ўринлари тўғрисида маълумот | D21: 1 | E21: кунлик | H21: subsidy.job_searchers_list | J21: https://10.190.2.81/api/account-chamber/job-searchers-list | K21: Камбағалликни қисқартириш ва бандлик вазирлиги | L21: Фуқароларни ишга жойлаштиришда кўмаклашиш (ишга жойлаштирилган фуқаролар) | M21: Фуқароларни ишга жойлаштиришда кўмаклашиш (жисмоний шахсларнинг меҳнат фаолияти тўғрисидаги маълумотлар) | N21: {"params": [{"type": "str", "child": false, "field": "fio", "name_cr": "F.I.SH", "name_en": "F.I.SH", "name_ru": "F.I.SH", "name_uz": "F.I.SH"}, {"type": "str", "child": false, "field": "gender", "name_cr": "Jinsi", "name_en": "Jinsi", "name_ru": "Jinsi", "name_uz": "Jinsi"}, {"type": "str", "child": false, "field": "birth_date", "name_cr": "Tug‘ilgan sanasi", "name_en": "Tug‘ilgan sanasi", "name_ru": "Tug‘ilgan sanasi", "name_uz": "Tug‘ilgan sanasi"}, {"type": "str", "child": false, "field": "passport", "name_cr": "Pasport seriya va raqami", "name_en": "Pasport seriya va raqami", "name_ru": "Pasport seriya va raqami", "name_uz": "Pasport seriya va raqami"}, {"type": "str", "child": false, "field": "tin", "name_cr": "STIR (INN)", "name_en": "STIR (INN)", "name_ru": "STIR (INN)", "name_uz": "STIR (INN)"}, {"type": "str", "child": false, "field": "pin", "name_cr": "PINFL", "name_en": "PINFL", "name_ru": "PINFL", "name_uz": "PINFL"}, {"type": "str", "child": false, "field": "phone", "name_cr": "Tel raqami", "name_en": "Tel raqami", "name_ru": "Tel raqami", "name_uz": "Tel raqami"}, {"type": "str", "child": false, "field": "application_date", "name_cr": "Ishsizlik bo‘yicha murojaat sanasi", "name_en": "Ishsizlik bo‘yicha murojaat sanasi", "name_ru": "Ishsizlik bo‘yicha murojaat sanasi", "name_uz": "Ishsizlik bo‘yicha murojaat sanasi"}, {"type": "str", "child": false, "field": "employed_date", "name_cr": "Ishga joylashtirilgan sanasi", "name_en": "Ishga joylashtirilgan sanasi", "name_ru": "Ishga joylashtirilgan sanasi", "name_uz": "Ishga joylashtirilgan sanasi"}, {"type": "str", "child": false, "field": "region_name", "name_cr": "Hudud (viloyat) nomi", "name_en": "Hudud (viloyat) nomi", "name_ru": "Hudud (viloyat) nomi", "name_uz": "Hudud (viloyat) nomi"}, {"type": "str", "child": false, "field": "region_soato", "name_cr": "Hudud (viloyat) SOATO kodi", "name_en": "Hudud (viloyat) SOATO kodi", "name_ru": "Hudud (viloyat) SOATO kodi", "name_uz": "Hudud (viloyat) SOATO kodi"}, {"type": "str", "child": false, "field": "district_name", "name_cr": "Tuman (shahar) nomi", "name_en": "Tuman (shahar) nomi", "name_ru": "Tuman (shahar) nomi", "name_uz": "Tuman (shahar) nomi"}, {"type": "str", "child": false, "field": "city_soato", "name_cr": "Tuman (shahar) SOATO kodi", "name_en": "Tuman (shahar) SOATO kodi", "name_ru": "Tuman (shahar) SOATO kodi", "name_uz": "Tuman (shahar) SOATO kodi"}, {"type": "str", "child": false, "field": "company_tin", "name_cr": "Korxona STIR", "name_en": "Korxona STIR", "name_ru": "Korxona STIR", "name_uz": "Korxona STIR"}, {"type": "str", "child": false, "field": "company_name", "name_cr": "Korxona nomi", "name_en": "Korxona nomi", "name_ru": "Korxona nomi", "name_uz": "Korxona nomi"}, {"type": "str", "child": false, "field": "salary", "name_cr": "Oylik ish haqi miqdori", "name_en": "Oylik ish haqi miqdori", "name_ru": "Oylik ish haqi miqdori", "name_uz": "Oylik ish haqi miqdori"}, {"type": "str", "child": false, "field": "contract_date", "name_cr": "Mehnat shartnomasi sanasi", "name_en": "Mehnat shartnomasi sanasi", "name_ru": "Mehnat shartnomasi sanasi", "name_uz": "Mehnat shartnomasi sanasi"}, {"type": "str", "child": false, "field": "contract_expire_date", "name_cr": "Mehnat shartnomasi amal qilish muddati", "name_en": "Mehnat shartnomasi amal qilish muddati", "name_ru": "Mehnat shartnomasi amal qilish muddati", "name_uz": "Mehnat shartnomasi amal qilish muddati"}, {"type": "str", "child": false, "field": "age", "name_cr": "Yoshi", "name_en": "Yoshi", "name_ru": "Yoshi", "name_uz": "Yoshi"}]}
A22: =MAX(A$2:A21)+1 -> 16 | B22: Ҳунарманд шогирдларга асбоб ускуна учун субсидия | D22: 1 | E22: кунлик | H22: subsidy.for_students | J22: https://10.190.2.81/api/account-chamber/master-craftsman-list/for-students | K22: Камбағалликни қисқартириш ва бандлик вазирлиги | L22: Ҳунарманд шогирдларга асбоб ускуна учун субсидия | M22: Ҳунарманд шогирдларга асбоб ускуна учун субсидия | N22: {"params": [{"type": "string", "child": false, "field": "region_name", "name_cr": "region_name", "name_en": "region_name", "name_ru": "region_name", "name_uz": "region_name"}, {"type": "string", "child": false, "field": "region_soato", "name_cr": "region_soato", "name_en": "region_soato", "name_ru": "region_soato", "name_uz": "region_soato"}, {"type": "string", "child": false, "field": "district_name", "name_cr": "district_name", "name_en": "district_name", "name_ru": "district_name", "name_uz": "district_name"}, {"type": "string", "child": false, "field": "city_soato", "name_cr": "city_soato", "name_en": "city_soato", "name_ru": "city_soato", "name_uz": "city_soato"}, {"type": "string", "child": false, "field": "bdate", "name_cr": "bdate", "name_en": "bdate", "name_ru": "bdate", "name_uz": "bdate"}, {"type": "string", "child": false, "field": "psdata", "name_cr": "psdata", "name_en": "psdata", "name_ru": "psdata", "name_uz": "psdata"}, {"type": "string", "child": false, "field": "inn", "name_cr": "inn", "name_en": "inn", "name_ru": "inn", "name_uz": "inn"}, {"type": "string", "child": false, "field": "pinfl", "name_cr": "pinfl", "name_en": "pinfl", "name_ru": "pinfl", "name_uz": "pinfl"}, {"type": "string", "child": false, "field": "sex", "name_cr": "sex", "name_en": "sex", "name_ru": "sex", "name_uz": "sex"}, {"type": "string", "child": false, "field": "full_name", "name_cr": "full_name", "name_en": "full_name", "name_ru": "full_name", "name_uz": "full_name"}, {"type": "string", "child": false, "field": "subsidy_amount", "name_cr": "subsidy_amount", "name_en": "subsidy_amount", "name_ru": "subsidy_amount", "name_uz": "subsidy_amount"}, {"type": "string", "child": false, "field": "subsidy_date", "name_cr": "subsidy_date", "name_en": "subsidy_date", "name_ru": "subsidy_date", "name_uz": "subsidy_date"}, {"type": "string", "child": false, "field": "subsidy_name", "name_cr": "subsidy_name", "name_en": "subsidy_name", "name_ru": "subsidy_name", "name_uz": "subsidy_name"}]}
A23: =MAX(A$2:A22)+1 -> 17 | B23: Ҳунарманд уюшмасига аъзолик бадалини қоплаш учун субсидия | D23: 1 | E23: кунлик | H23: subsidy.for_membership_fee | J23: https://10.190.2.81/api/account-chamber/master-craftsman-list/for-membership-fee | K23: Камбағалликни қисқартириш ва бандлик вазирлиги | L23: Ҳунарманд уюшмасига аъзолик бадалини қоплаш учун субсидия | M23: Ҳунарманд уюшмасига аъзолик бадалини қоплаш учун субсидия | N23: {"params": [{"type": "string", "child": false, "field": "region_name", "name_cr": "region_name", "name_en": "region_name", "name_ru": "region_name", "name_uz": "region_name"}, {"type": "string", "child": false, "field": "region_soato", "name_cr": "region_soato", "name_en": "region_soato", "name_ru": "region_soato", "name_uz": "region_soato"}, {"type": "string", "child": false, "field": "district_name", "name_cr": "district_name", "name_en": "district_name", "name_ru": "district_name", "name_uz": "district_name"}, {"type": "string", "child": false, "field": "city_soato", "name_cr": "city_soato", "name_en": "city_soato", "name_ru": "city_soato", "name_uz": "city_soato"}, {"type": "string", "child": false, "field": "bdate", "name_cr": "bdate", "name_en": "bdate", "name_ru": "bdate", "name_uz": "bdate"}, {"type": "string", "child": false, "field": "psdata", "name_cr": "psdata", "name_en": "psdata", "name_ru": "psdata", "name_uz": "psdata"}, {"type": "string", "child": false, "field": "inn", "name_cr": "inn", "name_en": "inn", "name_ru": "inn", "name_uz": "inn"}, {"type": "string", "child": false, "field": "pinfl", "name_cr": "pinfl", "name_en": "pinfl", "name_ru": "pinfl", "name_uz": "pinfl"}, {"type": "string", "child": false, "field": "sex", "name_cr": "sex", "name_en": "sex", "name_ru": "sex", "name_uz": "sex"}, {"type": "string", "child": false, "field": "full_name", "name_cr": "full_name", "name_en": "full_name", "name_ru": "full_name", "name_uz": "full_name"}, {"type": "string", "child": false, "field": "subsidy_amount", "name_cr": "subsidy_amount", "name_en": "subsidy_amount", "name_ru": "subsidy_amount", "name_uz": "subsidy_amount"}, {"type": "string", "child": false, "field": "subsidy_date", "name_cr": "subsidy_date", "name_en": "subsidy_date", "name_ru": "subsidy_date", "name_uz": "subsidy_date"}, {"type": "string", "child": false, "field": "subsidy_name", "name_cr": "subsidy_name", "name_en": "subsidy_name", "name_ru": "subsidy_name", "name_uz": "subsidy_name"}]}
A24: =MAX(A$2:A23)+1 -> 18 | B24: Касбга ўқитиш хизматидан фойдаланган жисмоний шахслар тўғрисидаги маълумотлар | D24: 1 | E24: кунлик | H24: subsidy.kasbga_yun_fuqaro | J24: https://10.190.2.81/api/account-chamber/retraining-list | K24: Камбағалликни қисқартириш ва бандлик вазирлиги | L24: Касбга ўқитиш хизматидан фойдаланган жисмоний шахслар тўғрисидаги маълумотлар | M24: Касбга ўқитиш хизматидан фойдаланган жисмоний шахслар тўғрисидаги маълумотлар | N24: {"params": [{"type": "string", "child": false, "field": "parent_structure", "name_cr": "parent_structure", "name_en": "parent_structure", "name_ru": "parent_structure", "name_uz": "parent_structure"}, {"type": "string", "child": false, "field": "structure", "name_cr": "structure", "name_en": "structure", "name_ru": "structure", "name_uz": "structure"}, {"type": "string", "child": false, "field": "soato", "name_cr": "soato", "name_en": "soato", "name_ru": "soato", "name_uz": "soato"}, {"type": "string", "child": false, "field": "sector", "name_cr": "sector", "name_en": "sector", "name_ru": "sector", "name_uz": "sector"}, {"type": "string", "child": false, "field": "makhalla", "name_cr": "makhalla", "name_en": "makhalla", "name_ru": "makhalla", "name_uz": "makhalla"}, {"type": "string", "child": false, "field": "date_from", "name_cr": "date_from", "name_en": "date_from", "name_ru": "date_from", "name_uz": "date_from"}, {"type": "string", "child": false, "field": "date_to", "name_cr": "date_to", "name_en": "date_to", "name_ru": "date_to", "name_uz": "date_to"}, {"type": "string", "child": false, "field": "full_name", "name_cr": "full_name", "name_en": "full_name", "name_ru": "full_name", "name_uz": "full_name"}, {"type": "string", "child": false, "field": "type", "name_cr": "type", "name_en": "type", "name_ru": "type", "name_uz": "type"}, {"type": "string", "child": false, "field": "service_result", "name_cr": "service_result", "name_en": "service_result", "name_ru": "service_result", "name_uz": "service_result"}, {"type": "string", "child": false, "field": "birth_date", "name_cr": "birth_date", "name_en": "birth_date", "name_ru": "birth_date", "name_uz": "birth_date"}, {"type": "string", "child": false, "field": "passport", "name_cr": "passport", "name_en": "passport", "name_ru": "passport", "name_uz": "passport"}, {"type": "string", "child": false, "field": "pin", "name_cr": "pin", "name_en": "pin", "name_ru": "pin", "name_uz": "pin"}, {"type": "string", "child": false, "field": "gender", "name_cr": "gender", "name_en": "gender", "name_ru": "gender", "name_uz": "gender"}, {"type": "string", "child": false, "field": "phone", "name_cr": "phone", "name_en": "phone", "name_ru": "phone", "name_uz": "phone"}, {"type": "string", "child": false, "field": "scholarship", "name_cr": "scholarship", "name_en": "scholarship", "name_ru": "scholarship", "name_uz": "scholarship"}, {"type": "string", "child": false, "field": "service_date", "name_cr": "service_date", "name_en": "service_date", "name_ru": "service_date", "name_uz": "service_date"}, {"type": "string", "child": false, "field": "institution_name", "name_cr": "institution_name", "name_en": "institution_name", "name_ru": "institution_name", "name_uz": "institution_name"}, {"type": "string", "child": false, "field": "institution_tin", "name_cr": "institution_tin", "name_en": "institution_tin", "name_ru": "institution_tin", "name_uz": "institution_tin"}, {"type": "string", "child": false, "field": "institution_address", "name_cr": "institution_address", "name_en": "institution_address", "name_ru": "institution_address", "name_uz": "institution_address"}, {"type": "string", "child": false, "field": "direction", "name_cr": "direction", "name_en": "direction", "name_ru": "direction", "name_uz": "direction"}, {"type": "string", "child": false, "field": "period", "name_cr": "period", "name_en": "period", "name_ru": "period", "name_uz": "period"}]}
A25: =MAX(A$2:A24)+1 -> 19 | B25: Jamoat ishlarida band bo‘lganlar to‘g‘risidagi ma’lumotlar. | D25: 1 | E25: кунлик | H25: subsidy.public_workers_list | J25: https://10.190.2.81/api/account-chamber/public-workers-list | K25: Камбағалликни қисқартириш ва бандлик вазирлиги | L25: Жамоат ишларида банд бўлганлар тўғрисидаги маълумотлар | M25: Ҳақ тўланадиган жамоат ишларига жалб қилиш (жамоат ишларида банд бўлганлар тўғрисидаги маълумотлар) | N25: {"params": [{"type": "string", "child": false, "field": "ID", "name_cr": "ID", "name_en": "ID", "name_ru": "ID", "name_uz": "ID"}, {"type": "string", "child": false, "field": "region_name", "name_cr": "region_name", "name_en": "region_name", "name_ru": "region_name", "name_uz": "region_name"}, {"type": "string", "child": false, "field": "region_soato", "name_cr": "region_soato", "name_en": "region_soato", "name_ru": "region_soato", "name_uz": "region_soato"}, {"type": "string", "child": false, "field": "district_name", "name_cr": "district_name", "name_en": "district_name", "name_ru": "district_name", "name_uz": "district_name"}, {"type": "string", "child": false, "field": "city_soato", "name_cr": "city_soato", "name_en": "city_soato", "name_ru": "city_soato", "name_uz": "city_soato"}, {"type": "string", "child": false, "field": "company_tin", "name_cr": "company_tin", "name_en": "company_tin", "name_ru": "company_tin", "name_uz": "company_tin"}, {"type": "string", "child": false, "field": "company_name", "name_cr": "company_name", "name_en": "company_name", "name_ru": "company_name", "name_uz": "company_name"}, {"type": "string", "child": false, "field": "passport", "name_cr": "passport", "name_en": "passport", "name_ru": "passport", "name_uz": "passport"}, {"type": "string", "child": false, "field": "tin", "name_cr": "tin", "name_en": "tin", "name_ru": "tin", "name_uz": "tin"}, {"type": "string", "child": false, "field": "pin", "name_cr": "pin", "name_en": "pin", "name_ru": "pin", "name_uz": "pin"}, {"type": "string", "child": false, "field": "phone", "name_cr": "phone", "name_en": "phone", "name_ru": "phone", "name_uz": "phone"}, {"type": "string", "child": false, "field": "gender", "name_cr": "gender", "name_en": "gender", "name_ru": "gender", "name_uz": "gender"}, {"type": "string", "child": false, "field": "birth_date", "name_cr": "birth_date", "name_en": "birth_date", "name_ru": "birth_date", "name_uz": "birth_date"}, {"type": "string", "child": false, "field": "salary", "name_cr": "salary", "name_en": "salary", "name_ru": "salary", "name_uz": "salary"}, {"type": "string", "child": false, "field": "start_date", "name_cr": "start_date", "name_en": "start_date", "name_ru": "start_date", "name_uz": "start_date"}, {"type": "string", "child": false, "field": "end_date", "name_cr": "end_date", "name_en": "end_date", "name_ru": "end_date", "name_uz": "end_date"}, {"type": "string", "child": false, "field": "attended_sdate", "name_cr": "attended_sdate", "name_en": "attended_sdate", "name_ru": "attended_sdate", "name_uz": "attended_sdate"}, {"type": "string", "child": false, "field": "fullname", "name_cr": "fullname", "name_en": "fullname", "name_ru": "fullname", "name_uz": "fullname"}, {"type": "string", "child": false, "field": "company_type", "name_cr": "company_type", "name_en": "company_type", "name_ru": "company_type", "name_uz": "company_type"}, {"type": "string", "child": false, "field": "activity", "name_cr": "activity", "name_en": "activity", "name_ru": "activity", "name_uz": "activity"}, {"type": "string", "child": false, "field": "attended_edate", "name_cr": "attended_edate", "name_en": "attended_edate", "name_ru": "attended_edate", "name_uz": "attended_edate"}, {"type": "string", "child": false, "field": "age", "name_cr": "age", "name_en": "age", "name_ru": "age", "name_uz": "age"}]}
A26: =MAX(A$2:A25)+1 -> 20 | B26: Ishsizlik nafaqasini olayotgan fuqarolar to‘g‘risidagi ma’lumotlar. | D26: 1 | E26: кунлик | H26: subsidy.unemployment_list | J26: https://10.190.2.81/api/account-chamber/unemployment-list | K26: Камбағалликни қисқартириш ва бандлик вазирлиги | L26: Ишсизлик нафақасини олаётган фуқаролар тўғрисидаги маълумотлар | M26: Ишсизлик нафақасини олаётган фуқаролар тўғрисидаги маълумотлар | N26: {"params": [{"type": "str", "child": false, "field": "birth_date", "name_cr": "Tug‘ilgan sanasi", "name_en": "Tug‘ilgan sanasi", "name_ru": "Tug‘ilgan sanasi", "name_uz": "Tug‘ilgan sanasi"}, {"type": "str", "child": false, "field": "continued_date", "name_cr": "Davom ettirilgan sanasi", "name_en": "Davom ettirilgan sanasi", "name_ru": "Davom ettirilgan sanasi", "name_uz": "Davom ettirilgan sanasi"}, {"type": "str", "child": false, "field": "date_from", "name_cr": "Nafaqa muddati boshlanish sanasi (dan)", "name_en": "Nafaqa muddati boshlanish sanasi (dan)", "name_ru": "Nafaqa muddati boshlanish sanasi (dan)", "name_uz": "Nafaqa muddati boshlanish sanasi (dan)"}, {"type": "str", "child": false, "field": "date_to", "name_cr": "Nafaqa muddati tugash sanasi (gacha)", "name_en": "Nafaqa muddati tugash sanasi (gacha)", "name_ru": "Nafaqa muddati tugash sanasi (gacha)", "name_uz": "Nafaqa muddati tugash sanasi (gacha)"}, {"type": "str", "child": false, "field": "full_name", "name_cr": "F.I.O", "name_en": "F.I.O", "name_ru": "F.I.O", "name_uz": "F.I.O"}, {"type": "str", "child": false, "field": "gender", "name_cr": "Jinsi", "name_en": "Jinsi", "name_ru": "Jinsi", "name_uz": "Jinsi"}, {"type": "str", "child": false, "field": "makhalla", "name_cr": "Mahalla nomi", "name_en": "Mahalla nomi", "name_ru": "Mahalla nomi", "name_uz": "Mahalla nomi"}, {"type": "str", "child": false, "field": "parent_structure", "name_cr": "Hudud", "name_en": "Hudud", "name_ru": "Hudud", "name_uz": "Hudud"}, {"type": "str", "child": false, "field": "parent_structure", "name_cr": "Hudud", "name_en": "Hudud", "name_ru": "Hudud", "name_uz": "Hudud"}, {"type": "str", "child": false, "field": "passport", "name_cr": "Pasport seriya va raqami", "name_en": "Pasport seriya va raqami", "name_ru": "Pasport seriya va raqami", "name_uz": "Pasport seriya va raqami"}, {"type": "str", "child": false, "field": "paused_date", "name_cr": "Vaqtincha to‘xtatilgan sana", "name_en": "Vaqtincha to‘xtatilgan sana", "name_ru": "Vaqtincha to‘xtatilgan sana", "name_uz": "Vaqtincha to‘xtatilgan sana"}, {"type": "str", "child": false, "field": "paused_reason", "name_cr": "Vaqtincha to‘xtatish sababi", "name_en": "Vaqtincha to‘xtatish sababi", "name_ru": "Vaqtincha to‘xtatish sababi", "name_uz": "Vaqtincha to‘xtatish sababi"}, {"type": "str", "child": false, "field": "payment_summ", "name_cr": "Nafaqa miqdori", "name_en": "Nafaqa miqdori", "name_ru": "Nafaqa miqdori", "name_uz": "Nafaqa miqdori"}, {"type": "str", "child": false, "field": "phone", "name_cr": "Telefon raqami", "name_en": "Telefon raqami", "name_ru": "Telefon raqami", "name_uz": "Telefon raqami"}, {"type": "str", "child": false, "field": "pin", "name_cr": "JSHSHIR", "name_en": "JSHSHIR", "name_ru": "JSHSHIR", "name_uz": "JSHSHIR"}, {"type": "str", "child": false, "field": "sector", "name_cr": "Tuman sektor raqami", "name_en": "Tuman sektor raqami", "name_ru": "Tuman sektor raqami", "name_uz": "Tuman sektor raqami"}, {"type": "str", "child": false, "field": "service_date", "name_cr": "Xizmat yaratilgan (ko‘rsatilgan) sana", "name_en": "Xizmat yaratilgan (ko‘rsatilgan) sana", "name_ru": "Xizmat yaratilgan (ko‘rsatilgan) sana", "name_uz": "Xizmat yaratilgan (ko‘rsatilgan) sana"}, {"type": "str", "child": false, "field": "service_result", "name_cr": "Xizmat holati (hozirgi vaqtda)", "name_en": "Xizmat holati (hozirgi vaqtda)", "name_ru": "Xizmat holati (hozirgi vaqtda)", "name_uz": "Xizmat holati (hozirgi vaqtda)"}, {"type": "str", "child": false, "field": "soato", "name_cr": "Tuman (shahar) SOATO kodi", "name_en": "Tuman (shahar) SOATO kodi", "name_ru": "Tuman (shahar) SOATO kodi", "name_uz": "Tuman (shahar) SOATO kodi"}, {"type": "str", "child": false, "field": "stopped_reason", "name_cr": "Tugatilish sababi", "name_en": "Tugatilish sababi", "name_ru": "Tugatilish sababi", "name_uz": "Tugatilish sababi"}, {"type": "str", "child": false, "field": "structure", "name_cr": "Tuman (shahar)", "name_en": "Tuman (shahar)", "name_ru": "Tuman (shahar)", "name_uz": "Tuman (shahar)"}]}
A27: =MAX(A$2:A26)+1 -> 21 | B27: Tijorat maqsadida subsidiya olgan fuqarolar ma’lumotlari. | D27: 1 | E27: кунлик | H27: subsidy.phys_subsidies_list | J27: https://10.190.2.81/api/account-chamber/phys-subsidies-list | K27: Камбағалликни қисқартириш ва бандлик вазирлиги | L27: Субсидия олган фуқаролар тўғрисидаги маълумотлар | M27: Субсидия олган фуқаролар тўғрисидаги маълумотлар | N27: {"params": [{"type": "str", "child": false, "field": "region_name", "name_cr": "Hudud (viloyat) nomi", "name_en": "Hudud (viloyat) nomi", "name_ru": "Hudud (viloyat) nomi", "name_uz": "Hudud (viloyat) nomi"}, {"type": "str", "child": false, "field": "region_soato", "name_cr": "Hudud (viloyat) SOATO kodi", "name_en": "Hudud (viloyat) SOATO kodi", "name_ru": "Hudud (viloyat) SOATO kodi", "name_uz": "Hudud (viloyat) SOATO kodi"}, {"type": "str", "child": false, "field": "district_name", "name_cr": "Tuman (shahar) nomi", "name_en": "Tuman (shahar) nomi", "name_ru": "Tuman (shahar) nomi", "name_uz": "Tuman (shahar) nomi"}, {"type": "str", "child": false, "field": "city_soato", "name_cr": "Tuman (shahar) SOATO kodi", "name_en": "Tuman (shahar) SOATO kodi", "name_ru": "Tuman (shahar) SOATO kodi", "name_uz": "Tuman (shahar) SOATO kodi"}, {"type": "str", "child": false, "field": "bdate", "name_cr": "Tug'ilgan sanasi", "name_en": "Tug'ilgan sanasi", "name_ru": "Tug'ilgan sanasi", "name_uz": "Tug'ilgan sanasi"}, {"type": "str", "child": false, "field": "inn", "name_cr": "INN", "name_en": "INN", "name_ru": "INN", "name_uz": "INN"}, {"type": "str", "child": false, "field": "pinfl", "name_cr": "JShShIR", "name_en": "JShShIR", "name_ru": "JShShIR", "name_uz": "JShShIR"}, {"type": "str", "child": false, "field": "sex", "name_cr": "Jinsi (1-erkak 2-ayol)", "name_en": "Jinsi (1-erkak 2-ayol)", "name_ru": "Jinsi (1-erkak 2-ayol)", "name_uz": "Jinsi (1-erkak 2-ayol)"}, {"type": "str", "child": false, "field": "fname", "name_cr": "Familiya", "name_en": "Familiya", "name_ru": "Familiya", "name_uz": "Familiya"}, {"type": "str", "child": false, "field": "lname", "name_cr": "Ism", "name_en": "Ism", "name_ru": "Ism", "name_uz": "Ism"}, {"type": "str", "child": false, "field": "mname", "name_cr": "Sharifi", "name_en": "Sharifi", "name_ru": "Sharifi", "name_uz": "Sharifi"}, {"type": "str", "child": false, "field": "psdata", "name_cr": "Passport raqami", "name_en": "Passport raqami", "name_ru": "Passport raqami", "name_uz": "Passport raqami"}, {"type": "str", "child": false, "field": "subsidiya_name", "name_cr": "Subsidiya turi", "name_en": "Subsidiya turi", "name_ru": "Subsidiya turi", "name_uz": "Subsidiya turi"}, {"type": "str", "child": false, "field": "subsidiya_date", "name_cr": "Subsidiya ajratilgan sana", "name_en": "Subsidiya ajratilgan sana", "name_ru": "Subsidiya ajratilgan sana", "name_uz": "Subsidiya ajratilgan sana"}, {"type": "str", "child": false, "field": "subsidiya_summa", "name_cr": "Ajratilgan summa miqdori", "name_en": "Ajratilgan summa miqdori", "name_ru": "Ajratilgan summa miqdori", "name_uz": "Ajratilgan summa miqdori"}]}
A28: =MAX(A$2:A27)+1 -> 22 | B28: Tijorat maqsadida subsidiya olgan tashkilot ma’lumotlari. | D28: 1 | E28: кунлик | H28: subsidy.yur_subsidies_list | J28: https://10.190.2.81/api/account-chamber/yur-subsidies-list | K28: Камбағалликни қисқартириш ва бандлик вазирлиги | L28: Субсидия олган ташкилот тўғрисидаги маълумотлар | M28: Субсидия олган ташкилот тўғрисидаги маълумотлар | N28: {"params": [{"type": "str", "child": false, "field": "region_name", "name_cr": "Hudud (viloyat) nomi", "name_en": "Hudud (viloyat) nomi", "name_ru": "Hudud (viloyat) nomi", "name_uz": "Hudud (viloyat) nomi"}, {"type": "str", "child": false, "field": "region_soato", "name_cr": "Hudud (viloyat) SOATO kodi", "name_en": "Hudud (viloyat) SOATO kodi", "name_ru": "Hudud (viloyat) SOATO kodi", "name_uz": "Hudud (viloyat) SOATO kodi"}, {"type": "str", "child": false, "field": "district_name", "name_cr": "Tuman (shahar) nomi", "name_en": "Tuman (shahar) nomi", "name_ru": "Tuman (shahar) nomi", "name_uz": "Tuman (shahar) nomi"}, {"type": "str", "child": false, "field": "city_soato", "name_cr": "Tuman (shahar) SOATO kodi", "name_en": "Tuman (shahar) SOATO kodi", "name_ru": "Tuman (shahar) SOATO kodi", "name_uz": "Tuman (shahar) SOATO kodi"}, {"type": "str", "child": false, "field": "subsidy_date", "name_cr": "Subsidiya ajratilgan sana", "name_en": "Subsidiya ajratilgan sana", "name_ru": "Subsidiya ajratilgan sana", "name_uz": "Subsidiya ajratilgan sana"}, {"type": "str", "child": false, "field": "company_tin", "name_cr": "Korxona STIR", "name_en": "Korxona STIR", "name_ru": "Korxona STIR", "name_uz": "Korxona STIR"}, {"type": "str", "child": false, "field": "company_name", "name_cr": "Korxona nomi", "name_en": "Korxona nomi", "name_ru": "Korxona nomi", "name_uz": "Korxona nomi"}, {"type": "str", "child": false, "field": "subsidy_name", "name_cr": "Subsidiya turi", "name_en": "Subsidiya turi", "name_ru": "Subsidiya turi", "name_uz": "Subsidiya turi"}, {"type": "str", "child": false, "field": "subsidy_amount", "name_cr": "Ajratilgan subsidiya miqdori", "name_en": "Ajratilgan subsidiya miqdori", "name_ru": "Ajratilgan subsidiya miqdori", "name_uz": "Ajratilgan subsidiya miqdori"}]}
A29: =MAX(A$2:A28)+1 -> 23 | B29: Ҳунармандларга шогирд тайёрлаш учун субсидия | D29: 1 | E29: кунлик | H29: subsidy.for_student_training | J29: https://10.190.2.81/api/account-chamber/master-craftsman-list/for-student-training | K29: Камбағалликни қисқартириш ва бандлик вазирлиги | L29: Ҳунармандларга шогирд тайёрлаш учун субсидия | M29: Ҳунармандларга шогирд тайёрлаш учун субсидия | N29: {"params": [{"type": "string", "child": false, "field": "region_name", "name_cr": "region_name", "name_en": "region_name", "name_ru": "region_name", "name_uz": "region_name"}, {"type": "string", "child": false, "field": "region_soato", "name_cr": "region_soato", "name_en": "region_soato", "name_ru": "region_soato", "name_uz": "region_soato"}, {"type": "string", "child": false, "field": "district_name", "name_cr": "district_name", "name_en": "district_name", "name_ru": "district_name", "name_uz": "district_name"}, {"type": "string", "child": false, "field": "city_soato", "name_cr": "city_soato", "name_en": "city_soato", "name_ru": "city_soato", "name_uz": "city_soato"}, {"type": "string", "child": false, "field": "bdate", "name_cr": "bdate", "name_en": "bdate", "name_ru": "bdate", "name_uz": "bdate"}, {"type": "string", "child": false, "field": "psdata", "name_cr": "psdata", "name_en": "psdata", "name_ru": "psdata", "name_uz": "psdata"}, {"type": "string", "child": false, "field": "inn", "name_cr": "inn", "name_en": "inn", "name_ru": "inn", "name_uz": "inn"}, {"type": "string", "child": false, "field": "pinfl", "name_cr": "pinfl", "name_en": "pinfl", "name_ru": "pinfl", "name_uz": "pinfl"}, {"type": "string", "child": false, "field": "sex", "name_cr": "sex", "name_en": "sex", "name_ru": "sex", "name_uz": "sex"}, {"type": "string", "child": false, "field": "full_name", "name_cr": "full_name", "name_en": "full_name", "name_ru": "full_name", "name_uz": "full_name"}, {"type": "string", "child": false, "field": "subsidy_amount", "name_cr": "subsidy_amount", "name_en": "subsidy_amount", "name_ru": "subsidy_amount", "name_uz": "subsidy_amount"}, {"type": "string", "child": false, "field": "subsidy_date", "name_cr": "subsidy_date", "name_en": "subsidy_date", "name_ru": "subsidy_date", "name_uz": "subsidy_date"}, {"type": "string", "child": false, "field": "subsidy_name", "name_cr": "subsidy_name", "name_en": "subsidy_name", "name_ru": "subsidy_name", "name_uz": "subsidy_name"}]}
A30: =MAX(A$2:A29)+1 -> 24 | B30: Ҳунармандларга интернет сайтини яратиш учун субсидия | D30: 1 | E30: кунлик | H30: subsidy.for_web_sites | J30: https://10.190.2.81/api/account-chamber/master-craftsman-list/for-web-sites | K30: Камбағалликни қисқартириш ва бандлик вазирлиги | L30: Ҳунармандларга интернет сайтини яратиш учун субсидия | M30: Ҳунармандларга интернет сайтини яратиш учун субсидия | N30: {"params": [{"type": "string", "child": false, "field": "region_name", "name_cr": "region_name", "name_en": "region_name", "name_ru": "region_name", "name_uz": "region_name"}, {"type": "string", "child": false, "field": "region_soato", "name_cr": "region_soato", "name_en": "region_soato", "name_ru": "region_soato", "name_uz": "region_soato"}, {"type": "string", "child": false, "field": "district_name", "name_cr": "district_name", "name_en": "district_name", "name_ru": "district_name", "name_uz": "district_name"}, {"type": "string", "child": false, "field": "city_soato", "name_cr": "city_soato", "name_en": "city_soato", "name_ru": "city_soato", "name_uz": "city_soato"}, {"type": "string", "child": false, "field": "bdate", "name_cr": "bdate", "name_en": "bdate", "name_ru": "bdate", "name_uz": "bdate"}, {"type": "string", "child": false, "field": "psdata", "name_cr": "psdata", "name_en": "psdata", "name_ru": "psdata", "name_uz": "psdata"}, {"type": "string", "child": false, "field": "inn", "name_cr": "inn", "name_en": "inn", "name_ru": "inn", "name_uz": "inn"}, {"type": "string", "child": false, "field": "pinfl", "name_cr": "pinfl", "name_en": "pinfl", "name_ru": "pinfl", "name_uz": "pinfl"}, {"type": "string", "child": false, "field": "sex", "name_cr": "sex", "name_en": "sex", "name_ru": "sex", "name_uz": "sex"}, {"type": "string", "child": false, "field": "full_name", "name_cr": "full_name", "name_en": "full_name", "name_ru": "full_name", "name_uz": "full_name"}, {"type": "string", "child": false, "field": "subsidy_amount", "name_cr": "subsidy_amount", "name_en": "subsidy_amount", "name_ru": "subsidy_amount", "name_uz": "subsidy_amount"}, {"type": "string", "child": false, "field": "subsidy_date", "name_cr": "subsidy_date", "name_en": "subsidy_date", "name_ru": "subsidy_date", "name_uz": "subsidy_date"}, {"type": "string", "child": false, "field": "subsidy_name", "name_cr": "subsidy_name", "name_en": "subsidy_name", "name_ru": "subsidy_name", "name_uz": "subsidy_name"}]}
A31: =MAX(A$2:A30)+1 -> 25 | B31: Ишлаб чиқариш бирлашмаси (кооператив) аъзолигига олинган ҳар бир аъзо учун субсидия олиш | D31: 1 | E31: кунлик | H31: subsidy.coop_subsidies | J31: https://10.190.2.81/api/account-chamber/coop-subsidies | K31: Камбағалликни қисқартириш ва бандлик вазирлиги | L31: Ишлаб чиқариш бирлашмаси (кооператив) аъзолигига олинган ҳар бир аъзо учун субсидия олиш | M31: Ишлаб чиқариш бирлашмаси (кооператив) аъзолигига олинган ҳар бир аъзо учун субсидия олиш | N31: {"params": [{"type": "string", "child": false, "field": "region_name", "name_cr": "region_name", "name_en": "region_name", "name_ru": "region_name", "name_uz": "region_name"}, {"type": "string", "child": false, "field": "region_soato", "name_cr": "region_soato", "name_en": "region_soato", "name_ru": "region_soato", "name_uz": "region_soato"}, {"type": "string", "child": false, "field": "district_name", "name_cr": "district_name", "name_en": "district_name", "name_ru": "district_name", "name_uz": "district_name"}, {"type": "string", "child": false, "field": "city_soato", "name_cr": "city_soato", "name_en": "city_soato", "name_ru": "city_soato", "name_uz": "city_soato"}, {"type": "string", "child": false, "field": "subsidy_date", "name_cr": "subsidy_date", "name_en": "subsidy_date", "name_ru": "subsidy_date", "name_uz": "subsidy_date"}, {"type": "string", "child": false, "field": "company_tin", "name_cr": "company_tin", "name_en": "company_tin", "name_ru": "company_tin", "name_uz": "company_tin"}, {"type": "string", "child": false, "field": "company_name", "name_cr": "company_name", "name_en": "company_name", "name_ru": "company_name", "name_uz": "company_name"}, {"type": "string", "child": false, "field": "subsidy_name", "name_cr": "subsidy_name", "name_en": "subsidy_name", "name_ru": "subsidy_name", "name_uz": "subsidy_name"}, {"type": "string", "child": false, "field": "subsidy_amount", "name_cr": "subsidy_amount", "name_en": "subsidy_amount", "name_ru": "subsidy_amount", "name_uz": "subsidy_amount"}]}
A32: =MAX(A$2:A31)+1 -> 26 | B32: Эскпортни рағбатлантириш агентлиги Экспортчи корхоналар учун ажратилган субсидиялар тўғрисидаги маъл | D32: 1 | E32: ойлик | H32: subsidy.credits | J32: https://apiapply.epauzb.uz/api/v1/integration/requests/credit | K32: Камбағалликни қисқартириш ва бандлик вазирлиги | L32: Экспортни рағбатлантириш агентлиги томонидан тижорат банкларига тақдим этилган молиявий ресурсларнинг ажратилиши бўйича маълумотлар | M32: Экспортни рағбатлантириш агентлиги томонидан тижорат банкларига тақдим этилган молиявий ресурсларнинг ажратилиши бўйича маълумотлар | N32: {"params": [{"type": "string", "child": false, "field": "application_id", "name_cr": "application_id", "name_en": "application_id", "name_ru": "application_id", "name_uz": "application_id"}, {"type": "string", "child": false, "field": "submission_date", "name_cr": "submission_date", "name_en": "submission_date", "name_ru": "submission_date", "name_uz": "submission_date"}, {"type": "string", "child": false, "field": "commission_date", "name_cr": "commission_date", "name_en": "commission_date", "name_ru": "commission_date", "name_uz": "commission_date"}, {"type": "string", "child": false, "field": "company_name", "name_cr": "company_name", "name_en": "company_name", "name_ru": "company_name", "name_uz": "company_name"}, {"type": "string", "child": false, "field": "inn", "name_cr": "inn", "name_en": "inn", "name_ru": "inn", "name_uz": "inn"}, {"type": "string", "child": false, "field": "region", "name_cr": "region", "name_en": "region", "name_ru": "region", "name_uz": "region"}, {"type": "string", "child": false, "field": "district", "name_cr": "district", "name_en": "district", "name_ru": "district", "name_uz": "district"}, {"type": "string", "child": false, "field": "bank_name", "name_cr": "bank_name", "name_en": "bank_name", "name_ru": "bank_name", "name_uz": "bank_name"}, {"type": "string", "child": false, "field": "trading_type_name", "name_cr": "trading_type_name", "name_en": "trading_type_name", "name_ru": "trading_type_name", "name_uz": "trading_type_name"}, {"type": "string", "child": false, "field": "credit_point", "name_cr": "credit_point", "name_en": "credit_point", "name_ru": "credit_point", "name_uz": "credit_point"}, {"type": "string", "child": false, "field": "country_name", "name_cr": "country_name", "name_en": "country_name", "name_ru": "country_name", "name_uz": "country_name"}, {"type": "string", "child": false, "field": "trade_production_type", "name_cr": "trade_production_type", "name_en": "trade_production_type", "name_ru": "trade_production_type", "name_uz": "trade_production_type"}, {"type": "string", "child": false, "field": "credit_resource", "name_cr": "credit_resource", "name_en": "credit_resource", "name_ru": "credit_resource", "name_uz": "credit_resource"}, {"type": "string", "child": false, "field": "credit_sum", "name_cr": "credit_sum", "name_en": "credit_sum", "name_ru": "credit_sum", "name_uz": "credit_sum"}, {"type": "string", "child": false, "field": "credit_expire", "name_cr": "credit_expire", "name_en": "credit_expire", "name_ru": "credit_expire", "name_uz": "credit_expire"}, {"type": "string", "child": false, "field": "export_sum", "name_cr": "export_sum", "name_en": "export_sum", "name_ru": "export_sum", "name_uz": "export_sum"}, {"type": "string", "child": false, "field": "funded_at", "name_cr": "funded_at", "name_en": "funded_at", "name_ru": "funded_at", "name_uz": "funded_at"}, {"type": "list", "child": true, "field": "products", "name_cr": "products", "name_en": "products", "name_ru": "products", "name_uz": "products", "children": [{"type": "string", "child": false, "field": "tncode", "name_cr": "tncode", "name_en": "tncode", "name_ru": "tncode", "name_uz": "tncode"}, {"type": "string", "child": false, "field": "product_name", "name_cr": "product_name", "name_en": "product_name", "name_ru": "product_name", "name_uz": "product_name"}, {"type": "string", "child": false, "field": "contract_id", "name_cr": "contract_id", "name_en": "contract_id", "name_ru": "contract_id", "name_uz": "contract_id"}]}]}
... A45: =MAX(A$2:A44)+1 -> 39 | B45: Ёшлар сиёсати ва спорт вазирлиги: "Ёшлар дафтари"га рўйхатга олинган ҳамда моддий ёрдам олган жами ё | D45: 1 | E45: ойлик | H45: subsidy.yuonger_all_report | J45: https://api.yoshlardaftari.uz/api/v2/hisob-palatasi/statistic-out-notebook-data | K45: Ёшлар ишлари агентлиги | L45: "Ёшлар дафтари"га киритилиб ёрдам олган жами ёшлар тўғрисида маълумотлар | M45: "Ёшлар дафтари"га киритилиб ёрдам олган жами ёшлар тўғрисида маълумотлар | N45: {"params": [{"type": "string", "child": false, "field": "total", "name_cr": "total", "name_en": "total", "name_ru": "total", "name_uz": "total"}, {"type": "string", "child": false, "field": "material_support", "name_cr": "material_support", "name_en": "material_support", "name_ru": "material_support", "name_uz": "material_support"}, {"type": "string", "child": false, "field": "vacational_training", "name_cr": "vacational_training", "name_en": "vacational_training", "name_ru": "vacational_training", "name_uz": "vacational_training"}, {"type": "string", "child": false, "field": "driving_training", "name_cr": "driving_training", "name_en": "driving_training", "name_ru": "driving_training", "name_uz": "driving_training"}, {"type": "string", "child": false, "field": "seeding_subsidy", "name_cr": "seeding_subsidy", "name_en": "seeding_subsidy", "name_ru": "seeding_subsidy", "name_uz": "seeding_subsidy"}, {"type": "string", "child": false, "field": "non_residential_rent", "name_cr": "non_residential_rent", "name_en": "non_residential_rent", "name_ru": "non_residential_rent", "name_uz": "non_residential_rent"}, {"type": "string", "child": false, "field": "equipment_subsidy", "name_cr": "equipment_subsidy", "name_en": "equipment_subsidy", "name_ru": "equipment_subsidy", "name_uz": "equipment_subsidy"}, {"type": "string", "child": false, "field": "edu_contract_subsidy", "name_cr": "edu_contract_subsidy", "name_en": "edu_contract_subsidy", "name_ru": "edu_contract_subsidy", "name_uz": "edu_contract_subsidy"}, {"type": "string", "child": false, "field": "kelajak_kasblari", "name_cr": "kelajak_kasblari", "name_en": "kelajak_kasblari", "name_ru": "kelajak_kasblari", "name_uz": "kelajak_kasblari"}, {"type": "string", "child": false, "field": "training_subsidy", "name_cr": "training_subsidy", "name_en": "training_subsidy", "name_ru": "training_subsidy", "name_uz": "training_subsidy"}, {"type": "string", "child": false, "field": "loc_compet_exp", "name_cr": "loc_compet_exp", "name_en": "loc_compet_exp", "name_ru": "loc_compet_exp", "name_uz": "loc_compet_exp"}, {"type": "string", "child": false, "field": "treatment_expense", "name_cr": "treatment_expense", "name_en": "treatment_expense", "name_ru": "treatment_expense", "name_uz": "treatment_expense"}, {"type": "string", "child": false, "field": "psychological_expense", "name_cr": "psychological_expense", "name_en": "psychological_expense", "name_ru": "psychological_expense", "name_uz": "psychological_expense"}, {"type": "string", "child": false, "field": "schr", "name_cr": "schr", "name_en": "schr", "name_ru": "schr", "name_uz": "schr"}, {"type": "string", "child": false, "field": "credits", "name_cr": "credits", "name_en": "credits", "name_ru": "credits", "name_uz": "credits"}, {"type": "string", "child": false, "field": "residential_rent", "name_cr": "residential_rent", "name_en": "residential_rent", "name_ru": "residential_rent", "name_uz": "residential_rent"}, {"type": "string", "child": false, "field": "employment", "name_cr": "employment", "name_en": "employment", "name_ru": "employment", "name_uz": "employment"}, {"type": "string", "child": false, "field": "entrepreneurship", "name_cr": "entrepreneurship", "name_en": "entrepreneurship", "name_ru": "entrepreneurship", "name_uz": "entrepreneurship"}, {"type": "string", "child": false, "field": "migration", "name_cr": "migration", "name_en": "migration", "name_ru": "migration", "name_uz": "migration"}, {"type": "string", "child": false, "field": "school_uniform", "name_cr": "school_uniform", "name_en": "school_uniform", "name_ru": "school_uniform", "name_uz": "school_uniform"}, {"type": "string", "child": false, "field": "passport_fee", "name_cr": "passport_fee", "name_en": "passport_fee", "name_ru": "passport_fee", "name_uz": "passport_fee"}, {"type": "string", "child": false, "field": "tour_expense", "name_cr": "tour_expense", "name_en": "tour_expense", "name_ru": "tour_expense", "name_uz": "tour_expense"}, {"type": "string", "child": false, "field": "int_compet_exp", "name_cr": "int_compet_exp", "name_en": "int_compet_exp", "name_ru": "int_compet_exp", "name_uz": "int_compet_exp"}, {"type": "string", "child": false, "field": "seperated_land", "name_cr": "seperated_land", "name_en": "seperated_land", "name_ru": "seperated_land", "name_uz": "seperated_land"}]}
A46: =MAX(A$2:A45)+1 -> 40 | B46: Ҳоким ёрдамчилари тавсияси асосида берилган жами субсидиялар тўғрисида маълумот олиш | D46: 1 | E46: кунлик | H46: mahalla.subsidiya | I46: Субсидия схемасига ўтказиб номини хоким ёрдамчи тавсия қилиш керак | J46: https://api.online-mahalla.uz/api/v1/sync/subsidy/hp
A47: =MAX(A$2:A46)+1 -> 41 | B47: Юридик шахсларга ногиронлиги бўлган шахсларни ишга мослаштирганлиги учун субсидия | D47: 1 | E47: кунлик | H47: subsidy.adjustment_jobs | J47: https://10.190.2.81/api/account-chamber/adjustment-jobs | K47: Камбағалликни қисқартириш ва бандлик вазирлиги | L47: Юридик шахсларга ногиронлиги бўлган шахсларни ишга мослаштирганлиги учун субсидия | M47: Юридик шахсларга ногиронлиги бўлган шахсларни ишга мослаштирганлиги учун субсидия | N47: {"params": [{"type": "string", "child": false, "field": "region_name", "name_cr": "region_name", "name_en": "region_name", "name_ru": "region_name", "name_uz": "region_name"}, {"type": "string", "child": false, "field": "region_soato", "name_cr": "region_soato", "name_en": "region_soato", "name_ru": "region_soato", "name_uz": "region_soato"}, {"type": "string", "child": false, "field": "district_name", "name_cr": "district_name", "name_en": "district_name", "name_ru": "district_name", "name_uz": "district_name"}, {"type": "string", "child": false, "field": "city_soato", "name_cr": "city_soato", "name_en": "city_soato", "name_ru": "city_soato", "name_uz": "city_soato"}, {"type": "string", "child": false, "field": "company_tin", "name_cr": "company_tin", "name_en": "company_tin", "name_ru": "company_tin", "name_uz": "company_tin"}, {"type": "string", "child": false, "field": "company_name", "name_cr": "company_name", "name_en": "company_name", "name_ru": "company_name", "name_uz": "company_name"}, {"type": "string", "child": false, "field": "subsidy_date", "name_cr": "subsidy_date", "name_en": "subsidy_date", "name_ru": "subsidy_date", "name_uz": "subsidy_date"}, {"type": "string", "child": false, "field": "subsidy_amount", "name_cr": "subsidy_amount", "name_en": "subsidy_amount", "name_ru": "subsidy_amount", "name_uz": "subsidy_amount"}, {"type": "string", "child": false, "field": "subsidy_name", "name_cr": "subsidy_name", "name_en": "subsidy_name", "name_ru": "subsidy_name", "name_uz": "subsidy_name"}]}
A48: =MAX(A$2:A47)+1 -> 42 | B48: Қишлоқ хўжалиги субъектларига ажратилган субсидиялар тўғрисида маълумот | D48: 1 | E48: ойлик | H48: subsidy.agricultures | J48: https://api.agro.uz/openapi/hisob_palata/fetch-subsidiya | K48: Қишлоқ хўжалиги вазирлиги | L48: Қишлоқ хўжалиги субъектларига ажратилган субсидиялар тўғрисида маълумот | M48: Қишлоқ хўжалиги субъектларига ажратилган субсидиялар тўғрисида маълумот | N48: {"params": [{"type": "string", "child": false, "field": "District_id", "name_cr": "District_id", "name_en": "District_id", "name_ru": "District_id", "name_uz": "District_id"}, {"type": "string", "child": false, "field": "Ekin_turi", "name_cr": "Ekin_turi", "name_en": "Ekin_turi", "name_ru": "Ekin_turi", "name_uz": "Ekin_turi"}, {"type": "string", "child": false, "field": "OrgInn", "name_cr": "OrgInn", "name_en": "OrgInn", "name_ru": "OrgInn", "name_uz": "OrgInn"}, {"type": "string", "child": false, "field": "OrgName", "name_cr": "OrgName", "name_en": "OrgName", "name_ru": "OrgName", "name_uz": "OrgName"}, {"type": "string", "child": false, "field": "Purpose", "name_cr": "Purpose", "name_en": "Purpose", "name_ru": "Purpose", "name_uz": "Purpose"}, {"type": "string", "child": false, "field": "Region_id", "name_cr": "Region_id", "name_en": "Region_id", "name_ru": "Region_id", "name_uz": "Region_id"}, {"type": "string", "child": false, "field": "Status", "name_cr": "Status", "name_en": "Status", "name_ru": "Status", "name_uz": "Status"}, {"type": "string", "child": false, "field": "Summa_mln", "name_cr": "Summa_mln", "name_en": "Summa_mln", "name_ru": "Summa_mln", "name_uz": "Summa_mln"}, {"type": "string", "child": false, "field": "Task_date", "name_cr": "Task_date", "name_en": "Task_date", "name_ru": "Task_date", "name_uz": "Task_date"}, {"type": "string", "child": false, "field": "Task_done_date", "name_cr": "Task_done_date", "name_en": "Task_done_date", "name_ru": "Task_done_date", "name_uz": "Task_done_date"}, {"type": "string", "child": false, "field": "Task_id", "name_cr": "Task_id", "name_en": "Task_id", "name_ru": "Task_id", "name_uz": "Task_id"}, {"type": "string", "child": false, "field": "district", "name_cr": "district", "name_en": "district", "name_ru": "district", "name_uz": "district"}, {"type": "string", "child": false, "field": "province", "name_cr": "province", "name_en": "province", "name_ru": "province", "name_uz": "province"}, {"type": "string", "child": false, "field": "yer_maydoniHajm", "name_cr": "yer_maydoniHajm", "name_en": "yer_maydoniHajm", "name_ru": "yer_maydoniHajm", "name_uz": "yer_maydoniHajm"}]}
A49: =MAX(A$2:A48)+1 -> 43 | B49: "Ёшлар дафтари"га рўйхатга олинган ҳамда моддий ёрдам олган ёшлар тўғрисидаги маълумотлар | D49: 1 | E49: ойлик | H49: subsidy.younger_help | J49: https://api.yoshlardaftari.uz/api/v2/hisob-palatasi/out-notebook-data | K49: Ёшлар ишлари агентлиги | L49: "Ёшлар дафтари"га киритилиб ёрдам олган ёшлар тўғрисида маълумотлар | M49: "Ёшлар дафтари"га киритилиб ёрдам олган ёшлар тўғрисида маълумотлар | N49: {"params": [{"type": "string", "child": false, "field": "id", "name_cr": "id", "name_en": "id", "name_ru": "id", "name_uz": "id"}, {"type": "string", "child": false, "field": "region", "name_cr": "region", "name_en": "region", "name_ru": "region", "name_uz": "region"}, {"type": "string", "child": false, "field": "region_soato", "name_cr": "region_soato", "name_en": "region_soato", "name_ru": "region_soato", "name_uz": "region_soato"}, {"type": "string", "child": false, "field": "city", "name_cr": "city", "name_en": "city", "name_ru": "city", "name_uz": "city"}, {"type": "string", "child": false, "field": "city_soato", "name_cr": "city_soato", "name_en": "city_soato", "name_ru": "city_soato", "name_uz": "city_soato"}, {"type": "string", "child": false, "field": "address", "name_cr": "address", "name_en": "address", "name_ru": "address", "name_uz": "address"}, {"type": "string", "child": false, "field": "surname", "name_cr": "surname", "name_en": "surname", "name_ru": "surname", "name_uz": "surname"}, {"type": "string", "child": false, "field": "firstname", "name_cr": "firstname", "name_en": "firstname", "name_ru": "firstname", "name_uz": "firstname"}, {"type": "string", "child": false, "field": "patronymic", "name_cr": "patronymic", "name_en": "patronymic", "name_ru": "patronymic", "name_uz": "patronymic"}, {"type": "string", "child": false, "field": "birth_date", "name_cr": "birth_date", "name_en": "birth_date", "name_ru": "birth_date", "name_uz": "birth_date"}, {"type": "string", "child": false, "field": "pin", "name_cr": "pin", "name_en": "pin", "name_ru": "pin", "name_uz": "pin"}, {"type": "string", "child": false, "field": "passport", "name_cr": "passport", "name_en": "passport", "name_ru": "passport", "name_uz": "passport"}, {"type": "string", "child": false, "field": "gender", "name_cr": "gender", "name_en": "gender", "name_ru": "gender", "name_uz": "gender"}, {"type": "string", "child": false, "field": "social_status", "name_cr": "social_status", "name_en": "social_status", "name_ru": "social_status", "name_uz": "social_status"}, {"type": "string", "child": false, "field": "reason", "name_cr": "reason", "name_en": "reason", "name_ru": "reason", "name_uz": "reason"}, {"type": "string", "child": false, "field": "enter_date", "name_cr": "enter_date", "name_en": "enter_date", "name_ru": "enter_date", "name_uz": "enter_date"}, {"type": "string", "child": false, "field": "out_date", "name_cr": "out_date", "name_en": "out_date", "name_ru": "out_date", "name_uz": "out_date"}, {"type": "string", "child": false, "field": "help_type", "name_cr": "help_type", "name_en": "help_type", "name_ru": "help_type", "name_uz": "help_type"}, {"type": "string", "child": false, "field": "company_name", "name_cr": "company_name", "name_en": "company_name", "name_ru": "company_name", "name_uz": "company_name"}, {"type": "string", "child": false, "field": "help_source", "name_cr": "help_source", "name_en": "help_source", "name_ru": "help_source", "name_uz": "help_source"}]}
B50: 4. Давлат активлари
A51: =MAX(A$2:A50)+1 -> 44 | B51: Ustav fondida davlat ulushi mavjud xo‘jalik jamiyatlari va davlat korxonalari to‘g‘risidagi ma'lumot | D51: 1 | E51: ойлик | H51: public.gos_active_reestr | I51: ГосАктив схемага ўтказиш | J51: http://10.190.5.2:8675/reestr/v4 | K51: Давлат активларини бошқариш агентлиги | L51: Устав фондида давлат улуши мавжуд хўжалик жамиятлари ва давлат корхоналари тўғрисидаги маълумотлар | M51: Ташкилот СТИР рақами киритилган ҳолда маълумотлар олинади | N51: {"params": [{"type": "string", "child": false, "field": "ID_DOCUMENT", "name_cr": "ID_DOCUMENT", "name_en": "ID_DOCUMENT", "name_ru": "ID_DOCUMENT", "name_uz": "ID_DOCUMENT"}, {"type": "string", "child": false, "field": "SEND_DATE", "name_cr": "SEND_DATE", "name_en": "SEND_DATE", "name_ru": "SEND_DATE", "name_uz": "SEND_DATE"}, {"type": "string", "child": false, "field": "NAME", "name_cr": "NAME", "name_en": "NAME", "name_ru": "NAME", "name_uz": "NAME"}, {"type": "string", "child": false, "field": "NS10", "name_cr": "NS10", "name_en": "NS10", "name_ru": "NS10", "name_uz": "NS10"}, {"type": "string", "child": false, "field": "NS11", "name_cr": "NS11", "name_en": "NS11", "name_ru": "NS11", "name_uz": "NS11"}, {"type": "string", "child": false, "field": "ADDRESS", "name_cr": "ADDRESS", "name_en": "ADDRESS", "name_ru": "ADDRESS", "name_uz": "ADDRESS"}, {"type": "string", "child": false, "field": "TIN", "name_cr": "TIN", "name_en": "TIN", "name_ru": "TIN", "name_uz": "TIN"}, {"type": "string", "child": false, "field": "SHARE1", "name_cr": "SHARE1", "name_en": "SHARE1", "name_ru": "SHARE1", "name_uz": "SHARE1"}, {"type": "string", "child": false, "field": "ORG_TYPE_NAME", "name_cr": "ORG_TYPE_NAME", "name_en": "ORG_TYPE_NAME", "name_ru": "ORG_TYPE_NAME", "name_uz": "ORG_TYPE_NAME"}, {"type": "string", "child": false, "field": "STATUS", "name_cr": "STATUS", "name_en": "STATUS", "name_ru": "STATUS", "name_uz": "STATUS"}]}
A52: =MAX(A$2:A51)+1 -> 45 | B52: Gos Active ijara | D52: 1 | E52: Чораклик | H52: public.ijara_contracts | I52: ГосАктив схемага ўтказиш | J52: http://10.190.34.202:8146/api/get-rent-contract | K52: Давлат активларини бошқариш агентлиги | L52: Ижарага берилган давлат мулклари тўғрисида маълумотлар | M52: Мулкка эгалик қилувчи ташкилот, СТИР рақами киритилган ҳолда маълумотлар олинади | N52: {"params": [{"type": "string", "child": false, "field": "id", "name_cr": "id", "name_en": "id", "name_ru": "id", "name_uz": "id"}, {"type": "string", "child": false, "field": "sent_date", "name_cr": "sent_date", "name_en": "sent_date", "name_ru": "sent_date", "name_uz": "sent_date"}, {"type": "string", "child": false, "field": "contract_number", "name_cr": "contract_number", "name_en": "contract_number", "name_ru": "contract_number", "name_uz": "contract_number"}, {"type": "string", "child": false, "field": "object_region", "name_cr": "object_region", "name_en": "object_region", "name_ru": "object_region", "name_uz": "object_region"}, {"type": "string", "child": false, "field": "object_district", "name_cr": "object_district", "name_en": "object_district", "name_ru": "object_district", "name_uz": "object_district"}, {"type": "string", "child": false, "field": "contract_sum", "name_cr": "contract_sum", "name_en": "contract_sum", "name_ru": "contract_sum", "name_uz": "contract_sum"}, {"type": "string", "child": false, "field": "contract_date", "name_cr": "contract_date", "name_en": "contract_date", "name_ru": "contract_date", "name_uz": "contract_date"}, {"type": "string", "child": false, "field": "owner_name", "name_cr": "owner_name", "name_en": "owner_name", "name_ru": "owner_name", "name_uz": "owner_name"}, {"type": "string", "child": false, "field": "owner_tin", "name_cr": "owner_tin", "name_en": "owner_tin", "name_ru": "owner_tin", "name_uz": "owner_tin"}, {"type": "string", "child": false, "field": "owner_region", "name_cr": "owner_region", "name_en": "owner_region", "name_ru": "owner_region", "name_uz": "owner_region"}, {"type": "string", "child": false, "field": "owner_district", "name_cr": "owner_district", "name_en": "owner_district", "name_ru": "owner_district", "name_uz": "owner_district"}, {"type": "string", "child": false, "field": "owner_address", "name_cr": "owner_address", "name_en": "owner_address", "name_ru": "owner_address", "name_uz": "owner_address"}, {"type": "string", "child": false, "field": "renter_name", "name_cr": "renter_name", "name_en": "renter_name", "name_ru": "renter_name", "name_uz": "renter_name"}, {"type": "string", "child": false, "field": "renter_tin", "name_cr": "renter_tin", "name_en": "renter_tin", "name_ru": "renter_tin", "name_uz": "renter_tin"}, {"type": "string", "child": false, "field": "renter_region", "name_cr": "renter_region", "name_en": "renter_region", "name_ru": "renter_region", "name_uz": "renter_region"}, {"type": "string", "child": false, "field": "renter_district", "name_cr": "renter_district", "name_en": "renter_district", "name_ru": "renter_district", "name_uz": "renter_district"}, {"type": "string", "child": false, "field": "renter_address", "name_cr": "renter_address", "name_en": "renter_address", "name_ru": "renter_address", "name_uz": "renter_address"}, {"type": "string", "child": false, "field": "activity_type_id", "name_cr": "activity_type_id", "name_en": "activity_type_id", "name_ru": "activity_type_id", "name_uz": "activity_type_id"}, {"type": "string", "child": false, "field": "rental_area", "name_cr": "rental_area", "name_en": "rental_area", "name_ru": "rental_area", "name_uz": "rental_area"}]}
B53: 5. Статистика
A54: =MAX(A$2:A53)+1 -> 46 | B54: Statistika saytini Parse qilish | D54: 1 | E54: ойлик | H54: tax.org_info_stat | I54: Статистика схемасига ўтказиш | J54: https://registr.stat.uz
A55: =MAX(A$2:A54)+1 -> 47 | B55: Organization state | D55: 1 | E55: ойлик | H55: info_organization_state | I55: Статистика схемасига ўтказиш | J55: http://10.190.4.11/inps/api/UzRXP/GetSqlQuery
B56: 6. Олий таълим
A57: =MAX(A$2:A56)+1 -> 48 | B57: Talabalrga hisoblangan stipendiyalar | D57: 1 | E57: ойлик | H57: education.student_nach | J57: https://api.hemis.uz/api/university
A58: =MAX(A$2:A57)+1 -> 49 | B58: Student Kontrakt | D58: 1 | E58: ойлик | H58: education.contract | J58: https://api.hemis.uz/api/university
A59: =MAX(A$2:A58)+1 -> 50 | B59: Diplomlar | D59: 1 | E59: ойлик | H59: education.diplom | J59: https://api.hemis.uz/api/university
A60: =MAX(A$2:A59)+1 -> 51 | B60: PHD | D60: 1 | E60: ойлик | H60: education.phd | J60: http://api-phd.mininnovation.uz/api-account-chamber/doctorates
A61: =MAX(A$2:A60)+1 -> 52 | B61: Talabalar ro'yxati | D61: 1 | E61: ойлик | H61: education.student_info | J61: https://api.hemis.uz/api/university
A62: =MAX(A$2:A61)+1 -> 53 | B62: OTM inn va o'qituvchi ilmiy darajasi bo'yicha o'qituvchilar ro'yxatini olish | D62: 1 | E62: ойлик | H62: education.teacher | J62: https://api.hemis.uz/api/university
B63: 7. Спорт
A64: =MAX(A$2:A63)+1 -> 54 | B64: Bolalar sport maktablari to‘g‘risida ma’lumotlar. | D64: 1 | E64: ойлик | H64: sport.organization_info | J64: https://erp-integration.sport.uz/api/v1/hp/HP/OrganizationInfo | K64: Ёшлар сиёсати ва спорт вазирлиги | L64: Болалар спорт мактаблари тўғрисида маълумотлар | M64: Болалар спорт мактаблари тўғрисида маълумотлар | N64: {"params": [{"type": "string", "child": false, "field": "company_profile_name", "name_cr": "company_profile_name"}, {"type": "string", "child": false, "field": "company_tin", "name_cr": "company_tin"}, {"type": "string", "child": false, "field": "pinfl", "name_cr": "pinfl"}, {"type": "string", "child": false, "field": "fullname", "name_cr": "fullname"}, {"type": "string", "child": false, "field": "birth_date", "name_cr": "birth_date"}, {"type": "string", "child": false, "field": "date_start", "name_cr": "date_start"}, {"type": "string", "child": false, "field": "date_stop", "name_cr": "date_stop"}, {"type": "string", "child": false, "field": "id", "name_cr": "id"}, {"type": "string", "child": false, "field": "order_date", "name_cr": "order_date"}, {"type": "string", "child": false, "field": "order_number", "name_cr": "order_number"}, {"type": "string", "child": false, "field": "parent_id", "name_cr": "parent_id"}, {"type": "string", "child": false, "field": "position_name", "name_cr": "position_name"}, {"type": "string", "child": false, "field": "position_name_ru", "name_cr": "position_name_ru"}, {"type": "string", "child": false, "field": "structure_name", "name_cr": "structure_name"}, {"type": "string", "child": false, "field": "structure_name_ru", "name_cr": "structure_name_ru"}, {"type": "string", "child": false, "field": "work_type", "name_cr": "work_type"}, {"type": "string", "child": false, "field": "kodp_pn", "name_cr": "kodp_pn"}, {"type": "string", "child": false, "field": "kodp_nskz_code", "name_cr": "kodp_nskz_code"}, {"type": "string", "child": false, "field": "kodp_personal_category", "name_cr": "kodp_personal_category"}, {"type": "string", "child": false, "field": "kodp_min_education", "name_cr": "kodp_min_education"}, {"type": "string", "child": false, "field": "classifier_name_uz", "name_cr": "classifier_name_uz"}, {"type": "string", "child": false, "field": "classifier_name_ru", "name_cr": "classifier_name_ru"}]}
A65: =MAX(A$2:A64)+1 -> 55 | B65: “ERP” tizimidagi o‘qituvchi pedagoglar to‘g‘risidagi ma’lumotlar. | D65: 1 | E65: ойлик | H65: sport.employee_info | J65: https://erp-integration.sport.uz/api/v1/hp/HP/GetEmployeeInfo | K65: Ёшлар сиёсати ва спорт вазирлиги | L65: “ЕРП” тизимидаги ўқитувчи педагоглар тўғрисидаги маълумотлар | M65: “ЕРП” тизимидаги ўқитувчи педагоглар тўғрисидаги маълумотлар | N65: {"params": [{"type": "string", "child": false, "field": "organizationoblast", "name_cr": "organizationoblast", "name_en": "organizationoblast", "name_ru": "organizationoblast", "name_uz": "organizationoblast"}, {"type": "string", "child": false, "field": "organizationregion", "name_cr": "organizationregion", "name_en": "organizationregion", "name_ru": "organizationregion", "name_uz": "organizationregion"}, {"type": "string", "child": false, "field": "organizationaddress", "name_cr": "organizationaddress", "name_en": "organizationaddress", "name_ru": "organizationaddress", "name_uz": "organizationaddress"}, {"type": "string", "child": false, "field": "id", "name_cr": "id", "name_en": "id", "name_ru": "id", "name_uz": "id"}, {"type": "string", "child": false, "field": "organizationname", "name_cr": "organizationname", "name_en": "organizationname", "name_ru": "organizationname", "name_uz": "organizationname"}, {"type": "string", "child": false, "field": "organizationinn", "name_cr": "organizationinn", "name_en": "organizationinn", "name_ru": "organizationinn", "name_uz": "organizationinn"}, {"type": "string", "child": false, "field": "pinfl", "name_cr": "pinfl", "name_en": "pinfl", "name_ru": "pinfl", "name_uz": "pinfl"}, {"type": "string", "child": false, "field": "pasportsn", "name_cr": "pasportsn", "name_en": "pasportsn", "name_ru": "pasportsn", "name_uz": "pasportsn"}, {"type": "string", "child": false, "field": "familyname", "name_cr": "familyname", "name_en": "familyname", "name_ru": "familyname", "name_uz": "familyname"}, {"type": "string", "child": false, "field": "firstname", "name_cr": "firstname", "name_en": "firstname", "name_ru": "firstname", "name_uz": "firstname"}, {"type": "string", "child": false, "field": "lastname", "name_cr": "lastname", "name_en": "lastname", "name_ru": "lastname", "name_uz": "lastname"}, {"type": "string", "child": false, "field": "liveoblastname", "name_cr": "liveoblastname", "name_en": "liveoblastname", "name_ru": "liveoblastname", "name_uz": "liveoblastname"}, {"type": "string", "child": false, "field": "liveregionname", "name_cr": "liveregionname", "name_en": "liveregionname", "name_ru": "liveregionname", "name_uz": "liveregionname"}, {"type": "string", "child": false, "field": "adress", "name_cr": "adress", "name_en": "adress", "name_ru": "adress", "name_uz": "adress"}, {"type": "string", "child": false, "field": "contractdate", "name_cr": "contractdate", "name_en": "contractdate", "name_ru": "contractdate", "name_uz": "contractdate"}, {"type": "string", "child": false, "field": "qualcategory", "name_cr": "qualcategory", "name_en": "qualcategory", "name_ru": "qualcategory", "name_uz": "qualcategory"}, {"type": "string", "child": false, "field": "employmentrate", "name_cr": "employmentrate", "name_en": "employmentrate", "name_ru": "employmentrate", "name_uz": "employmentrate"}, {"type": "string", "child": false, "field": "positionname", "name_cr": "positionname", "name_en": "positionname", "name_ru": "positionname", "name_uz": "positionname"}, {"type": "list", "child": true, "field": "qualificationcategory", "name_cr": "qualificationcategory", "name_en": "qualificationcategory", "name_ru": "qualificationcategory", "name_uz": "qualificationcategory", "children": [{"type": "string", "child": false, "field": "docnumber", "name_cr": "docnumber", "name_en": "docnumber", "name_ru": "docnumber", "name_uz": "docnumber"}, {"type": "string", "child": false, "field": "docdate", "name_cr": "docdate", "name_en": "docdate", "name_ru": "docdate", "name_uz": "docdate"}, {"type": "string", "child": false, "field": "startdate", "name_cr": "startdate", "name_en": "startdate", "name_ru": "startdate", "name_uz": "startdate"}, {"type": "string", "child": false, "field": "enddate", "name_cr": "enddate", "name_en": "enddate", "name_ru": "enddate", "name_uz": "enddate"}]}]}
A66: =MAX(A$2:A65)+1 -> 56 | B66: Trenerlarga berilgan malaka sertifikati bo‘yicha ma’lumotlar. | D66: 1 | E66: ойлик | H66: sport.trener_app_qual_category | J66: https://erp-integration.sport.uz/api/v1/hp/HP/GetTrenerAppQualCategory | K66: Ёшлар сиёсати ва спорт вазирлиги | L66: Trenerlarga berilgan malaka sertifikati bo‘yicha ma’lumotlar | M66: Trenerlarga berilgan malaka sertifikati bo‘yicha ma’lumotlar | N66: {"params": [{"type": "string", "child": false, "field": "oblastname", "name_cr": "oblastname", "name_en": "oblastname", "name_ru": "oblastname", "name_uz": "oblastname"}, {"type": "string", "child": false, "field": "regionname", "name_cr": "regionname", "name_en": "regionname", "name_ru": "regionname", "name_uz": "regionname"}, {"type": "string", "child": false, "field": "adress", "name_cr": "adress", "name_en": "adress", "name_ru": "adress", "name_uz": "adress"}, {"type": "string", "child": false, "field": "id", "name_cr": "id", "name_en": "id", "name_ru": "id", "name_uz": "id"}, {"type": "string", "child": false, "field": "pinfl", "name_cr": "pinfl", "name_en": "pinfl", "name_ru": "pinfl", "name_uz": "pinfl"}, {"type": "string", "child": false, "field": "pasportsn", "name_cr": "pasportsn", "name_en": "pasportsn", "name_ru": "pasportsn", "name_uz": "pasportsn"}, {"type": "string", "child": false, "field": "familyname", "name_cr": "familyname", "name_en": "familyname", "name_ru": "familyname", "name_uz": "familyname"}, {"type": "string", "child": false, "field": "firstname", "name_cr": "firstname", "name_en": "firstname", "name_ru": "firstname", "name_uz": "firstname"}, {"type": "string", "child": false, "field": "lastname", "name_cr": "lastname", "name_en": "lastname", "name_ru": "lastname", "name_uz": "lastname"}, {"type": "string", "child": false, "field": "sporttypeclassifiername", "name_cr": "sporttypeclassifiername", "name_en": "sporttypeclassifiername", "name_ru": "sporttypeclassifiername", "name_uz": "sporttypeclassifiername"}, {"type": "string", "child": false, "field": "hascertificate", "name_cr": "hascertificate", "name_en": "hascertificate", "name_ru": "hascertificate", "name_uz": "hascertificate"}, {"type": "string", "child": false, "field": "certificatesn", "name_cr": "certificatesn", "name_en": "certificatesn", "name_ru": "certificatesn", "name_uz": "certificatesn"}, {"type": "string", "child": false, "field": "certificategivendate", "name_cr": "certificategivendate", "name_en": "certificategivendate", "name_ru": "certificategivendate", "name_uz": "certificategivendate"}, {"type": "string", "child": false, "field": "certificateexpiredate", "name_cr": "certificateexpiredate", "name_en": "certificateexpiredate", "name_ru": "certificateexpiredate", "name_uz": "certificateexpiredate"}, {"type": "string", "child": false, "field": "qualificationcategoryname", "name_cr": "qualificationcategoryname", "name_en": "qualificationcategoryname", "name_ru": "qualificationcategoryname", "name_uz": "qualificationcategoryname"}, {"type": "string", "child": false, "field": "certificateissuedorganization", "name_cr": "certificateissuedorganization", "name_en": "certificateissuedorganization", "name_ru": "certificateissuedorganization", "name_uz": "certificateissuedorganization"}]}
A67: =MAX(A$2:A66)+1 -> 57 | B67: Hakamlarga berilgan malaka sertifikati bo‘yicha ma’lumotlar | D67: 1 | E67: ойлик | H67: sport.jury_app_qual_category | J67: https://erp-integration.sport.uz/api/v1/hp/HP/GetJuryAppQualCategory | K67: Ёшлар сиёсати ва спорт вазирлиги | L67: Ҳакамларга берилган малака сертификати бўйича маълумотлар | M67: Ҳакамларга берилган малака сертификати бўйича маълумотлар | N67: {"params": [{"type": "string", "child": false, "field": "oblastname", "name_cr": "oblastname", "name_en": "oblastname", "name_ru": "oblastname", "name_uz": "oblastname"}, {"type": "string", "child": false, "field": "regionname", "name_cr": "regionname", "name_en": "regionname", "name_ru": "regionname", "name_uz": "regionname"}, {"type": "string", "child": false, "field": "adress", "name_cr": "adress", "name_en": "adress", "name_ru": "adress", "name_uz": "adress"}, {"type": "string", "child": false, "field": "id", "name_cr": "id", "name_en": "id", "name_ru": "id", "name_uz": "id"}, {"type": "string", "child": false, "field": "pinfl", "name_cr": "pinfl", "name_en": "pinfl", "name_ru": "pinfl", "name_uz": "pinfl"}, {"type": "string", "child": false, "field": "pasportsn", "name_cr": "pasportsn", "name_en": "pasportsn", "name_ru": "pasportsn", "name_uz": "pasportsn"}, {"type": "string", "child": false, "field": "familyname", "name_cr": "familyname", "name_en": "familyname", "name_ru": "familyname", "name_uz": "familyname"}, {"type": "string", "child": false, "field": "firstname", "name_cr": "firstname", "name_en": "firstname", "name_ru": "firstname", "name_uz": "firstname"}, {"type": "string", "child": false, "field": "lastname", "name_cr": "lastname", "name_en": "lastname", "name_ru": "lastname", "name_uz": "lastname"}, {"type": "string", "child": false, "field": "sporttypeclassifiername", "name_cr": "sporttypeclassifiername", "name_en": "sporttypeclassifiername", "name_ru": "sporttypeclassifiername", "name_uz": "sporttypeclassifiername"}, {"type": "string", "child": false, "field": "hascertificate", "name_cr": "hascertificate", "name_en": "hascertificate", "name_ru": "hascertificate", "name_uz": "hascertificate"}, {"type": "string", "child": false, "field": "certificatesn", "name_cr": "certificatesn", "name_en": "certificatesn", "name_ru": "certificatesn", "name_uz": "certificatesn"}, {"type": "string", "child": false, "field": "certificategivendate", "name_cr": "certificategivendate", "name_en": "certificategivendate", "name_ru": "certificategivendate", "name_uz": "certificategivendate"}, {"type": "string", "child": false, "field": "certificateexpiredate", "name_cr": "certificateexpiredate", "name_en": "certificateexpiredate", "name_ru": "certificateexpiredate", "name_uz": "certificateexpiredate"}, {"type": "string", "child": false, "field": "qualificationcategoryname", "name_cr": "qualificationcategoryname", "name_en": "qualificationcategoryname", "name_ru": "qualificationcategoryname", "name_uz": "qualificationcategoryname"}, {"type": "string", "child": false, "field": "certificateissuedorganization", "name_cr": "certificateissuedorganization", "name_en": "certificateissuedorganization", "name_ru": "certificateissuedorganization", "name_uz": "certificateissuedorganization"}]}
A68: =MAX(A$2:A67)+1 -> 58 | B68: Instruktor-metodestlar to‘g‘risidagi ma’lumotlar. | D68: 1 | E68: ойлик | H68: sport.instructor_app_qual_category | J68: https://erp-integration.sport.uz/api/v1/hp/HP/GetInstructorAppQualCategory | K68: Ёшлар сиёсати ва спорт вазирлиги | L68: Инструктор-методестлар тўғрисидаги маълумотлар | M68: Инструктор-методестлар тўғрисидаги маълумотлар | N68: {"params": [{"type": "string", "child": false, "field": "oblastname", "name_cr": "oblastname", "name_en": "oblastname", "name_ru": "oblastname", "name_uz": "oblastname"}, {"type": "string", "child": false, "field": "regionname", "name_cr": "regionname", "name_en": "regionname", "name_ru": "regionname", "name_uz": "regionname"}, {"type": "string", "child": false, "field": "adress", "name_cr": "adress", "name_en": "adress", "name_ru": "adress", "name_uz": "adress"}, {"type": "string", "child": false, "field": "id", "name_cr": "id", "name_en": "id", "name_ru": "id", "name_uz": "id"}, {"type": "string", "child": false, "field": "pinfl", "name_cr": "pinfl", "name_en": "pinfl", "name_ru": "pinfl", "name_uz": "pinfl"}, {"type": "string", "child": false, "field": "pasportsn", "name_cr": "pasportsn", "name_en": "pasportsn", "name_ru": "pasportsn", "name_uz": "pasportsn"}, {"type": "string", "child": false, "field": "familyname", "name_cr": "familyname", "name_en": "familyname", "name_ru": "familyname", "name_uz": "familyname"}, {"type": "string", "child": false, "field": "firstname", "name_cr": "firstname", "name_en": "firstname", "name_ru": "firstname", "name_uz": "firstname"}, {"type": "string", "child": false, "field": "lastname", "name_cr": "lastname", "name_en": "lastname", "name_ru": "lastname", "name_uz": "lastname"}, {"type": "string", "child": false, "field": "sporttypeclassifiername", "name_cr": "sporttypeclassifiername", "name_en": "sporttypeclassifiername", "name_ru": "sporttypeclassifiername", "name_uz": "sporttypeclassifiername"}, {"type": "string", "child": false, "field": "hascertificate", "name_cr": "hascertificate", "name_en": "hascertificate", "name_ru": "hascertificate", "name_uz": "hascertificate"}, {"type": "string", "child": false, "field": "certificatesn", "name_cr": "certificatesn", "name_en": "certificatesn", "name_ru": "certificatesn", "name_uz": "certificatesn"}, {"type": "string", "child": false, "field": "certificategivendate", "name_cr": "certificategivendate", "name_en": "certificategivendate", "name_ru": "certificategivendate", "name_uz": "certificategivendate"}, {"type": "string", "child": false, "field": "certificateexpiredate", "name_cr": "certificateexpiredate", "name_en": "certificateexpiredate", "name_ru": "certificateexpiredate", "name_uz": "certificateexpiredate"}, {"type": "string", "child": false, "field": "qualificationcategoryname", "name_cr": "qualificationcategoryname", "name_en": "qualificationcategoryname", "name_ru": "qualificationcategoryname", "name_uz": "qualificationcategoryname"}, {"type": "string", "child": false, "field": "certificateissuedorganization", "name_cr": "certificateissuedorganization", "name_en": "certificateissuedorganization", "name_ru": "certificateissuedorganization", "name_uz": "certificateissuedorganization"}]}
A69: =MAX(A$2:A68)+1 -> 59 | B69: Sudiyalar to‘g‘risidagi ma’lumotlar. | D69: 1 | E69: ойлик | H69: sport.trener_info | J69: https://erp-integration.sport.uz/api/v1/hp/HP/GetTrenerInfo | K69: Ёшлар сиёсати ва спорт вазирлиги | L69: Судиялар тўғрисидаги маълумотлар | M69: Судиялар тўғрисидаги маълумотлар | N69: {"params": [{"type": "string", "child": false, "field": "oblastname", "name_cr": "oblastname", "name_en": "oblastname", "name_ru": "oblastname", "name_uz": "oblastname"}, {"type": "string", "child": false, "field": "regionname", "name_cr": "regionname", "name_en": "regionname", "name_ru": "regionname", "name_uz": "regionname"}, {"type": "string", "child": false, "field": "adress", "name_cr": "adress", "name_en": "adress", "name_ru": "adress", "name_uz": "adress"}, {"type": "string", "child": false, "field": "id", "name_cr": "id", "name_en": "id", "name_ru": "id", "name_uz": "id"}, {"type": "string", "child": false, "field": "pinfl", "name_cr": "pinfl", "name_en": "pinfl", "name_ru": "pinfl", "name_uz": "pinfl"}, {"type": "string", "child": false, "field": "pasportsn", "name_cr": "pasportsn", "name_en": "pasportsn", "name_ru": "pasportsn", "name_uz": "pasportsn"}, {"type": "string", "child": false, "field": "familyname", "name_cr": "familyname", "name_en": "familyname", "name_ru": "familyname", "name_uz": "familyname"}, {"type": "string", "child": false, "field": "firstname", "name_cr": "firstname", "name_en": "firstname", "name_ru": "firstname", "name_uz": "firstname"}, {"type": "string", "child": false, "field": "lastname", "name_cr": "lastname", "name_en": "lastname", "name_ru": "lastname", "name_uz": "lastname"}, {"type": "string", "child": false, "field": "sporttypeclassifiername", "name_cr": "sporttypeclassifiername", "name_en": "sporttypeclassifiername", "name_ru": "sporttypeclassifiername", "name_uz": "sporttypeclassifiername"}, {"type": "string", "child": false, "field": "hascertificate", "name_cr": "hascertificate", "name_en": "hascertificate", "name_ru": "hascertificate", "name_uz": "hascertificate"}, {"type": "string", "child": false, "field": "certificatesn", "name_cr": "certificatesn", "name_en": "certificatesn", "name_ru": "certificatesn", "name_uz": "certificatesn"}, {"type": "string", "child": false, "field": "certificategivendate", "name_cr": "certificategivendate", "name_en": "certificategivendate", "name_ru": "certificategivendate", "name_uz": "certificategivendate"}, {"type": "string", "child": false, "field": "certificateexpiredate", "name_cr": "certificateexpiredate", "name_en": "certificateexpiredate", "name_ru": "certificateexpiredate", "name_uz": "certificateexpiredate"}, {"type": "string", "child": false, "field": "qualificationcategoryname", "name_cr": "qualificationcategoryname", "name_en": "qualificationcategoryname", "name_ru": "qualificationcategoryname", "name_uz": "qualificationcategoryname"}, {"type": "string", "child": false, "field": "certificateissuedorganization", "name_cr": "certificateissuedorganization", "name_en": "certificateissuedorganization", "name_ru": "certificateissuedorganization", "name_uz": "certificateissuedorganization"}, {"type": "string", "child": false, "field": "studentcount", "name_cr": "studentcount", "name_en": "studentcount", "name_ru": "studentcount", "name_uz": "studentcount"}, {"type": "string", "child": false, "field": "organizationname", "name_cr": "organizationname", "name_en": "organizationname", "name_ru": "organizationname", "name_uz": "organizationname"}]}
B70: 8. Банк
A71: =MAX(A$2:A70)+1 -> 60 | B71: Bank Malumotlarini yuklash | D71: 1 | E71: кунлик | H71: bank.{table_name}
A72: =MAX(A$2:A71)+1 -> 61 | B72: Bank xodimlarining yaqin qarindoshlarining ko'chmas mulklarini yig'ish | D72: 1 | E72: ойлик | H72: bank.cadastr | J72: https://maspd:19030/api/info-all
A73: =MAX(A$2:A72)+1 -> 62 | B73: Bank xodimlarining yaqin qarindoshlarining transportlarini yig'ish | D73: 1 | E73: ойлик | H73: bank.car_information | J73: https://mspd:19022/api/v2/account-chamber/car-search-06-method
B74: 9. УзСтандарт
A75: =MAX(A$2:A74)+1 -> 63 | B75: Ҳисобга олиш приборлари ва ускуналарининг қиёслов ва метрологик кўриги тўғрисида маълумот олиш | D75: 1 | E75: ойлик | H75: uzstandart.devices_certificate | J75: http://mspd:19002/api/investitsiya/devices-certificate
A76: =MAX(A$2:A75)+1 -> 64 | B76: Маиший ҳисоблагичларни давлат қиёсловидан ўтказилганлиги ҳақидаги маълумот олиш | D76: 1 | E76: ойлик | H76: uzstandart.devices_two_certificate | J76: http://mspd:19027/api/investitsiya/devices-two-certificate
A77: =MAX(A$2:A76)+1 -> 65 | B77: "Э-Аккредитация" oрган ва лабораториялар ҳақида маълумотлар. (Ўзбекистон техник жиҳатдан тартибга со | D77: 1 | E77: ойлик | H77: uzstandart.e_accreditation | J77: https://akkred.uz:8081/main/registries
A78: =MAX(A$2:A77)+1 -> 66 | B78: Маҳсулотнинг мувофиқлик сертификати маълумотлар олиш | D78: 1 | E78: ойлик | H78: uzstandart.product_certifications | J78: http://mspd:19027/api/investment/certificate
A79: =MAX(A$2:A78)+1 -> 67 | B79: Узстандарт базасидан Аккредитация буйича маълумот олиш | D79: 1 | E79: ойлик | H79: uzstandart.registries | J79: https://akkred.uz:8081/main/registries
B80: 10. Божхона
A81: =MAX(A$2:A80)+1 -> 68 | B81: Bojxona Export | D81: 1 | E81: кунлик | H81: bojxona.export | J81: http://10.190.0.118:8889/api/get-form1 | K81: Божхона қўмитаси | L81: Амалга оширилган экспорт операциялари тўғрисида маълумот (товар коди) | M81: 1 йилдан кўп оралиқни киритиш мумкин эмас ( 365 кундан ортиқ киритилиши мумкин эмас ) | N81: {"params": [{"type": "string", "child": false, "field": "g7a", "name_cr": "Пост коди", "name_en": "g7a", "name_ru": "Код поста", "name_uz": "Пост коди"}, {"type": "string", "child": false, "field": "g7b", "name_cr": "БЮД санаси", "name_en": "g7b", "name_ru": "Дата ГТД", "name_uz": "БЮД санаси"}, {"type": "string", "child": false, "field": "g7c", "name_cr": "БЮД тартиб рақами", "name_en": "g7c", "name_ru": "Порядковый номер ГТД", "name_uz": "БЮД тартиб рақами"}, {"type": "string", "child": false, "field": "rejim", "name_cr": "Режим", "name_en": "rejim", "name_ru": "Режим", "name_uz": "Режим"}, {"type": "string", "child": false, "field": "g43", "name_cr": "Мақсади", "name_en": "g43", "name_ru": "Цель", "name_uz": "Мақсади"}, {"type": "string", "child": false, "field": "inn", "name_cr": "СТИР", "name_en": "inn", "name_ru": "ИНН", "name_uz": "СТИР"}, {"type": "string", "child": false, "field": "g2name", "name_cr": "Юк жўнатувчи", "name_en": "g2name", "name_ru": "Отправитель", "name_uz": "Юк жўнатувчи"}, {"type": "string", "child": false, "field": "g8name", "name_cr": "Юк қабул қилувчи", "name_en": "g8name", "name_ru": "Получатель", "name_uz": "Юк қабул қилувчи"}, {"type": "string", "child": false, "field": "g22a", "name_cr": "Шартнома валютаси коди", "name_en": "g22a", "name_ru": "Валюта контракта", "name_uz": "Шартнома валютаси коди"}, {"type": "string", "child": false, "field": "g32", "name_cr": "Товар тартиб рақами", "name_en": "g32", "name_ru": "Номер товара", "name_uz": "Товар тартиб рақами"}, {"type": "string", "child": false, "field": "g33", "name_cr": "ТИФ ТН коди", "name_en": "g33", "name_ru": "Код ТН ВЭД", "name_uz": "ТИФ ТН коди"}, {"type": "string", "child": false, "field": "g31name", "name_cr": "Товар номи", "name_en": "g31name", "name_ru": "Наименование товара", "name_uz": "Товар номи"}, {"type": "string", "child": false, "field": "g38", "name_cr": "Нетто вазн, кг", "name_en": "g38", "name_ru": "Вес нетто, кг", "name_uz": "Нетто вазн, кг"}, {"type": "string", "child": false, "field": "g46", "name_cr": "Статистик қиймат (минг доллар)", "name_en": "g46", "name_ru": "Стат. стоимость (тыс. дол)", "name_uz": "Статистик қиймат (минг доллар)"}, {"type": "string", "child": false, "field": "g42", "name_cr": "Фактура қиймати (шартнома валютасида)", "name_en": "g42", "name_ru": "Фактурная стоимость (в валюте контракта)", "name_uz": "Фактура қиймати (шартнома валютасида)"}, {"type": "string", "child": false, "field": "g31amount", "name_cr": "Товар миқдори", "name_en": "g31amount", "name_ru": "Количество товара", "name_uz": "Товар миқдори"}, {"type": "string", "child": false, "field": "g41", "name_cr": "Қўшимча ўлчов бирлиги", "name_en": "g41", "name_ru": "Доп ед. измерения", "name_uz": "Қўшимча ўлчов бирлиги"}, {"type": "string", "child": false, "field": "g17", "name_cr": "Келиб тушадиган мамлакат", "name_en": "g17", "name_ru": "Страна назначения", "name_uz": "Келиб тушадиган мамлакат"}, {"type": "string", "child": false, "field": "g34", "name_cr": "Ишлаб чиқарилган мамлакат", "name_en": "g34", "name_ru": "Код страны происхождения", "name_uz": "Ишлаб чиқарилган мамлакат"}, {"type": "string", "child": false, "field": "g11", "name_cr": "Савдо қилинаётган мамлакат", "name_en": "g11", "name_ru": "Торгующая страна", "name_uz": "Савдо қилинаётган мамлакат"}, {"type": "string", "child": false, "field": "g23", "name_cr": "Шартнома валютаси курси", "name_en": "g23", "name_ru": "Курс валюты", "name_uz": "Шартнома валютаси курси"}, {"type": "string", "child": false, "field": "g23scale", "name_cr": "Валюта бирлиги", "name_en": "g23scale", "name_ru": "отношения к национальной валюте", "name_uz": "Валюта бирлиги"}, {"type": "string", "child": false, "field": "g13", "name_cr": "АҚШ доллари курси", "name_en": "g13", "name_ru": "Курс доллара", "name_uz": "АҚШ доллари курси"}, {"type": "string", "child": false, "field": "gdvipdate", "name_cr": "Расмийлаштирилган сана", "name_en": "gdvipdate", "name_ru": "Дата оформление", "name_uz": "Расмийлаштирилган сана"}]}
A82: =MAX(A$2:A81)+1 -> 69 | B82: Bojxona Import | D82: 1 | E82: кунлик | H82: bojxona.import_data | J82: http://10.190.0.118:8889/api/get-form2 | K82: Божхона қўмитаси | L82: Амалга оширилган импорт операциялари тўғрисида маълумот (СТИР) | M82: 1 йилдан кўп оралиқни киритиш мумкин эмас ( 365 кундан ортиқ киритилиши мумкин эмас ) | N82: {"params": [{"type": "string", "child": false, "field": "g7a", "name_cr": "g7a", "name_en": "g7a", "name_ru": "g7a", "name_uz": "g7a"}, {"type": "string", "child": false, "field": "g7b", "name_cr": "g7b", "name_en": "g7b", "name_ru": "g7b", "name_uz": "g7b"}, {"type": "string", "child": false, "field": "g7c", "name_cr": "g7c", "name_en": "g7c", "name_ru": "g7c", "name_uz": "g7c"}, {"type": "string", "child": false, "field": "rejim", "name_cr": "rejim", "name_en": "rejim", "name_ru": "rejim", "name_uz": "rejim"}, {"type": "string", "child": false, "field": "g37", "name_cr": "g37", "name_en": "g37", "name_ru": "g37", "name_uz": "g37"}, {"type": "string", "child": false, "field": "g43", "name_cr": "g43", "name_en": "g43", "name_ru": "g43", "name_uz": "g43"}, {"type": "string", "child": false, "field": "inn", "name_cr": "inn", "name_en": "inn", "name_ru": "inn", "name_uz": "inn"}, {"type": "string", "child": false, "field": "g2name", "name_cr": "g2name", "name_en": "g2name", "name_ru": "g2name", "name_uz": "g2name"}, {"type": "string", "child": false, "field": "g8name", "name_cr": "g8name", "name_en": "g8name", "name_ru": "g8name", "name_uz": "g8name"}, {"type": "string", "child": false, "field": "g22a", "name_cr": "g22a", "name_en": "g22a", "name_ru": "g22a", "name_uz": "g22a"}, {"type": "string", "child": false, "field": "g42", "name_cr": "g42", "name_en": "g42", "name_ru": "g42", "name_uz": "g42"}, {"type": "string", "child": false, "field": "g32", "name_cr": "g32", "name_en": "g32", "name_ru": "g32", "name_uz": "g32"}, {"type": "string", "child": false, "field": "g33", "name_cr": "g33", "name_en": "g33", "name_ru": "g33", "name_uz": "g33"}, {"type": "string", "child": false, "field": "g31name", "name_cr": "g31name", "name_en": "g31name", "name_ru": "g31name", "name_uz": "g31name"}, {"type": "string", "child": false, "field": "g38", "name_cr": "g38", "name_en": "g38", "name_ru": "g38", "name_uz": "g38"}, {"type": "string", "child": false, "field": "g46", "name_cr": "g46", "name_en": "g46", "name_ru": "g46", "name_uz": "g46"}, {"type": "string", "child": false, "field": "g45", "name_cr": "g45", "name_en": "g45", "name_ru": "g45", "name_uz": "g45"}, {"type": "string", "child": false, "field": "g31amount", "name_cr": "g31amount", "name_en": "g31amount", "name_ru": "g31amount", "name_uz": "g31amount"}, {"type": "string", "child": false, "field": "g41", "name_cr": "g41", "name_en": "g41", "name_ru": "g41", "name_uz": "g41"}, {"type": "string", "child": false, "field": "g17", "name_cr": "g17", "name_en": "g17", "name_ru": "g17", "name_uz": "g17"}, {"type": "string", "child": false, "field": "g34", "name_cr": "g34", "name_en": "g34", "name_ru": "g34", "name_uz": "g34"}, {"type": "string", "child": false, "field": "g11", "name_cr": "g11", "name_en": "g11", "name_ru": "g11", "name_uz": "g11"}, {"type": "string", "child": false, "field": "g23", "name_cr": "g23", "name_en": "g23", "name_ru": "g23", "name_uz": "g23"}, {"type": "string", "child": false, "field": "g23scale", "name_cr": "g23scale", "name_en": "g23scale", "name_ru": "g23scale", "name_uz": "g23scale"}, {"type": "string", "child": false, "field": "g13", "name_cr": "g13", "name_en": "g13", "name_ru": "g13", "name_uz": "g13"}, {"type": "string", "child": false, "field": "pay20", "name_cr": "pay20", "name_en": "pay20", "name_ru": "pay20", "name_uz": "pay20"}, {"type": "string", "child": false, "field": "pay27", "name_cr": "pay27", "name_en": "pay27", "name_ru": "pay27", "name_uz": "pay27"}, {"type": "string", "child": false, "field": "pay29", "name_cr": "pay29", "name_en": "pay29", "name_ru": "pay29", "name_uz": "pay29"}, {"type": "string", "child": false, "field": "otherPay", "name_cr": "otherPay", "name_en": "otherPay", "name_ru": "otherPay", "name_uz": "otherPay"}, {"type": "string", "child": false, "field": "gdvipdate", "name_cr": "gdvipdate", "name_en": "gdvipdate", "name_ru": "gdvipdate", "name_uz": "gdvipdate"}]}
A83: =MAX(A$2:A82)+1 -> 70 | B83: Bojxona Ombor | D83: 1 | E83: кунлик | H83: bojxona.ombor | J83: http://10.190.0.118:8889/api/get-form4 | K83: Божхона қўмитаси | L83: Омборхона тўғрисида маълумот (ТОВАР) | M83: 1 йилдан кўп оралиқни киритиш мумкин эмас ( 365 кундан ортиқ киритилиши мумкин эмас ) | N83: {"params": [{"type": "string", "child": false, "field": "g7a", "name_cr": "g7a", "name_en": "g7a", "name_ru": "g7a", "name_uz": "g7a"}, {"type": "string", "child": false, "field": "g7b", "name_cr": "g7b", "name_en": "g7b", "name_ru": "g7b", "name_uz": "g7b"}, {"type": "string", "child": false, "field": "g7c", "name_cr": "g7c", "name_en": "g7c", "name_ru": "g7c", "name_uz": "g7c"}, {"type": "string", "child": false, "field": "g1a", "name_cr": "g1a", "name_en": "g1a", "name_ru": "g1a", "name_uz": "g1a"}, {"type": "string", "child": false, "field": "g1b", "name_cr": "g1b", "name_en": "g1b", "name_ru": "g1b", "name_uz": "g1b"}, {"type": "string", "child": false, "field": "g8name", "name_cr": "g8name", "name_en": "g8name", "name_ru": "g8name", "name_uz": "g8name"}, {"type": "string", "child": false, "field": "g8code2", "name_cr": "g8code2", "name_en": "g8code2", "name_ru": "g8code2", "name_uz": "g8code2"}, {"type": "string", "child": false, "field": "g54date", "name_cr": "g54date", "name_en": "g54date", "name_ru": "g54date", "name_uz": "g54date"}, {"type": "string", "child": false, "field": "g32", "name_cr": "g32", "name_en": "g32", "name_ru": "g32", "name_uz": "g32"}, {"type": "string", "child": false, "field": "g31name", "name_cr": "g31name", "name_en": "g31name", "name_ru": "g31name", "name_uz": "g31name"}, {"type": "string", "child": false, "field": "g33", "name_cr": "g33", "name_en": "g33", "name_ru": "g33", "name_uz": "g33"}, {"type": "string", "child": false, "field": "g38", "name_cr": "g38", "name_en": "g38", "name_ru": "g38", "name_uz": "g38"}, {"type": "string", "child": false, "field": "g31amount", "name_cr": "g31amount", "name_en": "g31amount", "name_ru": "g31amount", "name_uz": "g31amount"}, {"type": "string", "child": false, "field": "g41", "name_cr": "g41", "name_en": "g41", "name_ru": "g41", "name_uz": "g41"}, {"type": "string", "child": false, "field": "g46", "name_cr": "g46", "name_en": "g46", "name_ru": "g46", "name_uz": "g46"}]}
A84: =MAX(A$2:A83)+1 -> 71 | B84: Bojxona to'lovlar | D84: 1 | E84: кунлик | H84: bojxona.payments | J84: http://10.190.0.118:8889/api/get-form3 | K84: Божхона қўмитаси | L84: Амалга оширилган тўловлар тўғрисида маълумот (товар коди) | M84: 1 йилдан кўп оралиқни киритиш мумкин эмас ( 365 кундан ортиқ киритилиши мумкин эмас ) | N84: {"params": [{"type": "string", "child": false, "field": "gtd", "name_cr": "БЮД рақами", "name_en": "gtd", "name_ru": "Номер ГТД", "name_uz": "БЮД рақами"}, {"type": "string", "child": false, "field": "g7a", "name_cr": "Пост коди", "name_en": "g7a", "name_ru": "Код поста", "name_uz": "Пост коди"}, {"type": "string", "child": false, "field": "g7b", "name_cr": "БЮД санаси", "name_en": "g7b", "name_ru": "Дата ГТД", "name_uz": "БЮД санаси"}, {"type": "string", "child": false, "field": "g7c", "name_cr": "БЮД рақами", "name_en": "g7c", "name_ru": "Номер ГТД", "name_uz": "БЮД рақами"}, {"type": "string", "child": false, "field": "rejim", "name_cr": "Режим", "name_en": "rejim", "name_ru": "Режим", "name_uz": "Режим"}, {"type": "string", "child": false, "field": "g37", "name_cr": "Процедура", "name_en": "g37", "name_ru": "Процедура", "name_uz": "Процедура"}, {"type": "string", "child": false, "field": "g43", "name_cr": "Мақсади", "name_en": "g43", "name_ru": "Цель", "name_uz": "Мақсади"}, {"type": "string", "child": false, "field": "inn", "name_cr": "СТИР", "name_en": "inn", "name_ru": "ИНН", "name_uz": "СТИР"}, {"type": "string", "child": false, "field": "g2name", "name_cr": "Юк жўнатувчи", "name_en": "g2name", "name_ru": "Отправитель", "name_uz": "Юк жўнатувчи"}, {"type": "string", "child": false, "field": "g8name", "name_cr": "Юк қабул қилувчи", "name_en": "g8name", "name_ru": "Получатель", "name_uz": "Юк қабул қилувчи"}, {"type": "string", "child": false, "field": "g14code2", "name_cr": "Брокер СТИР", "name_en": "g14code2", "name_ru": "ИНН брокера", "name_uz": "Брокер СТИР"}, {"type": "string", "child": false, "field": "g14name", "name_cr": "Брокер", "name_en": "g14name", "name_ru": "Брокер", "name_uz": "Брокер"}, {"type": "string", "child": false, "field": "g9code2", "name_cr": "СТИР", "name_en": "g9code2", "name_ru": "ИНН", "name_uz": "СТИР"}, {"type": "string", "child": false, "field": "g9name", "name_cr": "Молиявий тартибга солиш учун жавобгар шахс", "name_en": "g9name", "name_ru": "Лицо, ответственное за финансовое урегулирование", "name_uz": "Молиявий тартибга солиш учун жавобгар шахс"}, {"type": "string", "child": false, "field": "g22a", "name_cr": "g22a", "name_en": "g22a", "name_ru": "g22a", "name_uz": "g22a"}, {"type": "string", "child": false, "field": "g42", "name_cr": "g42", "name_en": "g42", "name_ru": "g42", "name_uz": "g42"}, {"type": "string", "child": false, "field": "g32", "name_cr": "g32", "name_en": "g32", "name_ru": "g32", "name_uz": "g32"}, {"type": "string", "child": false, "field": "g33", "name_cr": "g33", "name_en": "g33", "name_ru": "g33", "name_uz": "g33"}, {"type": "string", "child": false, "field": "g31name", "name_cr": "g31name", "name_en": "g31name", "name_ru": "g31name", "name_uz": "g31name"}, {"type": "string", "child": false, "field": "g38", "name_cr": "g38", "name_en": "g38", "name_ru": "g38", "name_uz": "g38"}, {"type": "string", "child": false, "field": "g35", "name_cr": "g35", "name_en": "g35", "name_ru": "g35", "name_uz": "g35"}, {"type": "string", "child": false, "field": "g46", "name_cr": "g46", "name_en": "g46", "name_ru": "g46", "name_uz": "g46"}, {"type": "string", "child": false, "field": "g45", "name_cr": "g45", "name_en": "g45", "name_ru": "g45", "name_uz": "g45"}, {"type": "string", "child": false, "field": "g31amount", "name_cr": "g31amount", "name_en": "g31amount", "name_ru": "g31amount", "name_uz": "g31amount"}, {"type": "string", "child": false, "field": "g41", "name_cr": "g41", "name_en": "g41", "name_ru": "g41", "name_uz": "g41"}, {"type": "string", "child": false, "field": "g20b", "name_cr": "g20b", "name_en": "g20b", "name_ru": "g20b", "name_uz": "g20b"}, {"type": "string", "child": false, "field": "g20name", "name_cr": "g20name", "name_en": "g20name", "name_ru": "g20name", "name_uz": "g20name"}, {"type": "string", "child": false, "field": "g20a", "name_cr": "g20a", "name_en": "g20a", "name_ru": "g20a", "name_uz": "g20a"}, {"type": "string", "child": false, "field": "g17", "name_cr": "g17", "name_en": "g17", "name_ru": "g17", "name_uz": "g17"}, {"type": "string", "child": false, "field": "g34", "name_cr": "g34", "name_en": "g34", "name_ru": "g34", "name_uz": "g34"}, {"type": "string", "child": false, "field": "g11", "name_cr": "g11", "name_en": "g11", "name_ru": "g11", "name_uz": "g11"}, {"type": "string", "child": false, "field": "g23", "name_cr": "g23", "name_en": "g23", "name_ru": "g23", "name_uz": "g23"}, {"type": "string", "child": false, "field": "g23scale", "name_cr": "g23scale", "name_en": "g23scale", "name_ru": "g23scale", "name_uz": "g23scale"}, {"type": "string", "child": false, "field": "g13", "name_cr": "g13", "name_en": "g13", "name_ru": "g13", "name_uz": "g13"}, {"type": "string", "child": false, "field": "pay20Lgot", "name_cr": "pay20Lgot", "name_en": "pay20Lgot", "name_ru": "pay20Lgot", "name_uz": "pay20Lgot"}, {"type": "string", "child": false, "field": "pay27Lgot", "name_cr": "pay27Lgot", "name_en": "pay27Lgot", "name_ru": "pay27Lgot", "name_uz": "pay27Lgot"}, {"type": "string", "child": false, "field": "pay29Lgot", "name_cr": "pay29Lgot", "name_en": "pay29Lgot", "name_ru": "pay29Lgot", "name_uz": "pay29Lgot"}, {"type": "string", "child": false, "field": "otherPayLgot", "name_cr": "otherPayLgot", "name_en": "otherPayLgot", "name_ru": "otherPayLgot", "name_uz": "otherPayLgot"}, {"type": "string", "child": false, "field": "pay20", "name_cr": "pay20", "name_en": "pay20", "name_ru": "pay20", "name_uz": "pay20"}, {"type": "string", "child": false, "field": "pay27", "name_cr": "pay27", "name_en": "pay27", "name_ru": "pay27", "name_uz": "pay27"}, {"type": "string", "child": false, "field": "pay29", "name_cr": "pay29", "name_en": "pay29", "name_ru": "pay29", "name_uz": "pay29"}, {"type": "string", "child": false, "field": "otherPay", "name_cr": "otherPay", "name_en": "otherPay", "name_ru": "otherPay", "name_uz": "otherPay"}, {"type": "list", "child": true, "field": "docNoLgot", "name_cr": "docNoLgot", "name_en": "docNoLgot", "name_ru": "docNoLgot", "name_uz": "docNoLgot", "children": [{"type": "string", "child": false, "field": "docNo", "name_cr": "docNo", "name_en": "docNo", "name_ru": "docNo", "name_uz": "docNo"}]}, {"type": "string", "child": false, "field": "gdvipdate", "name_cr": "gdvipdate", "name_en": "gdvipdate", "name_ru": "gdvipdate", "name_uz": "gdvipdate"}, {"type": "string", "child": false, "field": "sfer", "name_cr": "sfer", "name_en": "sfer", "name_ru": "sfer", "name_uz": "sfer"}, {"type": "string", "child": false, "field": "gcodinves", "name_cr": "gcodinves", "name_en": "gcodinves", "name_ru": "gcodinves", "name_uz": "gcodinves"}, {"type": "string", "child": false, "field": "gdocno", "name_cr": "gdocno", "name_en": "gdocno", "name_ru": "gdocno", "name_uz": "gdocno"}, {"type": "string", "child": false, "field": "gdcodate", "name_cr": "gdcodate", "name_en": "gdcodate", "name_ru": "gdcodate", "name_uz": "gdcodate"}, {"type": "string", "child": false, "field": "gidn", "name_cr": "gidn", "name_en": "gidn", "name_ru": "gidn", "name_uz": "gidn"}]}
B85: 11. Бандлик вазирлиги
A86: =MAX(A$2:A85)+1 -> 72 | B86: O'lganlar haqida malumot olish | D86: 1 | E86: ойлик | H86: employement.died_person
A87: =MAX(A$2:A86)+1 -> 73 | B87: Yammt dan mehnat shartnomlarini olish | D87: 1 | E87: ойлик | H87: employement.employee_history | J87: https://10.190.10.74/api/accounting-chamber/citizen/get-experiences/by-companies | K87: Камбағалликни қисқартириш ва бандлик вазирлиги | L87: Корхона ва ташкилотларда ишловчи жисмоний шахсларнинг меҳнат фаолияти тўғрисида маълумотлар (ЯММТ) | M87: Ташкилотлар кесимида жисмоний шахсларнинг меҳнат фаолияти тўғрисида маълумотлар | N87: {"params": [{"type": "string", "child": false, "field": "id", "name_cr": "id", "name_en": "id", "name_ru": "id", "name_uz": "id"}, {"type": "string", "child": false, "field": "company_profile_name", "name_cr": "company_profile_name", "name_en": "company_profile_name", "name_ru": "company_profile_name", "name_uz": "company_profile_name"}, {"type": "string", "child": false, "field": "company_tin", "name_cr": "company_tin", "name_en": "company_tin", "name_ru": "company_tin", "name_uz": "company_tin"}, {"type": "string", "child": false, "field": "pinfl", "name_cr": "pinfl", "name_en": "pinfl", "name_ru": "pinfl", "name_uz": "pinfl"}, {"type": "string", "child": false, "field": "full_name", "name_cr": "full_name", "name_en": "full_name", "name_ru": "full_name", "name_uz": "full_name"}, {"type": "string", "child": false, "field": "date_start", "name_cr": "date_start", "name_en": "date_start", "name_ru": "date_start", "name_uz": "date_start"}, {"type": "string", "child": false, "field": "date_stop", "name_cr": "date_stop", "name_en": "date_stop", "name_ru": "date_stop", "name_uz": "date_stop"}, {"type": "string", "child": false, "field": "order_date", "name_cr": "order_date", "name_en": "order_date", "name_ru": "order_date", "name_uz": "order_date"}, {"type": "string", "child": false, "field": "birth_date", "name_cr": "birth_date", "name_en": "birth_date", "name_ru": "birth_date", "name_uz": "birth_date"}, {"type": "string", "child": false, "field": "order_number", "name_cr": "order_number", "name_en": "order_number", "name_ru": "order_number", "name_uz": "order_number"}, {"type": "string", "child": false, "field": "parent_id", "name_cr": "parent_id", "name_en": "parent_id", "name_ru": "parent_id", "name_uz": "parent_id"}, {"type": "string", "child": false, "field": "position_name", "name_cr": "position_name", "name_en": "position_name", "name_ru": "position_name", "name_uz": "position_name"}, {"type": "string", "child": false, "field": "position_name_ru", "name_cr": "position_name_ru", "name_en": "position_name_ru", "name_ru": "position_name_ru", "name_uz": "position_name_ru"}, {"type": "string", "child": false, "field": "kodp_pn", "name_cr": "kodp_pn", "name_en": "kodp_pn", "name_ru": "kodp_pn", "name_uz": "kodp_pn"}, {"type": "string", "child": false, "field": "kodp_nskz_code", "name_cr": "kodp_nskz_code", "name_en": "kodp_nskz_code", "name_ru": "kodp_nskz_code", "name_uz": "kodp_nskz_code"}, {"type": "string", "child": false, "field": "kodp_personal_category", "name_cr": "kodp_personal_category", "name_en": "kodp_personal_category", "name_ru": "kodp_personal_category", "name_uz": "kodp_personal_category"}, {"type": "string", "child": false, "field": "structure_name", "name_cr": "structure_name", "name_en": "structure_name", "name_ru": "structure_name", "name_uz": "structure_name"}, {"type": "string", "child": false, "field": "structure_name_ru", "name_cr": "structure_name_ru", "name_en": "structure_name_ru", "name_ru": "structure_name_ru", "name_uz": "structure_name_ru"}, {"type": "string", "child": false, "field": "work_type", "name_cr": "work_type", "name_en": "work_type", "name_ru": "work_type", "name_uz": "work_type"}, {"type": "string", "child": false, "field": "classifier_name_uz", "name_cr": "classifier_name_uz", "name_en": "classifier_name_uz", "name_ru": "classifier_name_uz", "name_uz": "classifier_name_uz"}, {"type": "string", "child": false, "field": "classifier_name_ru", "name_cr": "classifier_name_ru", "name_en": "classifier_name_ru", "name_ru": "classifier_name_ru", "name_uz": "classifier_name_ru"}, {"type": "string", "child": false, "field": "kodp_min_education", "name_cr": "kodp_min_education", "name_en": "kodp_min_education", "name_ru": "kodp_min_education", "name_uz": "kodp_min_education"}, {"type": "string", "child": false, "field": "created_at", "name_cr": "created_at", "name_en": "created_at", "name_ru": "created_at", "name_uz": "created_at"}]}
A88: =MAX(A$2:A87)+1 -> 74 | B88: Hunarmandlar | D88: 1 | E88: ойлик | H88: employement.hunarmand | J88: https://hunar.uz/api/accounts-chamber/get-hunarmand | K88: Ўзбекистон Республикаси “Ҳунарманд” уюшмаси | L88: Ҳунарманд реестр тўғрисида маълумотлар | M88: Ҳунарманд реестр тўғрисида маълумотлар | N88: {"params": [{"type": "string", "child": false, "field": "id", "name_cr": "id", "name_en": "id", "name_ru": "id", "name_uz": "id"}, {"type": "string", "child": false, "field": "registration_date", "name_cr": "registration_date", "name_en": "registration_date", "name_ru": "registration_date", "name_uz": "registration_date"}, {"type": "string", "child": false, "field": "tin", "name_cr": "tin", "name_en": "tin", "name_ru": "tin", "name_uz": "tin"}, {"type": "string", "child": false, "field": "pinfl", "name_cr": "pinfl", "name_en": "pinfl", "name_ru": "pinfl", "name_uz": "pinfl"}, {"type": "string", "child": false, "field": "fio", "name_cr": "fio", "name_en": "fio", "name_ru": "fio", "name_uz": "fio"}, {"type": "string", "child": false, "field": "a_region_soato", "name_cr": "a_region_soato", "name_en": "a_region_soato", "name_ru": "a_region_soato", "name_uz": "a_region_soato"}, {"type": "string", "child": false, "field": "a_sub_region_soatoio", "name_cr": "a_sub_region_soatoio", "name_en": "a_sub_region_soatoio", "name_ru": "a_sub_region_soatoio", "name_uz": "a_sub_region_soatoio"}, {"type": "string", "child": false, "field": "a_village_soato", "name_cr": "a_village_soato", "name_en": "a_village_soato", "name_ru": "a_village_soato", "name_uz": "a_village_soato"}, {"type": "string", "child": false, "field": "home_region_soato", "name_cr": "home_region_soato", "name_en": "home_region_soato", "name_ru": "home_region_soato", "name_uz": "home_region_soato"}, {"type": "string", "child": false, "field": "home_sub_region_soato", "name_cr": "home_sub_region_soato", "name_en": "home_sub_region_soato", "name_ru": "home_sub_region_soato", "name_uz": "home_sub_region_soato"}, {"type": "string", "child": false, "field": "mahalla", "name_cr": "mahalla", "name_en": "mahalla", "name_ru": "mahalla", "name_uz": "mahalla"}, {"type": "string", "child": false, "field": "home_street", "name_cr": "home_street", "name_en": "home_street", "name_ru": "home_street", "name_uz": "home_street"}, {"type": "string", "child": false, "field": "activity_type", "name_cr": "activity_type", "name_en": "activity_type", "name_ru": "activity_type", "name_uz": "activity_type"}, {"type": "string", "child": false, "field": "expiry_date", "name_cr": "expiry_date", "name_en": "expiry_date", "name_ru": "expiry_date", "name_uz": "expiry_date"}, {"type": "string", "child": false, "field": "birthday", "name_cr": "birthday", "name_en": "birthday", "name_ru": "birthday", "name_uz": "birthday"}, {"type": "string", "child": false, "field": "nationality", "name_cr": "nationality", "name_en": "nationality", "name_ru": "nationality", "name_uz": "nationality"}, {"type": "string", "child": false, "field": "phones", "name_cr": "phones", "name_en": "phones", "name_ru": "phones", "name_uz": "phones"}, {"type": "string", "child": false, "field": "passport_serial", "name_cr": "passport_serial", "name_en": "passport_serial", "name_ru": "passport_serial", "name_uz": "passport_serial"}]}
A89: =MAX(A$2:A88)+1 -> 75 | B89: Hunarmamnd Shogirtlar | D89: 1 | E89: ойлик | H89: employement.hunarmand_shogird | J89: https://hunar.uz/api/accounts-chamber/get-student | K89: Ўзбекистон Республикаси “Ҳунарманд” уюшмаси | L89: Шогирд реестр тўғрисида маълумотлар | M89: Шогирд реестр тўғрисида маълумотлар | N89: {"params": [{"type": "string", "child": false, "field": "id", "name_cr": "id", "name_en": "id", "name_ru": "id", "name_uz": "id"}, {"type": "string", "child": false, "field": "passport_serial", "name_cr": "passport_serial", "name_en": "passport_serial", "name_ru": "passport_serial", "name_uz": "passport_serial"}, {"type": "string", "child": false, "field": "tin", "name_cr": "tin", "name_en": "tin", "name_ru": "tin", "name_uz": "tin"}, {"type": "string", "child": false, "field": "pinfl", "name_cr": "pinfl", "name_en": "pinfl", "name_ru": "pinfl", "name_uz": "pinfl"}, {"type": "string", "child": false, "field": "fio", "name_cr": "fio", "name_en": "fio", "name_ru": "fio", "name_uz": "fio"}, {"type": "string", "child": false, "field": "phones", "name_cr": "phones", "name_en": "phones", "name_ru": "phones", "name_uz": "phones"}, {"type": "string", "child": false, "field": "nationality", "name_cr": "nationality", "name_en": "nationality", "name_ru": "nationality", "name_uz": "nationality"}, {"type": "string", "child": false, "field": "home_region_soato", "name_cr": "home_region_soato", "name_en": "home_region_soato", "name_ru": "home_region_soato", "name_uz": "home_region_soato"}, {"type": "string", "child": false, "field": "home_sub_region_soato", "name_cr": "home_sub_region_soato", "name_en": "home_sub_region_soato", "name_ru": "home_sub_region_soato", "name_uz": "home_sub_region_soato"}, {"type": "string", "child": false, "field": "home_address", "name_cr": "home_address", "name_en": "home_address", "name_ru": "home_address", "name_uz": "home_address"}, {"type": "string", "child": false, "field": "birthday", "name_cr": "birthday", "name_en": "birthday", "name_ru": "birthday", "name_uz": "birthday"}, {"type": "string", "child": false, "field": "registration_date", "name_cr": "registration_date", "name_en": "registration_date", "name_ru": "registration_date", "name_uz": "registration_date"}, {"type": "string", "child": false, "field": "is_tax_payed", "name_cr": "is_tax_payed", "name_en": "is_tax_payed", "name_ru": "is_tax_payed", "name_uz": "is_tax_payed"}, {"type": "string", "child": false, "field": "mahalla", "name_cr": "mahalla", "name_en": "mahalla", "name_ru": "mahalla", "name_uz": "mahalla"}, {"type": "string", "child": false, "field": "master_id", "name_cr": "master_id", "name_en": "master_id", "name_ru": "master_id", "name_uz": "master_id"}, {"type": "string", "child": false, "field": "master_tin", "name_cr": "master_tin", "name_en": "master_tin", "name_ru": "master_tin", "name_uz": "master_tin"}, {"type": "string", "child": false, "field": "master_pinfl", "name_cr": "master_pinfl", "name_en": "master_pinfl", "name_ru": "master_pinfl", "name_uz": "master_pinfl"}, {"type": "string", "child": false, "field": "master_fio", "name_cr": "master_fio", "name_en": "master_fio", "name_ru": "master_fio", "name_uz": "master_fio"}, {"type": "string", "child": false, "field": "master_phones", "name_cr": "master_phones", "name_en": "master_phones", "name_ru": "master_phones", "name_uz": "master_phones"}, {"type": "string", "child": false, "field": "master_nationality", "name_cr": "master_nationality", "name_en": "master_nationality", "name_ru": "master_nationality", "name_uz": "master_nationality"}, {"type": "string", "child": false, "field": "master_home_region_soato", "name_cr": "master_home_region_soato", "name_en": "master_home_region_soato", "name_ru": "master_home_region_soato", "name_uz": "master_home_region_soato"}, {"type": "string", "child": false, "field": "master_home_sub_region_soato", "name_cr": "master_home_sub_region_soato", "name_en": "master_home_sub_region_soato", "name_ru": "master_home_sub_region_soato", "name_uz": "master_home_sub_region_soato"}, {"type": "string", "child": false, "field": "master_activity_type", "name_cr": "master_activity_type", "name_en": "master_activity_type", "name_ru": "master_activity_type", "name_uz": "master_activity_type"}]}
A90: =MAX(A$2:A89)+1 -> 76 | B90: Mehnat daftarini olish | D90: 1 | E90: ойлик | H90: employement.mehnat_daftar | J90: https://10.190.10.74/api/accounting-chamber/citizen/get-experiences/by-pinfl | K90: Камбағалликни қисқартириш ва бандлик вазирлиги | L90: Жисмоний шахсларнинг электрон меҳнат дафтарчаси тўғрисида маълумотлар | M90: Жисмоний шахсларнинг электрон меҳнат дафтарчаси тўғрисида маълумотлар | N90: {"params": [{"type": "string", "child": false, "field": "company_profile_name", "name_cr": "company_profile_name", "name_en": "company_profile_name", "name_ru": "company_profile_name", "name_uz": "company_profile_name"}, {"type": "string", "child": false, "field": "company_tin", "name_cr": "company_tin", "name_en": "company_tin", "name_ru": "company_tin", "name_uz": "company_tin"}, {"type": "string", "child": false, "field": "passport", "name_cr": "passport", "name_en": "passport", "name_ru": "passport", "name_uz": "passport"}, {"type": "string", "child": false, "field": "pin", "name_cr": "pin", "name_en": "pin", "name_ru": "pin", "name_uz": "pin"}, {"type": "string", "child": false, "field": "person_tin", "name_cr": "person_tin", "name_en": "person_tin", "name_ru": "person_tin", "name_uz": "person_tin"}, {"type": "string", "child": false, "field": "full_name", "name_cr": "full_name", "name_en": "full_name", "name_ru": "full_name", "name_uz": "full_name"}, {"type": "string", "child": false, "field": "date_start", "name_cr": "date_start", "name_en": "date_start", "name_ru": "date_start", "name_uz": "date_start"}, {"type": "string", "child": false, "field": "date_stop", "name_cr": "date_stop", "name_en": "date_stop", "name_ru": "date_stop", "name_uz": "date_stop"}, {"type": "string", "child": false, "field": "order_date", "name_cr": "order_date", "name_en": "order_date", "name_ru": "order_date", "name_uz": "order_date"}, {"type": "string", "child": false, "field": "birth_date", "name_cr": "birth_date", "name_en": "birth_date", "name_ru": "birth_date", "name_uz": "birth_date"}, {"type": "string", "child": false, "field": "order_number", "name_cr": "order_number", "name_en": "order_number", "name_ru": "order_number", "name_uz": "order_number"}, {"type": "string", "child": false, "field": "position_name", "name_cr": "position_name", "name_en": "position_name", "name_ru": "position_name", "name_uz": "position_name"}, {"type": "string", "child": false, "field": "structure_name", "name_cr": "structure_name", "name_en": "structure_name", "name_ru": "structure_name", "name_uz": "structure_name"}, {"type": "string", "child": false, "field": "region_soato", "name_cr": "region_soato", "name_en": "region_soato", "name_ru": "region_soato", "name_uz": "region_soato"}, {"type": "string", "child": false, "field": "city_soato", "name_cr": "city_soato", "name_en": "city_soato", "name_ru": "city_soato", "name_uz": "city_soato"}, {"type": "string", "child": false, "field": "rate", "name_cr": "rate", "name_en": "rate", "name_ru": "rate", "name_uz": "rate"}, {"type": "string", "child": false, "field": "city_name", "name_cr": "city_name", "name_en": "city_name", "name_ru": "city_name", "name_uz": "city_name"}, {"type": "string", "child": false, "field": "region_name", "name_cr": "region_name", "name_en": "region_name", "name_ru": "region_name", "name_uz": "region_name"}]}
A91: =MAX(A$2:A90)+1 -> 77 | B91: Hunarmand turistlar | D91: 1 | E91: ойлик | H91: employement.turists | J91: https://hunar.uz/api/accounts-chamber/get-tourist | K91: Ўзбекистон Республикаси “Ҳунарманд” уюшмаси | L91: Туризм фаолияти реестр тўғрисида маълумотлар | M91: Туризм фаолияти реестр тўғрисида маълумотлар | N91: {"params": [{"type": "string", "child": false, "field": "turist_id", "name_cr": "turist_id", "name_en": "turist_id", "name_ru": "turist_id", "name_uz": "turist_id"}, {"type": "string", "child": false, "field": "turist_created_at", "name_cr": "turist_created_at", "name_en": "turist_created_at", "name_ru": "turist_created_at", "name_uz": "turist_created_at"}, {"type": "string", "child": false, "field": "id", "name_cr": "id", "name_en": "id", "name_ru": "id", "name_uz": "id"}, {"type": "string", "child": false, "field": "registration_date", "name_cr": "registration_date", "name_en": "registration_date", "name_ru": "registration_date", "name_uz": "registration_date"}, {"type": "string", "child": false, "field": "tin", "name_cr": "tin", "name_en": "tin", "name_ru": "tin", "name_uz": "tin"}, {"type": "string", "child": false, "field": "pinfl", "name_cr": "pinfl", "name_en": "pinfl", "name_ru": "pinfl", "name_uz": "pinfl"}, {"type": "string", "child": false, "field": "fio", "name_cr": "fio", "name_en": "fio", "name_ru": "fio", "name_uz": "fio"}, {"type": "string", "child": false, "field": "a_region_soato", "name_cr": "a_region_soato", "name_en": "a_region_soato", "name_ru": "a_region_soato", "name_uz": "a_region_soato"}, {"type": "string", "child": false, "field": "a_sub_region_soato", "name_cr": "a_sub_region_soato", "name_en": "a_sub_region_soato", "name_ru": "a_sub_region_soato", "name_uz": "a_sub_region_soato"}, {"type": "string", "child": false, "field": "a_village_soato", "name_cr": "a_village_soato", "name_en": "a_village_soato", "name_ru": "a_village_soato", "name_uz": "a_village_soato"}, {"type": "string", "child": false, "field": "home_region_soato", "name_cr": "home_region_soato", "name_en": "home_region_soato", "name_ru": "home_region_soato", "name_uz": "home_region_soato"}, {"type": "string", "child": false, "field": "home_sub_region_soato", "name_cr": "home_sub_region_soato", "name_en": "home_sub_region_soato", "name_ru": "home_sub_region_soato", "name_uz": "home_sub_region_soato"}, {"type": "string", "child": false, "field": "mahalla", "name_cr": "mahalla", "name_en": "mahalla", "name_ru": "mahalla", "name_uz": "mahalla"}, {"type": "string", "child": false, "field": "home_street", "name_cr": "home_street", "name_en": "home_street", "name_ru": "home_street", "name_uz": "home_street"}, {"type": "string", "child": false, "field": "activity_type", "name_cr": "activity_type", "name_en": "activity_type", "name_ru": "activity_type", "name_uz": "activity_type"}, {"type": "string", "child": false, "field": "expiry_date", "name_cr": "expiry_date", "name_en": "expiry_date", "name_ru": "expiry_date", "name_uz": "expiry_date"}, {"type": "string", "child": false, "field": "birthday", "name_cr": "birthday", "name_en": "birthday", "name_ru": "birthday", "name_uz": "birthday"}, {"type": "string", "child": false, "field": "phones", "name_cr": "phones", "name_en": "phones", "name_ru": "phones", "name_uz": "phones"}]}
B92: 12. Ҳудуд газ
A93: =MAX(A$2:A92)+1 -> 78 | B93: hgt-org-customers | D93: 1 | E93: ойлик | H93: gaz_elektr.gaz_main_data | J93: http://10.190.7.43:8192/hgt-org-customers | K93: "Ҳудудгазтаъминот" АЖ | L93: Улгуржи истеъмолчилар ҳисоблагичлари ва уларнинг фойдаланган газ ҳажмлари тўғрисидаги маълумотлар | M93: Улгуржи истеъмолчилар ҳисоблагичлари ва уларнинг фойдаланган газ ҳажмлари тўғрисидаги маълумотларни олиш | N93: {"params": [{"type": "string", "child": false, "field": "id", "name_cr": "ID", "name_en": "ID", "name_ru": "ID", "name_uz": "ID"}, {"type": "string", "child": false, "field": "customer_code", "name_cr": "Ҳисоб рақами", "name_en": "Ҳисоб рақами", "name_ru": "Ҳисоб рақами", "name_uz": "Ҳисоб рақами"}, {"type": "string", "child": false, "field": "contract_number", "name_cr": "Шартнома рақами", "name_en": "Шартнома рақами", "name_ru": "Шартнома рақами", "name_uz": "Шартнома рақами"}, {"type": "string", "child": false, "field": "contract_date", "name_cr": "Шартнома санаси", "name_en": "Шартнома санаси", "name_ru": "Шартнома санаси", "name_uz": "Шартнома санаси"}, {"type": "string", "child": false, "field": "name", "name_cr": "Ташкилот номи", "name_en": "Ташкилот номи", "name_ru": "Ташкилот номи", "name_uz": "Ташкилот номи"}, {"type": "string", "child": false, "field": "director", "name_cr": "Раҳбар ФИШ", "name_en": "Раҳбар ФИШ", "name_ru": "Раҳбар ФИШ", "name_uz": "Раҳбар ФИШ"}, {"type": "string", "child": false, "field": "regions_id", "name_cr": "Ҳудуд IDси", "name_en": "Ҳудуд IDси", "name_ru": "Ҳудуд IDси", "name_uz": "Ҳудуд IDси"}, {"type": "string", "child": false, "field": "regions_name", "name_cr": "Ҳудуд номи", "name_en": "Ҳудуд номи", "name_ru": "Ҳудуд номи", "name_uz": "Ҳудуд номи"}, {"type": "string", "child": false, "field": "areas_id", "name_cr": "Туман IDси", "name_en": "Туман IDси", "name_ru": "Туман IDси", "name_uz": "Туман IDси"}, {"type": "string", "child": false, "field": "areas_name", "name_cr": "Туман номи", "name_en": "Туман номи", "name_ru": "Туман номи", "name_uz": "Туман номи"}, {"type": "string", "child": false, "field": "address", "name_cr": "Манзил", "name_en": "Манзил", "name_ru": "Манзил", "name_uz": "Манзил"}, {"type": "string", "child": false, "field": "inn", "name_cr": "СТИР", "name_en": "СТИР", "name_ru": "СТИР", "name_uz": "СТИР"}, {"type": "string", "child": false, "field": "phone", "name_cr": "Телефон", "name_en": "Телефон", "name_ru": "Телефон", "name_uz": "Телефон"}, {"type": "string", "child": false, "field": "period", "name_cr": "Ҳисоб-китоб даври", "name_en": "Ҳисоб-китоб даври", "name_ru": "Ҳисоб-китоб даври", "name_uz": "Ҳисоб-китоб даври"}, {"type": "string", "child": false, "field": "saldo_in", "name_cr": "Ой бошига қарздорлик", "name_en": "Ой бошига қарздорлик", "name_ru": "Ой бошига қарздорлик", "name_uz": "Ой бошига қарздорлик"}, {"type": "string", "child": false, "field": "current_balance", "name_cr": "Жорий қолдиқ", "name_en": "Жорий қолдиқ", "name_ru": "Жорий қолдиқ", "name_uz": "Жорий қолдиқ"}, {"type": "string", "child": false, "field": "gas_limit", "name_cr": "Газ бўйича лимит", "name_en": "Газ бўйича лимит", "name_ru": "Газ бўйича лимит", "name_uz": "Газ бўйича лимит"}, {"type": "string", "child": false, "field": "gas_consume", "name_cr": "Газ истеъмоли", "name_en": "Газ истеъмоли", "name_ru": "Газ истеъмоли", "name_uz": "Газ истеъмоли"}, {"type": "string", "child": false, "field": "gas_overlimit", "name_cr": "Лимитдан ортиқча газ истеъмоли", "name_en": "Лимитдан ортиқча газ истеъмоли", "name_ru": "Лимитдан ортиқча газ истеъмоли", "name_uz": "Лимитдан ортиқча газ истеъмоли"}, {"type": "string", "child": false, "field": "accrual_total", "name_cr": "Жами ҳисобланган сумма", "name_en": "Жами ҳисобланган сумма", "name_ru": "Жами ҳисобланган сумма", "name_uz": "Жами ҳисобланган сумма"}, {"type": "string", "child": false, "field": "accrual_overlimit", "name_cr": "Лимитдан ортиқча газ учун ҳисобланган сумма", "name_en": "Лимитдан ортиқча газ учун ҳисобланган сумма", "name_ru": "Лимитдан ортиқча газ учун ҳисобланган сумма", "name_uz": "Лимитдан ортиқча газ учун ҳисобланган сумма"}, {"type": "string", "child": false, "field": "payment_total", "name_cr": "Жами тўланган сумма", "name_en": "Жами тўланган сумма", "name_ru": "Жами тўланган сумма", "name_uz": "Жами тўланган сумма"}, {"type": "string", "child": false, "field": "payment_munis", "name_cr": "Мунис тўлов сумма", "name_en": "Мунис тўлов сумма", "name_ru": "Мунис тўлов сумма", "name_uz": "Мунис тўлов сумма"}, {"type": "string", "child": false, "field": "payment_transfer", "name_cr": "Пул ўтқазма тўлов сумма", "name_en": "Пул ўтқазма тўлов сумма", "name_ru": "Пул ўтқазма тўлов сумма", "name_uz": "Пул ўтқазма тўлов сумма"}, {"type": "string", "child": false, "field": "act", "name_cr": "Далолатнома суммаси", "name_en": "Далолатнома суммаси", "name_ru": "Далолатнома суммаси", "name_uz": "Далолатнома суммаси"}, {"type": "string", "child": false, "field": "saldo_out", "name_cr": "Давр охирига қарздорлик", "name_en": "Давр охирига қарздорлик", "name_ru": "Давр охирига қарздорлик", "name_uz": "Давр охирига қарздорлик"}, {"type": "list", "child": true, "field": "consumers", "name_cr": "Истеъмолчилар", "name_en": "Истеъмолчилар", "name_ru": "Истеъмолчилар", "name_uz": "Истеъмолчилар", "children": [{"type": "string", "child": false, "field": "id", "name_cr": "ID", "name_en": "ID", "name_ru": "ID", "name_uz": "ID"}, {"type": "string", "child": false, "field": "name", "name_cr": "Ташкилот номи", "name_en": "Ташкилот номи", "name_ru": "Ташкилот номи", "name_uz": "Ташкилот номи"}, {"type": "string", "child": false, "field": "regions_id", "name_cr": "Ҳудуд IDси", "name_en": "Ҳудуд IDси", "name_ru": "Ҳудуд IDси", "name_uz": "Ҳудуд IDси"}, {"type": "string", "child": false, "field": "regions_name", "name_cr": "Ҳудуд номи", "name_en": "Ҳудуд номи", "name_ru": "Ҳудуд номи", "name_uz": "Ҳудуд номи"}, {"type": "string", "child": false, "field": "areas_id", "name_cr": "Туман IDси", "name_en": "Туман IDси", "name_ru": "Туман IDси", "name_uz": "Туман IDси"}, {"type": "string", "child": false, "field": "areas_name", "name_cr": "Туман номи", "name_en": "Туман номи", "name_ru": "Туман номи", "name_uz": "Туман номи"}, {"type": "string", "child": false, "field": "address", "name_cr": "Манзил", "name_en": "Манзил", "name_ru": "Манзил", "name_uz": "Манзил"}, {"type": "string", "child": false, "field": "tariff", "name_cr": "Тариф суммаси", "name_en": "Тариф суммаси", "name_ru": "Тариф суммаси", "name_uz": "Тариф суммаси"}, {"type": "string", "child": false, "field": "gas_consume", "name_cr": "Газ истеъмоли", "name_en": "Газ истеъмоли", "name_ru": "Газ истеъмоли", "name_uz": "Газ истеъмоли"}]}]}
A94: =MAX(A$2:A93)+1 -> 79 | B94: ЭР ва ТЖХАБТ томонидан газ етказиб берилган хўжалик юритувчи субъектлар тўғрисида маълумот (кунлик) | D94: 1 | E94: кунлик | H94: uztransgaz.device_data | J94: https://emcapi.utg.uz/api/v3/archive/daily | K94: "Узтрансгаз" АЖ | L94: ЭР ва ТЖХАБ тизими томонидан газ етказиб берилган хўжалик юритувчи субъектлар тўғрисида маълумот (кунлик) | M94: ЭР ва ТЖХАБ тизими томонидан газ етказиб берилган хўжалик юритувчи субъектлар тўғрисида маълумот (кунлик) | N94: {"params": [{"type": "string", "child": false, "field": "requestedDate", "name_cr": "Ҳисоблагич кўрсаткичи санаси", "name_en": "Ҳисоблагич кўрсаткичи санаси", "name_ru": "Ҳисоблагич кўрсаткичи санаси", "name_uz": "Ҳисоблагич кўрсаткичи санаси"}, {"type": "int", "child": false, "field": "valuesCount", "name_cr": "Юборилган қийматлар сони", "name_en": "Юборилган қийматлар сони", "name_ru": "Юборилган қийматлар сони", "name_uz": "Юборилган қийматлар сони"}, {"type": "string", "child": false, "field": "pointCode", "name_cr": "Объектнинг уникал рақами", "name_en": "Объектнинг уникал рақами", "name_ru": "Объектнинг уникал рақами", "name_uz": "Объектнинг уникал рақами"}, {"type": "int", "child": false, "field": "pointId", "name_cr": "Ҳисоблагич ID си", "name_en": "Ҳисоблагич ID си", "name_ru": "Ҳисоблагич ID си", "name_uz": "Ҳисоблагич ID си"}, {"type": "string", "child": false, "field": "deviceSerialNumber", "name_cr": "Ҳисоблагичнинг завод рақами", "name_en": "Ҳисоблагичнинг завод рақами", "name_ru": "Ҳисоблагичнинг завод рақами", "name_uz": "Ҳисоблагичнинг завод рақами"}, {"type": "string", "child": false, "field": "deviceType", "name_cr": "Ҳисоблагич тури", "name_en": "Ҳисоблагич тури", "name_ru": "Ҳисоблагич тури", "name_uz": "Ҳисоблагич тури"}, {"type": "list", "child": true, "field": "values", "name_cr": "Қийматлар", "name_en": "Қийматлар", "name_ru": "Қийматлар", "name_uz": "Қийматлар", "children": [{"type": "string", "child": false, "field": "timestamp", "name_cr": "Ҳисоблагич кўрсатгич санаси", "name_en": "Ҳисоблагич кўрсатгич санаси", "name_ru": "Ҳисоблагич кўрсатгич санаси", "name_uz": "Ҳисоблагич кўрсатгич санаси"}, {"type": "string", "child": false, "field": "differentialPressure", "name_cr": "Ҳисоблагичдаги босим-нинг дефференциал кўрсаткичи (1440 дақиқа dP (Па))", "name_en": "Ҳисоблагичдаги босим-нинг дефференциал кўрсаткичи (1440 дақиқа dP (Па))", "name_ru": "Ҳисоблагичдаги босим-нинг дефференциал кўрсаткичи (1440 дақиқа dP (Па))", "name_uz": "Ҳисоблагичдаги босим-нинг дефференциал кўрсаткичи (1440 дақиқа dP (Па))"}, {"type": "string", "child": false, "field": "pressure", "name_cr": "Ҳисоблагичдаги босим-нинг кўрсаткичи (1440 дақиқа dP (Па))", "name_en": "Ҳисоблагичдаги босим-нинг кўрсаткичи (1440 дақиқа dP (Па))", "name_ru": "Ҳисоблагичдаги босим-нинг кўрсаткичи (1440 дақиқа dP (Па))", "name_uz": "Ҳисоблагичдаги босим-нинг кўрсаткичи (1440 дақиқа dP (Па))"}, {"type": "string", "child": false, "field": "temperature", "name_cr": "Ҳисоблагичдаги ҳарорат (1440 дақиқа Т (С))", "name_en": "Ҳисоблагичдаги ҳарорат (1440 дақиқа Т (С))", "name_ru": "Ҳисоблагичдаги ҳарорат (1440 дақиқа Т (С))", "name_uz": "Ҳисоблагичдаги ҳарорат (1440 дақиқа Т (С))"}, {"type": "string", "child": false, "field": "volume", "name_cr": "Ҳисоблагичдан ўтган газ ҳажми (1440 дақиқа Q (м3))", "name_en": "Ҳисоблагичдан ўтган газ ҳажми (1440 дақиқа Q (м3))", "name_ru": "Ҳисоблагичдан ўтган газ ҳажми (1440 дақиқа Q (м3))", "name_uz": "Ҳисоблагичдан ўтган газ ҳажми (1440 дақиқа Q (м3))"}, {"type": "string", "child": false, "field": "accountingTime", "name_cr": "Газ ҳисоблагичнинг ишлаш вақти (соат)", "name_en": "Газ ҳисоблагичнинг ишлаш вақти (соат)", "name_ru": "Газ ҳисоблагичнинг ишлаш вақти (соат)", "name_uz": "Газ ҳисоблагичнинг ишлаш вақти (соат)"}]}]}
A95: =MAX(A$2:A94)+1 -> 80 | B95: #ЭР ва ТЖХАБТ мавжуд хисобга олиш пунктлари тўғрисидаги маълумот (pointId) олиш | D95: 1 | E95: ойлик | H95: uztransgaz.point_ids | J95: https://emcapi.utg.uz/api/v3/points/ids
A96: =MAX(A$2:A95)+1 -> 81 | B96: #ЭР ва ТЖХАБТ томонидан газ оқими ҳисобини юритувчи ўлчов ҳисоблагичлари тўғрисида маълумот | D96: 1 | E96: сўровга асосан | H96: uztransgaz.points_info | J96: https://emcapi.utg.uz/api/v3/point
B97: 13. Экология
A98: =MAX(A$2:A97)+1 -> 82 | B98: #“Кон ишларини ривожлантириш йиллик # режалари”да қазиб олиниши кутилаётган фойдали қазилмаларнинг ч | D98: 1 | E98: ойлик | H98: geo_eco.choraklik_hajm | J98: http://geoservice.uz/api/v1/hp/fourth-table | K98: Тоғ-кон саноати ва геология вазирлиги | L98: “Кон ишларини ривожлантириш йиллик режалари”да қазиб олиниши кутилаётган фойдали қазилмаларнинг чораклар кесимидаги ҳажмлари | M98: “Кон ишларини ривожлантириш йиллик режалари”да қазиб олиниши кутилаётган фойдали қазилмаларнинг чораклар кесимидаги ҳажмлари тўғрисидаги маълумотлар | N98: {"params": [{"type": "string", "child": false, "field": "id", "name_cr": "id", "name_en": "id", "name_ru": "id", "name_uz": "id"}, {"type": "string", "child": false, "field": "region_id", "name_cr": "region_id", "name_en": "region_id", "name_ru": "region_id", "name_uz": "region_id"}, {"type": "string", "child": false, "field": "district_id", "name_cr": "district_id", "name_en": "district_id", "name_ru": "district_id", "name_uz": "district_id"}, {"type": "string", "child": false, "field": "region_name", "name_cr": "region_name", "name_en": "region_name", "name_ru": "region_name", "name_uz": "region_name"}, {"type": "string", "child": false, "field": "district_name", "name_cr": "district_name", "name_en": "district_name", "name_ru": "district_name", "name_uz": "district_name"}, {"type": "string", "child": false, "field": "name", "name_cr": "name", "name_en": "name", "name_ru": "name", "name_uz": "name"}, {"type": "string", "child": false, "field": "tin", "name_cr": "tin", "name_en": "tin", "name_ru": "tin", "name_uz": "tin"}, {"type": "string", "child": false, "field": "bground_name", "name_cr": "bground_name", "name_en": "bground_name", "name_ru": "bground_name", "name_uz": "bground_name"}, {"type": "string", "child": false, "field": "bground_address", "name_cr": "bground_address", "name_en": "bground_address", "name_ru": "bground_address", "name_uz": "bground_address"}, {"type": "string", "child": false, "field": "product_name", "name_cr": "product_name", "name_en": "product_name", "name_ru": "product_name", "name_uz": "product_name"}, {"type": "string", "child": false, "field": "unit", "name_cr": "unit", "name_en": "unit", "name_ru": "unit", "name_uz": "unit"}, {"type": "string", "child": false, "field": "volume", "name_cr": "volume", "name_en": "volume", "name_ru": "volume", "name_uz": "volume"}, {"type": "string", "child": false, "field": "remainder", "name_cr": "remainder", "name_en": "remainder", "name_ru": "remainder", "name_uz": "remainder"}, {"type": "string", "child": false, "field": "remainder_end", "name_cr": "remainder_end", "name_en": "remainder_end", "name_ru": "remainder_end", "name_uz": "remainder_end"}]}
A99: =MAX(A$2:A98)+1 -> 83 | B99: Ер қаъри участкаларидан фойдаланувчилар томонидан йиллик қазиб олинган # фойдали қазилмалар ҳажмлари | D99: 1 | E99: ойлик | H99: geo_eco.qazilma_hajmi | J99: http://geoservice.uz/api/v1/hp/second-table | K99: Тоғ-кон саноати ва геология вазирлиги | L99: Ер қаъри участкаларидан фойдаланувчилар томонидан йиллик қазиб олинган фойдали қазилмалар ҳажмлари | M99: Ер қаъри участкаларидан фойдаланувчилар томонидан йиллик қазиб олинган фойдали қазилмалар ҳажмлари тўғрисидаги маълумотлар | N99: {"params": [{"type": "string", "child": false, "field": "id", "name_cr": "id", "name_en": "id", "name_ru": "id", "name_uz": "id"}, {"type": "string", "child": false, "field": "region", "name_cr": "region", "name_en": "region", "name_ru": "region", "name_uz": "region"}, {"type": "string", "child": false, "field": "region_name", "name_cr": "region_name", "name_en": "region_name", "name_ru": "region_name", "name_uz": "region_name"}, {"type": "string", "child": false, "field": "district", "name_cr": "district", "name_en": "district", "name_ru": "district", "name_uz": "district"}, {"type": "string", "child": false, "field": "district_name", "name_cr": "district_name", "name_en": "district_name", "name_ru": "district_name", "name_uz": "district_name"}, {"type": "string", "child": false, "field": "name", "name_cr": "name", "name_en": "name", "name_ru": "name", "name_uz": "name"}, {"type": "string", "child": false, "field": "tin", "name_cr": "tin", "name_en": "tin", "name_ru": "tin", "name_uz": "tin"}, {"type": "string", "child": false, "field": "bground_name", "name_cr": "bground_name", "name_en": "bground_name", "name_ru": "bground_name", "name_uz": "bground_name"}, {"type": "string", "child": false, "field": "bground_address", "name_cr": "bground_address", "name_en": "bground_address", "name_ru": "bground_address", "name_uz": "bground_address"}, {"type": "string", "child": false, "field": "product_name", "name_cr": "product_name", "name_en": "product_name", "name_ru": "product_name", "name_uz": "product_name"}, {"type": "string", "child": false, "field": "unit", "name_cr": "unit", "name_en": "unit", "name_ru": "unit", "name_uz": "unit"}, {"type": "string", "child": false, "field": "volume", "name_cr": "volume", "name_en": "volume", "name_ru": "volume", "name_uz": "volume"}, {"type": "string", "child": false, "field": "remainder", "name_cr": "remainder", "name_en": "remainder", "name_ru": "remainder", "name_uz": "remainder"}, {"type": "string", "child": false, "field": "remainder_end", "name_cr": "remainder_end", "name_en": "remainder_end", "name_ru": "remainder_end", "name_uz": "remainder_end"}]}
A100: =MAX(A$2:A99)+1 -> 84 | B100: Qum shag'al excel eksport | D100: 1 | E100: ойлик | H100: geo_eco.tax_qum_shagal
A101: =MAX(A$2:A100)+1 -> 85 | B101: Ер ости сувларидан фойдаланувчи тадбиркорлик субъектлари ва олинган сув ҳажми тўғрисидаги маълумотла | D101: 1 | E101: ойлик | H101: geo_eco.yer_osti_suv | J101: http://geoservice.uz/api/v1/hp/third-table | K101: Тоғ-кон саноати ва геология вазирлиги | L101: Ер ости сувларидан фойдаланувчи тадбиркорлик субъектлари ва олинган сув ҳажми | M101: Ер ости сувларидан фойдаланувчи тадбиркорлик субъектлари ва олинган сув ҳажми тўғрисидаги маълумотлар | N101: {"params": [{"type": "string", "child": false, "field": "id", "name_cr": "id", "name_en": "id", "name_ru": "id", "name_uz": "id"}, {"type": "string", "child": false, "field": "region_id", "name_cr": "region_id", "name_en": "region_id", "name_ru": "region_id", "name_uz": "region_id"}, {"type": "string", "child": false, "field": "district_id", "name_cr": "district_id", "name_en": "district_id", "name_ru": "district_id", "name_uz": "district_id"}, {"type": "string", "child": false, "field": "region_name", "name_cr": "region_name", "name_en": "region_name", "name_ru": "region_name", "name_uz": "region_name"}, {"type": "string", "child": false, "field": "district_name", "name_cr": "district_name", "name_en": "district_name", "name_ru": "district_name", "name_uz": "district_name"}, {"type": "string", "child": false, "field": "name", "name_cr": "name", "name_en": "name", "name_ru": "name", "name_uz": "name"}, {"type": "string", "child": false, "field": "tin", "name_cr": "tin", "name_en": "tin", "name_ru": "tin", "name_uz": "tin"}, {"type": "string", "child": false, "field": "lic_date", "name_cr": "lic_date", "name_en": "lic_date", "name_ru": "lic_date", "name_uz": "lic_date"}, {"type": "string", "child": false, "field": "lic_num", "name_cr": "lic_num", "name_en": "lic_num", "name_ru": "lic_num", "name_uz": "lic_num"}, {"type": "string", "child": false, "field": "lic_period", "name_cr": "lic_period", "name_en": "lic_period", "name_ru": "lic_period", "name_uz": "lic_period"}, {"type": "string", "child": false, "field": "wather_pur", "name_cr": "wather_pur", "name_en": "wather_pur", "name_ru": "wather_pur", "name_uz": "wather_pur"}, {"type": "string", "child": false, "field": "wather_dlim", "name_cr": "wather_dlim", "name_en": "wather_dlim", "name_ru": "wather_dlim", "name_uz": "wather_dlim"}, {"type": "string", "child": false, "field": "wather_ylim", "name_cr": "wather_ylim", "name_en": "wather_ylim", "name_ru": "wather_ylim", "name_uz": "wather_ylim"}, {"type": "string", "child": false, "field": "wather_all", "name_cr": "wather_all", "name_en": "wather_all", "name_ru": "wather_all", "name_uz": "wather_all"}, {"type": "string", "child": false, "field": "diff", "name_cr": "diff", "name_en": "diff", "name_ru": "diff", "name_uz": "diff"}]}
A102: =MAX(A$2:A101)+1 -> 86 | B102: Ер қаъри участкаларидан фойдаланиш ҳуқуқи учун лицензия берилганлиги, # уларнинг амал қилиши вақтинч | D102: 1 | E102: ойлик | H102: geo_eco.yer_osti_uchastka | J102: http://geoservice.uz/api/v1/hp/first-table | K102: Тоғ-кон саноати ва геология вазирлиги | L102: Ер қаъри участкаларидан фойдаланиш ҳуқуқи учун лицензия берилганлиги, уларнинг амал қилиши вақтинча тўхтатилганлиги ва тугатилганлиги, ҳамда мазкур ҳужжатлар бекор қилинганлиги тўғрисидаги маълумотлар | M102: Тоғ-кон саноати ва геология вазирлиги томонидан тақдим этилган | N102: {"params": [{"type": "string", "child": false, "field": "id", "name_cr": "id", "name_en": "id", "name_ru": "id", "name_uz": "id"}, {"type": "string", "child": false, "field": "org_name", "name_cr": "org_name", "name_en": "org_name", "name_ru": "org_name", "name_uz": "org_name"}, {"type": "string", "child": false, "field": "stir", "name_cr": "stir", "name_en": "stir", "name_ru": "stir", "name_uz": "stir"}, {"type": "string", "child": false, "field": "bground_name", "name_cr": "bground_name", "name_en": "bground_name", "name_ru": "bground_name", "name_uz": "bground_name"}, {"type": "string", "child": false, "field": "bground_address", "name_cr": "bground_address", "name_en": "bground_address", "name_ru": "bground_address", "name_uz": "bground_address"}, {"type": "string", "child": false, "field": "license_date", "name_cr": "license_date", "name_en": "license_date", "name_ru": "license_date", "name_uz": "license_date"}, {"type": "string", "child": false, "field": "license_drop", "name_cr": "license_drop", "name_en": "license_drop", "name_ru": "license_drop", "name_uz": "license_drop"}, {"type": "string", "child": false, "field": "license_end", "name_cr": "license_end", "name_en": "license_end", "name_ru": "license_end", "name_uz": "license_end"}, {"type": "string", "child": false, "field": "license_name", "name_cr": "license_name", "name_en": "license_name", "name_ru": "license_name", "name_uz": "license_name"}, {"type": "string", "child": false, "field": "license_num", "name_cr": "license_num", "name_en": "license_num", "name_ru": "license_num", "name_uz": "license_num"}, {"type": "string", "child": false, "field": "license_period", "name_cr": "license_period", "name_en": "license_period", "name_ru": "license_period", "name_uz": "license_period"}, {"type": "string", "child": false, "field": "license_sery", "name_cr": "license_sery", "name_en": "license_sery", "name_ru": "license_sery", "name_uz": "license_sery"}, {"type": "string", "child": false, "field": "license_stop", "name_cr": "license_stop", "name_en": "license_stop", "name_ru": "license_stop", "name_uz": "license_stop"}, {"type": "string", "child": false, "field": "license_type", "name_cr": "license_type", "name_en": "license_type", "name_ru": "license_type", "name_uz": "license_type"}, {"type": "string", "child": false, "field": "region", "name_cr": "region", "name_en": "region", "name_ru": "region", "name_uz": "region"}, {"type": "string", "child": false, "field": "district", "name_cr": "district", "name_en": "district", "name_ru": "district", "name_uz": "district"}, {"type": "string", "child": false, "field": "olicense_sery", "name_cr": "olicense_sery", "name_en": "olicense_sery", "name_ru": "olicense_sery", "name_uz": "olicense_sery"}, {"type": "string", "child": false, "field": "olicense_num", "name_cr": "olicense_num", "name_en": "olicense_num", "name_ru": "olicense_num", "name_uz": "olicense_num"}, {"type": "string", "child": false, "field": "olicense_type", "name_cr": "olicense_type", "name_en": "olicense_type", "name_ru": "olicense_type", "name_uz": "olicense_type"}, {"type": "string", "child": false, "field": "olicense_date", "name_cr": "olicense_date", "name_en": "olicense_date", "name_ru": "olicense_date", "name_uz": "olicense_date"}, {"type": "string", "child": false, "field": "unit", "name_cr": "unit", "name_en": "unit", "name_ru": "unit", "name_uz": "unit"}, {"type": "string", "child": false, "field": "volume", "name_cr": "volume", "name_en": "volume", "name_ru": "volume", "name_uz": "volume"}, {"type": "string", "child": false, "field": "created_at", "name_cr": "created_at", "name_en": "created_at", "name_ru": "created_at", "name_uz": "created_at"}, {"type": "string", "child": false, "field": "region_name", "name_cr": "region_name", "name_en": "region_name", "name_ru": "region_name", "name_uz": "region_name"}, {"type": "string", "child": false, "field": "district_name", "name_cr": "district_name", "name_en": "district_name", "name_ru": "district_name", "name_uz": "district_name"}]}
B103: 14. Капитал қуйилмалар
A104: =MAX(A$2:A103)+1 -> 87 | B104: Қурилиш объектлари кодлари тўғрисида маълумот олиш | D104: 1 | E104: ойлик | H104: kapital_quyilma.object_codes | J104: https://kapital-admin.imv.uz/api/rest-api/api/audit/object-codes
A105: =MAX(A$2:A104)+1 -> 88 | B105: Қурилиш объекти тўғрисида тўлиқ маълумот олиш | D105: 1 | E105: ойлик | H105: kapital_quyilma.project_data | J105: https://kapital-admin.imv.uz/api/rest-api/api/audit/object-detail | K105: Иқтисодиёт ва молия вазирлиги | L105: Қурилиш қўйилмалари: Қурилиш объекти тўғрисида тўлиқ маълумот олиш | M105: Қурилиш қўйилмалари: Қурилиш объекти тўғрисида тўлиқ маълумот олиш | N105: {"params": [{"type": "string", "child": false, "field": "id", "name_cr": "Лойиҳа ID cи", "name_en": "Лойиҳа ID cи", "name_ru": "Лойиҳа ID cи", "name_uz": "Лойиҳа ID cи"}, {"type": "string", "child": false, "field": "objectCode", "name_cr": "Қурилиш объекти ID cи", "name_en": "Қурилиш объекти ID cи", "name_ru": "Қурилиш объекти ID cи", "name_uz": "Қурилиш объекти ID cи"}, {"type": "string", "child": false, "field": "objectName", "name_cr": "Қурилиш объектининг номи ", "name_en": "Қурилиш объектининг номи ", "name_ru": "Қурилиш объектининг номи ", "name_uz": "Қурилиш объектининг номи "}, {"type": "string", "child": false, "field": "sphereName", "name_cr": "Қурилиш объектининг соҳаси", "name_en": "Қурилиш объектининг соҳаси", "name_ru": "Қурилиш объектининг соҳаси", "name_uz": "Қурилиш объектининг соҳаси"}, {"type": "string", "child": false, "field": "networkName", "name_cr": "Қурилиш объектининг йўналиши", "name_en": "Қурилиш объектининг йўналиши", "name_ru": "Қурилиш объектининг йўналиши", "name_uz": "Қурилиш объектининг йўналиши"}, {"type": "string", "child": false, "field": "regionName", "name_cr": "Объект жойлашган ҳудуд номи", "name_en": "Объект жойлашган ҳудуд номи", "name_ru": "Объект жойлашган ҳудуд номи", "name_uz": "Объект жойлашган ҳудуд номи"}, {"type": "string", "child": false, "field": "districtName", "name_cr": "Объект жойлашган туман (шаҳар) номи", "name_en": "Объект жойлашган туман (шаҳар) номи", "name_ru": "Объект жойлашган туман (шаҳар) номи", "name_uz": "Объект жойлашган туман (шаҳар) номи"}, {"type": "string", "child": false, "field": "constructionTypeName", "name_cr": "Қурилиш тури номи", "name_en": "Қурилиш тури номи", "name_ru": "Қурилиш тури номи", "name_uz": "Қурилиш тури номи"}, {"type": "string", "child": false, "field": "periodicityName", "name_cr": "Лойиҳа статуси (янгидан бошланувчи, йилдан йилга ўтувчи)", "name_en": "Лойиҳа статуси (янгидан бошланувчи, йилдан йилга ўтувчи)", "name_ru": "Лойиҳа статуси (янгидан бошланувчи, йилдан йилга ўтувчи)", "name_uz": "Лойиҳа статуси (янгидан бошланувчи, йилдан йилга ўтувчи)"}, {"type": "string", "child": false, "field": "fundingSourceName", "name_cr": "Молиялаштириш манбаси", "name_en": "Молиялаштириш манбаси", "name_ru": "Молиялаштириш манбаси", "name_uz": "Молиялаштириш манбаси"}, {"type": "string", "child": false, "field": "statusName", "name_cr": "Объект амалга ошириш ҳолати", "name_en": "Объект амалга ошириш ҳолати", "name_ru": "Объект амалга ошириш ҳолати", "name_uz": "Объект амалга ошириш ҳолати"}, {"type": "string", "child": false, "field": "totalCost", "name_cr": "Лойиҳа қиймати", "name_en": "Лойиҳа қиймати", "name_ru": "Лойиҳа қиймати", "name_uz": "Лойиҳа қиймати"}, {"type": "string", "child": false, "field": "accounts", "name_cr": "Объектнинг шахсий ғазна ҳисобварағи", "name_en": "Объектнинг шахсий ғазна ҳисобварағи", "name_ru": "Объектнинг шахсий ғазна ҳисобварағи", "name_uz": "Объектнинг шахсий ғазна ҳисобварағи"}, {"type": "string", "child": false, "field": "implementationPeriod", "name_cr": "Амалга ошириш даври", "name_en": "Амалга ошириш даври", "name_ru": "Амалга ошириш даври", "name_uz": "Амалга ошириш даври"}, {"type": "string", "child": false, "field": "link", "name_cr": "Ҳаволалар", "name_en": "Ҳаволалар", "name_ru": "Ҳаволалар", "name_uz": "Ҳаволалар"}, {"type": "string", "child": false, "field": "funding", "name_cr": "Молиялаштириш", "name_en": "Молиялаштириш", "name_ru": "Молиялаштириш", "name_uz": "Молиялаштириш"}, {"type": "string", "child": false, "field": "customerDetail", "name_cr": "Буюртмачи маълумотлари", "name_en": "Буюртмачи маълумотлари", "name_ru": "Буюртмачи маълумотлари", "name_uz": "Буюртмачи маълумотлари"}, {"type": "string", "child": false, "field": "designerDetails", "name_cr": "Лойиҳачи маълумотлари", "name_en": "Лойиҳачи маълумотлари", "name_ru": "Лойиҳачи маълумотлари", "name_uz": "Лойиҳачи маълумотлари"}, {"type": "string", "child": false, "field": "builderDetails", "name_cr": "Пудратчи маълумотлари", "name_en": "Пудратчи маълумотлари", "name_ru": "Пудратчи маълумотлари", "name_uz": "Пудратчи маълумотлари"}, {"type": "string", "child": false, "field": "designerContracts", "name_cr": "Лойиҳа шартномаси", "name_en": "Лойиҳа шартномаси", "name_ru": "Лойиҳа шартномаси", "name_uz": "Лойиҳа шартномаси"}, {"type": "string", "child": false, "field": "builderContracts", "name_cr": "Пудратчи шартномаси", "name_en": "Пудратчи шартномаси", "name_ru": "Пудратчи шартномаси", "name_uz": "Пудратчи шартномаси"}, {"type": "string", "child": false, "field": "designerPayments", "name_cr": "Лойиҳачи ташкилотнинг тўлов кўрсатгичлари", "name_en": "Лойиҳачи ташкилотнинг тўлов кўрсатгичлари", "name_ru": "Лойиҳачи ташкилотнинг тўлов кўрсатгичлари", "name_uz": "Лойиҳачи ташкилотнинг тўлов кўрсатгичлари"}, {"type": "string", "child": false, "field": "builderPayments", "name_cr": "Пудратчи ташкилотнинг тўлов кўрсатгичлари", "name_en": "Пудратчи ташкилотнинг тўлов кўрсатгичлари", "name_ru": "Пудратчи ташкилотнинг тўлов кўрсатгичлари", "name_uz": "Пудратчи ташкилотнинг тўлов кўрсатгичлари"}, {"type": "string", "child": false, "field": "designerInvoices", "name_cr": "Лойиҳачи ташкилотнинг ҳисоб-фактура кўрсатгичлари", "name_en": "Лойиҳачи ташкилотнинг ҳисоб-фактура кўрсатгичлари", "name_ru": "Лойиҳачи ташкилотнинг ҳисоб-фактура кўрсатгичлари", "name_uz": "Лойиҳачи ташкилотнинг ҳисоб-фактура кўрсатгичлари"}, {"type": "string", "child": false, "field": "builderInvoices", "name_cr": "Пудратчи ташкилотнинг ҳисоб-фактура кўрсатгичлари", "name_en": "Пудратчи ташкилотнинг ҳисоб-фактура кўрсатгичлари", "name_ru": "Пудратчи ташкилотнинг ҳисоб-фактура кўрсатгичлари", "name_uz": "Пудратчи ташкилотнинг ҳисоб-фактура кўрсатгичлари"}]}
B106: 14. Пенсия жамғармаси
A107: =MAX(A$2:A106)+1 -> 89 | B107: Pensiya Malumotlari | D107: 1 | E107: кунлик | H107: pensiya.sched
B108: 15. Қимматли қоғозлар
A109: =MAX(A$2:A108)+1 -> 90 | B109: Қимматли қоғозлар тўғрисидаги маълумотларни олиш | D109: 1 | E109: ойлик | H109: qimmatli_qogoz.qimmatli_qogoz | J109: http://10.190.36.226:5000/api/schetnayaPalata/sendRequest
B110: 16. Қишлоқ хўжалиги вазирлиги
A111: =MAX(A$2:A110)+1 -> 91 | B111: Лотларни туман кесимида маълум периодга схифалаб олиш Qishloq xo'jaligi | D111: 1 | E111: ойлик | H111: qishloq_xojaligi.auction_data | J111: http://10.190.25.12/api/integration/winners/info-list
A112: =MAX(A$2:A111)+1 -> 92 | B112: Qishloq Xo'jaligi E-ijara | D112: 1 | E112: ойлик | H112: qishloq_xojaligi.e_ijara | J112: https://api.agro.uz/openapi/hisob_palata/fetch-eijara | K112: Қишлоқ хўжалиги вазирлиги | L112: Қишлоқ хўжалиги ерларини "E-IJARA" ахборот тизимига киритилиши ва "E-AUKSION" га чиқарилиши натижасида ғолиб бўлган субъектлар тўғрисида маълумотлар | M112: Қишлоқ хўжалиги ерларини "E-IJARA" ахборот тизимига киритилиши ва "E-AUKSION" га чиқарилиши натижасида ғолиб бўлган субъектлар тўғрисида маълумотлар | N112: {"params": [{"type": "string", "child": false, "field": "area", "name_cr": "area", "name_en": "area", "name_ru": "area", "name_uz": "area"}, {"type": "string", "child": false, "field": "contract", "name_cr": "contract", "name_en": "contract", "name_ru": "contract", "name_uz": "contract"}, {"type": "string", "child": false, "field": "contract_url", "name_cr": "contract_url", "name_en": "contract_url", "name_ru": "contract_url", "name_uz": "contract_url"}, {"type": "string", "child": false, "field": "district", "name_cr": "district", "name_en": "district", "name_ru": "district", "name_uz": "district"}, {"type": "string", "child": false, "field": "district_id", "name_cr": "district_id", "name_en": "district_id", "name_ru": "district_id", "name_uz": "district_id"}, {"type": "string", "child": false, "field": "inn", "name_cr": "inn", "name_en": "inn", "name_ru": "inn", "name_uz": "inn"}, {"type": "string", "child": false, "field": "name", "name_cr": "name", "name_en": "name", "name_ru": "name", "name_uz": "name"}, {"type": "string", "child": false, "field": "pin", "name_cr": "pin", "name_en": "pin", "name_ru": "pin", "name_uz": "pin"}, {"type": "string", "child": false, "field": "region", "name_cr": "region", "name_en": "region", "name_ru": "region", "name_uz": "region"}, {"type": "string", "child": false, "field": "region_id", "name_cr": "region_id", "name_en": "region_id", "name_ru": "region_id", "name_uz": "region_id"}, {"type": "string", "child": false, "field": "regnum", "name_cr": "regnum", "name_en": "regnum", "name_ru": "regnum", "name_uz": "regnum"}, {"type": "string", "child": false, "field": "subject_type", "name_cr": "subject_type", "name_en": "subject_type", "name_ru": "subject_type", "name_uz": "subject_type"}, {"type": "string", "child": false, "field": "summa", "name_cr": "summa", "name_en": "summa", "name_ru": "summa", "name_uz": "summa"}]}
A113: =MAX(A$2:A112)+1 -> 93 | B113: Qishloq xo'jaligi Subsidiya | D113: 1 | E113: ойлик | H113: qishloq_xojaligi.subsidiya | J113: https://api.agro.uz/openapi/hisob_palata/fetch-subsidiya | K113: Қишлоқ хўжалиги вазирлиги | L113: Қишлоқ хўжалиги субъектларига ажратилган субсидиялар тўғрисида маълумот | M113: Қишлоқ хўжалиги субъектларига ажратилган субсидиялар тўғрисида маълумот | N113: {"params": [{"type": "string", "child": false, "field": "District_id", "name_cr": "District_id", "name_en": "District_id", "name_ru": "District_id", "name_uz": "District_id"}, {"type": "string", "child": false, "field": "Ekin_turi", "name_cr": "Ekin_turi", "name_en": "Ekin_turi", "name_ru": "Ekin_turi", "name_uz": "Ekin_turi"}, {"type": "string", "child": false, "field": "OrgInn", "name_cr": "OrgInn", "name_en": "OrgInn", "name_ru": "OrgInn", "name_uz": "OrgInn"}, {"type": "string", "child": false, "field": "OrgName", "name_cr": "OrgName", "name_en": "OrgName", "name_ru": "OrgName", "name_uz": "OrgName"}, {"type": "string", "child": false, "field": "Purpose", "name_cr": "Purpose", "name_en": "Purpose", "name_ru": "Purpose", "name_uz": "Purpose"}, {"type": "string", "child": false, "field": "Region_id", "name_cr": "Region_id", "name_en": "Region_id", "name_ru": "Region_id", "name_uz": "Region_id"}, {"type": "string", "child": false, "field": "Status", "name_cr": "Status", "name_en": "Status", "name_ru": "Status", "name_uz": "Status"}, {"type": "string", "child": false, "field": "Summa_mln", "name_cr": "Summa_mln", "name_en": "Summa_mln", "name_ru": "Summa_mln", "name_uz": "Summa_mln"}, {"type": "string", "child": false, "field": "Task_date", "name_cr": "Task_date", "name_en": "Task_date", "name_ru": "Task_date", "name_uz": "Task_date"}, {"type": "string", "child": false, "field": "Task_done_date", "name_cr": "Task_done_date", "name_en": "Task_done_date", "name_ru": "Task_done_date", "name_uz": "Task_done_date"}, {"type": "string", "child": false, "field": "Task_id", "name_cr": "Task_id", "name_en": "Task_id", "name_ru": "Task_id", "name_uz": "Task_id"}, {"type": "string", "child": false, "field": "district", "name_cr": "district", "name_en": "district", "name_ru": "district", "name_uz": "district"}, {"type": "string", "child": false, "field": "province", "name_cr": "province", "name_en": "province", "name_ru": "province", "name_uz": "province"}, {"type": "string", "child": false, "field": "yer_maydoniHajm", "name_cr": "yer_maydoniHajm", "name_en": "yer_maydoniHajm", "name_ru": "yer_maydoniHajm", "name_uz": "yer_maydoniHajm"}]}
...

Sheet Свод
A1: Ҳисоб палатасининг "Масофавий аудит" автоматлаштирилган ахборот тизимини ишлаб чиқиш босқичлари тўғрисида
A2: МАЪЛУМОТ
A4: № | B4: Модул | C4: Қисқача мазмуни | D4: Жами модуллар | E4: шундан | H4: Қамраб олиш фоизи | I4: Якунланган | J4: Жараёнда фоизи | K4: Режада фоизи | L4: Масъул ходимлар | M4: Ҳозирги ҳолати | N4: Якунлаш муддати
E5: якунланган | F5: жараёндаги | G5: режада (кейинги босқич)
A6: Жами | D6: =+D7+D10+D15+D21+D25+D34+D37+D42+D46+D49+D53+D55+D60+D61+D62+D63+D64+D69+D70+D71+D73+D72+D74+D75+D81+D76 -> 867 | E6: =+E7+E10+E15+E21+E25+E34+E37+E42+E46+E49+E53+E55+E60+E61+E62+E63+E64+E69+E70+E71+E73+E72+E74+E75+E81+E76 -> 821 | F6: =+F7+F10+F15+F21+F25+F34+F37+F42+F46+F49+F53+F55+F60+F61+F62+F63+F64+F69+F70+F71+F73+F72+F74+F75+F81+F76 -> 33 | G6: =+G7+G10+G15+G21+G25+G34+G37+G42+G46+G49+G53+G55+G60+G61+G62+G63+G64+G69+G70+G71+G73+G72+G74+G75+G81+G76 -> 13 | H6: =(E6+F6)/D6 -> 0.98500577 | I6: =E6/D6 -> 0.94694348 | J6: =F6/D6 -> 0.038062284 | K6: =G6/D6 -> 0.014994233
A7: 1 | B7: Тизимларнинг умумий дизайнини ишлаб чиқиш | C7: Мавжуд модулларни фойдаланувчига акс этиш дизайнини ишлаб чиқиш | D7: =SUM(D8:D9) -> 2 | E7: =SUM(E8:E9) -> 1 | F7: =SUM(F8:F9) -> 1 | G7: =SUM(G8:G9) -> 0 | H7: =(E7+F7)/D7 -> 1 | I7: =E7/D7 -> 0.5 | J7: =F7/D7 -> 0.5 | K7: =G7/D7 -> 0 | L7: Ш.Тошпўлатов С.Йўлдошев С.Адизов | M7: Доимий
C8: - тизим дизайнини ишлаб чиқиш | D8: 1 | E8: 0 | F8: 1 | G8: 0 | H8: =(E8+F8)/D8 -> 1 | I8: =E8/D8 -> 0 | J8: =F8/D8 -> 1 | K8: =G8/D8 -> 0
C9: - кунлик ҳисобот маълумотларини ишлаб чиқиш | D9: 1 | E9: 1 | F9: 0 | G9: 0 | H9: =(E9+F9)/D9 -> 1 | I9: =E9/D9 -> 1 | J9: =F9/D9 -> 0 | K9: =G9/D9 -> 0
A10: 2 | B10: Микросервис (автоматик маълумотларни жамлаш тизими) | C10: Вазирлик ва идораларнинг маълумотлар базаларидан кунлик, ойлик ва чораклик маълумотларни Ҳисоб палатасининг маълумотлар базасига жамлаш. | D10: =SUM(D11:D14) -> 150 | E10: =SUM(E11:E14) -> 150 | F10: =SUM(F11:F14) -> 0 | G10: =SUM(G11:G14) -> 0 | H10: =(E10+F10)/D10 -> 1 | I10: =E10/D10 -> 1 | J10: =F10/D10 -> 0 | K10: =G10/D10 -> 0 | L10: Д.Бахриддинов А.Атоев Ж.Дўстқулов А.Гулмуродов | M10: Доимий
C11: - кунлик | D11: =COUNTIFS(Микросервис!D:D,MID(C11,4,99)) -> 53 | E11: =COUNTIFS(Микросервис!D:D,MID(C11,4,99)) -> 53 | F11: =COUNTIFS(Микросервис!D:D,MID(C11,4,99),Микросервис!D:D,0) -> 0 | G11: =D11-E11-F11 -> 0 | H11: =IFERROR((E11+F11)/D11,0) -> 1 | I11: =IFERROR(E11/D11,0) -> 1 | J11: =IFERROR(F11/D11,0) -> 0 | K11: =IFERROR(G11/D11,0) -> 0
C12: - ойлик | D12: =COUNTIFS(Микросервис!D:D,MID(C12,4,99)) -> 97 | E12: =COUNTIFS(Микросервис!D:D,MID(C12,4,99)) -> 97 | F12: =COUNTIFS(Микросервис!D:D,MID(C12,4,99),Микросервис!D:D,0) -> 0 | G12: =D12-E12-F12 -> 0 | H12: =IFERROR((E12+F12)/D12,0) -> 1 | I12: =IFERROR(E12/D12,0) -> 1 | J12: =IFERROR(F12/D12,0) -> 0 | K12: =IFERROR(G12/D12,0) -> 0
C13: - чораклик | D13: =COUNTIFS(Микросервис!D:D,MID(C13,4,99)) -> 0 | E13: =COUNTIFS(Микросервис!D:D,MID(C13,4,99)) -> 0 | F13: =COUNTIFS(Микросервис!D:D,MID(C13,4,99),Микросервис!D:D,0) -> 0 | G13: =D13-E13-F13 -> 0 | H13: =IFERROR((E13+F13)/D13,0) -> 0 | I13: =IFERROR(E13/D13,0) -> 0 | J13: =IFERROR(F13/D13,0) -> 0 | K13: =IFERROR(G13/D13,0) -> 0
C14: - йиллик | D14: =COUNTIFS(Микросервис!D:D,MID(C14,4,99)) -> 0 | E14: =COUNTIFS(Микросервис!D:D,MID(C14,4,99)) -> 0 | F14: =COUNTIFS(Микросервис!D:D,MID(C14,4,99),Микросервис!D:D,0) -> 0 | G14: =D14-E14-F14 -> 0 | H14: =IFERROR((E14+F14)/D14,0) -> 0 | I14: =IFERROR(E14/D14,0) -> 0 | J14: =IFERROR(F14/D14,0) -> 0 | K14: =IFERROR(G14/D14,0) -> 0
A15: 3 | B15: Ташқи манба базаларидан маълумотларни жамлаш | C15: Ҳисоб палатаси томонидан ўтказилаётган назорат тадбирлари учун микросервислар орқали жамланган базалардан маълумотларни олиш. | D15: =SUM(D16:D20) -> 521 | E15: =SUM(E16:E20) -> 505 | F15: =SUM(F16:F20) -> 15 | G15: =SUM(G16:G20) -> 1 | H15: =(E15+F15)/D15 -> 0.99808061 | I15: =E15/D15 -> 0.96928983 | J15: =F15/D15 -> 0.028790787 | K15: =G15/D15 -> 0.0019193858 | L15: О.Рўзимуродов Ҳ.Абдупаттоев А.Гулмуродов Ж.Доуров О.Рўзимуродов Умид, Бахром | M15: Якунланган
C16: - фойдаланувчилар (администратор) томонидан интеграция API ларини дастурга автоматик тарзда улаш | D16: 1 | E16: 1 | F16: 0 | G16: =D16-E16-F16 -> 0 | H16: =(E16+F16)/D16 -> 1 | I16: =E16/D16 -> 1 | J16: =F16/D16 -> 0 | K16: =G16/D16 -> 0
C17: - интеграция ҳужжатларини вазирлик ва идоралар кесимида ташқи манба тизимига бириктириш ва интеграция натижасида олинган маълумотларни устун номларини ўзгартириш | D17: 1 | E17: 1 | F17: 0 | G17: =D17-E17-F17 -> 0 | H17: =(E17+F17)/D17 -> 1 | I17: =E17/D17 -> 1 | J17: =F17/D17 -> 0 | K17: =G17/D17 -> 0
C18: - икки ва ундан ортиқ маълумотларни жамлаш ва юкламалар модули орқали юклаб олиш | D18: 1 | E18: 1 | F18: 0 | G18: =D18-E18-F18 -> 0 | H18: =(E18+F18)/D18 -> 1 | I18: =E18/D18 -> 1 | J18: =F18/D18 -> 0 | K18: =G18/D18 -> 0
C19: Электрон ҳукумат марказидан вазирлик ва идоралар томонидан тақдим этиладиган маълумотларни онлайн олиш | D19: =COUNTIFS('Ташқи манба'!D:D,2) -> 80 | E19: =COUNTIFS('Ташқи манба'!D:D,2) -> 80 | F19: 0 | G19: =D19-E19-F19 -> 0 | H19: =(E19+F19)/D19 -> 1 | I19: =E19/D19 -> 1 | J19: =F19/D19 -> 0 | K19: =G19/D19 -> 0
C20: Вазирлик ва идоралар томонидан тақдим этиладиган маълумотларни тўғридан-тўғри онлайн олиш | D20: =COUNTIFS('Ташқи манба'!A:A,">0")-D19 -> 438 | E20: =COUNTIFS('Ташқи манба'!D:D,1) -> 422 | F20: =COUNTIFS('Ташқи манба'!D:D,3) -> 15 | G20: =D20-E20-F20 -> 1 | H20: =(E20+F20)/D20 -> 0.99771689 | I20: =E20/D20 -> 0.96347032 | J20: =F20/D20 -> 0.034246575 | K20: =G20/D20 -> 0.002283105
A21: 4 | B21: Риск йўналишлари | C21: Ҳисоб палатасининг "Масофавий назорат" маркази ходимлари томонидан тақдим этилган риск йўналишлари | D21: =SUM(D22:D24) -> 75 | E21: =SUM(E22:E24) -> 62 | F21: =SUM(F22:F24) -> 2 | G21: =SUM(G22:G24) -> 11 | H21: =(E21+F21)/D21 -> 0.85333333 | I21: =E21/D21 -> 0.82666667 | J21: =F21/D21 -> 0.026666667 | K21: =G21/D21 -> 0.14666667 | L21: Д.Бахриддинов А.Атоев | M21: Доимий
C22: - Харажат | D22: =COUNTIFS('Риск йўналишлари (1)'!D:D,MID(C22,4,99)) -> 66 | E22: =COUNTIFS('Риск йўналишлари (1)'!D:D,MID(C22,4,99),'Риск йўналишлари (1)'!H:H,"3")+COUNTIFS('Риск йўналишлари (1)'!D:D,MID(C22,4,99),'Риск йўналишлари (1)'!H:H,"4") -> 39 | F22: =COUNTIFS('Риск йўналишлари (1)'!D:D,MID(C22,4,99),'Риск йўналишлари (1)'!H:H,"1") -> 2 | G22: =COUNTIFS('Риск йўналишлари (1)'!D:D,MID(C22,4,99),'Риск йўналишлари (1)'!H:H,"0") -> 11 | H22: =(E22+F22)/D22 -> 0.62121212 | I22: =E22/D22 -> 0.59090909 | J22: =F22/D22 -> 0.03030303 | K22: =G22/D22 -> 0.16666667
C23: - Даромад | D23: =COUNTIFS('Риск йўналишлари (1)'!D:D,MID(C23,4,99)) -> 9 | E23: =COUNTIFS('Риск йўналишлари (1)'!D:D,MID(C23,4,99),'Риск йўналишлари (1)'!H:H,"3")+COUNTIFS('Риск йўналишлари (1)'!D:D,MID(C23,4,99),'Риск йўналишлари (1)'!H:H,"4") -> 9 | F23: =COUNTIFS('Риск йўналишлари (1)'!D:D,MID(C23,4,99),'Риск йўналишлари (1)'!H:H,"1") -> 0 | G23: =COUNTIFS('Риск йўналишлари (1)'!D:D,MID(C23,4,99),'Риск йўналишлари (1)'!H:H,"0") -> 0 | H23: =(E23+F23)/D23 -> 1 | I23: =E23/D23 -> 1 | J23: =F23/D23 -> 0 | K23: =G23/D23 -> 0
C24: - Ишлаб турган риск йўналишлари | D24: 0 | E24: =COUNTIFS('Риск йўналишлари (1)'!H:H,"2") -> 14 | F24: 0 | G24: 0
A25: 5 | B25: Аниқланган камчиликларни бартараф этиш | C25: "Масофавий назорат" маркази томонидан қонун бузилиш риски сифатида баҳоланган ҳолатларни Ҳисоб палатаси томонидан ёки вазирлик ва идоралар (камчиликларни энг қуйи ижрочисигача тушириш ва натижасини олиш) томонидан бартараф этилишини назорат қилиш | D25: =SUM(D26:D33) -> 8 | E25: =SUM(E26:E33) -> 8 | F25: =SUM(F26:F33) -> 0 | G25: =SUM(G26:G33) -> 0 | H25: =(E25+F25)/D25 -> 1 | I25: =E25/D25 -> 1 | J25: =F25/D25 -> 0 | K25: =G25/D25 -> 0 | L25: М.Эшқулов Ҳ.Абдупаттоев А.Атоев | M25: Якунланган
C26: - аниқланган қонун бузилиш ҳолатларини хавф даражаларига тақсимлаш | D26: 1 | E26: 1 | F26: 0 | G26: =D26-E26-F26 -> 0 | H26: =(E26+F26)/D26 -> 1 | I26: =E26/D26 -> 1 | J26: =F26/D26 -> 0 | K26: =G26/D26 -> 0
C27: - қонун бузилиш ҳолатларини бартараф этиш мақсадида масъулларни белгилаш | D27: 1 | E27: 1 | F27: 0 | G27: =D27-E27-F27 -> 0 | H27: =(E27+F27)/D27 -> 1 | I27: =E27/D27 -> 1 | J27: =F27/D27 -> 0 | K27: =G27/D27 -> 0
C28: - қонун бузилиш ҳолатларини бартараф этилишида республика, вилоят, туман ва корхоналарга юбориш, фойдаланувчиларни республика, вилоят ва туман даражаси бўйича ролларни белгилаш. | D28: 1 | E28: 1 | F28: 0 | G28: =D28-E28-F28 -> 0 | H28: =(E28+F28)/D28 -> 1 | I28: =E28/D28 -> 1 | J28: =F28/D28 -> 0 | K28: =G28/D28 -> 0
C29: - қонун бузилиш ҳолатларини бартараф этилишини назорат қилиш (назоратдан ечиш, қайта назоратга юбориш) | D29: 1 | E29: 1 | F29: 0 | G29: =D29-E29-F29 -> 0 | H29: =(E29+F29)/D29 -> 1 | I29: =E29/D29 -> 1 | J29: =F29/D29 -> 0 | K29: =G29/D29 -> 0
C30: - аниқланган ва бартараф этилган ҳолатлар интерфейсини фойдаланувчи томонидан устунларни қўшиш, олиб ташлаш, номларини ўзгартириш. | D30: 1 | E30: 1 | F30: 0 | G30: =D30-E30-F30 -> 0 | H30: =(E30+F30)/D30 -> 1 | I30: =E30/D30 -> 1 | J30: =F30/D30 -> 0 | K30: =G30/D30 -> 0
C31: - аниқланган ва бартараф этилган ҳолатлар юзасидан риск йўналишининг самарадорлигини кузатиш | D31: 1 | E31: 1 | F31: 0 | G31: =D31-E31-F31 -> 0 | H31: =(E31+F31)/D31 -> 1 | I31: =E31/D31 -> 1 | J31: =F31/D31 -> 0 | K31: =G31/D31 -> 0
C32: - риск ҳолатларини аниқлаш жараёнига фойдаланувчи томонидан қўшимча фильтрлар қўшиш орқали аниқланадиган риск ҳолатларини сифатини ошириш (мантиқий назорат) | D32: 1 | E32: 1 | F32: 0 | G32: =D32-E32-F32 -> 0 | H32: =(E32+F32)/D32 -> 1 | I32: =E32/D32 -> 1 | J32: =F32/D32 -> 0 | K32: =G32/D32 -> 0
C33: - риск ҳолатларини аниқлаш жараёнига фойдаланувчиларга тушунтириш мақсадида администраторлар томонидан таҳлил схемасини қўшиш ва ўзгартириш | D33: 1 | E33: 1 | F33: 0 | G33: =D33-E33-F33 -> 0 | H33: =(E33+F33)/D33 -> 1 | I33: =E33/D33 -> 1 | J33: =F33/D33 -> 0 | K33: =G33/D33 -> 0
A34: 6 | B34: Ҳисобот кўрсаткичлари | C34: Риск ҳолатларини аниқланиши ва уларнинг бартараф этилиши юзасидан маълумотлар | D34: =D35+D36 -> 37 | E34: =E35+E36 -> 37 | F34: =F35+F36 -> 0 | G34: =G35+G36 -> 0 | H34: =(E34+F34)/D34 -> 1 | I34: =E34/D34 -> 1 | J34: =F34/D34 -> 0 | K34: =G34/D34 -> 0 | L34: Масофавий назорат маркази ходимлари | M34: Доимий
C35: - асосий ойна | D35: 14 | E35: 14 | F35: 0 | G35: =D35-E35-F35 -> 0 | H35: =(E35+F35)/D35 -> 1 | I35: =E35/D35 -> 1 | J35: =IFERROR(F35/D35,0) -> 0 | K35: =IFERROR(G35/D35,0) -> 0
C36: - ҳисоботлар | D36: 23 | E36: 23 | F36: =COUNTIFS('Муаммолик АПИ'!I:I,C36,'Муаммолик АПИ'!D:D,2) -> 0 | G36: =D36-E36-F36 -> 0 | H36: =(E36+F36)/D36 -> 1 | I36: =E36/D36 -> 1 | J36: =IFERROR(F36/D36,0) -> 0 | K36: =IFERROR(G36/D36,0) -> 0
A37: 7 | B37: Банк мониторинги | C37: Банклар томонидан юборилган маълумотларни қайта ишлаш | D37: =SUM(D38:D41) -> 4 | E37: =SUM(E38:E41) -> 4 | F37: =SUM(F38:F41) -> 0 | G37: =SUM(G38:G41) -> 0 | H37: =(E37+F37)/D37 -> 1 | I37: =E37/D37 -> 1 | J37: =IFERROR(F37/D37,0) -> 0 | K37: =IFERROR(G37/D37,0) -> 0 | L37: Д.Бахриддинов А.Каримов | M37: якунланган
C38: - банклар томонидан маълумотлар тақдим этилиши учун хавфсиз канал яратиб ҳар бир банк учун тегишли логин, пароль ва RSA калитларни яратиш ҳамда уларга тақдим этиш | D38: 1 | E38: 1 | F38: 0 | G38: =D38-E38-F38 -> 0 | H38: =(E38+F38)/D38 -> 1 | I38: =E38/D38 -> 1 | J38: =IFERROR(F38/D38,0) -> 0 | K38: =IFERROR(G38/D38,0) -> 0
C39: - банклар томонидан тақдим этилган маълумотларни серверга жамлаш | D39: 1 | E39: 1 | F39: 0 | G39: =D39-E39-F39 -> 0 | H39: =(E39+F39)/D39 -> 1 | I39: =E39/D39 -> 1 | J39: =IFERROR(F39/D39,0) -> 0 | K39: =IFERROR(G39/D39,0) -> 0
C40: - тақдим этилган маълумотлар жамланмасини фойдаланувчиларга кўрсатиш ва қайта таҳлил қилиш учун экспорт қилиш | D40: 1 | E40: 1 | F40: 0 | G40: =D40-E40-F40 -> 0 | H40: =(E40+F40)/D40 -> 1 | I40: =E40/D40 -> 1 | J40: =IFERROR(F40/D40,0) -> 0 | K40: =IFERROR(G40/D40,0) -> 0
C41: - банклар томонидан тақдим этилган маълумотларини банк масъул ходимлари томонидан "Масофавий аудит" ААТ орқали текшириб кўриш | D41: 1 | E41: 1 | F41: 0 | G41: =D41-E41-F41 -> 0 | H41: =(E41+F41)/D41 -> 1 | I41: =E41/D41 -> 1 | J41: =IFERROR(F41/D41,0) -> 0 | K41: =IFERROR(G41/D41,0) -> 0
A42: 8 | B42: Буюртмалар | C42: Ҳисоб палатасининг назорат тадбирлари учун талаб этиладиган маълумотларни вазирлик ва идораларнинг маълумотлар базаларидан олиб бериш ҳамда уларни қайта ишлаш | D42: =SUM(D43:D45) -> 3 | E42: =SUM(E43:E45) -> 3 | F42: =SUM(F43:F45) -> 0 | G42: =SUM(G43:G45) -> 0 | H42: =(E42+F42)/D42 -> 1 | I42: =E42/D42 -> 1 | J42: =IFERROR(F42/D42,0) -> 0 | K42: =IFERROR(G42/D42,0) -> 0 | L42: А.Атоев Д.Бахриддинов Ҳ.Абдупаттоев Х.Файзуллаев | M42: Якунланган
C43: - фойдаланувчи томонидан маълумотларни жамлаб бериш ёки риск таҳлилларини амалга оширилиши юзасидан сўров юбориш | D43: 1 | E43: 1 | F43: 0 | G43: =D43-E43-F43 -> 0 | H43: =(E43+F43)/D43 -> 1 | I43: =E43/D43 -> 1 | J43: =IFERROR(F43/D43,0) -> 0 | K43: =IFERROR(G43/D43,0) -> 0
C44: - юборилган сўровни қабул қилиб ижрочини белгилаш ва назоратга қўйиш | D44: 1 | E44: 1 | F44: 0 | G44: =D44-E44-F44 -> 0 | H44: =(E44+F44)/D44 -> 1 | I44: =E44/D44 -> 1 | J44: =IFERROR(F44/D44,0) -> 0 | K44: =IFERROR(G44/D44,0) -> 0
C45: - ижрога қабул қилинган мурожаатни назоратдан ечиш | D45: 1 | E45: 1 | F45: 0 | G45: =D45-E45-F45 -> 0 | H45: =(E45+F45)/D45 -> 1 | I45: =E45/D45 -> 1 | J45: =IFERROR(F45/D45,0) -> 0 | K45: =IFERROR(G45/D45,0) -> 0
A46: 9 | B46: Қайта алоқа | C46: Тизим фойдаланувчиларида юзага келган саволларга модул орқали жавобларни онлайн жўнатиш | D46: =SUM(D47:D48) -> 2 | E46: =SUM(E47:E48) -> 2 | F46: =SUM(F47:F48) -> 0 | G46: =SUM(G47:G48) -> 0 | H46: =(E46+F46)/D46 -> 1 | I46: =E46/D46 -> 1 | J46: =IFERROR(F46/D46,0) -> 0 | K46: =IFERROR(G46/D46,0) -> 0 | L46: А.Атоев Д.Бахриддинов Ҳ.Абдупаттоев | M46: Якунланган
C47: - савол ва жавоблар модули | D47: 1 | E47: 1 | F47: 0 | G47: =D47-E47-F47 -> 0 | H47: =(E47+F47)/D47 -> 1 | I47: =E47/D47 -> 1 | J47: =IFERROR(F47/D47,0) -> 0 | K47: =IFERROR(G47/D47,0) -> 0
C48: - барча фойдаланувчиларга хабар жўнатиш | D48: 1 | E48: 1 | F48: 0 | G48: =D48-E48-F48 -> 0 | H48: =(E48+F48)/D48 -> 1 | I48: =E48/D48 -> 1 | J48: =IFERROR(F48/D48,0) -> 0 | K48: =IFERROR(G48/D48,0) -> 0
A49: 10 | B49: Мониторинглар | C49: Тизимда мавжуд барча API лар ҳамда микросервисларни онлайн мониторинг қилиш орқали ишлашида хатолик юз бериш ҳолатларини аниқлаш ва бартараф этиш мақсадида тизим ишлаб чиқувчиларни ва администраторларни хабардор қилиш | D49: =SUM(D50:D52) -> 3 | E49: =SUM(E50:E52) -> 3 | F49: =SUM(F50:F52) -> 0 | G49: =SUM(G50:G52) -> 0 | H49: =(E49+F49)/D49 -> 1 | I49: =E49/D49 -> 1 | J49: =IFERROR(F49/D49,0) -> 0 | K49: =IFERROR(G49/D49,0) -> 0 | L49: Д.Бахриддинов М.Эшқулов Ж.Доуров Ҳ.Абдупаттоев | M49: Якунланган
C50: - ташқи манба мониторинги, API лар ишлашида юзага келган камчиликлар бўйича ҲП масъулларини огохлантириш ҳамда вазирлик ва идоралар билан ташкил этилган телеграм каналларида камчилик юзасидан маълумот юбориш | D50: 1 | E50: 1 | F50: 0 | G50: =D50-E50-F50 -> 0 | H50: =(E50+F50)/D50 -> 1 | I50: =E50/D50 -> 1 | J50: =IFERROR(F50/D50,0) -> 0 | K50: =IFERROR(G50/D50,0) -> 0
