Workbook

Sheet Риск йўналишлари
A1: "Масофавий аудит" ААТ томонидан аниқланган риск ҳолатларини назоратга олиш ҳамда уларни бартараф этилиши тўғрисида риск йўналишлари кесимида маълумот
A3: № | B3: Риск йўналиши | C3: Масъул ходим | D3: Охирги аниқланган сана | E3: Жами | K3: Охирги 16 кунликда | P3: Охирги 16 - 30 кунликда | U3: Охирги 1 - 6 ойгача | Z3: Охирги 6 - 12 ойгача | AE3: 1 йилдан ортиқ
E4: Аниқланган | F4: Назоратга олинмаган | G4: Назоратга олинган | H4: Назоратга олинган лекин ижроси таъминланмаган | I4: Шундан назоратдан ечиш учун юборилган | J4: Назоратдан ечилган | K4: Аниқланган | L4: Назоратга олинмаган | M4: Назоратга олинган | N4: Шундан назоратдан ечиш учун юборилган | O4: Назоратдан ечилган | P4: Аниқланган | Q4: Назоратга олинмаган | R4: Назоратга олинган лекин ижроси таъминланмаган | S4: Шундан назоратдан ечиш учун юборилган | T4: Назоратдан ечилган | U4: Аниқланган | V4: Назоратга олинмаган | W4: Назоратга олинган лекин ижроси таъминланмаган | X4: Шундан назоратдан ечиш учун юборилган | Y4: Назоратдан ечилган | Z4: Аниқланган | AA4: Назоратга олинмаган | AB4: Назоратга олинган лекин ижроси таъминланмаган | AC4: Шундан назоратдан ечиш учун юборилган | AD4: Назоратдан ечилган | AE4: Аниқланган | AF4: Назоратга олинмаган | AG4: Назоратга олинган лекин ижроси таъминланмаган | AH4: Шундан назоратдан ечиш учун юборилган | AI4: Назоратдан ечилган
B5: Жами: | E5: =SUM(E6:E10044) | F5: =SUM(F6:F10044) | G5: =SUM(G6:G10044) | H5: =SUM(H6:H10044) | I5: =SUM(I6:I10044) | J5: =SUM(J6:J10044) | K5: =SUM(K6:K10044) | L5: =SUM(L6:L10044) | ... AI5: =SUM(AI6:AI10044)
A6: 1 | B6: Иш ҳақининг энг кам миқдоридан кам ҳисобланган ойлик иш ҳақлари таҳлили | C6: =IFERROR(VLOOKUP(B6,Рўйхат!A:E,5,0),"") | D6: =IFERROR(VLOOKUP(B6,Рўйхат!A:F,6,0),"") | E6: =+SUMIF(Рўйхат!$A:$A,'Риск йўналишлари'!$B6,Рўйхат!G:G) | F6: =+SUMIF(Рўйхат!$A:$A,'Риск йўналишлари'!$B6,Рўйхат!H:H) | G6: =M6 | H6: =R6+W6+AB6+AG6 | I6: =+SUMIF(Рўйхат!$A:$A,'Риск йўналишлари'!$B6,Рўйхат!J:J) | J6: =+SUMIF(Рўйхат!$A:$A,'Риск йўналишлари'!$B6,Рўйхат!K:K) | K6: =+SUMIF(Рўйхат!$A:$A,'Риск йўналишлари'!$B6,Рўйхат!L:L) | L6: =+SUMIF(Рўйхат!$A:$A,'Риск йўналишлари'!$B6,Рўйхат!M:M) | M6: =+SUMIF(Рўйхат!$A:$A,'Риск йўналишлари'!$B6,Рўйхат!N:N) | N6: =+SUMIF(Рўйхат!$A:$A,'Риск йўналишлари'!$B6,Рўйхат!O:O) | O6: =+SUMIF(Рўйхат!$A:$A,'Риск йўналишлари'!$B6,Рўйхат!P:P) | P6: =+SUMIF(Рўйхат!$A:$A,'Риск йўналишлари'!$B6,Рўйхат!Q:Q) | Q6: =+SUMIF(Рўйхат!$A:$A,'Риск йўналишлари'!$B6,Рўйхат!R:R) | R6: =+SUMIF(Рўйхат!$A:$A,'Риск йўналишлари'!$B6,Рўйхат!S:S) | S6: =+SUMIF(Рўйхат!$A:$A,'Риск йўналишлари'!$B6,Рўйхат!T:T) | T6: =+SUMIF(Рўйхат!$A:$A,'Риск йўналишлари'!$B6,Рўйхат!U:U) | U6: =+SUMIF(Рўйхат!$A:$A,'Риск йўналишлари'!$B6,Рўйхат!V:V) | V6: =+SUMIF(Рўйхат!$A:$A,'Риск йўналишлари'!$B6,Рўйхат!W:W) | W6: =+SUMIF(Рўйхат!$A:$A,'Риск йўналишлари'!$B6,Рўйхат!X:X) | X6: =+SUMIF(Рўйхат!$A:$A,'Риск йўналишлари'!$B6,Рўйхат!Y:Y) | Y6: =+SUMIF(Рўйхат!$A:$A,'Риск йўналишлари'!$B6,Рўйхат!Z:Z) | Z6: =+SUMIF(Рўйхат!$A:$A,'Риск йўналишлари'!$B6,Рўйхат!AA:AA) | AA6: =+SUMIF(Рўйхат!$A:$A,'Риск йўналишлари'!$B6,Рўйхат!AB:AB) | AB6: =+SUMIF(Рўйхат!$A:$A,'Риск йўналишлари'!$B6,Рўйхат!AC:AC) | AC6: =+SUMIF(Рўйхат!$A:$A,'Риск йўналишлари'!$B6,Рўйхат!AD:AD) | AD6: =+SUMIF(Рўйхат!$A:$A,'Риск йўналишлари'!$B6,Рўйхат!AE:AE) | AE6: =+SUMIF(Рўйхат!$A:$A,'Риск йўналишлари'!$B6,Рўйхат!AF:AF) | AF6: =+SUMIF(Рўйхат!$A:$A,'Риск йўналишлари'!$B6,Рўйхат!AG:AG) | AG6: =+SUMIF(Рўйхат!$A:$A,'Риск йўналишлари'!$B6,Рўйхат!AH:AH) | AH6: =+SUMIF(Рўйхат!$A:$A,'Риск йўналишлари'!$B6,Рўйхат!AI:AI) | AI6: =+SUMIF(Рўйхат!$A:$A,'Риск йўналишлари'!$B6,Рўйхат!AJ:AJ)
A7: 2 | B7: Мансабдор шахсларга боғлиқ етказиб берувчилар билан тузилган шартномалар | C7: =IFERROR(VLOOKUP(B7,Рўйхат!A:E,5,0),"") | D7: =IFERROR(VLOOKUP(B7,Рўйхат!A:F,6,0),"") | E7: =+SUMIF(Рўйхат!$A:$A,'Риск йўналишлари'!$B7,Рўйхат!G:G) | F7: =+SUMIF(Рўйхат!$A:$A,'Риск йўналишлари'!$B7,Рўйхат!H:H) | G7: =M7 | H7: =R7+W7+AB7+AG7 | I7: =+SUMIF(Рўйхат!$A:$A,'Риск йўналишлари'!$B7,Рўйхат!J:J) | J7: =+SUMIF(Рўйхат!$A:$A,'Риск йўналишлари'!$B7,Рўйхат!K:K) | K7: =+SUMIF(Рўйхат!$A:$A,'Риск йўналишлари'!$B7,Рўйхат!L:L) | L7: =+SUMIF(Рўйхат!$A:$A,'Риск йўналишлари'!$B7,Рўйхат!M:M) | M7: =+SUMIF(Рўйхат!$A:$A,'Риск йўналишлари'!$B7,Рўйхат!N:N) | N7: =+SUMIF(Рўйхат!$A:$A,'Риск йўналишлари'!$B7,Рўйхат!O:O) | O7: =+SUMIF(Рўйхат!$A:$A,'Риск йўналишлари'!$B7,Рўйхат!P:P) | P7: =+SUMIF(Рўйхат!$A:$A,'Риск йўналишлари'!$B7,Рўйхат!Q:Q) | Q7: =+SUMIF(Рўйхат!$A:$A,'Риск йўналишлари'!$B7,Рўйхат!R:R) | R7: =+SUMIF(Рўйхат!$A:$A,'Риск йўналишлари'!$B7,Рўйхат!S:S) | S7: =+SUMIF(Рўйхат!$A:$A,'Риск йўналишлари'!$B7,Рўйхат!T:T) | T7: =+SUMIF(Рўйхат!$A:$A,'Риск йўналишлари'!$B7,Рўйхат!U:U) | U7: =+SUMIF(Рўйхат!$A:$A,'Риск йўналишлари'!$B7,Рўйхат!V:V) | V7: =+SUMIF(Рўйхат!$A:$A,'Риск йўналишлари'!$B7,Рўйхат!W:W) | W7: =+SUMIF(Рўйхат!$A:$A,'Риск йўналишлари'!$B7,Рўйхат!X:X) | X7: =+SUMIF(Рўйхат!$A:$A,'Риск йўналишлари'!$B7,Рўйхат!Y:Y) | Y7: =+SUMIF(Рўйхат!$A:$A,'Риск йўналишлари'!$B7,Рўйхат!Z:Z) | Z7: =+SUMIF(Рўйхат!$A:$A,'Риск йўналишлари'!$B7,Рўйхат!AA:AA) | AA7: =+SUMIF(Рўйхат!$A:$A,'Риск йўналишлари'!$B7,Рўйхат!AB:AB) | AB7: =+SUMIF(Рўйхат!$A:$A,'Риск йўналишлари'!$B7,Рўйхат!AC:AC) | AC7: =+SUMIF(Рўйхат!$A:$A,'Риск йўналишлари'!$B7,Рўйхат!AD:AD) | AD7: =+SUMIF(Рўйхат!$A:$A,'Риск йўналишлари'!$B7,Рўйхат!AE:AE) | AE7: =+SUMIF(Рўйхат!$A:$A,'Риск йўналишлари'!$B7,Рўйхат!AF:AF) | AF7: =+SUMIF(Рўйхат!$A:$A,'Риск йўналишлари'!$B7,Рўйхат!AG:AG) | AG7: =+SUMIF(Рўйхат!$A:$A,'Риск йўналишлари'!$B7,Рўйхат!AH:AH) | AH7: =+SUMIF(Рўйхат!$A:$A,'Риск йўналишлари'!$B7,Рўйхат!AI:AI) | AI7: =+SUMIF(Рўйхат!$A:$A,'Риск йўналишлари'!$B7,Рўйхат!AJ:AJ)
A8: 3 | B8: Давлат улуши мавжуд корхоналарда непотизм таҳлили | C8: =IFERROR(VLOOKUP(B8,Рўйхат!A:E,5,0),"") | D8: =IFERROR(VLOOKUP(B8,Рўйхат!A:F,6,0),"") | E8: =+SUMIF(Рўйхат!$A:$A,'Риск йўналишлари'!$B8,Рўйхат!G:G) | F8: =+SUMIF(Рўйхат!$A:$A,'Риск йўналишлари'!$B8,Рўйхат!H:H) | G8: =M8 | H8: =R8+W8+AB8+AG8 | I8: =+SUMIF(Рўйхат!$A:$A,'Риск йўналишлари'!$B8,Рўйхат!J:J) | J8: =+SUMIF(Рўйхат!$A:$A,'Риск йўналишлари'!$B8,Рўйхат!K:K) | K8: =+SUMIF(Рўйхат!$A:$A,'Риск йўналишлари'!$B8,Рўйхат!L:L) | L8: =+SUMIF(Рўйхат!$A:$A,'Риск йўналишлари'!$B8,Рўйхат!M:M) | M8: =+SUMIF(Рўйхат!$A:$A,'Риск йўналишлари'!$B8,Рўйхат!N:N) | N8: =+SUMIF(Рўйхат!$A:$A,'Риск йўналишлари'!$B8,Рўйхат!O:O) | O8: =+SUMIF(Рўйхат!$A:$A,'Риск йўналишлари'!$B8,Рўйхат!P:P) | P8: =+SUMIF(Рўйхат!$A:$A,'Риск йўналишлари'!$B8,Рўйхат!Q:Q) | Q8: =+SUMIF(Рўйхат!$A:$A,'Риск йўналишлари'!$B8,Рўйхат!R:R) | R8: =+SUMIF(Рўйхат!$A:$A,'Риск йўналишлари'!$B8,Рўйхат!S:S) | S8: =+SUMIF(Рўйхат!$A:$A,'Риск йўналишлари'!$B8,Рўйхат!T:T) | T8: =+SUMIF(Рўйхат!$A:$A,'Риск йўналишлари'!$B8,Рўйхат!U:U) | U8: =+SUMIF(Рўйхат!$A:$A,'Риск йўналишлари'!$B8,Рўйхат!V:V) | V8: =+SUMIF(Рўйхат!$A:$A,'Риск йўналишлари'!$B8,Рўйхат!W:W) | W8: =+SUMIF(Рўйхат!$A:$A,'Риск йўналишлари'!$B8,Рўйхат!X:X) | X8: =+SUMIF(Рўйхат!$A:$A,'Риск йўналишлари'!$B8,Рўйхат!Y:Y) | Y8: =+SUMIF(Рўйхат!$A:$A,'Риск йўналишлари'!$B8,Рўйхат!Z:Z) | Z8: =+SUMIF(Рўйхат!$A:$A,'Риск йўналишлари'!$B8,Рўйхат!AA:AA) | AA8: =+SUMIF(Рўйхат!$A:$A,'Риск йўналишлари'!$B8,Рўйхат!AB:AB) | AB8: =+SUMIF(Рўйхат!$A:$A,'Риск йўналишлари'!$B8,Рўйхат!AC:AC) | AC8: =+SUMIF(Рўйхат!$A:$A,'Риск йўналишлари'!$B8,Рўйхат!AD:AD) | AD8: =+SUMIF(Рўйхат!$A:$A,'Риск йўналишлари'!$B8,Рўйхат!AE:AE) | AE8: =+SUMIF(Рўйхат!$A:$A,'Риск йўналишлари'!$B8,Рўйхат!AF:AF) | AF8: =+SUMIF(Рўйхат!$A:$A,'Риск йўналишлари'!$B8,Рўйхат!AG:AG) | AG8: =+SUMIF(Рўйхат!$A:$A,'Риск йўналишлари'!$B8,Рўйхат!AH:AH) | AH8: =+SUMIF(Рўйхат!$A:$A,'Риск йўналишлари'!$B8,Рўйхат!AI:AI) | AI8: =+SUMIF(Рўйхат!$A:$A,'Риск йўналишлари'!$B8,Рўйхат!AJ:AJ)
A9: 4 | B9: Тўғридан-тўғри шартномалар мониторинги | C9: =IFERROR(VLOOKUP(B9,Рўйхат!A:E,5,0),"") | D9: =IFERROR(VLOOKUP(B9,Рўйхат!A:F,6,0),"") | E9: =+SUMIF(Рўйхат!$A:$A,'Риск йўналишлари'!$B9,Рўйхат!G:G) | F9: =+SUMIF(Рўйхат!$A:$A,'Риск йўналишлари'!$B9,Рўйхат!H:H) | G9: =M9 | H9: =R9+W9+AB9+AG9 | I9: =+SUMIF(Рўйхат!$A:$A,'Риск йўналишлари'!$B9,Рўйхат!J:J) | J9: =+SUMIF(Рўйхат!$A:$A,'Риск йўналишлари'!$B9,Рўйхат!K:K) | K9: =+SUMIF(Рўйхат!$A:$A,'Риск йўналишлари'!$B9,Рўйхат!L:L) | L9: =+SUMIF(Рўйхат!$A:$A,'Риск йўналишлари'!$B9,Рўйхат!M:M) | M9: =+SUMIF(Рўйхат!$A:$A,'Риск йўналишлари'!$B9,Рўйхат!N:N) | N9: =+SUMIF(Рўйхат!$A:$A,'Риск йўналишлари'!$B9,Рўйхат!O:O) | O9: =+SUMIF(Рўйхат!$A:$A,'Риск йўналишлари'!$B9,Рўйхат!P:P) | P9: =+SUMIF(Рўйхат!$A:$A,'Риск йўналишлари'!$B9,Рўйхат!Q:Q) | Q9: =+SUMIF(Рўйхат!$A:$A,'Риск йўналишлари'!$B9,Рўйхат!R:R) | R9: =+SUMIF(Рўйхат!$A:$A,'Риск йўналишлари'!$B9,Рўйхат!S:S) | S9: =+SUMIF(Рўйхат!$A:$A,'Риск йўналишлари'!$B9,Рўйхат!T:T) | T9: =+SUMIF(Рўйхат!$A:$A,'Риск йўналишлари'!$B9,Рўйхат!U:U) | U9: =+SUMIF(Рўйхат!$A:$A,'Риск йўналишлари'!$B9,Рўйхат!V:V) | V9: =+SUMIF(Рўйхат!$A:$A,'Риск йўналишлари'!$B9,Рўйхат!W:W) | W9: =+SUMIF(Рўйхат!$A:$A,'Риск йўналишлари'!$B9,Рўйхат!X:X) | X9: =+SUMIF(Рўйхат!$A:$A,'Риск йўналишлари'!$B9,Рўйхат!Y:Y) | Y9: =+SUMIF(Рўйхат!$A:$A,'Риск йўналишлари'!$B9,Рўйхат!Z:Z) | Z9: =+SUMIF(Рўйхат!$A:$A,'Риск йўналишлари'!$B9,Рўйхат!AA:AA) | AA9: =+SUMIF(Рўйхат!$A:$A,'Риск йўналишлари'!$B9,Рўйхат!AB:AB) | AB9: =+SUMIF(Рўйхат!$A:$A,'Риск йўналишлари'!$B9,Рўйхат!AC:AC) | AC9: =+SUMIF(Рўйхат!$A:$A,'Риск йўналишлари'!$B9,Рўйхат!AD:AD) | AD9: =+SUMIF(Рўйхат!$A:$A,'Риск йўналишлари'!$B9,Рўйхат!AE:AE) | AE9: =+SUMIF(Рўйхат!$A:$A,'Риск йўналишлари'!$B9,Рўйхат!AF:AF) | AF9: =+SUMIF(Рўйхат!$A:$A,'Риск йўналишлари'!$B9,Рўйхат!AG:AG) | AG9: =+SUMIF(Рўйхат!$A:$A,'Риск йўналишлари'!$B9,Рўйхат!AH:AH) | AH9: =+SUMIF(Рўйхат!$A:$A,'Риск йўналишлари'!$B9,Рўйхат!AI:AI) | AI9: =+SUMIF(Рўйхат!$A:$A,'Риск йўналишлари'!$B9,Рўйхат!AJ:AJ)
A10: 5 | B10: Қишлоқ хўжалигида фойдаланилган сув ҳажми таҳлили | C10: =IFERROR(VLOOKUP(B10,Рўйхат!A:E,5,0),"") | D10: =IFERROR(VLOOKUP(B10,Рўйхат!A:F,6,0),"") | E10: =+SUMIF(Рўйхат!$A:$A,'Риск йўналишлари'!$B10,Рўйхат!G:G) | F10: =+SUMIF(Рўйхат!$A:$A,'Риск йўналишлари'!$B10,Рўйхат!H:H) | G10: =M10 | H10: =R10+W10+AB10+AG10 | I10: =+SUMIF(Рўйхат!$A:$A,'Риск йўналишлари'!$B10,Рўйхат!J:J) | J10: =+SUMIF(Рўйхат!$A:$A,'Риск йўналишлари'!$B10,Рўйхат!K:K) | K10: =+SUMIF(Рўйхат!$A:$A,'Риск йўналишлари'!$B10,Рўйхат!L:L) | L10: =+SUMIF(Рўйхат!$A:$A,'Риск йўналишлари'!$B10,Рўйхат!M:M) | M10: =+SUMIF(Рўйхат!$A:$A,'Риск йўналишлари'!$B10,Рўйхат!N:N) | N10: =+SUMIF(Рўйхат!$A:$A,'Риск йўналишлари'!$B10,Рўйхат!O:O) | O10: =+SUMIF(Рўйхат!$A:$A,'Риск йўналишлари'!$B10,Рўйхат!P:P) | P10: =+SUMIF(Рўйхат!$A:$A,'Риск йўналишлари'!$B10,Рўйхат!Q:Q) | Q10: =+SUMIF(Рўйхат!$A:$A,'Риск йўналишлари'!$B10,Рўйхат!R:R) | R10: =+SUMIF(Рўйхат!$A:$A,'Риск йўналишлари'!$B10,Рўйхат!S:S) | S10: =+SUMIF(Рўйхат!$A:$A,'Риск йўналишлари'!$B10,Рўйхат!T:T) | T10: =+SUMIF(Рўйхат!$A:$A,'Риск йўналишлари'!$B10,Рўйхат!U:U) | U10: =+SUMIF(Рўйхат!$A:$A,'Риск йўналишлари'!$B10,Рўйхат!V:V) | V10: =+SUMIF(Рўйхат!$A:$A,'Риск йўналишлари'!$B10,Рўйхат!W:W) | W10: =+SUMIF(Рўйхат!$A:$A,'Риск йўналишлари'!$B10,Рўйхат!X:X) | X10: =+SUMIF(Рўйхат!$A:$A,'Риск йўналишлари'!$B10,Рўйхат!Y:Y) | Y10: =+SUMIF(Рўйхат!$A:$A,'Риск йўналишлари'!$B10,Рўйхат!Z:Z) | Z10: =+SUMIF(Рўйхат!$A:$A,'Риск йўналишлари'!$B10,Рўйхат!AA:AA) | AA10: =+SUMIF(Рўйхат!$A:$A,'Риск йўналишлари'!$B10,Рўйхат!AB:AB) | AB10: =+SUMIF(Рўйхат!$A:$A,'Риск йўналишлари'!$B10,Рўйхат!AC:AC) | AC10: =+SUMIF(Рўйхат!$A:$A,'Риск йўналишлари'!$B10,Рўйхат!AD:AD) | AD10: =+SUMIF(Рўйхат!$A:$A,'Риск йўналишлари'!$B10,Рўйхат!AE:AE) | AE10: =+SUMIF(Рўйхат!$A:$A,'Риск йўналишлари'!$B10,Рўйхат!AF:AF) | AF10: =+SUMIF(Рўйхат!$A:$A,'Риск йўналишлари'!$B10,Рўйхат!AG:AG) | AG10: =+SUMIF(Рўйхат!$A:$A,'Риск йўналишлари'!$B10,Рўйхат!AH:AH) | AH10: =+SUMIF(Рўйхат!$A:$A,'Риск йўналишлари'!$B10,Рўйхат!AI:AI) | AI10: =+SUMIF(Рўйхат!$A:$A,'Риск йўналишлари'!$B10,Рўйхат!AJ:AJ)
A11: 6 | B11: Манфаатлар тўқнашуви (COOPERATION AI) | C11: =IFERROR(VLOOKUP(B11,Рўйхат!A:E,5,0),"") | D11: =IFERROR(VLOOKUP(B11,Рўйхат!A:F,6,0),"") | E11: =+SUMIF(Рўйхат!$A:$A,'Риск йўналишлари'!$B11,Рўйхат!G:G) | F11: =+SUMIF(Рўйхат!$A:$A,'Риск йўналишлари'!$B11,Рўйхат!H:H) | G11: =M11 | H11: =R11+W11+AB11+AG11 | I11: =+SUMIF(Рўйхат!$A:$A,'Риск йўналишлари'!$B11,Рўйхат!J:J) | J11: =+SUMIF(Рўйхат!$A:$A,'Риск йўналишлари'!$B11,Рўйхат!K:K) | K11: =+SUMIF(Рўйхат!$A:$A,'Риск йўналишлари'!$B11,Рўйхат!L:L) | L11: =+SUMIF(Рўйхат!$A:$A,'Риск йўналишлари'!$B11,Рўйхат!M:M) | M11: =+SUMIF(Рўйхат!$A:$A,'Риск йўналишлари'!$B11,Рўйхат!N:N) | N11: =+SUMIF(Рўйхат!$A:$A,'Риск йўналишлари'!$B11,Рўйхат!O:O) | O11: =+SUMIF(Рўйхат!$A:$A,'Риск йўналишлари'!$B11,Рўйхат!P:P) | P11: =+SUMIF(Рўйхат!$A:$A,'Риск йўналишлари'!$B11,Рўйхат!Q:Q) | Q11: =+SUMIF(Рўйхат!$A:$A,'Риск йўналишлари'!$B11,Рўйхат!R:R) | R11: =+SUMIF(Рўйхат!$A:$A,'Риск йўналишлари'!$B11,Рўйхат!S:S) | S11: =+SUMIF(Рўйхат!$A:$A,'Риск йўналишлари'!$B11,Рўйхат!T:T) | T11: =+SUMIF(Рўйхат!$A:$A,'Риск йўналишлари'!$B11,Рўйхат!U:U) | U11: =+SUMIF(Рўйхат!$A:$A,'Риск йўналишлари'!$B11,Рўйхат!V:V) | V11: =+SUMIF(Рўйхат!$A:$A,'Риск йўналишлари'!$B11,Рўйхат!W:W) | W11: =+SUMIF(Рўйхат!$A:$A,'Риск йўналишлари'!$B11,Рўйхат!X:X) | X11: =+SUMIF(Рўйхат!$A:$A,'Риск йўналишлари'!$B11,Рўйхат!Y:Y) | Y11: =+SUMIF(Рўйхат!$A:$A,'Риск йўналишлари'!$B11,Рўйхат!Z:Z) | Z11: =+SUMIF(Рўйхат!$A:$A,'Риск йўналишлари'!$B11,Рўйхат!AA:AA) | AA11: =+SUMIF(Рўйхат!$A:$A,'Риск йўналишлари'!$B11,Рўйхат!AB:AB) | AB11: =+SUMIF(Рўйхат!$A:$A,'Риск йўналишлари'!$B11,Рўйхат!AC:AC) | AC11: =+SUMIF(Рўйхат!$A:$A,'Риск йўналишлари'!$B11,Рўйхат!AD:AD) | AD11: =+SUMIF(Рўйхат!$A:$A,'Риск йўналишлари'!$B11,Рўйхат!AE:AE) | AE11: =+SUMIF(Рўйхат!$A:$A,'Риск йўналишлари'!$B11,Рўйхат!AF:AF) | AF11: =+SUMIF(Рўйхат!$A:$A,'Риск йўналишлари'!$B11,Рўйхат!AG:AG) | AG11: =+SUMIF(Рўйхат!$A:$A,'Риск йўналишлари'!$B11,Рўйхат!AH:AH) | AH11: =+SUMIF(Рўйхат!$A:$A,'Риск йўналишлари'!$B11,Рўйхат!AI:AI) | AI11: =+SUMIF(Рўйхат!$A:$A,'Риск йўналишлари'!$B11,Рўйхат!AJ:AJ)
A12: 7 | B12: Ундириш имкони мавжуд бўлган жисмоний шахсларнинг баланс ҳисобидан чиқарилган кредитлари таҳлили | C12: =IFERROR(VLOOKUP(B12,Рўйхат!A:E,5,0),"") | D12: =IFERROR(VLOOKUP(B12,Рўйхат!A:F,6,0),"") | E12: =+SUMIF(Рўйхат!$A:$A,'Риск йўналишлари'!$B12,Рўйхат!G:G) | F12: =+SUMIF(Рўйхат!$A:$A,'Риск йўналишлари'!$B12,Рўйхат!H:H) | G12: =M12 | H12: =R12+W12+AB12+AG12 | I12: =+SUMIF(Рўйхат!$A:$A,'Риск йўналишлари'!$B12,Рўйхат!J:J) | J12: =+SUMIF(Рўйхат!$A:$A,'Риск йўналишлари'!$B12,Рўйхат!K:K) | K12: =+SUMIF(Рўйхат!$A:$A,'Риск йўналишлари'!$B12,Рўйхат!L:L) | L12: =+SUMIF(Рўйхат!$A:$A,'Риск йўналишлари'!$B12,Рўйхат!M:M) | M12: =+SUMIF(Рўйхат!$A:$A,'Риск йўналишлари'!$B12,Рўйхат!N:N) | N12: =+SUMIF(Рўйхат!$A:$A,'Риск йўналишлари'!$B12,Рўйхат!O:O) | O12: =+SUMIF(Рўйхат!$A:$A,'Риск йўналишлари'!$B12,Рўйхат!P:P) | P12: =+SUMIF(Рўйхат!$A:$A,'Риск йўналишлари'!$B12,Рўйхат!Q:Q) | Q12: =+SUMIF(Рўйхат!$A:$A,'Риск йўналишлари'!$B12,Рўйхат!R:R) | R12: =+SUMIF(Рўйхат!$A:$A,'Риск йўналишлари'!$B12,Рўйхат!S:S) | S12: =+SUMIF(Рўйхат!$A:$A,'Риск йўналишлари'!$B12,Рўйхат!T:T) | T12: =+SUMIF(Рўйхат!$A:$A,'Риск йўналишлари'!$B12,Рўйхат!U:U) | U12: =+SUMIF(Рўйхат!$A:$A,'Риск йўналишлари'!$B12,Рўйхат!V:V) | V12: =+SUMIF(Рўйхат!$A:$A,'Риск йўналишлари'!$B12,Рўйхат!W:W) | W12: =+SUMIF(Рўйхат!$A:$A,'Риск йўналишлари'!$B12,Рўйхат!X:X) | X12: =+SUMIF(Рўйхат!$A:$A,'Риск йўналишлари'!$B12,Рўйхат!Y:Y) | Y12: =+SUMIF(Рўйхат!$A:$A,'Риск йўналишлари'!$B12,Рўйхат!Z:Z) | Z12: =+SUMIF(Рўйхат!$A:$A,'Риск йўналишлари'!$B12,Рўйхат!AA:AA) | AA12: =+SUMIF(Рўйхат!$A:$A,'Риск йўналишлари'!$B12,Рўйхат!AB:AB) | AB12: =+SUMIF(Рўйхат!$A:$A,'Риск йўналишлари'!$B12,Рўйхат!AC:AC) | AC12: =+SUMIF(Рўйхат!$A:$A,'Риск йўналишлари'!$B12,Рўйхат!AD:AD) | AD12: =+SUMIF(Рўйхат!$A:$A,'Риск йўналишлари'!$B12,Рўйхат!AE:AE) | AE12: =+SUMIF(Рўйхат!$A:$A,'Риск йўналишлари'!$B12,Рўйхат!AF:AF) | AF12: =+SUMIF(Рўйхат!$A:$A,'Риск йўналишлари'!$B12,Рўйхат!AG:AG) | AG12: =+SUMIF(Рўйхат!$A:$A,'Риск йўналишлари'!$B12,Рўйхат!AH:AH) | AH12: =+SUMIF(Рўйхат!$A:$A,'Риск йўналишлари'!$B12,Рўйхат!AI:AI) | AI12: =+SUMIF(Рўйхат!$A:$A,'Риск йўналишлари'!$B12,Рўйхат!AJ:AJ)
A13: 8 | B13: Рейтинг бали шаклланишида ишчи ходим сони таҳлили | C13: =IFERROR(VLOOKUP(B13,Рўйхат!A:E,5,0),"") | D13: =IFERROR(VLOOKUP(B13,Рўйхат!A:F,6,0),"") | E13: =+SUMIF(Рўйхат!$A:$A,'Риск йўналишлари'!$B13,Рўйхат!G:G) | F13: =+SUMIF(Рўйхат!$A:$A,'Риск йўналишлари'!$B13,Рўйхат!H:H) | G13: =M13 | H13: =R13+W13+AB13+AG13 | I13: =+SUMIF(Рўйхат!$A:$A,'Риск йўналишлари'!$B13,Рўйхат!J:J) | J13: =+SUMIF(Рўйхат!$A:$A,'Риск йўналишлари'!$B13,Рўйхат!K:K) | K13: =+SUMIF(Рўйхат!$A:$A,'Риск йўналишлари'!$B13,Рўйхат!L:L) | L13: =+SUMIF(Рўйхат!$A:$A,'Риск йўналишлари'!$B13,Рўйхат!M:M) | M13: =+SUMIF(Рўйхат!$A:$A,'Риск йўналишлари'!$B13,Рўйхат!N:N) | N13: =+SUMIF(Рўйхат!$A:$A,'Риск йўналишлари'!$B13,Рўйхат!O:O) | O13: =+SUMIF(Рўйхат!$A:$A,'Риск йўналишлари'!$B13,Рўйхат!P:P) | P13: =+SUMIF(Рўйхат!$A:$A,'Риск йўналишлари'!$B13,Рўйхат!Q:Q) | Q13: =+SUMIF(Рўйхат!$A:$A,'Риск йўналишлари'!$B13,Рўйхат!R:R) | R13: =+SUMIF(Рўйхат!$A:$A,'Риск йўналишлари'!$B13,Рўйхат!S:S) | S13: =+SUMIF(Рўйхат!$A:$A,'Риск йўналишлари'!$B13,Рўйхат!T:T) | T13: =+SUMIF(Рўйхат!$A:$A,'Риск йўналишлари'!$B13,Рўйхат!U:U) | U13: =+SUMIF(Рўйхат!$A:$A,'Риск йўналишлари'!$B13,Рўйхат!V:V) | V13: =+SUMIF(Рўйхат!$A:$A,'Риск йўналишлари'!$B13,Рўйхат!W:W) | W13: =+SUMIF(Рўйхат!$A:$A,'Риск йўналишлари'!$B13,Рўйхат!X:X) | X13: =+SUMIF(Рўйхат!$A:$A,'Риск йўналишлари'!$B13,Рўйхат!Y:Y) | Y13: =+SUMIF(Рўйхат!$A:$A,'Риск йўналишлари'!$B13,Рўйхат!Z:Z) | Z13: =+SUMIF(Рўйхат!$A:$A,'Риск йўналишлари'!$B13,Рўйхат!AA:AA) | AA13: =+SUMIF(Рўйхат!$A:$A,'Риск йўналишлари'!$B13,Рўйхат!AB:AB) | AB13: =+SUMIF(Рўйхат!$A:$A,'Риск йўналишлари'!$B13,Рўйхат!AC:AC) | AC13: =+SUMIF(Рўйхат!$A:$A,'Риск йўналишлари'!$B13,Рўйхат!AD:AD) | AD13: =+SUMIF(Рўйхат!$A:$A,'Риск йўналишлари'!$B13,Рўйхат!AE:AE) | AE13: =+SUMIF(Рўйхат!$A:$A,'Риск йўналишлари'!$B13,Рўйхат!AF:AF) | AF13: =+SUMIF(Рўйхат!$A:$A,'Риск йўналишлари'!$B13,Рўйхат!AG:AG) | AG13: =+SUMIF(Рўйхат!$A:$A,'Риск йўналишлари'!$B13,Рўйхат!AH:AH) | AH13: =+SUMIF(Рўйхат!$A:$A,'Риск йўналишлари'!$B13,Рўйхат!AI:AI) | AI13: =+SUMIF(Рўйхат!$A:$A,'Риск йўналишлари'!$B13,Рўйхат!AJ:AJ)
A14: 9 | B14: Импорт маҳсулотлари таҳлили | C14: =IFERROR(VLOOKUP(B14,Рўйхат!A:E,5,0),"") | D14: =IFERROR(VLOOKUP(B14,Рўйхат!A:F,6,0),"") | E14: =+SUMIF(Рўйхат!$A:$A,'Риск йўналишлари'!$B14,Рўйхат!G:G) | F14: =+SUMIF(Рўйхат!$A:$A,'Риск йўналишлари'!$B14,Рўйхат!H:H) | G14: =M14 | H14: =R14+W14+AB14+AG14 | I14: =+SUMIF(Рўйхат!$A:$A,'Риск йўналишлари'!$B14,Рўйхат!J:J) | J14: =+SUMIF(Рўйхат!$A:$A,'Риск йўналишлари'!$B14,Рўйхат!K:K) | K14: =+SUMIF(Рўйхат!$A:$A,'Риск йўналишлари'!$B14,Рўйхат!L:L) | L14: =+SUMIF(Рўйхат!$A:$A,'Риск йўналишлари'!$B14,Рўйхат!M:M) | M14: =+SUMIF(Рўйхат!$A:$A,'Риск йўналишлари'!$B14,Рўйхат!N:N) | N14: =+SUMIF(Рўйхат!$A:$A,'Риск йўналишлари'!$B14,Рўйхат!O:O) | O14: =+SUMIF(Рўйхат!$A:$A,'Риск йўналишлари'!$B14,Рўйхат!P:P) | P14: =+SUMIF(Рўйхат!$A:$A,'Риск йўналишлари'!$B14,Рўйхат!Q:Q) | Q14: =+SUMIF(Рўйхат!$A:$A,'Риск йўналишлари'!$B14,Рўйхат!R:R) | R14: =+SUMIF(Рўйхат!$A:$A,'Риск йўналишлари'!$B14,Рўйхат!S:S) | S14: =+SUMIF(Рўйхат!$A:$A,'Риск йўналишлари'!$B14,Рўйхат!T:T) | T14: =+SUMIF(Рўйхат!$A:$A,'Риск йўналишлари'!$B14,Рўйхат!U:U) | U14: =+SUMIF(Рўйхат!$A:$A,'Риск йўналишлари'!$B14,Рўйхат!V:V) | V14: =+SUMIF(Рўйхат!$A:$A,'Риск йўналишлари'!$B14,Рўйхат!W:W) | W14: =+SUMIF(Рўйхат!$A:$A,'Риск йўналишлари'!$B14,Рўйхат!X:X) | X14: =+SUMIF(Рўйхат!$A:$A,'Риск йўналишлари'!$B14,Рўйхат!Y:Y) | Y14: =+SUMIF(Рўйхат!$A:$A,'Риск йўналишлари'!$B14,Рўйхат!Z:Z) | Z14: =+SUMIF(Рўйхат!$A:$A,'Риск йўналишлари'!$B14,Рўйхат!AA:AA) | AA14: =+SUMIF(Рўйхат!$A:$A,'Риск йўналишлари'!$B14,Рўйхат!AB:AB) | AB14: =+SUMIF(Рўйхат!$A:$A,'Риск йўналишлари'!$B14,Рўйхат!AC:AC) | AC14: =+SUMIF(Рўйхат!$A:$A,'Риск йўналишлари'!$B14,Рўйхат!AD:AD) | AD14: =+SUMIF(Рўйхат!$A:$A,'Риск йўналишлари'!$B14,Рўйхат!AE:AE) | AE14: =+SUMIF(Рўйхат!$A:$A,'Риск йўналишлари'!$B14,Рўйхат!AF:AF) | AF14: =+SUMIF(Рўйхат!$A:$A,'Риск йўналишлари'!$B14,Рўйхат!AG:AG) | AG14: =+SUMIF(Рўйхат!$A:$A,'Риск йўналишлари'!$B14,Рўйхат!AH:AH) | AH14: =+SUMIF(Рўйхат!$A:$A,'Риск йўналишлари'!$B14,Рўйхат!AI:AI) | AI14: =+SUMIF(Рўйхат!$A:$A,'Риск йўналишлари'!$B14,Рўйхат!AJ:AJ)
A15: 10 | B15: Бюджет ташкилотларида непотизм ҳолатлари таҳлили | C15: =IFERROR(VLOOKUP(B15,Рўйхат!A:E,5,0),"") | D15: =IFERROR(VLOOKUP(B15,Рўйхат!A:F,6,0),"") | E15: =+SUMIF(Рўйхат!$A:$A,'Риск йўналишлари'!$B15,Рўйхат!G:G) | F15: =+SUMIF(Рўйхат!$A:$A,'Риск йўналишлари'!$B15,Рўйхат!H:H) | G15: =M15 | H15: =R15+W15+AB15+AG15 | I15: =+SUMIF(Рўйхат!$A:$A,'Риск йўналишлари'!$B15,Рўйхат!J:J) | J15: =+SUMIF(Рўйхат!$A:$A,'Риск йўналишлари'!$B15,Рўйхат!K:K) | K15: =+SUMIF(Рўйхат!$A:$A,'Риск йўналишлари'!$B15,Рўйхат!L:L) | L15: =+SUMIF(Рўйхат!$A:$A,'Риск йўналишлари'!$B15,Рўйхат!M:M) | M15: =+SUMIF(Рўйхат!$A:$A,'Риск йўналишлари'!$B15,Рўйхат!N:N) | N15: =+SUMIF(Рўйхат!$A:$A,'Риск йўналишлари'!$B15,Рўйхат!O:O) | O15: =+SUMIF(Рўйхат!$A:$A,'Риск йўналишлари'!$B15,Рўйхат!P:P) | P15: =+SUMIF(Рўйхат!$A:$A,'Риск йўналишлари'!$B15,Рўйхат!Q:Q) | Q15: =+SUMIF(Рўйхат!$A:$A,'Риск йўналишлари'!$B15,Рўйхат!R:R) | R15: =+SUMIF(Рўйхат!$A:$A,'Риск йўналишлари'!$B15,Рўйхат!S:S) | S15: =+SUMIF(Рўйхат!$A:$A,'Риск йўналишлари'!$B15,Рўйхат!T:T) | T15: =+SUMIF(Рўйхат!$A:$A,'Риск йўналишлари'!$B15,Рўйхат!U:U) | U15: =+SUMIF(Рўйхат!$A:$A,'Риск йўналишлари'!$B15,Рўйхат!V:V) | V15: =+SUMIF(Рўйхат!$A:$A,'Риск йўналишлари'!$B15,Рўйхат!W:W) | W15: =+SUMIF(Рўйхат!$A:$A,'Риск йўналишлари'!$B15,Рўйхат!X:X) | X15: =+SUMIF(Рўйхат!$A:$A,'Риск йўналишлари'!$B15,Рўйхат!Y:Y) | Y15: =+SUMIF(Рўйхат!$A:$A,'Риск йўналишлари'!$B15,Рўйхат!Z:Z) | Z15: =+SUMIF(Рўйхат!$A:$A,'Риск йўналишлари'!$B15,Рўйхат!AA:AA) | AA15: =+SUMIF(Рўйхат!$A:$A,'Риск йўналишлари'!$B15,Рўйхат!AB:AB) | AB15: =+SUMIF(Рўйхат!$A:$A,'Риск йўналишлари'!$B15,Рўйхат!AC:AC) | AC15: =+SUMIF(Рўйхат!$A:$A,'Риск йўналишлари'!$B15,Рўйхат!AD:AD) | AD15: =+SUMIF(Рўйхат!$A:$A,'Риск йўналишлари'!$B15,Рўйхат!AE:AE) | AE15: =+SUMIF(Рўйхат!$A:$A,'Риск йўналишлари'!$B15,Рўйхат!AF:AF) | AF15: =+SUMIF(Рўйхат!$A:$A,'Риск йўналишлари'!$B15,Рўйхат!AG:AG) | AG15: =+SUMIF(Рўйхат!$A:$A,'Риск йўналишлари'!$B15,Рўйхат!AH:AH) | AH15: =+SUMIF(Рўйхат!$A:$A,'Риск йўналишлари'!$B15,Рўйхат!AI:AI) | AI15: =+SUMIF(Рўйхат!$A:$A,'Риск йўналишлари'!$B15,Рўйхат!AJ:AJ)
A16: 11 | B16: Ундириш имкони мавжуд бўлган жисмоний шахсларнинг муаммоли кредитлари таҳлили | C16: =IFERROR(VLOOKUP(B16,Рўйхат!A:E,5,0),"") | D16: =IFERROR(VLOOKUP(B16,Рўйхат!A:F,6,0),"") | E16: =+SUMIF(Рўйхат!$A:$A,'Риск йўналишлари'!$B16,Рўйхат!G:G) | F16: =+SUMIF(Рўйхат!$A:$A,'Риск йўналишлари'!$B16,Рўйхат!H:H) | G16: =M16 | H16: =R16+W16+AB16+AG16 | I16: =+SUMIF(Рўйхат!$A:$A,'Риск йўналишлари'!$B16,Рўйхат!J:J) | J16: =+SUMIF(Рўйхат!$A:$A,'Риск йўналишлари'!$B16,Рўйхат!K:K) | K16: =+SUMIF(Рўйхат!$A:$A,'Риск йўналишлари'!$B16,Рўйхат!L:L) | L16: =+SUMIF(Рўйхат!$A:$A,'Риск йўналишлари'!$B16,Рўйхат!M:M) | M16: =+SUMIF(Рўйхат!$A:$A,'Риск йўналишлари'!$B16,Рўйхат!N:N) | N16: =+SUMIF(Рўйхат!$A:$A,'Риск йўналишлари'!$B16,Рўйхат!O:O) | O16: =+SUMIF(Рўйхат!$A:$A,'Риск йўналишлари'!$B16,Рўйхат!P:P) | P16: =+SUMIF(Рўйхат!$A:$A,'Риск йўналишлари'!$B16,Рўйхат!Q:Q) | Q16: =+SUMIF(Рўйхат!$A:$A,'Риск йўналишлари'!$B16,Рўйхат!R:R) | R16: =+SUMIF(Рўйхат!$A:$A,'Риск йўналишлари'!$B16,Рўйхат!S:S) | S16: =+SUMIF(Рўйхат!$A:$A,'Риск йўналишлари'!$B16,Рўйхат!T:T) | T16: =+SUMIF(Рўйхат!$A:$A,'Риск йўналишлари'!$B16,Рўйхат!U:U) | U16: =+SUMIF(Рўйхат!$A:$A,'Риск йўналишлари'!$B16,Рўйхат!V:V) | V16: =+SUMIF(Рўйхат!$A:$A,'Риск йўналишлари'!$B16,Рўйхат!W:W) | W16: =+SUMIF(Рўйхат!$A:$A,'Риск йўналишлари'!$B16,Рўйхат!X:X) | X16: =+SUMIF(Рўйхат!$A:$A,'Риск йўналишлари'!$B16,Рўйхат!Y:Y) | Y16: =+SUMIF(Рўйхат!$A:$A,'Риск йўналишлари'!$B16,Рўйхат!Z:Z) | Z16: =+SUMIF(Рўйхат!$A:$A,'Риск йўналишлари'!$B16,Рўйхат!AA:AA) | AA16: =+SUMIF(Рўйхат!$A:$A,'Риск йўналишлари'!$B16,Рўйхат!AB:AB) | AB16: =+SUMIF(Рўйхат!$A:$A,'Риск йўналишлари'!$B16,Рўйхат!AC:AC) | AC16: =+SUMIF(Рўйхат!$A:$A,'Риск йўналишлари'!$B16,Рўйхат!AD:AD) | AD16: =+SUMIF(Рўйхат!$A:$A,'Риск йўналишлари'!$B16,Рўйхат!AE:AE) | AE16: =+SUMIF(Рўйхат!$A:$A,'Риск йўналишлари'!$B16,Рўйхат!AF:AF) | AF16: =+SUMIF(Рўйхат!$A:$A,'Риск йўналишлари'!$B16,Рўйхат!AG:AG) | AG16: =+SUMIF(Рўйхат!$A:$A,'Риск йўналишлари'!$B16,Рўйхат!AH:AH) | AH16: =+SUMIF(Рўйхат!$A:$A,'Риск йўналишлари'!$B16,Рўйхат!AI:AI) | AI16: =+SUMIF(Рўйхат!$A:$A,'Риск йўналишлари'!$B16,Рўйхат!AJ:AJ)
A17: 12 | B17: Бюджет ташкилотларида ишловчиларнинг 4 ва ундан ортиқ даромад манбаига эга фуқаролар | C17: =IFERROR(VLOOKUP(B17,Рўйхат!A:E,5,0),"") | D17: =IFERROR(VLOOKUP(B17,Рўйхат!A:F,6,0),"") | E17: =+SUMIF(Рўйхат!$A:$A,'Риск йўналишлари'!$B17,Рўйхат!G:G) | F17: =+SUMIF(Рўйхат!$A:$A,'Риск йўналишлари'!$B17,Рўйхат!H:H) | G17: =M17 | H17: =R17+W17+AB17+AG17 | I17: =+SUMIF(Рўйхат!$A:$A,'Риск йўналишлари'!$B17,Рўйхат!J:J) | J17: =+SUMIF(Рўйхат!$A:$A,'Риск йўналишлари'!$B17,Рўйхат!K:K) | K17: =+SUMIF(Рўйхат!$A:$A,'Риск йўналишлари'!$B17,Рўйхат!L:L) | L17: =+SUMIF(Рўйхат!$A:$A,'Риск йўналишлари'!$B17,Рўйхат!M:M) | M17: =+SUMIF(Рўйхат!$A:$A,'Риск йўналишлари'!$B17,Рўйхат!N:N) | N17: =+SUMIF(Рўйхат!$A:$A,'Риск йўналишлари'!$B17,Рўйхат!O:O) | O17: =+SUMIF(Рўйхат!$A:$A,'Риск йўналишлари'!$B17,Рўйхат!P:P) | P17: =+SUMIF(Рўйхат!$A:$A,'Риск йўналишлари'!$B17,Рўйхат!Q:Q) | Q17: =+SUMIF(Рўйхат!$A:$A,'Риск йўналишлари'!$B17,Рўйхат!R:R) | R17: =+SUMIF(Рўйхат!$A:$A,'Риск йўналишлари'!$B17,Рўйхат!S:S) | S17: =+SUMIF(Рўйхат!$A:$A,'Риск йўналишлари'!$B17,Рўйхат!T:T) | T17: =+SUMIF(Рўйхат!$A:$A,'Риск йўналишлари'!$B17,Рўйхат!U:U) | U17: =+SUMIF(Рўйхат!$A:$A,'Риск йўналишлари'!$B17,Рўйхат!V:V) | V17: =+SUMIF(Рўйхат!$A:$A,'Риск йўналишлари'!$B17,Рўйхат!W:W) | W17: =+SUMIF(Рўйхат!$A:$A,'Риск йўналишлари'!$B17,Рўйхат!X:X) | X17: =+SUMIF(Рўйхат!$A:$A,'Риск йўналишлари'!$B17,Рўйхат!Y:Y) | Y17: =+SUMIF(Рўйхат!$A:$A,'Риск йўналишлари'!$B17,Рўйхат!Z:Z) | Z17: =+SUMIF(Рўйхат!$A:$A,'Риск йўналишлари'!$B17,Рўйхат!AA:AA) | AA17: =+SUMIF(Рўйхат!$A:$A,'Риск йўналишлари'!$B17,Рўйхат!AB:AB) | AB17: =+SUMIF(Рўйхат!$A:$A,'Риск йўналишлари'!$B17,Рўйхат!AC:AC) | AC17: =+SUMIF(Рўйхат!$A:$A,'Риск йўналишлари'!$B17,Рўйхат!AD:AD) | AD17: =+SUMIF(Рўйхат!$A:$A,'Риск йўналишлари'!$B17,Рўйхат!AE:AE) | AE17: =+SUMIF(Рўйхат!$A:$A,'Риск йўналишлари'!$B17,Рўйхат!AF:AF) | AF17: =+SUMIF(Рўйхат!$A:$A,'Риск йўналишлари'!$B17,Рўйхат!AG:AG) | AG17: =+SUMIF(Рўйхат!$A:$A,'Риск йўналишлари'!$B17,Рўйхат!AH:AH) | AH17: =+SUMIF(Рўйхат!$A:$A,'Риск йўналишлари'!$B17,Рўйхат!AI:AI) | AI17: =+SUMIF(Рўйхат!$A:$A,'Риск йўналишлари'!$B17,Рўйхат!AJ:AJ)
... A98: 93 | B98: Лицензияга эга бўлмаган етказиб берувчилардан дори воситаларининг хариди | C98: =IFERROR(VLOOKUP(B98,Рўйхат!A:E,5,0),"") | D98: =IFERROR(VLOOKUP(B98,Рўйхат!A:F,6,0),"") | E98: =+SUMIF(Рўйхат!$A:$A,'Риск йўналишлари'!$B98,Рўйхат!G:G) | F98: =+SUMIF(Рўйхат!$A:$A,'Риск йўналишлари'!$B98,Рўйхат!H:H) | G98: =M98 | H98: =R98+W98+AB98+AG98 | I98: =+SUMIF(Рўйхат!$A:$A,'Риск йўналишлари'!$B98,Рўйхат!J:J) | J98: =+SUMIF(Рўйхат!$A:$A,'Риск йўналишлари'!$B98,Рўйхат!K:K) | K98: =+SUMIF(Рўйхат!$A:$A,'Риск йўналишлари'!$B98,Рўйхат!L:L) | L98: =+SUMIF(Рўйхат!$A:$A,'Риск йўналишлари'!$B98,Рўйхат!M:M) | M98: =+SUMIF(Рўйхат!$A:$A,'Риск йўналишлари'!$B98,Рўйхат!N:N) | N98: =+SUMIF(Рўйхат!$A:$A,'Риск йўналишлари'!$B98,Рўйхат!O:O) | O98: =+SUMIF(Рўйхат!$A:$A,'Риск йўналишлари'!$B98,Рўйхат!P:P) | P98: =+SUMIF(Рўйхат!$A:$A,'Риск йўналишлари'!$B98,Рўйхат!Q:Q) | Q98: =+SUMIF(Рўйхат!$A:$A,'Риск йўналишлари'!$B98,Рўйхат!R:R) | R98: =+SUMIF(Рўйхат!$A:$A,'Риск йўналишлари'!$B98,Рўйхат!S:S) | S98: =+SUMIF(Рўйхат!$A:$A,'Риск йўналишлари'!$B98,Рўйхат!T:T) | T98: =+SUMIF(Рўйхат!$A:$A,'Риск йўналишлари'!$B98,Рўйхат!U:U) | U98: =+SUMIF(Рўйхат!$A:$A,'Риск йўналишлари'!$B98,Рўйхат!V:V) | V98: =+SUMIF(Рўйхат!$A:$A,'Риск йўналишлари'!$B98,Рўйхат!W:W) | W98: =+SUMIF(Рўйхат!$A:$A,'Риск йўналишлари'!$B98,Рўйхат!X:X) | X98: =+SUMIF(Рўйхат!$A:$A,'Риск йўналишлари'!$B98,Рўйхат!Y:Y) | Y98: =+SUMIF(Рўйхат!$A:$A,'Риск йўналишлари'!$B98,Рўйхат!Z:Z) | Z98: =+SUMIF(Рўйхат!$A:$A,'Риск йўналишлари'!$B98,Рўйхат!AA:AA) | AA98: =+SUMIF(Рўйхат!$A:$A,'Риск йўналишлари'!$B98,Рўйхат!AB:AB) | AB98: =+SUMIF(Рўйхат!$A:$A,'Риск йўналишлари'!$B98,Рўйхат!AC:AC) | AC98: =+SUMIF(Рўйхат!$A:$A,'Риск йўналишлари'!$B98,Рўйхат!AD:AD) | AD98: =+SUMIF(Рўйхат!$A:$A,'Риск йўналишлари'!$B98,Рўйхат!AE:AE) | AE98: =+SUMIF(Рўйхат!$A:$A,'Риск йўналишлари'!$B98,Рўйхат!AF:AF) | AF98: =+SUMIF(Рўйхат!$A:$A,'Риск йўналишлари'!$B98,Рўйхат!AG:AG) | AG98: =+SUMIF(Рўйхат!$A:$A,'Риск йўналишлари'!$B98,Рўйхат!AH:AH) | AH98: =+SUMIF(Рўйхат!$A:$A,'Риск йўналишлари'!$B98,Рўйхат!AI:AI) | AI98: =+SUMIF(Рўйхат!$A:$A,'Риск йўналишлари'!$B98,Рўйхат!AJ:AJ)

Sheet Вазирликлар кесимида
A1: "Масофавий аудит" ААТ томонидан аниқланган риск ҳолатларини назоратга олиш ҳамда уларни бартараф этилиши тўғрисида вазирлик ва идоралар кесимида маълумот
A3: № | B3: Масъул ходим | C3: Тизим фойдаланувчилари сони | D3: Масъул ходим | E3: Жами | K3: Охирги 16 кунликда | P3: Охирги 16 - 30 кунликда | U3: Охирги 1 - 6 ойгача | Z3: Охирги 6 - 12 ойгача | AE3: 1 йилдан ортиқ
E4: Аниқланган | F4: Назоратга олинмаган | G4: Назоратга олинган | H4: Назоратга олинган лекин ижроси таъминланмаган | I4: Шундан назоратдан ечиш учун юборилган | J4: Назоратдан ечилган | K4: Аниқланган | L4: Назоратга олинмаган | M4: Назоратга олинган | N4: Шундан назоратдан ечиш учун юборилган | O4: Назоратдан ечилган | P4: Аниқланган | Q4: Назоратга олинмаган | R4: Назоратга олинган лекин ижроси таъминланмаган | S4: Шундан назоратдан ечиш учун юборилган | T4: Назоратдан ечилган | U4: Аниқланган | V4: Назоратга олинмаган | W4: Назоратга олинган лекин ижроси таъминланмаган | X4: Шундан назоратдан ечиш учун юборилган | Y4: Назоратдан ечилган | Z4: Аниқланган | AA4: Назоратга олинмаган | AB4: Назоратга олинган лекин ижроси таъминланмаган | AC4: Шундан назоратдан ечиш учун юборилган | AD4: Назоратдан ечилган | AE4: Аниқланган | AF4: Назоратга олинмаган | AG4: Назоратга олинган лекин ижроси таъминланмаган | AH4: Шундан назоратдан ечиш учун юборилган | AI4: Назоратдан ечилган
B5: Жами: | C5: =SUM(C6:C10013) | E5: =SUM(E6:E10026) | F5: =SUM(F6:F10026) | G5: =SUM(G6:G10026) | H5: =SUM(H6:H10026) | I5: =SUM(I6:I10026) | J5: =SUM(J6:J10026) | K5: =SUM(K6:K10026) | L5: =SUM(L6:L10026) | ... AI5: =SUM(AI6:AI10026)
A6: 1 | B6: Солиқ қўмитаси | C6: =IF(IFERROR(VLOOKUP(B6,Рўйхат!C:E,2,0),"")="[NULL]","",IFERROR(VLOOKUP(B6,Рўйхат!C:E,2,0),"")) | D6: =IFERROR(VLOOKUP(B6,Рўйхат!C:E,3,0),"") | E6: =+SUMIF(Рўйхат!$C:$C,$B6,Рўйхат!G:G) | F6: =+SUMIF(Рўйхат!$C:$C,$B6,Рўйхат!H:H) | G6: =M6 | H6: =R6+W6+AB6+AG6 | I6: =+SUMIF(Рўйхат!$C:$C,$B6,Рўйхат!J:J) | J6: =+SUMIF(Рўйхат!$C:$C,$B6,Рўйхат!K:K) | K6: =+SUMIF(Рўйхат!$C:$C,$B6,Рўйхат!L:L) | L6: =+SUMIF(Рўйхат!$C:$C,$B6,Рўйхат!M:M) | M6: =+SUMIF(Рўйхат!$C:$C,$B6,Рўйхат!N:N) | N6: =+SUMIF(Рўйхат!$C:$C,$B6,Рўйхат!O:O) | O6: =+SUMIF(Рўйхат!$C:$C,$B6,Рўйхат!P:P) | P6: =+SUMIF(Рўйхат!$C:$C,$B6,Рўйхат!Q:Q) | Q6: =+SUMIF(Рўйхат!$C:$C,$B6,Рўйхат!R:R) | R6: =+SUMIF(Рўйхат!$C:$C,$B6,Рўйхат!S:S) | S6: =+SUMIF(Рўйхат!$C:$C,$B6,Рўйхат!T:T) | T6: =+SUMIF(Рўйхат!$C:$C,$B6,Рўйхат!U:U) | U6: =+SUMIF(Рўйхат!$C:$C,$B6,Рўйхат!V:V) | V6: =+SUMIF(Рўйхат!$C:$C,$B6,Рўйхат!W:W) | W6: =+SUMIF(Рўйхат!$C:$C,$B6,Рўйхат!X:X) | X6: =+SUMIF(Рўйхат!$C:$C,$B6,Рўйхат!Y:Y) | Y6: =+SUMIF(Рўйхат!$C:$C,$B6,Рўйхат!Z:Z) | Z6: =+SUMIF(Рўйхат!$C:$C,$B6,Рўйхат!AA:AA) | AA6: =+SUMIF(Рўйхат!$C:$C,$B6,Рўйхат!AB:AB) | AB6: =+SUMIF(Рўйхат!$C:$C,$B6,Рўйхат!AC:AC) | AC6: =+SUMIF(Рўйхат!$C:$C,$B6,Рўйхат!AD:AD) | AD6: =+SUMIF(Рўйхат!$C:$C,$B6,Рўйхат!AE:AE) | AE6: =+SUMIF(Рўйхат!$C:$C,$B6,Рўйхат!AF:AF) | AF6: =+SUMIF(Рўйхат!$C:$C,$B6,Рўйхат!AG:AG) | AG6: =+SUMIF(Рўйхат!$C:$C,$B6,Рўйхат!AH:AH) | AH6: =+SUMIF(Рўйхат!$C:$C,$B6,Рўйхат!AI:AI) | AI6: =+SUMIF(Рўйхат!$C:$C,$B6,Рўйхат!AJ:AJ)
A7: =+A6+1 | B7: Мактабгача ва мактаб таълими вазирлиги | C7: =IF(IFERROR(VLOOKUP(B7,Рўйхат!C:E,2,0),"")="[NULL]","",IFERROR(VLOOKUP(B7,Рўйхат!C:E,2,0),"")) | D7: =IFERROR(VLOOKUP(B7,Рўйхат!C:E,3,0),"") | E7: =+SUMIF(Рўйхат!$C:$C,$B7,Рўйхат!G:G) | F7: =+SUMIF(Рўйхат!$C:$C,$B7,Рўйхат!H:H) | G7: =M7 | H7: =R7+W7+AB7+AG7 | I7: =+SUMIF(Рўйхат!$C:$C,$B7,Рўйхат!J:J) | J7: =+SUMIF(Рўйхат!$C:$C,$B7,Рўйхат!K:K) | K7: =+SUMIF(Рўйхат!$C:$C,$B7,Рўйхат!L:L) | L7: =+SUMIF(Рўйхат!$C:$C,$B7,Рўйхат!M:M) | M7: =+SUMIF(Рўйхат!$C:$C,$B7,Рўйхат!N:N) | N7: =+SUMIF(Рўйхат!$C:$C,$B7,Рўйхат!O:O) | O7: =+SUMIF(Рўйхат!$C:$C,$B7,Рўйхат!P:P) | P7: =+SUMIF(Рўйхат!$C:$C,$B7,Рўйхат!Q:Q) | Q7: =+SUMIF(Рўйхат!$C:$C,$B7,Рўйхат!R:R) | R7: =+SUMIF(Рўйхат!$C:$C,$B7,Рўйхат!S:S) | S7: =+SUMIF(Рўйхат!$C:$C,$B7,Рўйхат!T:T) | T7: =+SUMIF(Рўйхат!$C:$C,$B7,Рўйхат!U:U) | U7: =+SUMIF(Рўйхат!$C:$C,$B7,Рўйхат!V:V) | V7: =+SUMIF(Рўйхат!$C:$C,$B7,Рўйхат!W:W) | W7: =+SUMIF(Рўйхат!$C:$C,$B7,Рўйхат!X:X) | X7: =+SUMIF(Рўйхат!$C:$C,$B7,Рўйхат!Y:Y) | Y7: =+SUMIF(Рўйхат!$C:$C,$B7,Рўйхат!Z:Z) | Z7: =+SUMIF(Рўйхат!$C:$C,$B7,Рўйхат!AA:AA) | AA7: =+SUMIF(Рўйхат!$C:$C,$B7,Рўйхат!AB:AB) | AB7: =+SUMIF(Рўйхат!$C:$C,$B7,Рўйхат!AC:AC) | AC7: =+SUMIF(Рўйхат!$C:$C,$B7,Рўйхат!AD:AD) | AD7: =+SUMIF(Рўйхат!$C:$C,$B7,Рўйхат!AE:AE) | AE7: =+SUMIF(Рўйхат!$C:$C,$B7,Рўйхат!AF:AF) | AF7: =+SUMIF(Рўйхат!$C:$C,$B7,Рўйхат!AG:AG) | AG7: =+SUMIF(Рўйхат!$C:$C,$B7,Рўйхат!AH:AH) | AH7: =+SUMIF(Рўйхат!$C:$C,$B7,Рўйхат!AI:AI) | AI7: =+SUMIF(Рўйхат!$C:$C,$B7,Рўйхат!AJ:AJ)
A8: =+A7+1 | B8: Соғлиқни сақлаш вазирлиги | C8: =IF(IFERROR(VLOOKUP(B8,Рўйхат!C:E,2,0),"")="[NULL]","",IFERROR(VLOOKUP(B8,Рўйхат!C:E,2,0),"")) | D8: =IFERROR(VLOOKUP(B8,Рўйхат!C:E,3,0),"") | E8: =+SUMIF(Рўйхат!$C:$C,$B8,Рўйхат!G:G) | F8: =+SUMIF(Рўйхат!$C:$C,$B8,Рўйхат!H:H) | G8: =M8 | H8: =R8+W8+AB8+AG8 | I8: =+SUMIF(Рўйхат!$C:$C,$B8,Рўйхат!J:J) | J8: =+SUMIF(Рўйхат!$C:$C,$B8,Рўйхат!K:K) | K8: =+SUMIF(Рўйхат!$C:$C,$B8,Рўйхат!L:L) | L8: =+SUMIF(Рўйхат!$C:$C,$B8,Рўйхат!M:M) | M8: =+SUMIF(Рўйхат!$C:$C,$B8,Рўйхат!N:N) | N8: =+SUMIF(Рўйхат!$C:$C,$B8,Рўйхат!O:O) | O8: =+SUMIF(Рўйхат!$C:$C,$B8,Рўйхат!P:P) | P8: =+SUMIF(Рўйхат!$C:$C,$B8,Рўйхат!Q:Q) | Q8: =+SUMIF(Рўйхат!$C:$C,$B8,Рўйхат!R:R) | R8: =+SUMIF(Рўйхат!$C:$C,$B8,Рўйхат!S:S) | S8: =+SUMIF(Рўйхат!$C:$C,$B8,Рўйхат!T:T) | T8: =+SUMIF(Рўйхат!$C:$C,$B8,Рўйхат!U:U) | U8: =+SUMIF(Рўйхат!$C:$C,$B8,Рўйхат!V:V) | V8: =+SUMIF(Рўйхат!$C:$C,$B8,Рўйхат!W:W) | W8: =+SUMIF(Рўйхат!$C:$C,$B8,Рўйхат!X:X) | X8: =+SUMIF(Рўйхат!$C:$C,$B8,Рўйхат!Y:Y) | Y8: =+SUMIF(Рўйхат!$C:$C,$B8,Рўйхат!Z:Z) | Z8: =+SUMIF(Рўйхат!$C:$C,$B8,Рўйхат!AA:AA) | AA8: =+SUMIF(Рўйхат!$C:$C,$B8,Рўйхат!AB:AB) | AB8: =+SUMIF(Рўйхат!$C:$C,$B8,Рўйхат!AC:AC) | AC8: =+SUMIF(Рўйхат!$C:$C,$B8,Рўйхат!AD:AD) | AD8: =+SUMIF(Рўйхат!$C:$C,$B8,Рўйхат!AE:AE) | AE8: =+SUMIF(Рўйхат!$C:$C,$B8,Рўйхат!AF:AF) | AF8: =+SUMIF(Рўйхат!$C:$C,$B8,Рўйхат!AG:AG) | AG8: =+SUMIF(Рўйхат!$C:$C,$B8,Рўйхат!AH:AH) | AH8: =+SUMIF(Рўйхат!$C:$C,$B8,Рўйхат!AI:AI) | AI8: =+SUMIF(Рўйхат!$C:$C,$B8,Рўйхат!AJ:AJ)
A9: =+A8+1 | B9: Ғазначилик хизмати қўмитаси | C9: =IF(IFERROR(VLOOKUP(B9,Рўйхат!C:E,2,0),"")="[NULL]","",IFERROR(VLOOKUP(B9,Рўйхат!C:E,2,0),"")) | D9: =IFERROR(VLOOKUP(B9,Рўйхат!C:E,3,0),"") | E9: =+SUMIF(Рўйхат!$C:$C,$B9,Рўйхат!G:G) | F9: =+SUMIF(Рўйхат!$C:$C,$B9,Рўйхат!H:H) | G9: =M9 | H9: =R9+W9+AB9+AG9 | I9: =+SUMIF(Рўйхат!$C:$C,$B9,Рўйхат!J:J) | J9: =+SUMIF(Рўйхат!$C:$C,$B9,Рўйхат!K:K) | K9: =+SUMIF(Рўйхат!$C:$C,$B9,Рўйхат!L:L) | L9: =+SUMIF(Рўйхат!$C:$C,$B9,Рўйхат!M:M) | M9: =+SUMIF(Рўйхат!$C:$C,$B9,Рўйхат!N:N) | N9: =+SUMIF(Рўйхат!$C:$C,$B9,Рўйхат!O:O) | O9: =+SUMIF(Рўйхат!$C:$C,$B9,Рўйхат!P:P) | P9: =+SUMIF(Рўйхат!$C:$C,$B9,Рўйхат!Q:Q) | Q9: =+SUMIF(Рўйхат!$C:$C,$B9,Рўйхат!R:R) | R9: =+SUMIF(Рўйхат!$C:$C,$B9,Рўйхат!S:S) | S9: =+SUMIF(Рўйхат!$C:$C,$B9,Рўйхат!T:T) | T9: =+SUMIF(Рўйхат!$C:$C,$B9,Рўйхат!U:U) | U9: =+SUMIF(Рўйхат!$C:$C,$B9,Рўйхат!V:V) | V9: =+SUMIF(Рўйхат!$C:$C,$B9,Рўйхат!W:W) | W9: =+SUMIF(Рўйхат!$C:$C,$B9,Рўйхат!X:X) | X9: =+SUMIF(Рўйхат!$C:$C,$B9,Рўйхат!Y:Y) | Y9: =+SUMIF(Рўйхат!$C:$C,$B9,Рўйхат!Z:Z) | Z9: =+SUMIF(Рўйхат!$C:$C,$B9,Рўйхат!AA:AA) | AA9: =+SUMIF(Рўйхат!$C:$C,$B9,Рўйхат!AB:AB) | AB9: =+SUMIF(Рўйхат!$C:$C,$B9,Рўйхат!AC:AC) | AC9: =+SUMIF(Рўйхат!$C:$C,$B9,Рўйхат!AD:AD) | AD9: =+SUMIF(Рўйхат!$C:$C,$B9,Рўйхат!AE:AE) | AE9: =+SUMIF(Рўйхат!$C:$C,$B9,Рўйхат!AF:AF) | AF9: =+SUMIF(Рўйхат!$C:$C,$B9,Рўйхат!AG:AG) | AG9: =+SUMIF(Рўйхат!$C:$C,$B9,Рўйхат!AH:AH) | AH9: =+SUMIF(Рўйхат!$C:$C,$B9,Рўйхат!AI:AI) | AI9: =+SUMIF(Рўйхат!$C:$C,$B9,Рўйхат!AJ:AJ)
A10: =+A9+1 | B10: Қурилиш ва уй-жой коммунал хўжалиги вазирлиги | C10: =IF(IFERROR(VLOOKUP(B10,Рўйхат!C:E,2,0),"")="[NULL]","",IFERROR(VLOOKUP(B10,Рўйхат!C:E,2,0),"")) | D10: =IFERROR(VLOOKUP(B10,Рўйхат!C:E,3,0),"") | E10: =+SUMIF(Рўйхат!$C:$C,$B10,Рўйхат!G:G) | F10: =+SUMIF(Рўйхат!$C:$C,$B10,Рўйхат!H:H) | G10: =M10 | H10: =R10+W10+AB10+AG10 | I10: =+SUMIF(Рўйхат!$C:$C,$B10,Рўйхат!J:J) | J10: =+SUMIF(Рўйхат!$C:$C,$B10,Рўйхат!K:K) | K10: =+SUMIF(Рўйхат!$C:$C,$B10,Рўйхат!L:L) | L10: =+SUMIF(Рўйхат!$C:$C,$B10,Рўйхат!M:M) | M10: =+SUMIF(Рўйхат!$C:$C,$B10,Рўйхат!N:N) | N10: =+SUMIF(Рўйхат!$C:$C,$B10,Рўйхат!O:O) | O10: =+SUMIF(Рўйхат!$C:$C,$B10,Рўйхат!P:P) | P10: =+SUMIF(Рўйхат!$C:$C,$B10,Рўйхат!Q:Q) | Q10: =+SUMIF(Рўйхат!$C:$C,$B10,Рўйхат!R:R) | R10: =+SUMIF(Рўйхат!$C:$C,$B10,Рўйхат!S:S) | S10: =+SUMIF(Рўйхат!$C:$C,$B10,Рўйхат!T:T) | T10: =+SUMIF(Рўйхат!$C:$C,$B10,Рўйхат!U:U) | U10: =+SUMIF(Рўйхат!$C:$C,$B10,Рўйхат!V:V) | V10: =+SUMIF(Рўйхат!$C:$C,$B10,Рўйхат!W:W) | W10: =+SUMIF(Рўйхат!$C:$C,$B10,Рўйхат!X:X) | X10: =+SUMIF(Рўйхат!$C:$C,$B10,Рўйхат!Y:Y) | Y10: =+SUMIF(Рўйхат!$C:$C,$B10,Рўйхат!Z:Z) | Z10: =+SUMIF(Рўйхат!$C:$C,$B10,Рўйхат!AA:AA) | AA10: =+SUMIF(Рўйхат!$C:$C,$B10,Рўйхат!AB:AB) | AB10: =+SUMIF(Рўйхат!$C:$C,$B10,Рўйхат!AC:AC) | AC10: =+SUMIF(Рўйхат!$C:$C,$B10,Рўйхат!AD:AD) | AD10: =+SUMIF(Рўйхат!$C:$C,$B10,Рўйхат!AE:AE) | AE10: =+SUMIF(Рўйхат!$C:$C,$B10,Рўйхат!AF:AF) | AF10: =+SUMIF(Рўйхат!$C:$C,$B10,Рўйхат!AG:AG) | AG10: =+SUMIF(Рўйхат!$C:$C,$B10,Рўйхат!AH:AH) | AH10: =+SUMIF(Рўйхат!$C:$C,$B10,Рўйхат!AI:AI) | AI10: =+SUMIF(Рўйхат!$C:$C,$B10,Рўйхат!AJ:AJ)
A11: =+A10+1 | B11: Олий таълим, фан ва инновациялар вазирлиги | C11: =IF(IFERROR(VLOOKUP(B11,Рўйхат!C:E,2,0),"")="[NULL]","",IFERROR(VLOOKUP(B11,Рўйхат!C:E,2,0),"")) | D11: =IFERROR(VLOOKUP(B11,Рўйхат!C:E,3,0),"") | E11: =+SUMIF(Рўйхат!$C:$C,$B11,Рўйхат!G:G) | F11: =+SUMIF(Рўйхат!$C:$C,$B11,Рўйхат!H:H) | G11: =M11 | H11: =R11+W11+AB11+AG11 | I11: =+SUMIF(Рўйхат!$C:$C,$B11,Рўйхат!J:J) | J11: =+SUMIF(Рўйхат!$C:$C,$B11,Рўйхат!K:K) | K11: =+SUMIF(Рўйхат!$C:$C,$B11,Рўйхат!L:L) | L11: =+SUMIF(Рўйхат!$C:$C,$B11,Рўйхат!M:M) | M11: =+SUMIF(Рўйхат!$C:$C,$B11,Рўйхат!N:N) | N11: =+SUMIF(Рўйхат!$C:$C,$B11,Рўйхат!O:O) | O11: =+SUMIF(Рўйхат!$C:$C,$B11,Рўйхат!P:P) | P11: =+SUMIF(Рўйхат!$C:$C,$B11,Рўйхат!Q:Q) | Q11: =+SUMIF(Рўйхат!$C:$C,$B11,Рўйхат!R:R) | R11: =+SUMIF(Рўйхат!$C:$C,$B11,Рўйхат!S:S) | S11: =+SUMIF(Рўйхат!$C:$C,$B11,Рўйхат!T:T) | T11: =+SUMIF(Рўйхат!$C:$C,$B11,Рўйхат!U:U) | U11: =+SUMIF(Рўйхат!$C:$C,$B11,Рўйхат!V:V) | V11: =+SUMIF(Рўйхат!$C:$C,$B11,Рўйхат!W:W) | W11: =+SUMIF(Рўйхат!$C:$C,$B11,Рўйхат!X:X) | X11: =+SUMIF(Рўйхат!$C:$C,$B11,Рўйхат!Y:Y) | Y11: =+SUMIF(Рўйхат!$C:$C,$B11,Рўйхат!Z:Z) | Z11: =+SUMIF(Рўйхат!$C:$C,$B11,Рўйхат!AA:AA) | AA11: =+SUMIF(Рўйхат!$C:$C,$B11,Рўйхат!AB:AB) | AB11: =+SUMIF(Рўйхат!$C:$C,$B11,Рўйхат!AC:AC) | AC11: =+SUMIF(Рўйхат!$C:$C,$B11,Рўйхат!AD:AD) | AD11: =+SUMIF(Рўйхат!$C:$C,$B11,Рўйхат!AE:AE) | AE11: =+SUMIF(Рўйхат!$C:$C,$B11,Рўйхат!AF:AF) | AF11: =+SUMIF(Рўйхат!$C:$C,$B11,Рўйхат!AG:AG) | AG11: =+SUMIF(Рўйхат!$C:$C,$B11,Рўйхат!AH:AH) | AH11: =+SUMIF(Рўйхат!$C:$C,$B11,Рўйхат!AI:AI) | AI11: =+SUMIF(Рўйхат!$C:$C,$B11,Рўйхат!AJ:AJ)
A12: =+A11+1 | B12: “Ўзбекнефтгаз” АЖ | C12: =IF(IFERROR(VLOOKUP(B12,Рўйхат!C:E,2,0),"")="[NULL]","",IFERROR(VLOOKUP(B12,Рўйхат!C:E,2,0),"")) | D12: =IFERROR(VLOOKUP(B12,Рўйхат!C:E,3,0),"") | E12: =+SUMIF(Рўйхат!$C:$C,$B12,Рўйхат!G:G) | F12: =+SUMIF(Рўйхат!$C:$C,$B12,Рўйхат!H:H) | G12: =M12 | H12: =R12+W12+AB12+AG12 | I12: =+SUMIF(Рўйхат!$C:$C,$B12,Рўйхат!J:J) | J12: =+SUMIF(Рўйхат!$C:$C,$B12,Рўйхат!K:K) | K12: =+SUMIF(Рўйхат!$C:$C,$B12,Рўйхат!L:L) | L12: =+SUMIF(Рўйхат!$C:$C,$B12,Рўйхат!M:M) | M12: =+SUMIF(Рўйхат!$C:$C,$B12,Рўйхат!N:N) | N12: =+SUMIF(Рўйхат!$C:$C,$B12,Рўйхат!O:O) | O12: =+SUMIF(Рўйхат!$C:$C,$B12,Рўйхат!P:P) | P12: =+SUMIF(Рўйхат!$C:$C,$B12,Рўйхат!Q:Q) | Q12: =+SUMIF(Рўйхат!$C:$C,$B12,Рўйхат!R:R) | R12: =+SUMIF(Рўйхат!$C:$C,$B12,Рўйхат!S:S) | S12: =+SUMIF(Рўйхат!$C:$C,$B12,Рўйхат!T:T) | T12: =+SUMIF(Рўйхат!$C:$C,$B12,Рўйхат!U:U) | U12: =+SUMIF(Рўйхат!$C:$C,$B12,Рўйхат!V:V) | V12: =+SUMIF(Рўйхат!$C:$C,$B12,Рўйхат!W:W) | W12: =+SUMIF(Рўйхат!$C:$C,$B12,Рўйхат!X:X) | X12: =+SUMIF(Рўйхат!$C:$C,$B12,Рўйхат!Y:Y) | Y12: =+SUMIF(Рўйхат!$C:$C,$B12,Рўйхат!Z:Z) | Z12: =+SUMIF(Рўйхат!$C:$C,$B12,Рўйхат!AA:AA) | AA12: =+SUMIF(Рўйхат!$C:$C,$B12,Рўйхат!AB:AB) | AB12: =+SUMIF(Рўйхат!$C:$C,$B12,Рўйхат!AC:AC) | AC12: =+SUMIF(Рўйхат!$C:$C,$B12,Рўйхат!AD:AD) | AD12: =+SUMIF(Рўйхат!$C:$C,$B12,Рўйхат!AE:AE) | AE12: =+SUMIF(Рўйхат!$C:$C,$B12,Рўйхат!AF:AF) | AF12: =+SUMIF(Рўйхат!$C:$C,$B12,Рўйхат!AG:AG) | AG12: =+SUMIF(Рўйхат!$C:$C,$B12,Рўйхат!AH:AH) | AH12: =+SUMIF(Рўйхат!$C:$C,$B12,Рўйхат!AI:AI) | AI12: =+SUMIF(Рўйхат!$C:$C,$B12,Рўйхат!AJ:AJ)
A13: =+A12+1 | B13: АТ Халқ банк | C13: =IF(IFERROR(VLOOKUP(B13,Рўйхат!C:E,2,0),"")="[NULL]","",IFERROR(VLOOKUP(B13,Рўйхат!C:E,2,0),"")) | D13: =IFERROR(VLOOKUP(B13,Рўйхат!C:E,3,0),"") | E13: =+SUMIF(Рўйхат!$C:$C,$B13,Рўйхат!G:G) | F13: =+SUMIF(Рўйхат!$C:$C,$B13,Рўйхат!H:H) | G13: =M13 | H13: =R13+W13+AB13+AG13 | I13: =+SUMIF(Рўйхат!$C:$C,$B13,Рўйхат!J:J) | J13: =+SUMIF(Рўйхат!$C:$C,$B13,Рўйхат!K:K) | K13: =+SUMIF(Рўйхат!$C:$C,$B13,Рўйхат!L:L) | L13: =+SUMIF(Рўйхат!$C:$C,$B13,Рўйхат!M:M) | M13: =+SUMIF(Рўйхат!$C:$C,$B13,Рўйхат!N:N) | N13: =+SUMIF(Рўйхат!$C:$C,$B13,Рўйхат!O:O) | O13: =+SUMIF(Рўйхат!$C:$C,$B13,Рўйхат!P:P) | P13: =+SUMIF(Рўйхат!$C:$C,$B13,Рўйхат!Q:Q) | Q13: =+SUMIF(Рўйхат!$C:$C,$B13,Рўйхат!R:R) | R13: =+SUMIF(Рўйхат!$C:$C,$B13,Рўйхат!S:S) | S13: =+SUMIF(Рўйхат!$C:$C,$B13,Рўйхат!T:T) | T13: =+SUMIF(Рўйхат!$C:$C,$B13,Рўйхат!U:U) | U13: =+SUMIF(Рўйхат!$C:$C,$B13,Рўйхат!V:V) | V13: =+SUMIF(Рўйхат!$C:$C,$B13,Рўйхат!W:W) | W13: =+SUMIF(Рўйхат!$C:$C,$B13,Рўйхат!X:X) | X13: =+SUMIF(Рўйхат!$C:$C,$B13,Рўйхат!Y:Y) | Y13: =+SUMIF(Рўйхат!$C:$C,$B13,Рўйхат!Z:Z) | Z13: =+SUMIF(Рўйхат!$C:$C,$B13,Рўйхат!AA:AA) | AA13: =+SUMIF(Рўйхат!$C:$C,$B13,Рўйхат!AB:AB) | AB13: =+SUMIF(Рўйхат!$C:$C,$B13,Рўйхат!AC:AC) | AC13: =+SUMIF(Рўйхат!$C:$C,$B13,Рўйхат!AD:AD) | AD13: =+SUMIF(Рўйхат!$C:$C,$B13,Рўйхат!AE:AE) | AE13: =+SUMIF(Рўйхат!$C:$C,$B13,Рўйхат!AF:AF) | AF13: =+SUMIF(Рўйхат!$C:$C,$B13,Рўйхат!AG:AG) | AG13: =+SUMIF(Рўйхат!$C:$C,$B13,Рўйхат!AH:AH) | AH13: =+SUMIF(Рўйхат!$C:$C,$B13,Рўйхат!AI:AI) | AI13: =+SUMIF(Рўйхат!$C:$C,$B13,Рўйхат!AJ:AJ)
A14: =+A13+1 | B14: Маданият вазирлиги | C14: =IF(IFERROR(VLOOKUP(B14,Рўйхат!C:E,2,0),"")="[NULL]","",IFERROR(VLOOKUP(B14,Рўйхат!C:E,2,0),"")) | D14: =IFERROR(VLOOKUP(B14,Рўйхат!C:E,3,0),"") | E14: =+SUMIF(Рўйхат!$C:$C,$B14,Рўйхат!G:G) | F14: =+SUMIF(Рўйхат!$C:$C,$B14,Рўйхат!H:H) | G14: =M14 | H14: =R14+W14+AB14+AG14 | I14: =+SUMIF(Рўйхат!$C:$C,$B14,Рўйхат!J:J) | J14: =+SUMIF(Рўйхат!$C:$C,$B14,Рўйхат!K:K) | K14: =+SUMIF(Рўйхат!$C:$C,$B14,Рўйхат!L:L) | L14: =+SUMIF(Рўйхат!$C:$C,$B14,Рўйхат!M:M) | M14: =+SUMIF(Рўйхат!$C:$C,$B14,Рўйхат!N:N) | N14: =+SUMIF(Рўйхат!$C:$C,$B14,Рўйхат!O:O) | O14: =+SUMIF(Рўйхат!$C:$C,$B14,Рўйхат!P:P) | P14: =+SUMIF(Рўйхат!$C:$C,$B14,Рўйхат!Q:Q) | Q14: =+SUMIF(Рўйхат!$C:$C,$B14,Рўйхат!R:R) | R14: =+SUMIF(Рўйхат!$C:$C,$B14,Рўйхат!S:S) | S14: =+SUMIF(Рўйхат!$C:$C,$B14,Рўйхат!T:T) | T14: =+SUMIF(Рўйхат!$C:$C,$B14,Рўйхат!U:U) | U14: =+SUMIF(Рўйхат!$C:$C,$B14,Рўйхат!V:V) | V14: =+SUMIF(Рўйхат!$C:$C,$B14,Рўйхат!W:W) | W14: =+SUMIF(Рўйхат!$C:$C,$B14,Рўйхат!X:X) | X14: =+SUMIF(Рўйхат!$C:$C,$B14,Рўйхат!Y:Y) | Y14: =+SUMIF(Рўйхат!$C:$C,$B14,Рўйхат!Z:Z) | Z14: =+SUMIF(Рўйхат!$C:$C,$B14,Рўйхат!AA:AA) | AA14: =+SUMIF(Рўйхат!$C:$C,$B14,Рўйхат!AB:AB) | AB14: =+SUMIF(Рўйхат!$C:$C,$B14,Рўйхат!AC:AC) | AC14: =+SUMIF(Рўйхат!$C:$C,$B14,Рўйхат!AD:AD) | AD14: =+SUMIF(Рўйхат!$C:$C,$B14,Рўйхат!AE:AE) | AE14: =+SUMIF(Рўйхат!$C:$C,$B14,Рўйхат!AF:AF) | AF14: =+SUMIF(Рўйхат!$C:$C,$B14,Рўйхат!AG:AG) | AG14: =+SUMIF(Рўйхат!$C:$C,$B14,Рўйхат!AH:AH) | AH14: =+SUMIF(Рўйхат!$C:$C,$B14,Рўйхат!AI:AI) | AI14: =+SUMIF(Рўйхат!$C:$C,$B14,Рўйхат!AJ:AJ)
A15: =+A14+1 | B15: Ижтимоий ҳимоя миллий агентлиги | C15: =IF(IFERROR(VLOOKUP(B15,Рўйхат!C:E,2,0),"")="[NULL]","",IFERROR(VLOOKUP(B15,Рўйхат!C:E,2,0),"")) | D15: =IFERROR(VLOOKUP(B15,Рўйхат!C:E,3,0),"") | E15: =+SUMIF(Рўйхат!$C:$C,$B15,Рўйхат!G:G) | F15: =+SUMIF(Рўйхат!$C:$C,$B15,Рўйхат!H:H) | G15: =M15 | H15: =R15+W15+AB15+AG15 | I15: =+SUMIF(Рўйхат!$C:$C,$B15,Рўйхат!J:J) | J15: =+SUMIF(Рўйхат!$C:$C,$B15,Рўйхат!K:K) | K15: =+SUMIF(Рўйхат!$C:$C,$B15,Рўйхат!L:L) | L15: =+SUMIF(Рўйхат!$C:$C,$B15,Рўйхат!M:M) | M15: =+SUMIF(Рўйхат!$C:$C,$B15,Рўйхат!N:N) | N15: =+SUMIF(Рўйхат!$C:$C,$B15,Рўйхат!O:O) | O15: =+SUMIF(Рўйхат!$C:$C,$B15,Рўйхат!P:P) | P15: =+SUMIF(Рўйхат!$C:$C,$B15,Рўйхат!Q:Q) | Q15: =+SUMIF(Рўйхат!$C:$C,$B15,Рўйхат!R:R) | R15: =+SUMIF(Рўйхат!$C:$C,$B15,Рўйхат!S:S) | S15: =+SUMIF(Рўйхат!$C:$C,$B15,Рўйхат!T:T) | T15: =+SUMIF(Рўйхат!$C:$C,$B15,Рўйхат!U:U) | U15: =+SUMIF(Рўйхат!$C:$C,$B15,Рўйхат!V:V) | V15: =+SUMIF(Рўйхат!$C:$C,$B15,Рўйхат!W:W) | W15: =+SUMIF(Рўйхат!$C:$C,$B15,Рўйхат!X:X) | X15: =+SUMIF(Рўйхат!$C:$C,$B15,Рўйхат!Y:Y) | Y15: =+SUMIF(Рўйхат!$C:$C,$B15,Рўйхат!Z:Z) | Z15: =+SUMIF(Рўйхат!$C:$C,$B15,Рўйхат!AA:AA) | AA15: =+SUMIF(Рўйхат!$C:$C,$B15,Рўйхат!AB:AB) | AB15: =+SUMIF(Рўйхат!$C:$C,$B15,Рўйхат!AC:AC) | AC15: =+SUMIF(Рўйхат!$C:$C,$B15,Рўйхат!AD:AD) | AD15: =+SUMIF(Рўйхат!$C:$C,$B15,Рўйхат!AE:AE) | AE15: =+SUMIF(Рўйхат!$C:$C,$B15,Рўйхат!AF:AF) | AF15: =+SUMIF(Рўйхат!$C:$C,$B15,Рўйхат!AG:AG) | AG15: =+SUMIF(Рўйхат!$C:$C,$B15,Рўйхат!AH:AH) | AH15: =+SUMIF(Рўйхат!$C:$C,$B15,Рўйхат!AI:AI) | AI15: =+SUMIF(Рўйхат!$C:$C,$B15,Рўйхат!AJ:AJ)
A16: =+A15+1 | B16: Қишлоқ хўжалиги вазирлиги | C16: =IF(IFERROR(VLOOKUP(B16,Рўйхат!C:E,2,0),"")="[NULL]","",IFERROR(VLOOKUP(B16,Рўйхат!C:E,2,0),"")) | D16: =IFERROR(VLOOKUP(B16,Рўйхат!C:E,3,0),"") | E16: =+SUMIF(Рўйхат!$C:$C,$B16,Рўйхат!G:G) | F16: =+SUMIF(Рўйхат!$C:$C,$B16,Рўйхат!H:H) | G16: =M16 | H16: =R16+W16+AB16+AG16 | I16: =+SUMIF(Рўйхат!$C:$C,$B16,Рўйхат!J:J) | J16: =+SUMIF(Рўйхат!$C:$C,$B16,Рўйхат!K:K) | K16: =+SUMIF(Рўйхат!$C:$C,$B16,Рўйхат!L:L) | L16: =+SUMIF(Рўйхат!$C:$C,$B16,Рўйхат!M:M) | M16: =+SUMIF(Рўйхат!$C:$C,$B16,Рўйхат!N:N) | N16: =+SUMIF(Рўйхат!$C:$C,$B16,Рўйхат!O:O) | O16: =+SUMIF(Рўйхат!$C:$C,$B16,Рўйхат!P:P) | P16: =+SUMIF(Рўйхат!$C:$C,$B16,Рўйхат!Q:Q) | Q16: =+SUMIF(Рўйхат!$C:$C,$B16,Рўйхат!R:R) | R16: =+SUMIF(Рўйхат!$C:$C,$B16,Рўйхат!S:S) | S16: =+SUMIF(Рўйхат!$C:$C,$B16,Рўйхат!T:T) | T16: =+SUMIF(Рўйхат!$C:$C,$B16,Рўйхат!U:U) | U16: =+SUMIF(Рўйхат!$C:$C,$B16,Рўйхат!V:V) | V16: =+SUMIF(Рўйхат!$C:$C,$B16,Рўйхат!W:W) | W16: =+SUMIF(Рўйхат!$C:$C,$B16,Рўйхат!X:X) | X16: =+SUMIF(Рўйхат!$C:$C,$B16,Рўйхат!Y:Y) | Y16: =+SUMIF(Рўйхат!$C:$C,$B16,Рўйхат!Z:Z) | Z16: =+SUMIF(Рўйхат!$C:$C,$B16,Рўйхат!AA:AA) | AA16: =+SUMIF(Рўйхат!$C:$C,$B16,Рўйхат!AB:AB) | AB16: =+SUMIF(Рўйхат!$C:$C,$B16,Рўйхат!AC:AC) | AC16: =+SUMIF(Рўйхат!$C:$C,$B16,Рўйхат!AD:AD) | AD16: =+SUMIF(Рўйхат!$C:$C,$B16,Рўйхат!AE:AE) | AE16: =+SUMIF(Рўйхат!$C:$C,$B16,Рўйхат!AF:AF) | AF16: =+SUMIF(Рўйхат!$C:$C,$B16,Рўйхат!AG:AG) | AG16: =+SUMIF(Рўйхат!$C:$C,$B16,Рўйхат!AH:AH) | AH16: =+SUMIF(Рўйхат!$C:$C,$B16,Рўйхат!AI:AI) | AI16: =+SUMIF(Рўйхат!$C:$C,$B16,Рўйхат!AJ:AJ)
A17: =+A16+1 | B17: Сув хўжалиги вазирлиги | C17: =IF(IFERROR(VLOOKUP(B17,Рўйхат!C:E,2,0),"")="[NULL]","",IFERROR(VLOOKUP(B17,Рўйхат!C:E,2,0),"")) | D17: =IFERROR(VLOOKUP(B17,Рўйхат!C:E,3,0),"") | E17: =+SUMIF(Рўйхат!$C:$C,$B17,Рўйхат!G:G) | F17: =+SUMIF(Рўйхат!$C:$C,$B17,Рўйхат!H:H) | G17: =M17 | H17: =R17+W17+AB17+AG17 | I17: =+SUMIF(Рўйхат!$C:$C,$B17,Рўйхат!J:J) | J17: =+SUMIF(Рўйхат!$C:$C,$B17,Рўйхат!K:K) | K17: =+SUMIF(Рўйхат!$C:$C,$B17,Рўйхат!L:L) | L17: =+SUMIF(Рўйхат!$C:$C,$B17,Рўйхат!M:M) | M17: =+SUMIF(Рўйхат!$C:$C,$B17,Рўйхат!N:N) | N17: =+SUMIF(Рўйхат!$C:$C,$B17,Рўйхат!O:O) | O17: =+SUMIF(Рўйхат!$C:$C,$B17,Рўйхат!P:P) | P17: =+SUMIF(Рўйхат!$C:$C,$B17,Рўйхат!Q:Q) | Q17: =+SUMIF(Рўйхат!$C:$C,$B17,Рўйхат!R:R) | R17: =+SUMIF(Рўйхат!$C:$C,$B17,Рўйхат!S:S) | S17: =+SUMIF(Рўйхат!$C:$C,$B17,Рўйхат!T:T) | T17: =+SUMIF(Рўйхат!$C:$C,$B17,Рўйхат!U:U) | U17: =+SUMIF(Рўйхат!$C:$C,$B17,Рўйхат!V:V) | V17: =+SUMIF(Рўйхат!$C:$C,$B17,Рўйхат!W:W) | W17: =+SUMIF(Рўйхат!$C:$C,$B17,Рўйхат!X:X) | X17: =+SUMIF(Рўйхат!$C:$C,$B17,Рўйхат!Y:Y) | Y17: =+SUMIF(Рўйхат!$C:$C,$B17,Рўйхат!Z:Z) | Z17: =+SUMIF(Рўйхат!$C:$C,$B17,Рўйхат!AA:AA) | AA17: =+SUMIF(Рўйхат!$C:$C,$B17,Рўйхат!AB:AB) | AB17: =+SUMIF(Рўйхат!$C:$C,$B17,Рўйхат!AC:AC) | AC17: =+SUMIF(Рўйхат!$C:$C,$B17,Рўйхат!AD:AD) | AD17: =+SUMIF(Рўйхат!$C:$C,$B17,Рўйхат!AE:AE) | AE17: =+SUMIF(Рўйхат!$C:$C,$B17,Рўйхат!AF:AF) | AF17: =+SUMIF(Рўйхат!$C:$C,$B17,Рўйхат!AG:AG) | AG17: =+SUMIF(Рўйхат!$C:$C,$B17,Рўйхат!AH:AH) | AH17: =+SUMIF(Рўйхат!$C:$C,$B17,Рўйхат!AI:AI) | AI17: =+SUMIF(Рўйхат!$C:$C,$B17,Рўйхат!AJ:AJ)
A18: =+A17+1 | B18: Камбағалликни қисқартириш ва бандлик вазирлиги | C18: =IF(IFERROR(VLOOKUP(B18,Рўйхат!C:E,2,0),"")="[NULL]","",IFERROR(VLOOKUP(B18,Рўйхат!C:E,2,0),"")) | D18: =IFERROR(VLOOKUP(B18,Рўйхат!C:E,3,0),"") | E18: =+SUMIF(Рўйхат!$C:$C,$B18,Рўйхат!G:G) | F18: =+SUMIF(Рўйхат!$C:$C,$B18,Рўйхат!H:H) | G18: =M18 | H18: =R18+W18+AB18+AG18 | I18: =+SUMIF(Рўйхат!$C:$C,$B18,Рўйхат!J:J) | J18: =+SUMIF(Рўйхат!$C:$C,$B18,Рўйхат!K:K) | K18: =+SUMIF(Рўйхат!$C:$C,$B18,Рўйхат!L:L) | L18: =+SUMIF(Рўйхат!$C:$C,$B18,Рўйхат!M:M) | M18: =+SUMIF(Рўйхат!$C:$C,$B18,Рўйхат!N:N) | N18: =+SUMIF(Рўйхат!$C:$C,$B18,Рўйхат!O:O) | O18: =+SUMIF(Рўйхат!$C:$C,$B18,Рўйхат!P:P) | P18: =+SUMIF(Рўйхат!$C:$C,$B18,Рўйхат!Q:Q) | Q18: =+SUMIF(Рўйхат!$C:$C,$B18,Рўйхат!R:R) | R18: =+SUMIF(Рўйхат!$C:$C,$B18,Рўйхат!S:S) | S18: =+SUMIF(Рўйхат!$C:$C,$B18,Рўйхат!T:T) | T18: =+SUMIF(Рўйхат!$C:$C,$B18,Рўйхат!U:U) | U18: =+SUMIF(Рўйхат!$C:$C,$B18,Рўйхат!V:V) | V18: =+SUMIF(Рўйхат!$C:$C,$B18,Рўйхат!W:W) | W18: =+SUMIF(Рўйхат!$C:$C,$B18,Рўйхат!X:X) | X18: =+SUMIF(Рўйхат!$C:$C,$B18,Рўйхат!Y:Y) | Y18: =+SUMIF(Рўйхат!$C:$C,$B18,Рўйхат!Z:Z) | Z18: =+SUMIF(Рўйхат!$C:$C,$B18,Рўйхат!AA:AA) | AA18: =+SUMIF(Рўйхат!$C:$C,$B18,Рўйхат!AB:AB) | AB18: =+SUMIF(Рўйхат!$C:$C,$B18,Рўйхат!AC:AC) | AC18: =+SUMIF(Рўйхат!$C:$C,$B18,Рўйхат!AD:AD) | AD18: =+SUMIF(Рўйхат!$C:$C,$B18,Рўйхат!AE:AE) | AE18: =+SUMIF(Рўйхат!$C:$C,$B18,Рўйхат!AF:AF) | AF18: =+SUMIF(Рўйхат!$C:$C,$B18,Рўйхат!AG:AG) | AG18: =+SUMIF(Рўйхат!$C:$C,$B18,Рўйхат!AH:AH) | AH18: =+SUMIF(Рўйхат!$C:$C,$B18,Рўйхат!AI:AI) | AI18: =+SUMIF(Рўйхат!$C:$C,$B18,Рўйхат!AJ:AJ)
... A24: =+A23+1 | B24: Тошкент вилояти ҳокимлиги | C24: =IF(IFERROR(VLOOKUP(B24,Рўйхат!C:E,2,0),"")="[NULL]","",IFERROR(VLOOKUP(B24,Рўйхат!C:E,2,0),"")) | D24: =IFERROR(VLOOKUP(B24,Рўйхат!C:E,3,0),"") | E24: =+SUMIF(Рўйхат!$C:$C,$B24,Рўйхат!G:G) | F24: =+SUMIF(Рўйхат!$C:$C,$B24,Рўйхат!H:H) | G24: =M24 | H24: =R24+W24+AB24+AG24 | I24: =+SUMIF(Рўйхат!$C:$C,$B24,Рўйхат!J:J) | J24: =+SUMIF(Рўйхат!$C:$C,$B24,Рўйхат!K:K) | K24: =+SUMIF(Рўйхат!$C:$C,$B24,Рўйхат!L:L) | L24: =+SUMIF(Рўйхат!$C:$C,$B24,Рўйхат!M:M) | M24: =+SUMIF(Рўйхат!$C:$C,$B24,Рўйхат!N:N) | N24: =+SUMIF(Рўйхат!$C:$C,$B24,Рўйхат!O:O) | O24: =+SUMIF(Рўйхат!$C:$C,$B24,Рўйхат!P:P) | P24: =+SUMIF(Рўйхат!$C:$C,$B24,Рўйхат!Q:Q) | Q24: =+SUMIF(Рўйхат!$C:$C,$B24,Рўйхат!R:R) | R24: =+SUMIF(Рўйхат!$C:$C,$B24,Рўйхат!S:S) | S24: =+SUMIF(Рўйхат!$C:$C,$B24,Рўйхат!T:T) | T24: =+SUMIF(Рўйхат!$C:$C,$B24,Рўйхат!U:U) | U24: =+SUMIF(Рўйхат!$C:$C,$B24,Рўйхат!V:V) | V24: =+SUMIF(Рўйхат!$C:$C,$B24,Рўйхат!W:W) | W24: =+SUMIF(Рўйхат!$C:$C,$B24,Рўйхат!X:X) | X24: =+SUMIF(Рўйхат!$C:$C,$B24,Рўйхат!Y:Y) | Y24: =+SUMIF(Рўйхат!$C:$C,$B24,Рўйхат!Z:Z) | Z24: =+SUMIF(Рўйхат!$C:$C,$B24,Рўйхат!AA:AA) | AA24: =+SUMIF(Рўйхат!$C:$C,$B24,Рўйхат!AB:AB) | AB24: =+SUMIF(Рўйхат!$C:$C,$B24,Рўйхат!AC:AC) | AC24: =+SUMIF(Рўйхат!$C:$C,$B24,Рўйхат!AD:AD) | AD24: =+SUMIF(Рўйхат!$C:$C,$B24,Рўйхат!AE:AE) | AE24: =+SUMIF(Рўйхат!$C:$C,$B24,Рўйхат!AF:AF) | AF24: =+SUMIF(Рўйхат!$C:$C,$B24,Рўйхат!AG:AG) | AG24: =+SUMIF(Рўйхат!$C:$C,$B24,Рўйхат!AH:AH) | AH24: =+SUMIF(Рўйхат!$C:$C,$B24,Рўйхат!AI:AI) | AI24: =+SUMIF(Рўйхат!$C:$C,$B24,Рўйхат!AJ:AJ)
A25: =+A24+1 | B25: Қурилиш ва уй-жой коммунал хўжалиги соҳасида назорат қилиш инспекцияси | C25: =IF(IFERROR(VLOOKUP(B25,Рўйхат!C:E,2,0),"")="[NULL]","",IFERROR(VLOOKUP(B25,Рўйхат!C:E,2,0),"")) | E25: =+SUMIF(Рўйхат!$C:$C,$B25,Рўйхат!G:G) | F25: =+SUMIF(Рўйхат!$C:$C,$B25,Рўйхат!H:H) | G25: =M25 | H25: =R25+W25+AB25+AG25 | I25: =+SUMIF(Рўйхат!$C:$C,$B25,Рўйхат!J:J) | J25: =+SUMIF(Рўйхат!$C:$C,$B25,Рўйхат!K:K) | K25: =+SUMIF(Рўйхат!$C:$C,$B25,Рўйхат!L:L) | L25: =+SUMIF(Рўйхат!$C:$C,$B25,Рўйхат!M:M) | M25: =+SUMIF(Рўйхат!$C:$C,$B25,Рўйхат!N:N) | N25: =+SUMIF(Рўйхат!$C:$C,$B25,Рўйхат!O:O) | O25: =+SUMIF(Рўйхат!$C:$C,$B25,Рўйхат!P:P) | P25: =+SUMIF(Рўйхат!$C:$C,$B25,Рўйхат!Q:Q) | Q25: =+SUMIF(Рўйхат!$C:$C,$B25,Рўйхат!R:R) | R25: =+SUMIF(Рўйхат!$C:$C,$B25,Рўйхат!S:S) | S25: =+SUMIF(Рўйхат!$C:$C,$B25,Рўйхат!T:T) | T25: =+SUMIF(Рўйхат!$C:$C,$B25,Рўйхат!U:U) | U25: =+SUMIF(Рўйхат!$C:$C,$B25,Рўйхат!V:V) | V25: =+SUMIF(Рўйхат!$C:$C,$B25,Рўйхат!W:W) | W25: =+SUMIF(Рўйхат!$C:$C,$B25,Рўйхат!X:X) | X25: =+SUMIF(Рўйхат!$C:$C,$B25,Рўйхат!Y:Y) | Y25: =+SUMIF(Рўйхат!$C:$C,$B25,Рўйхат!Z:Z) | Z25: =+SUMIF(Рўйхат!$C:$C,$B25,Рўйхат!AA:AA) | AA25: =+SUMIF(Рўйхат!$C:$C,$B25,Рўйхат!AB:AB) | AB25: =+SUMIF(Рўйхат!$C:$C,$B25,Рўйхат!AC:AC) | AC25: =+SUMIF(Рўйхат!$C:$C,$B25,Рўйхат!AD:AD) | AD25: =+SUMIF(Рўйхат!$C:$C,$B25,Рўйхат!AE:AE) | AE25: =+SUMIF(Рўйхат!$C:$C,$B25,Рўйхат!AF:AF) | AF25: =+SUMIF(Рўйхат!$C:$C,$B25,Рўйхат!AG:AG) | AG25: =+SUMIF(Рўйхат!$C:$C,$B25,Рўйхат!AH:AH) | AH25: =+SUMIF(Рўйхат!$C:$C,$B25,Рўйхат!AI:AI) | AI25: =+SUMIF(Рўйхат!$C:$C,$B25,Рўйхат!AJ:AJ)
A26: =+A25+1 | B26: Адлия вазирлиги | C26: =IF(IFERROR(VLOOKUP(B26,Рўйхат!C:E,2,0),"")="[NULL]","",IFERROR(VLOOKUP(B26,Рўйхат!C:E,2,0),"")) | D26: =IFERROR(VLOOKUP(B26,Рўйхат!C:E,3,0),"") | E26: =+SUMIF(Рўйхат!$C:$C,$B26,Рўйхат!G:G) | F26: =+SUMIF(Рўйхат!$C:$C,$B26,Рўйхат!H:H) | G26: =M26 | H26: =R26+W26+AB26+AG26 | I26: =+SUMIF(Рўйхат!$C:$C,$B26,Рўйхат!J:J) | J26: =+SUMIF(Рўйхат!$C:$C,$B26,Рўйхат!K:K) | K26: =+SUMIF(Рўйхат!$C:$C,$B26,Рўйхат!L:L) | L26: =+SUMIF(Рўйхат!$C:$C,$B26,Рўйхат!M:M) | M26: =+SUMIF(Рўйхат!$C:$C,$B26,Рўйхат!N:N) | N26: =+SUMIF(Рўйхат!$C:$C,$B26,Рўйхат!O:O) | O26: =+SUMIF(Рўйхат!$C:$C,$B26,Рўйхат!P:P) | P26: =+SUMIF(Рўйхат!$C:$C,$B26,Рўйхат!Q:Q) | Q26: =+SUMIF(Рўйхат!$C:$C,$B26,Рўйхат!R:R) | R26: =+SUMIF(Рўйхат!$C:$C,$B26,Рўйхат!S:S) | S26: =+SUMIF(Рўйхат!$C:$C,$B26,Рўйхат!T:T) | T26: =+SUMIF(Рўйхат!$C:$C,$B26,Рўйхат!U:U) | U26: =+SUMIF(Рўйхат!$C:$C,$B26,Рўйхат!V:V) | V26: =+SUMIF(Рўйхат!$C:$C,$B26,Рўйхат!W:W) | W26: =+SUMIF(Рўйхат!$C:$C,$B26,Рўйхат!X:X) | X26: =+SUMIF(Рўйхат!$C:$C,$B26,Рўйхат!Y:Y) | Y26: =+SUMIF(Рўйхат!$C:$C,$B26,Рўйхат!Z:Z) | Z26: =+SUMIF(Рўйхат!$C:$C,$B26,Рўйхат!AA:AA) | AA26: =+SUMIF(Рўйхат!$C:$C,$B26,Рўйхат!AB:AB) | AB26: =+SUMIF(Рўйхат!$C:$C,$B26,Рўйхат!AC:AC) | AC26: =+SUMIF(Рўйхат!$C:$C,$B26,Рўйхат!AD:AD) | AD26: =+SUMIF(Рўйхат!$C:$C,$B26,Рўйхат!AE:AE) | AE26: =+SUMIF(Рўйхат!$C:$C,$B26,Рўйхат!AF:AF) | AF26: =+SUMIF(Рўйхат!$C:$C,$B26,Рўйхат!AG:AG) | AG26: =+SUMIF(Рўйхат!$C:$C,$B26,Рўйхат!AH:AH) | AH26: =+SUMIF(Рўйхат!$C:$C,$B26,Рўйхат!AI:AI) | AI26: =+SUMIF(Рўйхат!$C:$C,$B26,Рўйхат!AJ:AJ)
A27: =+A26+1 | B27: Самарқанд вилояти ҳокимлиги | C27: =IF(IFERROR(VLOOKUP(B27,Рўйхат!C:E,2,0),"")="[NULL]","",IFERROR(VLOOKUP(B27,Рўйхат!C:E,2,0),"")) | D27: =IFERROR(VLOOKUP(B27,Рўйхат!C:E,3,0),"") | E27: =+SUMIF(Рўйхат!$C:$C,$B27,Рўйхат!G:G) | F27: =+SUMIF(Рўйхат!$C:$C,$B27,Рўйхат!H:H) | G27: =M27 | H27: =R27+W27+AB27+AG27 | I27: =+SUMIF(Рўйхат!$C:$C,$B27,Рўйхат!J:J) | J27: =+SUMIF(Рўйхат!$C:$C,$B27,Рўйхат!K:K) | K27: =+SUMIF(Рўйхат!$C:$C,$B27,Рўйхат!L:L) | L27: =+SUMIF(Рўйхат!$C:$C,$B27,Рўйхат!M:M) | M27: =+SUMIF(Рўйхат!$C:$C,$B27,Рўйхат!N:N) | N27: =+SUMIF(Рўйхат!$C:$C,$B27,Рўйхат!O:O) | O27: =+SUMIF(Рўйхат!$C:$C,$B27,Рўйхат!P:P) | P27: =+SUMIF(Рўйхат!$C:$C,$B27,Рўйхат!Q:Q) | Q27: =+SUMIF(Рўйхат!$C:$C,$B27,Рўйхат!R:R) | R27: =+SUMIF(Рўйхат!$C:$C,$B27,Рўйхат!S:S) | S27: =+SUMIF(Рўйхат!$C:$C,$B27,Рўйхат!T:T) | T27: =+SUMIF(Рўйхат!$C:$C,$B27,Рўйхат!U:U) | U27: =+SUMIF(Рўйхат!$C:$C,$B27,Рўйхат!V:V) | V27: =+SUMIF(Рўйхат!$C:$C,$B27,Рўйхат!W:W) | W27: =+SUMIF(Рўйхат!$C:$C,$B27,Рўйхат!X:X) | X27: =+SUMIF(Рўйхат!$C:$C,$B27,Рўйхат!Y:Y) | Y27: =+SUMIF(Рўйхат!$C:$C,$B27,Рўйхат!Z:Z) | Z27: =+SUMIF(Рўйхат!$C:$C,$B27,Рўйхат!AA:AA) | AA27: =+SUMIF(Рўйхат!$C:$C,$B27,Рўйхат!AB:AB) | AB27: =+SUMIF(Рўйхат!$C:$C,$B27,Рўйхат!AC:AC) | AC27: =+SUMIF(Рўйхат!$C:$C,$B27,Рўйхат!AD:AD) | AD27: =+SUMIF(Рўйхат!$C:$C,$B27,Рўйхат!AE:AE) | AE27: =+SUMIF(Рўйхат!$C:$C,$B27,Рўйхат!AF:AF) | AF27: =+SUMIF(Рўйхат!$C:$C,$B27,Рўйхат!AG:AG) | AG27: =+SUMIF(Рўйхат!$C:$C,$B27,Рўйхат!AH:AH) | AH27: =+SUMIF(Рўйхат!$C:$C,$B27,Рўйхат!AI:AI) | AI27: =+SUMIF(Рўйхат!$C:$C,$B27,Рўйхат!AJ:AJ)
A28: =+A27+1 | B28: Сурхандарё вилояти ҳокимлиги | C28: =IF(IFERROR(VLOOKUP(B28,Рўйхат!C:E,2,0),"")="[NULL]","",IFERROR(VLOOKUP(B28,Рўйхат!C:E,2,0),"")) | D28: =IFERROR(VLOOKUP(B28,Рўйхат!C:E,3,0),"") | E28: =+SUMIF(Рўйхат!$C:$C,$B28,Рўйхат!G:G) | F28: =+SUMIF(Рўйхат!$C:$C,$B28,Рўйхат!H:H) | G28: =M28 | H28: =R28+W28+AB28+AG28 | I28: =+SUMIF(Рўйхат!$C:$C,$B28,Рўйхат!J:J) | J28: =+SUMIF(Рўйхат!$C:$C,$B28,Рўйхат!K:K) | K28: =+SUMIF(Рўйхат!$C:$C,$B28,Рўйхат!L:L) | L28: =+SUMIF(Рўйхат!$C:$C,$B28,Рўйхат!M:M) | M28: =+SUMIF(Рўйхат!$C:$C,$B28,Рўйхат!N:N) | N28: =+SUMIF(Рўйхат!$C:$C,$B28,Рўйхат!O:O) | O28: =+SUMIF(Рўйхат!$C:$C,$B28,Рўйхат!P:P) | P28: =+SUMIF(Рўйхат!$C:$C,$B28,Рўйхат!Q:Q) | Q28: =+SUMIF(Рўйхат!$C:$C,$B28,Рўйхат!R:R) | R28: =+SUMIF(Рўйхат!$C:$C,$B28,Рўйхат!S:S) | S28: =+SUMIF(Рўйхат!$C:$C,$B28,Рўйхат!T:T) | T28: =+SUMIF(Рўйхат!$C:$C,$B28,Рўйхат!U:U) | U28: =+SUMIF(Рўйхат!$C:$C,$B28,Рўйхат!V:V) | V28: =+SUMIF(Рўйхат!$C:$C,$B28,Рўйхат!W:W) | W28: =+SUMIF(Рўйхат!$C:$C,$B28,Рўйхат!X:X) | X28: =+SUMIF(Рўйхат!$C:$C,$B28,Рўйхат!Y:Y) | Y28: =+SUMIF(Рўйхат!$C:$C,$B28,Рўйхат!Z:Z) | Z28: =+SUMIF(Рўйхат!$C:$C,$B28,Рўйхат!AA:AA) | AA28: =+SUMIF(Рўйхат!$C:$C,$B28,Рўйхат!AB:AB) | AB28: =+SUMIF(Рўйхат!$C:$C,$B28,Рўйхат!AC:AC) | AC28: =+SUMIF(Рўйхат!$C:$C,$B28,Рўйхат!AD:AD) | AD28: =+SUMIF(Рўйхат!$C:$C,$B28,Рўйхат!AE:AE) | AE28: =+SUMIF(Рўйхат!$C:$C,$B28,Рўйхат!AF:AF) | AF28: =+SUMIF(Рўйхат!$C:$C,$B28,Рўйхат!AG:AG) | AG28: =+SUMIF(Рўйхат!$C:$C,$B28,Рўйхат!AH:AH) | AH28: =+SUMIF(Рўйхат!$C:$C,$B28,Рўйхат!AI:AI) | AI28: =+SUMIF(Рўйхат!$C:$C,$B28,Рўйхат!AJ:AJ)
A29: =+A28+1 | B29: Хоразм вилояти ҳокимлиги | C29: =IF(IFERROR(VLOOKUP(B29,Рўйхат!C:E,2,0),"")="[NULL]","",IFERROR(VLOOKUP(B29,Рўйхат!C:E,2,0),"")) | D29: =IFERROR(VLOOKUP(B29,Рўйхат!C:E,3,0),"") | E29: =+SUMIF(Рўйхат!$C:$C,$B29,Рўйхат!G:G) | F29: =+SUMIF(Рўйхат!$C:$C,$B29,Рўйхат!H:H) | G29: =M29 | H29: =R29+W29+AB29+AG29 | I29: =+SUMIF(Рўйхат!$C:$C,$B29,Рўйхат!J:J) | J29: =+SUMIF(Рўйхат!$C:$C,$B29,Рўйхат!K:K) | K29: =+SUMIF(Рўйхат!$C:$C,$B29,Рўйхат!L:L) | L29: =+SUMIF(Рўйхат!$C:$C,$B29,Рўйхат!M:M) | M29: =+SUMIF(Рўйхат!$C:$C,$B29,Рўйхат!N:N) | N29: =+SUMIF(Рўйхат!$C:$C,$B29,Рўйхат!O:O) | O29: =+SUMIF(Рўйхат!$C:$C,$B29,Рўйхат!P:P) | P29: =+SUMIF(Рўйхат!$C:$C,$B29,Рўйхат!Q:Q) | Q29: =+SUMIF(Рўйхат!$C:$C,$B29,Рўйхат!R:R) | R29: =+SUMIF(Рўйхат!$C:$C,$B29,Рўйхат!S:S) | S29: =+SUMIF(Рўйхат!$C:$C,$B29,Рўйхат!T:T) | T29: =+SUMIF(Рўйхат!$C:$C,$B29,Рўйхат!U:U) | U29: =+SUMIF(Рўйхат!$C:$C,$B29,Рўйхат!V:V) | V29: =+SUMIF(Рўйхат!$C:$C,$B29,Рўйхат!W:W) | W29: =+SUMIF(Рўйхат!$C:$C,$B29,Рўйхат!X:X) | X29: =+SUMIF(Рўйхат!$C:$C,$B29,Рўйхат!Y:Y) | Y29: =+SUMIF(Рўйхат!$C:$C,$B29,Рўйхат!Z:Z) | Z29: =+SUMIF(Рўйхат!$C:$C,$B29,Рўйхат!AA:AA) | AA29: =+SUMIF(Рўйхат!$C:$C,$B29,Рўйхат!AB:AB) | AB29: =+SUMIF(Рўйхат!$C:$C,$B29,Рўйхат!AC:AC) | AC29: =+SUMIF(Рўйхат!$C:$C,$B29,Рўйхат!AD:AD) | AD29: =+SUMIF(Рўйхат!$C:$C,$B29,Рўйхат!AE:AE) | AE29: =+SUMIF(Рўйхат!$C:$C,$B29,Рўйхат!AF:AF) | AF29: =+SUMIF(Рўйхат!$C:$C,$B29,Рўйхат!AG:AG) | AG29: =+SUMIF(Рўйхат!$C:$C,$B29,Рўйхат!AH:AH) | AH29: =+SUMIF(Рўйхат!$C:$C,$B29,Рўйхат!AI:AI) | AI29: =+SUMIF(Рўйхат!$C:$C,$B29,Рўйхат!AJ:AJ)
A30: =+A29+1 | B30: Спорт вазирлиги | C30: =IF(IFERROR(VLOOKUP(B30,Рўйхат!C:E,2,0),"")="[NULL]","",IFERROR(VLOOKUP(B30,Рўйхат!C:E,2,0),"")) | D30: =IFERROR(VLOOKUP(B30,Рўйхат!C:E,3,0),"") | E30: =+SUMIF(Рўйхат!$C:$C,$B30,Рўйхат!G:G) | F30: =+SUMIF(Рўйхат!$C:$C,$B30,Рўйхат!H:H) | G30: =M30 | H30: =R30+W30+AB30+AG30 | I30: =+SUMIF(Рўйхат!$C:$C,$B30,Рўйхат!J:J) | J30: =+SUMIF(Рўйхат!$C:$C,$B30,Рўйхат!K:K) | K30: =+SUMIF(Рўйхат!$C:$C,$B30,Рўйхат!L:L) | L30: =+SUMIF(Рўйхат!$C:$C,$B30,Рўйхат!M:M) | M30: =+SUMIF(Рўйхат!$C:$C,$B30,Рўйхат!N:N) | N30: =+SUMIF(Рўйхат!$C:$C,$B30,Рўйхат!O:O) | O30: =+SUMIF(Рўйхат!$C:$C,$B30,Рўйхат!P:P) | P30: =+SUMIF(Рўйхат!$C:$C,$B30,Рўйхат!Q:Q) | Q30: =+SUMIF(Рўйхат!$C:$C,$B30,Рўйхат!R:R) | R30: =+SUMIF(Рўйхат!$C:$C,$B30,Рўйхат!S:S) | S30: =+SUMIF(Рўйхат!$C:$C,$B30,Рўйхат!T:T) | T30: =+SUMIF(Рўйхат!$C:$C,$B30,Рўйхат!U:U) | U30: =+SUMIF(Рўйхат!$C:$C,$B30,Рўйхат!V:V) | V30: =+SUMIF(Рўйхат!$C:$C,$B30,Рўйхат!W:W) | W30: =+SUMIF(Рўйхат!$C:$C,$B30,Рўйхат!X:X) | X30: =+SUMIF(Рўйхат!$C:$C,$B30,Рўйхат!Y:Y) | Y30: =+SUMIF(Рўйхат!$C:$C,$B30,Рўйхат!Z:Z) | Z30: =+SUMIF(Рўйхат!$C:$C,$B30,Рўйхат!AA:AA) | AA30: =+SUMIF(Рўйхат!$C:$C,$B30,Рўйхат!AB:AB) | AB30: =+SUMIF(Рўйхат!$C:$C,$B30,Рўйхат!AC:AC) | AC30: =+SUMIF(Рўйхат!$C:$C,$B30,Рўйхат!AD:AD) | AD30: =+SUMIF(Рўйхат!$C:$C,$B30,Рўйхат!AE:AE) | AE30: =+SUMIF(Рўйхат!$C:$C,$B30,Рўйхат!AF:AF) | AF30: =+SUMIF(Рўйхат!$C:$C,$B30,Рўйхат!AG:AG) | AG30: =+SUMIF(Рўйхат!$C:$C,$B30,Рўйхат!AH:AH) | AH30: =+SUMIF(Рўйхат!$C:$C,$B30,Рўйхат!AI:AI) | AI30: =+SUMIF(Рўйхат!$C:$C,$B30,Рўйхат!AJ:AJ)
A31: =+A30+1 | B31: Бухоро вилоят ҳокимлиги | C31: =IF(IFERROR(VLOOKUP(B31,Рўйхат!C:E,2,0),"")="[NULL]","",IFERROR(VLOOKUP(B31,Рўйхат!C:E,2,0),"")) | D31: =IFERROR(VLOOKUP(B31,Рўйхат!C:E,3,0),"") | E31: =+SUMIF(Рўйхат!$C:$C,$B31,Рўйхат!G:G) | F31: =+SUMIF(Рўйхат!$C:$C,$B31,Рўйхат!H:H) | G31: =M31 | H31: =R31+W31+AB31+AG31 | I31: =+SUMIF(Рўйхат!$C:$C,$B31,Рўйхат!J:J) | J31: =+SUMIF(Рўйхат!$C:$C,$B31,Рўйхат!K:K) | K31: =+SUMIF(Рўйхат!$C:$C,$B31,Рўйхат!L:L) | L31: =+SUMIF(Рўйхат!$C:$C,$B31,Рўйхат!M:M) | M31: =+SUMIF(Рўйхат!$C:$C,$B31,Рўйхат!N:N) | N31: =+SUMIF(Рўйхат!$C:$C,$B31,Рўйхат!O:O) | O31: =+SUMIF(Рўйхат!$C:$C,$B31,Рўйхат!P:P) | P31: =+SUMIF(Рўйхат!$C:$C,$B31,Рўйхат!Q:Q) | Q31: =+SUMIF(Рўйхат!$C:$C,$B31,Рўйхат!R:R) | R31: =+SUMIF(Рўйхат!$C:$C,$B31,Рўйхат!S:S) | S31: =+SUMIF(Рўйхат!$C:$C,$B31,Рўйхат!T:T) | T31: =+SUMIF(Рўйхат!$C:$C,$B31,Рўйхат!U:U) | U31: =+SUMIF(Рўйхат!$C:$C,$B31,Рўйхат!V:V) | V31: =+SUMIF(Рўйхат!$C:$C,$B31,Рўйхат!W:W) | W31: =+SUMIF(Рўйхат!$C:$C,$B31,Рўйхат!X:X) | X31: =+SUMIF(Рўйхат!$C:$C,$B31,Рўйхат!Y:Y) | Y31: =+SUMIF(Рўйхат!$C:$C,$B31,Рўйхат!Z:Z) | Z31: =+SUMIF(Рўйхат!$C:$C,$B31,Рўйхат!AA:AA) | AA31: =+SUMIF(Рўйхат!$C:$C,$B31,Рўйхат!AB:AB) | AB31: =+SUMIF(Рўйхат!$C:$C,$B31,Рўйхат!AC:AC) | AC31: =+SUMIF(Рўйхат!$C:$C,$B31,Рўйхат!AD:AD) | AD31: =+SUMIF(Рўйхат!$C:$C,$B31,Рўйхат!AE:AE) | AE31: =+SUMIF(Рўйхат!$C:$C,$B31,Рўйхат!AF:AF) | AF31: =+SUMIF(Рўйхат!$C:$C,$B31,Рўйхат!AG:AG) | AG31: =+SUMIF(Рўйхат!$C:$C,$B31,Рўйхат!AH:AH) | AH31: =+SUMIF(Рўйхат!$C:$C,$B31,Рўйхат!AI:AI) | AI31: =+SUMIF(Рўйхат!$C:$C,$B31,Рўйхат!AJ:AJ)
A32: =+A31+1 | B32: Навоий вилояти ҳокимлиги | C32: =IF(IFERROR(VLOOKUP(B32,Рўйхат!C:E,2,0),"")="[NULL]","",IFERROR(VLOOKUP(B32,Рўйхат!C:E,2,0),"")) | D32: =IFERROR(VLOOKUP(B32,Рўйхат!C:E,3,0),"") | E32: =+SUMIF(Рўйхат!$C:$C,$B32,Рўйхат!G:G) | F32: =+SUMIF(Рўйхат!$C:$C,$B32,Рўйхат!H:H) | G32: =M32 | H32: =R32+W32+AB32+AG32 | I32: =+SUMIF(Рўйхат!$C:$C,$B32,Рўйхат!J:J) | J32: =+SUMIF(Рўйхат!$C:$C,$B32,Рўйхат!K:K) | K32: =+SUMIF(Рўйхат!$C:$C,$B32,Рўйхат!L:L) | L32: =+SUMIF(Рўйхат!$C:$C,$B32,Рўйхат!M:M) | M32: =+SUMIF(Рўйхат!$C:$C,$B32,Рўйхат!N:N) | N32: =+SUMIF(Рўйхат!$C:$C,$B32,Рўйхат!O:O) | O32: =+SUMIF(Рўйхат!$C:$C,$B32,Рўйхат!P:P) | P32: =+SUMIF(Рўйхат!$C:$C,$B32,Рўйхат!Q:Q) | Q32: =+SUMIF(Рўйхат!$C:$C,$B32,Рўйхат!R:R) | R32: =+SUMIF(Рўйхат!$C:$C,$B32,Рўйхат!S:S) | S32: =+SUMIF(Рўйхат!$C:$C,$B32,Рўйхат!T:T) | T32: =+SUMIF(Рўйхат!$C:$C,$B32,Рўйхат!U:U) | U32: =+SUMIF(Рўйхат!$C:$C,$B32,Рўйхат!V:V) | V32: =+SUMIF(Рўйхат!$C:$C,$B32,Рўйхат!W:W) | W32: =+SUMIF(Рўйхат!$C:$C,$B32,Рўйхат!X:X) | X32: =+SUMIF(Рўйхат!$C:$C,$B32,Рўйхат!Y:Y) | Y32: =+SUMIF(Рўйхат!$C:$C,$B32,Рўйхат!Z:Z) | Z32: =+SUMIF(Рўйхат!$C:$C,$B32,Рўйхат!AA:AA) | AA32: =+SUMIF(Рўйхат!$C:$C,$B32,Рўйхат!AB:AB) | AB32: =+SUMIF(Рўйхат!$C:$C,$B32,Рўйхат!AC:AC) | AC32: =+SUMIF(Рўйхат!$C:$C,$B32,Рўйхат!AD:AD) | AD32: =+SUMIF(Рўйхат!$C:$C,$B32,Рўйхат!AE:AE) | AE32: =+SUMIF(Рўйхат!$C:$C,$B32,Рўйхат!AF:AF) | AF32: =+SUMIF(Рўйхат!$C:$C,$B32,Рўйхат!AG:AG) | AG32: =+SUMIF(Рўйхат!$C:$C,$B32,Рўйхат!AH:AH) | AH32: =+SUMIF(Рўйхат!$C:$C,$B32,Рўйхат!AI:AI) | AI32: =+SUMIF(Рўйхат!$C:$C,$B32,Рўйхат!AJ:AJ)
A33: =+A32+1 | B33: Жиззах вилояти ҳокимлиги | C33: =IF(IFERROR(VLOOKUP(B33,Рўйхат!C:E,2,0),"")="[NULL]","",IFERROR(VLOOKUP(B33,Рўйхат!C:E,2,0),"")) | D33: =IFERROR(VLOOKUP(B33,Рўйхат!C:E,3,0),"") | E33: =+SUMIF(Рўйхат!$C:$C,$B33,Рўйхат!G:G) | F33: =+SUMIF(Рўйхат!$C:$C,$B33,Рўйхат!H:H) | G33: =M33 | H33: =R33+W33+AB33+AG33 | I33: =+SUMIF(Рўйхат!$C:$C,$B33,Рўйхат!J:J) | J33: =+SUMIF(Рўйхат!$C:$C,$B33,Рўйхат!K:K) | K33: =+SUMIF(Рўйхат!$C:$C,$B33,Рўйхат!L:L) | L33: =+SUMIF(Рўйхат!$C:$C,$B33,Рўйхат!M:M) | M33: =+SUMIF(Рўйхат!$C:$C,$B33,Рўйхат!N:N) | N33: =+SUMIF(Рўйхат!$C:$C,$B33,Рўйхат!O:O) | O33: =+SUMIF(Рўйхат!$C:$C,$B33,Рўйхат!P:P) | P33: =+SUMIF(Рўйхат!$C:$C,$B33,Рўйхат!Q:Q) | Q33: =+SUMIF(Рўйхат!$C:$C,$B33,Рўйхат!R:R) | R33: =+SUMIF(Рўйхат!$C:$C,$B33,Рўйхат!S:S) | S33: =+SUMIF(Рўйхат!$C:$C,$B33,Рўйхат!T:T) | T33: =+SUMIF(Рўйхат!$C:$C,$B33,Рўйхат!U:U) | U33: =+SUMIF(Рўйхат!$C:$C,$B33,Рўйхат!V:V) | V33: =+SUMIF(Рўйхат!$C:$C,$B33,Рўйхат!W:W) | W33: =+SUMIF(Рўйхат!$C:$C,$B33,Рўйхат!X:X) | X33: =+SUMIF(Рўйхат!$C:$C,$B33,Рўйхат!Y:Y) | Y33: =+SUMIF(Рўйхат!$C:$C,$B33,Рўйхат!Z:Z) | Z33: =+SUMIF(Рўйхат!$C:$C,$B33,Рўйхат!AA:AA) | AA33: =+SUMIF(Рўйхат!$C:$C,$B33,Рўйхат!AB:AB) | AB33: =+SUMIF(Рўйхат!$C:$C,$B33,Рўйхат!AC:AC) | AC33: =+SUMIF(Рўйхат!$C:$C,$B33,Рўйхат!AD:AD) | AD33: =+SUMIF(Рўйхат!$C:$C,$B33,Рўйхат!AE:AE) | AE33: =+SUMIF(Рўйхат!$C:$C,$B33,Рўйхат!AF:AF) | AF33: =+SUMIF(Рўйхат!$C:$C,$B33,Рўйхат!AG:AG) | AG33: =+SUMIF(Рўйхат!$C:$C,$B33,Рўйхат!AH:AH) | AH33: =+SUMIF(Рўйхат!$C:$C,$B33,Рўйхат!AI:AI) | AI33: =+SUMIF(Рўйхат!$C:$C,$B33,Рўйхат!AJ:AJ)
A34: =+A33+1 | B34: Марказий банк | C34: =IF(IFERROR(VLOOKUP(B34,Рўйхат!C:E,2,0),"")="[NULL]","",IFERROR(VLOOKUP(B34,Рўйхат!C:E,2,0),"")) | D34: =IFERROR(VLOOKUP(B34,Рўйхат!C:E,3,0),"") | E34: =+SUMIF(Рўйхат!$C:$C,$B34,Рўйхат!G:G) | F34: =+SUMIF(Рўйхат!$C:$C,$B34,Рўйхат!H:H) | G34: =M34 | H34: =R34+W34+AB34+AG34 | I34: =+SUMIF(Рўйхат!$C:$C,$B34,Рўйхат!J:J) | J34: =+SUMIF(Рўйхат!$C:$C,$B34,Рўйхат!K:K) | K34: =+SUMIF(Рўйхат!$C:$C,$B34,Рўйхат!L:L) | L34: =+SUMIF(Рўйхат!$C:$C,$B34,Рўйхат!M:M) | M34: =+SUMIF(Рўйхат!$C:$C,$B34,Рўйхат!N:N) | N34: =+SUMIF(Рўйхат!$C:$C,$B34,Рўйхат!O:O) | O34: =+SUMIF(Рўйхат!$C:$C,$B34,Рўйхат!P:P) | P34: =+SUMIF(Рўйхат!$C:$C,$B34,Рўйхат!Q:Q) | Q34: =+SUMIF(Рўйхат!$C:$C,$B34,Рўйхат!R:R) | R34: =+SUMIF(Рўйхат!$C:$C,$B34,Рўйхат!S:S) | S34: =+SUMIF(Рўйхат!$C:$C,$B34,Рўйхат!T:T) | T34: =+SUMIF(Рўйхат!$C:$C,$B34,Рўйхат!U:U) | U34: =+SUMIF(Рўйхат!$C:$C,$B34,Рўйхат!V:V) | V34: =+SUMIF(Рўйхат!$C:$C,$B34,Рўйхат!W:W) | W34: =+SUMIF(Рўйхат!$C:$C,$B34,Рўйхат!X:X) | X34: =+SUMIF(Рўйхат!$C:$C,$B34,Рўйхат!Y:Y) | Y34: =+SUMIF(Рўйхат!$C:$C,$B34,Рўйхат!Z:Z) | Z34: =+SUMIF(Рўйхат!$C:$C,$B34,Рўйхат!AA:AA) | AA34: =+SUMIF(Рўйхат!$C:$C,$B34,Рўйхат!AB:AB) | AB34: =+SUMIF(Рўйхат!$C:$C,$B34,Рўйхат!AC:AC) | AC34: =+SUMIF(Рўйхат!$C:$C,$B34,Рўйхат!AD:AD) | AD34: =+SUMIF(Рўйхат!$C:$C,$B34,Рўйхат!AE:AE) | AE34: =+SUMIF(Рўйхат!$C:$C,$B34,Рўйхат!AF:AF) | AF34: =+SUMIF(Рўйхат!$C:$C,$B34,Рўйхат!AG:AG) | AG34: =+SUMIF(Рўйхат!$C:$C,$B34,Рўйхат!AH:AH) | AH34: =+SUMIF(Рўйхат!$C:$C,$B34,Рўйхат!AI:AI) | AI34: =+SUMIF(Рўйхат!$C:$C,$B34,Рўйхат!AJ:AJ)
A35: =+A34+1 | B35: Андижон вилояти ҳокимлиги | C35: =IF(IFERROR(VLOOKUP(B35,Рўйхат!C:E,2,0),"")="[NULL]","",IFERROR(VLOOKUP(B35,Рўйхат!C:E,2,0),"")) | D35: =IFERROR(VLOOKUP(B35,Рўйхат!C:E,3,0),"") | E35: =+SUMIF(Рўйхат!$C:$C,$B35,Рўйхат!G:G) | F35: =+SUMIF(Рўйхат!$C:$C,$B35,Рўйхат!H:H) | G35: =M35 | H35: =R35+W35+AB35+AG35 | I35: =+SUMIF(Рўйхат!$C:$C,$B35,Рўйхат!J:J) | J35: =+SUMIF(Рўйхат!$C:$C,$B35,Рўйхат!K:K) | K35: =+SUMIF(Рўйхат!$C:$C,$B35,Рўйхат!L:L) | L35: =+SUMIF(Рўйхат!$C:$C,$B35,Рўйхат!M:M) | M35: =+SUMIF(Рўйхат!$C:$C,$B35,Рўйхат!N:N) | N35: =+SUMIF(Рўйхат!$C:$C,$B35,Рўйхат!O:O) | O35: =+SUMIF(Рўйхат!$C:$C,$B35,Рўйхат!P:P) | P35: =+SUMIF(Рўйхат!$C:$C,$B35,Рўйхат!Q:Q) | Q35: =+SUMIF(Рўйхат!$C:$C,$B35,Рўйхат!R:R) | R35: =+SUMIF(Рўйхат!$C:$C,$B35,Рўйхат!S:S) | S35: =+SUMIF(Рўйхат!$C:$C,$B35,Рўйхат!T:T) | T35: =+SUMIF(Рўйхат!$C:$C,$B35,Рўйхат!U:U) | U35: =+SUMIF(Рўйхат!$C:$C,$B35,Рўйхат!V:V) | V35: =+SUMIF(Рўйхат!$C:$C,$B35,Рўйхат!W:W) | W35: =+SUMIF(Рўйхат!$C:$C,$B35,Рўйхат!X:X) | X35: =+SUMIF(Рўйхат!$C:$C,$B35,Рўйхат!Y:Y) | Y35: =+SUMIF(Рўйхат!$C:$C,$B35,Рўйхат!Z:Z) | Z35: =+SUMIF(Рўйхат!$C:$C,$B35,Рўйхат!AA:AA) | AA35: =+SUMIF(Рўйхат!$C:$C,$B35,Рўйхат!AB:AB) | AB35: =+SUMIF(Рўйхат!$C:$C,$B35,Рўйхат!AC:AC) | AC35: =+SUMIF(Рўйхат!$C:$C,$B35,Рўйхат!AD:AD) | AD35: =+SUMIF(Рўйхат!$C:$C,$B35,Рўйхат!AE:AE) | AE35: =+SUMIF(Рўйхат!$C:$C,$B35,Рўйхат!AF:AF) | AF35: =+SUMIF(Рўйхат!$C:$C,$B35,Рўйхат!AG:AG) | AG35: =+SUMIF(Рўйхат!$C:$C,$B35,Рўйхат!AH:AH) | AH35: =+SUMIF(Рўйхат!$C:$C,$B35,Рўйхат!AI:AI) | AI35: =+SUMIF(Рўйхат!$C:$C,$B35,Рўйхат!AJ:AJ)
A36: =+A35+1 | B36: “Ўзавтосаноат” АЖ | C36: =IF(IFERROR(VLOOKUP(B36,Рўйхат!C:E,2,0),"")="[NULL]","",IFERROR(VLOOKUP(B36,Рўйхат!C:E,2,0),"")) | D36: =IFERROR(VLOOKUP(B36,Рўйхат!C:E,3,0),"") | E36: =+SUMIF(Рўйхат!$C:$C,$B36,Рўйхат!G:G) | F36: =+SUMIF(Рўйхат!$C:$C,$B36,Рўйхат!H:H) | G36: =M36 | H36: =R36+W36+AB36+AG36 | I36: =+SUMIF(Рўйхат!$C:$C,$B36,Рўйхат!J:J) | J36: =+SUMIF(Рўйхат!$C:$C,$B36,Рўйхат!K:K) | K36: =+SUMIF(Рўйхат!$C:$C,$B36,Рўйхат!L:L) | L36: =+SUMIF(Рўйхат!$C:$C,$B36,Рўйхат!M:M) | M36: =+SUMIF(Рўйхат!$C:$C,$B36,Рўйхат!N:N) | N36: =+SUMIF(Рўйхат!$C:$C,$B36,Рўйхат!O:O) | O36: =+SUMIF(Рўйхат!$C:$C,$B36,Рўйхат!P:P) | P36: =+SUMIF(Рўйхат!$C:$C,$B36,Рўйхат!Q:Q) | Q36: =+SUMIF(Рўйхат!$C:$C,$B36,Рўйхат!R:R) | R36: =+SUMIF(Рўйхат!$C:$C,$B36,Рўйхат!S:S) | S36: =+SUMIF(Рўйхат!$C:$C,$B36,Рўйхат!T:T) | T36: =+SUMIF(Рўйхат!$C:$C,$B36,Рўйхат!U:U) | U36: =+SUMIF(Рўйхат!$C:$C,$B36,Рўйхат!V:V) | V36: =+SUMIF(Рўйхат!$C:$C,$B36,Рўйхат!W:W) | W36: =+SUMIF(Рўйхат!$C:$C,$B36,Рўйхат!X:X) | X36: =+SUMIF(Рўйхат!$C:$C,$B36,Рўйхат!Y:Y) | Y36: =+SUMIF(Рўйхат!$C:$C,$B36,Рўйхат!Z:Z) | Z36: =+SUMIF(Рўйхат!$C:$C,$B36,Рўйхат!AA:AA) | AA36: =+SUMIF(Рўйхат!$C:$C,$B36,Рўйхат!AB:AB) | AB36: =+SUMIF(Рўйхат!$C:$C,$B36,Рўйхат!AC:AC) | AC36: =+SUMIF(Рўйхат!$C:$C,$B36,Рўйхат!AD:AD) | AD36: =+SUMIF(Рўйхат!$C:$C,$B36,Рўйхат!AE:AE) | AE36: =+SUMIF(Рўйхат!$C:$C,$B36,Рўйхат!AF:AF) | AF36: =+SUMIF(Рўйхат!$C:$C,$B36,Рўйхат!AG:AG) | AG36: =+SUMIF(Рўйхат!$C:$C,$B36,Рўйхат!AH:AH) | AH36: =+SUMIF(Рўйхат!$C:$C,$B36,Рўйхат!AI:AI) | AI36: =+SUMIF(Рўйхат!$C:$C,$B36,Рўйхат!AJ:AJ)
A37: =+A36+1 | B37: Тошкент шаҳар ҳокимлиги | C37: =IF(IFERROR(VLOOKUP(B37,Рўйхат!C:E,2,0),"")="[NULL]","",IFERROR(VLOOKUP(B37,Рўйхат!C:E,2,0),"")) | D37: =IFERROR(VLOOKUP(B37,Рўйхат!C:E,3,0),"") | E37: =+SUMIF(Рўйхат!$C:$C,$B37,Рўйхат!G:G) | F37: =+SUMIF(Рўйхат!$C:$C,$B37,Рўйхат!H:H) | G37: =M37 | H37: =R37+W37+AB37+AG37 | I37: =+SUMIF(Рўйхат!$C:$C,$B37,Рўйхат!J:J) | J37: =+SUMIF(Рўйхат!$C:$C,$B37,Рўйхат!K:K) | K37: =+SUMIF(Рўйхат!$C:$C,$B37,Рўйхат!L:L) | L37: =+SUMIF(Рўйхат!$C:$C,$B37,Рўйхат!M:M) | M37: =+SUMIF(Рўйхат!$C:$C,$B37,Рўйхат!N:N) | N37: =+SUMIF(Рўйхат!$C:$C,$B37,Рўйхат!O:O) | O37: =+SUMIF(Рўйхат!$C:$C,$B37,Рўйхат!P:P) | P37: =+SUMIF(Рўйхат!$C:$C,$B37,Рўйхат!Q:Q) | Q37: =+SUMIF(Рўйхат!$C:$C,$B37,Рўйхат!R:R) | R37: =+SUMIF(Рўйхат!$C:$C,$B37,Рўйхат!S:S) | S37: =+SUMIF(Рўйхат!$C:$C,$B37,Рўйхат!T:T) | T37: =+SUMIF(Рўйхат!$C:$C,$B37,Рўйхат!U:U) | U37: =+SUMIF(Рўйхат!$C:$C,$B37,Рўйхат!V:V) | V37: =+SUMIF(Рўйхат!$C:$C,$B37,Рўйхат!W:W) | W37: =+SUMIF(Рўйхат!$C:$C,$B37,Рўйхат!X:X) | X37: =+SUMIF(Рўйхат!$C:$C,$B37,Рўйхат!Y:Y) | Y37: =+SUMIF(Рўйхат!$C:$C,$B37,Рўйхат!Z:Z) | Z37: =+SUMIF(Рўйхат!$C:$C,$B37,Рўйхат!AA:AA) | AA37: =+SUMIF(Рўйхат!$C:$C,$B37,Рўйхат!AB:AB) | AB37: =+SUMIF(Рўйхат!$C:$C,$B37,Рўйхат!AC:AC) | AC37: =+SUMIF(Рўйхат!$C:$C,$B37,Рўйхат!AD:AD) | AD37: =+SUMIF(Рўйхат!$C:$C,$B37,Рўйхат!AE:AE) | AE37: =+SUMIF(Рўйхат!$C:$C,$B37,Рўйхат!AF:AF) | AF37: =+SUMIF(Рўйхат!$C:$C,$B37,Рўйхат!AG:AG) | AG37: =+SUMIF(Рўйхат!$C:$C,$B37,Рўйхат!AH:AH) | AH37: =+SUMIF(Рўйхат!$C:$C,$B37,Рўйхат!AI:AI) | AI37: =+SUMIF(Рўйхат!$C:$C,$B37,Рўйхат!AJ:AJ)
... A114: =+A113+1 | B114: Ўзбеккўмир АЖ | C114: =IF(IFERROR(VLOOKUP(B114,Рўйхат!C:E,2,0),"")="[NULL]","",IFERROR(VLOOKUP(B114,Рўйхат!C:E,2,0),"")) | D114: =IFERROR(VLOOKUP(B114,Рўйхат!C:E,3,0),"") | E114: =+SUMIF(Рўйхат!$C:$C,$B114,Рўйхат!G:G) | F114: =+SUMIF(Рўйхат!$C:$C,$B114,Рўйхат!H:H) | G114: =M114 | H114: =R114+W114+AB114+AG114 | I114: =+SUMIF(Рўйхат!$C:$C,$B114,Рўйхат!J:J) | J114: =+SUMIF(Рўйхат!$C:$C,$B114,Рўйхат!K:K) | K114: =+SUMIF(Рўйхат!$C:$C,$B114,Рўйхат!L:L) | L114: =+SUMIF(Рўйхат!$C:$C,$B114,Рўйхат!M:M) | M114: =+SUMIF(Рўйхат!$C:$C,$B114,Рўйхат!N:N) | N114: =+SUMIF(Рўйхат!$C:$C,$B114,Рўйхат!O:O) | O114: =+SUMIF(Рўйхат!$C:$C,$B114,Рўйхат!P:P) | P114: =+SUMIF(Рўйхат!$C:$C,$B114,Рўйхат!Q:Q) | Q114: =+SUMIF(Рўйхат!$C:$C,$B114,Рўйхат!R:R) | R114: =+SUMIF(Рўйхат!$C:$C,$B114,Рўйхат!S:S) | S114: =+SUMIF(Рўйхат!$C:$C,$B114,Рўйхат!T:T) | T114: =+SUMIF(Рўйхат!$C:$C,$B114,Рўйхат!U:U) | U114: =+SUMIF(Рўйхат!$C:$C,$B114,Рўйхат!V:V) | V114: =+SUMIF(Рўйхат!$C:$C,$B114,Рўйхат!W:W) | W114: =+SUMIF(Рўйхат!$C:$C,$B114,Рўйхат!X:X) | X114: =+SUMIF(Рўйхат!$C:$C,$B114,Рўйхат!Y:Y) | Y114: =+SUMIF(Рўйхат!$C:$C,$B114,Рўйхат!Z:Z) | Z114: =+SUMIF(Рўйхат!$C:$C,$B114,Рўйхат!AA:AA) | AA114: =+SUMIF(Рўйхат!$C:$C,$B114,Рўйхат!AB:AB) | AB114: =+SUMIF(Рўйхат!$C:$C,$B114,Рўйхат!AC:AC) | AC114: =+SUMIF(Рўйхат!$C:$C,$B114,Рўйхат!AD:AD) | AD114: =+SUMIF(Рўйхат!$C:$C,$B114,Рўйхат!AE:AE) | AE114: =+SUMIF(Рўйхат!$C:$C,$B114,Рўйхат!AF:AF) | AF114: =+SUMIF(Рўйхат!$C:$C,$B114,Рўйхат!AG:AG) | AG114: =+SUMIF(Рўйхат!$C:$C,$B114,Рўйхат!AH:AH) | AH114: =+SUMIF(Рўйхат!$C:$C,$B114,Рўйхат!AI:AI) | AI114: =+SUMIF(Рўйхат!$C:$C,$B114,Рўйхат!AJ:AJ)
A115: =+A114+1 | B115: “Issiqlikta’minoti” АЖ | C115: =IF(IFERROR(VLOOKUP(B115,Рўйхат!C:E,2,0),"")="[NULL]","",IFERROR(VLOOKUP(B115,Рўйхат!C:E,2,0),"")) | E115: =+SUMIF(Рўйхат!$C:$C,$B115,Рўйхат!G:G) | F115: =+SUMIF(Рўйхат!$C:$C,$B115,Рўйхат!H:H) | G115: =M115 | H115: =R115+W115+AB115+AG115 | I115: =+SUMIF(Рўйхат!$C:$C,$B115,Рўйхат!J:J) | J115: =+SUMIF(Рўйхат!$C:$C,$B115,Рўйхат!K:K) | K115: =+SUMIF(Рўйхат!$C:$C,$B115,Рўйхат!L:L) | L115: =+SUMIF(Рўйхат!$C:$C,$B115,Рўйхат!M:M) | M115: =+SUMIF(Рўйхат!$C:$C,$B115,Рўйхат!N:N) | N115: =+SUMIF(Рўйхат!$C:$C,$B115,Рўйхат!O:O) | O115: =+SUMIF(Рўйхат!$C:$C,$B115,Рўйхат!P:P) | P115: =+SUMIF(Рўйхат!$C:$C,$B115,Рўйхат!Q:Q) | Q115: =+SUMIF(Рўйхат!$C:$C,$B115,Рўйхат!R:R) | R115: =+SUMIF(Рўйхат!$C:$C,$B115,Рўйхат!S:S) | S115: =+SUMIF(Рўйхат!$C:$C,$B115,Рўйхат!T:T) | T115: =+SUMIF(Рўйхат!$C:$C,$B115,Рўйхат!U:U) | U115: =+SUMIF(Рўйхат!$C:$C,$B115,Рўйхат!V:V) | V115: =+SUMIF(Рўйхат!$C:$C,$B115,Рўйхат!W:W) | W115: =+SUMIF(Рўйхат!$C:$C,$B115,Рўйхат!X:X) | X115: =+SUMIF(Рўйхат!$C:$C,$B115,Рўйхат!Y:Y) | Y115: =+SUMIF(Рўйхат!$C:$C,$B115,Рўйхат!Z:Z) | Z115: =+SUMIF(Рўйхат!$C:$C,$B115,Рўйхат!AA:AA) | AA115: =+SUMIF(Рўйхат!$C:$C,$B115,Рўйхат!AB:AB) | AB115: =+SUMIF(Рўйхат!$C:$C,$B115,Рўйхат!AC:AC) | AC115: =+SUMIF(Рўйхат!$C:$C,$B115,Рўйхат!AD:AD) | AD115: =+SUMIF(Рўйхат!$C:$C,$B115,Рўйхат!AE:AE) | AE115: =+SUMIF(Рўйхат!$C:$C,$B115,Рўйхат!AF:AF) | AF115: =+SUMIF(Рўйхат!$C:$C,$B115,Рўйхат!AG:AG) | AG115: =+SUMIF(Рўйхат!$C:$C,$B115,Рўйхат!AH:AH) | AH115: =+SUMIF(Рўйхат!$C:$C,$B115,Рўйхат!AI:AI) | AI115: =+SUMIF(Рўйхат!$C:$C,$B115,Рўйхат!AJ:AJ)
A116: =+A115+1 | B116: “Навоийазот” АЖ | C116: =IF(IFERROR(VLOOKUP(B116,Рўйхат!C:E,2,0),"")="[NULL]","",IFERROR(VLOOKUP(B116,Рўйхат!C:E,2,0),"")) | E116: =+SUMIF(Рўйхат!$C:$C,$B116,Рўйхат!G:G) | F116: =+SUMIF(Рўйхат!$C:$C,$B116,Рўйхат!H:H) | G116: =M116 | H116: =R116+W116+AB116+AG116 | I116: =+SUMIF(Рўйхат!$C:$C,$B116,Рўйхат!J:J) | J116: =+SUMIF(Рўйхат!$C:$C,$B116,Рўйхат!K:K) | K116: =+SUMIF(Рўйхат!$C:$C,$B116,Рўйхат!L:L) | L116: =+SUMIF(Рўйхат!$C:$C,$B116,Рўйхат!M:M) | M116: =+SUMIF(Рўйхат!$C:$C,$B116,Рўйхат!N:N) | N116: =+SUMIF(Рўйхат!$C:$C,$B116,Рўйхат!O:O) | O116: =+SUMIF(Рўйхат!$C:$C,$B116,Рўйхат!P:P) | P116: =+SUMIF(Рўйхат!$C:$C,$B116,Рўйхат!Q:Q) | Q116: =+SUMIF(Рўйхат!$C:$C,$B116,Рўйхат!R:R) | R116: =+SUMIF(Рўйхат!$C:$C,$B116,Рўйхат!S:S) | S116: =+SUMIF(Рўйхат!$C:$C,$B116,Рўйхат!T:T) | T116: =+SUMIF(Рўйхат!$C:$C,$B116,Рўйхат!U:U) | U116: =+SUMIF(Рўйхат!$C:$C,$B116,Рўйхат!V:V) | V116: =+SUMIF(Рўйхат!$C:$C,$B116,Рўйхат!W:W) | W116: =+SUMIF(Рўйхат!$C:$C,$B116,Рўйхат!X:X) | X116: =+SUMIF(Рўйхат!$C:$C,$B116,Рўйхат!Y:Y) | Y116: =+SUMIF(Рўйхат!$C:$C,$B116,Рўйхат!Z:Z) | Z116: =+SUMIF(Рўйхат!$C:$C,$B116,Рўйхат!AA:AA) | AA116: =+SUMIF(Рўйхат!$C:$C,$B116,Рўйхат!AB:AB) | AB116: =+SUMIF(Рўйхат!$C:$C,$B116,Рўйхат!AC:AC) | AC116: =+SUMIF(Рўйхат!$C:$C,$B116,Рўйхат!AD:AD) | AD116: =+SUMIF(Рўйхат!$C:$C,$B116,Рўйхат!AE:AE) | AE116: =+SUMIF(Рўйхат!$C:$C,$B116,Рўйхат!AF:AF) | AF116: =+SUMIF(Рўйхат!$C:$C,$B116,Рўйхат!AG:AG) | AG116: =+SUMIF(Рўйхат!$C:$C,$B116,Рўйхат!AH:AH) | AH116: =+SUMIF(Рўйхат!$C:$C,$B116,Рўйхат!AI:AI) | AI116: =+SUMIF(Рўйхат!$C:$C,$B116,Рўйхат!AJ:AJ)
A117: =+A116+1 | B117: Ўзагролизинг АЖ | C117: =IF(IFERROR(VLOOKUP(B117,Рўйхат!C:E,2,0),"")="[NULL]","",IFERROR(VLOOKUP(B117,Рўйхат!C:E,2,0),"")) | E117: =+SUMIF(Рўйхат!$C:$C,$B117,Рўйхат!G:G) | F117: =+SUMIF(Рўйхат!$C:$C,$B117,Рўйхат!H:H) | G117: =M117 | H117: =R117+W117+AB117+AG117 | I117: =+SUMIF(Рўйхат!$C:$C,$B117,Рўйхат!J:J) | J117: =+SUMIF(Рўйхат!$C:$C,$B117,Рўйхат!K:K) | K117: =+SUMIF(Рўйхат!$C:$C,$B117,Рўйхат!L:L) | L117: =+SUMIF(Рўйхат!$C:$C,$B117,Рўйхат!M:M) | M117: =+SUMIF(Рўйхат!$C:$C,$B117,Рўйхат!N:N) | N117: =+SUMIF(Рўйхат!$C:$C,$B117,Рўйхат!O:O) | O117: =+SUMIF(Рўйхат!$C:$C,$B117,Рўйхат!P:P) | P117: =+SUMIF(Рўйхат!$C:$C,$B117,Рўйхат!Q:Q) | Q117: =+SUMIF(Рўйхат!$C:$C,$B117,Рўйхат!R:R) | R117: =+SUMIF(Рўйхат!$C:$C,$B117,Рўйхат!S:S) | S117: =+SUMIF(Рўйхат!$C:$C,$B117,Рўйхат!T:T) | T117: =+SUMIF(Рўйхат!$C:$C,$B117,Рўйхат!U:U) | U117: =+SUMIF(Рўйхат!$C:$C,$B117,Рўйхат!V:V) | V117: =+SUMIF(Рўйхат!$C:$C,$B117,Рўйхат!W:W) | W117: =+SUMIF(Рўйхат!$C:$C,$B117,Рўйхат!X:X) | X117: =+SUMIF(Рўйхат!$C:$C,$B117,Рўйхат!Y:Y) | Y117: =+SUMIF(Рўйхат!$C:$C,$B117,Рўйхат!Z:Z) | Z117: =+SUMIF(Рўйхат!$C:$C,$B117,Рўйхат!AA:AA) | AA117: =+SUMIF(Рўйхат!$C:$C,$B117,Рўйхат!AB:AB) | AB117: =+SUMIF(Рўйхат!$C:$C,$B117,Рўйхат!AC:AC) | AC117: =+SUMIF(Рўйхат!$C:$C,$B117,Рўйхат!AD:AD) | AD117: =+SUMIF(Рўйхат!$C:$C,$B117,Рўйхат!AE:AE) | AE117: =+SUMIF(Рўйхат!$C:$C,$B117,Рўйхат!AF:AF) | AF117: =+SUMIF(Рўйхат!$C:$C,$B117,Рўйхат!AG:AG) | AG117: =+SUMIF(Рўйхат!$C:$C,$B117,Рўйхат!AH:AH) | AH117: =+SUMIF(Рўйхат!$C:$C,$B117,Рўйхат!AI:AI) | AI117: =+SUMIF(Рўйхат!$C:$C,$B117,Рўйхат!AJ:AJ)
A118: =+A117+1 | B118: ЎЗБEКИСТОН РEСПУБЛИКА ВАЛЮТА БИРЖАСИ АЖ | C118: =IF(IFERROR(VLOOKUP(B118,Рўйхат!C:E,2,0),"")="[NULL]","",IFERROR(VLOOKUP(B118,Рўйхат!C:E,2,0),"")) | E118: =+SUMIF(Рўйхат!$C:$C,$B118,Рўйхат!G:G) | F118: =+SUMIF(Рўйхат!$C:$C,$B118,Рўйхат!H:H) | G118: =M118 | H118: =R118+W118+AB118+AG118 | I118: =+SUMIF(Рўйхат!$C:$C,$B118,Рўйхат!J:J) | J118: =+SUMIF(Рўйхат!$C:$C,$B118,Рўйхат!K:K) | K118: =+SUMIF(Рўйхат!$C:$C,$B118,Рўйхат!L:L) | L118: =+SUMIF(Рўйхат!$C:$C,$B118,Рўйхат!M:M) | M118: =+SUMIF(Рўйхат!$C:$C,$B118,Рўйхат!N:N) | N118: =+SUMIF(Рўйхат!$C:$C,$B118,Рўйхат!O:O) | O118: =+SUMIF(Рўйхат!$C:$C,$B118,Рўйхат!P:P) | P118: =+SUMIF(Рўйхат!$C:$C,$B118,Рўйхат!Q:Q) | Q118: =+SUMIF(Рўйхат!$C:$C,$B118,Рўйхат!R:R) | R118: =+SUMIF(Рўйхат!$C:$C,$B118,Рўйхат!S:S) | S118: =+SUMIF(Рўйхат!$C:$C,$B118,Рўйхат!T:T) | T118: =+SUMIF(Рўйхат!$C:$C,$B118,Рўйхат!U:U) | U118: =+SUMIF(Рўйхат!$C:$C,$B118,Рўйхат!V:V) | V118: =+SUMIF(Рўйхат!$C:$C,$B118,Рўйхат!W:W) | W118: =+SUMIF(Рўйхат!$C:$C,$B118,Рўйхат!X:X) | X118: =+SUMIF(Рўйхат!$C:$C,$B118,Рўйхат!Y:Y) | Y118: =+SUMIF(Рўйхат!$C:$C,$B118,Рўйхат!Z:Z) | Z118: =+SUMIF(Рўйхат!$C:$C,$B118,Рўйхат!AA:AA) | AA118: =+SUMIF(Рўйхат!$C:$C,$B118,Рўйхат!AB:AB) | AB118: =+SUMIF(Рўйхат!$C:$C,$B118,Рўйхат!AC:AC) | AC118: =+SUMIF(Рўйхат!$C:$C,$B118,Рўйхат!AD:AD) | AD118: =+SUMIF(Рўйхат!$C:$C,$B118,Рўйхат!AE:AE) | AE118: =+SUMIF(Рўйхат!$C:$C,$B118,Рўйхат!AF:AF) | AF118: =+SUMIF(Рўйхат!$C:$C,$B118,Рўйхат!AG:AG) | AG118: =+SUMIF(Рўйхат!$C:$C,$B118,Рўйхат!AH:AH) | AH118: =+SUMIF(Рўйхат!$C:$C,$B118,Рўйхат!AI:AI) | AI118: =+SUMIF(Рўйхат!$C:$C,$B118,Рўйхат!AJ:AJ)
A119: =+A118+1 | B119: ЎЗАГРОСЕРВИС АЖ | C119: =IF(IFERROR(VLOOKUP(B119,Рўйхат!C:E,2,0),"")="[NULL]","",IFERROR(VLOOKUP(B119,Рўйхат!C:E,2,0),"")) | E119: =+SUMIF(Рўйхат!$C:$C,$B119,Рўйхат!G:G) | F119: =+SUMIF(Рўйхат!$C:$C,$B119,Рўйхат!H:H) | G119: =M119 | H119: =R119+W119+AB119+AG119 | I119: =+SUMIF(Рўйхат!$C:$C,$B119,Рўйхат!J:J) | J119: =+SUMIF(Рўйхат!$C:$C,$B119,Рўйхат!K:K) | K119: =+SUMIF(Рўйхат!$C:$C,$B119,Рўйхат!L:L) | L119: =+SUMIF(Рўйхат!$C:$C,$B119,Рўйхат!M:M) | M119: =+SUMIF(Рўйхат!$C:$C,$B119,Рўйхат!N:N) | N119: =+SUMIF(Рўйхат!$C:$C,$B119,Рўйхат!O:O) | O119: =+SUMIF(Рўйхат!$C:$C,$B119,Рўйхат!P:P) | P119: =+SUMIF(Рўйхат!$C:$C,$B119,Рўйхат!Q:Q) | Q119: =+SUMIF(Рўйхат!$C:$C,$B119,Рўйхат!R:R) | R119: =+SUMIF(Рўйхат!$C:$C,$B119,Рўйхат!S:S) | S119: =+SUMIF(Рўйхат!$C:$C,$B119,Рўйхат!T:T) | T119: =+SUMIF(Рўйхат!$C:$C,$B119,Рўйхат!U:U) | U119: =+SUMIF(Рўйхат!$C:$C,$B119,Рўйхат!V:V) | V119: =+SUMIF(Рўйхат!$C:$C,$B119,Рўйхат!W:W) | W119: =+SUMIF(Рўйхат!$C:$C,$B119,Рўйхат!X:X) | X119: =+SUMIF(Рўйхат!$C:$C,$B119,Рўйхат!Y:Y) | Y119: =+SUMIF(Рўйхат!$C:$C,$B119,Рўйхат!Z:Z) | Z119: =+SUMIF(Рўйхат!$C:$C,$B119,Рўйхат!AA:AA) | AA119: =+SUMIF(Рўйхат!$C:$C,$B119,Рўйхат!AB:AB) | AB119: =+SUMIF(Рўйхат!$C:$C,$B119,Рўйхат!AC:AC) | AC119: =+SUMIF(Рўйхат!$C:$C,$B119,Рўйхат!AD:AD) | AD119: =+SUMIF(Рўйхат!$C:$C,$B119,Рўйхат!AE:AE) | AE119: =+SUMIF(Рўйхат!$C:$C,$B119,Рўйхат!AF:AF) | AF119: =+SUMIF(Рўйхат!$C:$C,$B119,Рўйхат!AG:AG) | AG119: =+SUMIF(Рўйхат!$C:$C,$B119,Рўйхат!AH:AH) | AH119: =+SUMIF(Рўйхат!$C:$C,$B119,Рўйхат!AI:AI) | AI119: =+SUMIF(Рўйхат!$C:$C,$B119,Рўйхат!AJ:AJ)
A120: =+A119+1 | B120: Электрон онлайн-аукционларни ташкил этиш АЖ | C120: =IF(IFERROR(VLOOKUP(B120,Рўйхат!C:E,2,0),"")="[NULL]","",IFERROR(VLOOKUP(B120,Рўйхат!C:E,2,0),"")) | E120: =+SUMIF(Рўйхат!$C:$C,$B120,Рўйхат!G:G) | F120: =+SUMIF(Рўйхат!$C:$C,$B120,Рўйхат!H:H) | G120: =M120 | H120: =R120+W120+AB120+AG120 | I120: =+SUMIF(Рўйхат!$C:$C,$B120,Рўйхат!J:J) | J120: =+SUMIF(Рўйхат!$C:$C,$B120,Рўйхат!K:K) | K120: =+SUMIF(Рўйхат!$C:$C,$B120,Рўйхат!L:L) | L120: =+SUMIF(Рўйхат!$C:$C,$B120,Рўйхат!M:M) | M120: =+SUMIF(Рўйхат!$C:$C,$B120,Рўйхат!N:N) | N120: =+SUMIF(Рўйхат!$C:$C,$B120,Рўйхат!O:O) | O120: =+SUMIF(Рўйхат!$C:$C,$B120,Рўйхат!P:P) | P120: =+SUMIF(Рўйхат!$C:$C,$B120,Рўйхат!Q:Q) | Q120: =+SUMIF(Рўйхат!$C:$C,$B120,Рўйхат!R:R) | R120: =+SUMIF(Рўйхат!$C:$C,$B120,Рўйхат!S:S) | S120: =+SUMIF(Рўйхат!$C:$C,$B120,Рўйхат!T:T) | T120: =+SUMIF(Рўйхат!$C:$C,$B120,Рўйхат!U:U) | U120: =+SUMIF(Рўйхат!$C:$C,$B120,Рўйхат!V:V) | V120: =+SUMIF(Рўйхат!$C:$C,$B120,Рўйхат!W:W) | W120: =+SUMIF(Рўйхат!$C:$C,$B120,Рўйхат!X:X) | X120: =+SUMIF(Рўйхат!$C:$C,$B120,Рўйхат!Y:Y) | Y120: =+SUMIF(Рўйхат!$C:$C,$B120,Рўйхат!Z:Z) | Z120: =+SUMIF(Рўйхат!$C:$C,$B120,Рўйхат!AA:AA) | AA120: =+SUMIF(Рўйхат!$C:$C,$B120,Рўйхат!AB:AB) | AB120: =+SUMIF(Рўйхат!$C:$C,$B120,Рўйхат!AC:AC) | AC120: =+SUMIF(Рўйхат!$C:$C,$B120,Рўйхат!AD:AD) | AD120: =+SUMIF(Рўйхат!$C:$C,$B120,Рўйхат!AE:AE) | AE120: =+SUMIF(Рўйхат!$C:$C,$B120,Рўйхат!AF:AF) | AF120: =+SUMIF(Рўйхат!$C:$C,$B120,Рўйхат!AG:AG) | AG120: =+SUMIF(Рўйхат!$C:$C,$B120,Рўйхат!AH:AH) | AH120: =+SUMIF(Рўйхат!$C:$C,$B120,Рўйхат!AI:AI) | AI120: =+SUMIF(Рўйхат!$C:$C,$B120,Рўйхат!AJ:AJ)
A121: =+A120+1 | B121: Uzbekistan airports АЖ | C121: =IF(IFERROR(VLOOKUP(B121,Рўйхат!C:E,2,0),"")="[NULL]","",IFERROR(VLOOKUP(B121,Рўйхат!C:E,2,0),"")) | E121: =+SUMIF(Рўйхат!$C:$C,$B121,Рўйхат!G:G) | F121: =+SUMIF(Рўйхат!$C:$C,$B121,Рўйхат!H:H) | G121: =M121 | H121: =R121+W121+AB121+AG121 | I121: =+SUMIF(Рўйхат!$C:$C,$B121,Рўйхат!J:J) | J121: =+SUMIF(Рўйхат!$C:$C,$B121,Рўйхат!K:K) | K121: =+SUMIF(Рўйхат!$C:$C,$B121,Рўйхат!L:L) | L121: =+SUMIF(Рўйхат!$C:$C,$B121,Рўйхат!M:M) | M121: =+SUMIF(Рўйхат!$C:$C,$B121,Рўйхат!N:N) | N121: =+SUMIF(Рўйхат!$C:$C,$B121,Рўйхат!O:O) | O121: =+SUMIF(Рўйхат!$C:$C,$B121,Рўйхат!P:P) | P121: =+SUMIF(Рўйхат!$C:$C,$B121,Рўйхат!Q:Q) | Q121: =+SUMIF(Рўйхат!$C:$C,$B121,Рўйхат!R:R) | R121: =+SUMIF(Рўйхат!$C:$C,$B121,Рўйхат!S:S) | S121: =+SUMIF(Рўйхат!$C:$C,$B121,Рўйхат!T:T) | T121: =+SUMIF(Рўйхат!$C:$C,$B121,Рўйхат!U:U) | U121: =+SUMIF(Рўйхат!$C:$C,$B121,Рўйхат!V:V) | V121: =+SUMIF(Рўйхат!$C:$C,$B121,Рўйхат!W:W) | W121: =+SUMIF(Рўйхат!$C:$C,$B121,Рўйхат!X:X) | X121: =+SUMIF(Рўйхат!$C:$C,$B121,Рўйхат!Y:Y) | Y121: =+SUMIF(Рўйхат!$C:$C,$B121,Рўйхат!Z:Z) | Z121: =+SUMIF(Рўйхат!$C:$C,$B121,Рўйхат!AA:AA) | AA121: =+SUMIF(Рўйхат!$C:$C,$B121,Рўйхат!AB:AB) | AB121: =+SUMIF(Рўйхат!$C:$C,$B121,Рўйхат!AC:AC) | AC121: =+SUMIF(Рўйхат!$C:$C,$B121,Рўйхат!AD:AD) | AD121: =+SUMIF(Рўйхат!$C:$C,$B121,Рўйхат!AE:AE) | AE121: =+SUMIF(Рўйхат!$C:$C,$B121,Рўйхат!AF:AF) | AF121: =+SUMIF(Рўйхат!$C:$C,$B121,Рўйхат!AG:AG) | AG121: =+SUMIF(Рўйхат!$C:$C,$B121,Рўйхат!AH:AH) | AH121: =+SUMIF(Рўйхат!$C:$C,$B121,Рўйхат!AI:AI) | AI121: =+SUMIF(Рўйхат!$C:$C,$B121,Рўйхат!AJ:AJ)
A122: =+A121+1 | B122: O`ZBEKISTON RESPUBLIKASI OLIY MAJLISI QONUNCHILIK PALATASINING DEVONI | C122: =IF(IFERROR(VLOOKUP(B122,Рўйхат!C:E,2,0),"")="[NULL]","",IFERROR(VLOOKUP(B122,Рўйхат!C:E,2,0),"")) | E122: =+SUMIF(Рўйхат!$C:$C,$B122,Рўйхат!G:G) | F122: =+SUMIF(Рўйхат!$C:$C,$B122,Рўйхат!H:H) | G122: =M122 | H122: =R122+W122+AB122+AG122 | I122: =+SUMIF(Рўйхат!$C:$C,$B122,Рўйхат!J:J) | J122: =+SUMIF(Рўйхат!$C:$C,$B122,Рўйхат!K:K) | K122: =+SUMIF(Рўйхат!$C:$C,$B122,Рўйхат!L:L) | L122: =+SUMIF(Рўйхат!$C:$C,$B122,Рўйхат!M:M) | M122: =+SUMIF(Рўйхат!$C:$C,$B122,Рўйхат!N:N) | N122: =+SUMIF(Рўйхат!$C:$C,$B122,Рўйхат!O:O) | O122: =+SUMIF(Рўйхат!$C:$C,$B122,Рўйхат!P:P) | P122: =+SUMIF(Рўйхат!$C:$C,$B122,Рўйхат!Q:Q) | Q122: =+SUMIF(Рўйхат!$C:$C,$B122,Рўйхат!R:R) | R122: =+SUMIF(Рўйхат!$C:$C,$B122,Рўйхат!S:S) | S122: =+SUMIF(Рўйхат!$C:$C,$B122,Рўйхат!T:T) | T122: =+SUMIF(Рўйхат!$C:$C,$B122,Рўйхат!U:U) | U122: =+SUMIF(Рўйхат!$C:$C,$B122,Рўйхат!V:V) | V122: =+SUMIF(Рўйхат!$C:$C,$B122,Рўйхат!W:W) | W122: =+SUMIF(Рўйхат!$C:$C,$B122,Рўйхат!X:X) | X122: =+SUMIF(Рўйхат!$C:$C,$B122,Рўйхат!Y:Y) | Y122: =+SUMIF(Рўйхат!$C:$C,$B122,Рўйхат!Z:Z) | Z122: =+SUMIF(Рўйхат!$C:$C,$B122,Рўйхат!AA:AA) | AA122: =+SUMIF(Рўйхат!$C:$C,$B122,Рўйхат!AB:AB) | AB122: =+SUMIF(Рўйхат!$C:$C,$B122,Рўйхат!AC:AC) | AC122: =+SUMIF(Рўйхат!$C:$C,$B122,Рўйхат!AD:AD) | AD122: =+SUMIF(Рўйхат!$C:$C,$B122,Рўйхат!AE:AE) | AE122: =+SUMIF(Рўйхат!$C:$C,$B122,Рўйхат!AF:AF) | AF122: =+SUMIF(Рўйхат!$C:$C,$B122,Рўйхат!AG:AG) | AG122: =+SUMIF(Рўйхат!$C:$C,$B122,Рўйхат!AH:AH) | AH122: =+SUMIF(Рўйхат!$C:$C,$B122,Рўйхат!AI:AI) | AI122: =+SUMIF(Рўйхат!$C:$C,$B122,Рўйхат!AJ:AJ)
A123: =+A122+1 | B123: Туризм қўмитаси | C123: =IF(IFERROR(VLOOKUP(B123,Рўйхат!C:E,2,0),"")="[NULL]","",IFERROR(VLOOKUP(B123,Рўйхат!C:E,2,0),"")) | E123: =+SUMIF(Рўйхат!$C:$C,$B123,Рўйхат!G:G) | F123: =+SUMIF(Рўйхат!$C:$C,$B123,Рўйхат!H:H) | G123: =M123 | H123: =R123+W123+AB123+AG123 | I123: =+SUMIF(Рўйхат!$C:$C,$B123,Рўйхат!J:J) | J123: =+SUMIF(Рўйхат!$C:$C,$B123,Рўйхат!K:K) | K123: =+SUMIF(Рўйхат!$C:$C,$B123,Рўйхат!L:L) | L123: =+SUMIF(Рўйхат!$C:$C,$B123,Рўйхат!M:M) | M123: =+SUMIF(Рўйхат!$C:$C,$B123,Рўйхат!N:N) | N123: =+SUMIF(Рўйхат!$C:$C,$B123,Рўйхат!O:O) | O123: =+SUMIF(Рўйхат!$C:$C,$B123,Рўйхат!P:P) | P123: =+SUMIF(Рўйхат!$C:$C,$B123,Рўйхат!Q:Q) | Q123: =+SUMIF(Рўйхат!$C:$C,$B123,Рўйхат!R:R) | R123: =+SUMIF(Рўйхат!$C:$C,$B123,Рўйхат!S:S) | S123: =+SUMIF(Рўйхат!$C:$C,$B123,Рўйхат!T:T) | T123: =+SUMIF(Рўйхат!$C:$C,$B123,Рўйхат!U:U) | U123: =+SUMIF(Рўйхат!$C:$C,$B123,Рўйхат!V:V) | V123: =+SUMIF(Рўйхат!$C:$C,$B123,Рўйхат!W:W) | W123: =+SUMIF(Рўйхат!$C:$C,$B123,Рўйхат!X:X) | X123: =+SUMIF(Рўйхат!$C:$C,$B123,Рўйхат!Y:Y) | Y123: =+SUMIF(Рўйхат!$C:$C,$B123,Рўйхат!Z:Z) | Z123: =+SUMIF(Рўйхат!$C:$C,$B123,Рўйхат!AA:AA) | AA123: =+SUMIF(Рўйхат!$C:$C,$B123,Рўйхат!AB:AB) | AB123: =+SUMIF(Рўйхат!$C:$C,$B123,Рўйхат!AC:AC) | AC123: =+SUMIF(Рўйхат!$C:$C,$B123,Рўйхат!AD:AD) | AD123: =+SUMIF(Рўйхат!$C:$C,$B123,Рўйхат!AE:AE) | AE123: =+SUMIF(Рўйхат!$C:$C,$B123,Рўйхат!AF:AF) | AF123: =+SUMIF(Рўйхат!$C:$C,$B123,Рўйхат!AG:AG) | AG123: =+SUMIF(Рўйхат!$C:$C,$B123,Рўйхат!AH:AH) | AH123: =+SUMIF(Рўйхат!$C:$C,$B123,Рўйхат!AI:AI) | AI123: =+SUMIF(Рўйхат!$C:$C,$B123,Рўйхат!AJ:AJ)
A124: =+A123+1 | B124: Ўзбекистон Республикаси Фанлар академияси ишлар бошқармаси | C124: =IF(IFERROR(VLOOKUP(B124,Рўйхат!C:E,2,0),"")="[NULL]","",IFERROR(VLOOKUP(B124,Рўйхат!C:E,2,0),"")) | E124: =+SUMIF(Рўйхат!$C:$C,$B124,Рўйхат!G:G) | F124: =+SUMIF(Рўйхат!$C:$C,$B124,Рўйхат!H:H) | G124: =M124 | H124: =R124+W124+AB124+AG124 | I124: =+SUMIF(Рўйхат!$C:$C,$B124,Рўйхат!J:J) | J124: =+SUMIF(Рўйхат!$C:$C,$B124,Рўйхат!K:K) | K124: =+SUMIF(Рўйхат!$C:$C,$B124,Рўйхат!L:L) | L124: =+SUMIF(Рўйхат!$C:$C,$B124,Рўйхат!M:M) | M124: =+SUMIF(Рўйхат!$C:$C,$B124,Рўйхат!N:N) | N124: =+SUMIF(Рўйхат!$C:$C,$B124,Рўйхат!O:O) | O124: =+SUMIF(Рўйхат!$C:$C,$B124,Рўйхат!P:P) | P124: =+SUMIF(Рўйхат!$C:$C,$B124,Рўйхат!Q:Q) | Q124: =+SUMIF(Рўйхат!$C:$C,$B124,Рўйхат!R:R) | R124: =+SUMIF(Рўйхат!$C:$C,$B124,Рўйхат!S:S) | S124: =+SUMIF(Рўйхат!$C:$C,$B124,Рўйхат!T:T) | T124: =+SUMIF(Рўйхат!$C:$C,$B124,Рўйхат!U:U) | U124: =+SUMIF(Рўйхат!$C:$C,$B124,Рўйхат!V:V) | V124: =+SUMIF(Рўйхат!$C:$C,$B124,Рўйхат!W:W) | W124: =+SUMIF(Рўйхат!$C:$C,$B124,Рўйхат!X:X) | X124: =+SUMIF(Рўйхат!$C:$C,$B124,Рўйхат!Y:Y) | Y124: =+SUMIF(Рўйхат!$C:$C,$B124,Рўйхат!Z:Z) | Z124: =+SUMIF(Рўйхат!$C:$C,$B124,Рўйхат!AA:AA) | AA124: =+SUMIF(Рўйхат!$C:$C,$B124,Рўйхат!AB:AB) | AB124: =+SUMIF(Рўйхат!$C:$C,$B124,Рўйхат!AC:AC) | AC124: =+SUMIF(Рўйхат!$C:$C,$B124,Рўйхат!AD:AD) | AD124: =+SUMIF(Рўйхат!$C:$C,$B124,Рўйхат!AE:AE) | AE124: =+SUMIF(Рўйхат!$C:$C,$B124,Рўйхат!AF:AF) | AF124: =+SUMIF(Рўйхат!$C:$C,$B124,Рўйхат!AG:AG) | AG124: =+SUMIF(Рўйхат!$C:$C,$B124,Рўйхат!AH:AH) | AH124: =+SUMIF(Рўйхат!$C:$C,$B124,Рўйхат!AI:AI) | AI124: =+SUMIF(Рўйхат!$C:$C,$B124,Рўйхат!AJ:AJ)
A125: 120 | B125: “Юнеско ишлари бўйича” Ўзбекистон Республикаси миллий коммисияси | C125: =IF(IFERROR(VLOOKUP(B125,Рўйхат!C:E,2,0),"")="[NULL]","",IFERROR(VLOOKUP(B125,Рўйхат!C:E,2,0),"")) | E125: =+SUMIF(Рўйхат!$C:$C,$B125,Рўйхат!G:G) | F125: =+SUMIF(Рўйхат!$C:$C,$B125,Рўйхат!H:H) | G125: =M125 | H125: =R125+W125+AB125+AG125 | I125: =+SUMIF(Рўйхат!$C:$C,$B125,Рўйхат!J:J) | J125: =+SUMIF(Рўйхат!$C:$C,$B125,Рўйхат!K:K) | K125: =+SUMIF(Рўйхат!$C:$C,$B125,Рўйхат!L:L) | L125: =+SUMIF(Рўйхат!$C:$C,$B125,Рўйхат!M:M) | M125: =+SUMIF(Рўйхат!$C:$C,$B125,Рўйхат!N:N) | N125: =+SUMIF(Рўйхат!$C:$C,$B125,Рўйхат!O:O) | O125: =+SUMIF(Рўйхат!$C:$C,$B125,Рўйхат!P:P) | P125: =+SUMIF(Рўйхат!$C:$C,$B125,Рўйхат!Q:Q) | Q125: =+SUMIF(Рўйхат!$C:$C,$B125,Рўйхат!R:R) | R125: =+SUMIF(Рўйхат!$C:$C,$B125,Рўйхат!S:S) | S125: =+SUMIF(Рўйхат!$C:$C,$B125,Рўйхат!T:T) | T125: =+SUMIF(Рўйхат!$C:$C,$B125,Рўйхат!U:U) | U125: =+SUMIF(Рўйхат!$C:$C,$B125,Рўйхат!V:V) | V125: =+SUMIF(Рўйхат!$C:$C,$B125,Рўйхат!W:W) | W125: =+SUMIF(Рўйхат!$C:$C,$B125,Рўйхат!X:X) | X125: =+SUMIF(Рўйхат!$C:$C,$B125,Рўйхат!Y:Y) | Y125: =+SUMIF(Рўйхат!$C:$C,$B125,Рўйхат!Z:Z) | Z125: =+SUMIF(Рўйхат!$C:$C,$B125,Рўйхат!AA:AA) | AA125: =+SUMIF(Рўйхат!$C:$C,$B125,Рўйхат!AB:AB) | AB125: =+SUMIF(Рўйхат!$C:$C,$B125,Рўйхат!AC:AC) | AC125: =+SUMIF(Рўйхат!$C:$C,$B125,Рўйхат!AD:AD) | AD125: =+SUMIF(Рўйхат!$C:$C,$B125,Рўйхат!AE:AE) | AE125: =+SUMIF(Рўйхат!$C:$C,$B125,Рўйхат!AF:AF) | AF125: =+SUMIF(Рўйхат!$C:$C,$B125,Рўйхат!AG:AG) | AG125: =+SUMIF(Рўйхат!$C:$C,$B125,Рўйхат!AH:AH) | AH125: =+SUMIF(Рўйхат!$C:$C,$B125,Рўйхат!AI:AI) | AI125: =+SUMIF(Рўйхат!$C:$C,$B125,Рўйхат!AJ:AJ)
A126: 121 | B126: Енгил саноатни ривожлантириш агентлиги | C126: =IF(IFERROR(VLOOKUP(B126,Рўйхат!C:E,2,0),"")="[NULL]","",IFERROR(VLOOKUP(B126,Рўйхат!C:E,2,0),"")) | E126: =+SUMIF(Рўйхат!$C:$C,$B126,Рўйхат!G:G) | F126: =+SUMIF(Рўйхат!$C:$C,$B126,Рўйхат!H:H) | G126: =M126 | H126: =R126+W126+AB126+AG126 | I126: =+SUMIF(Рўйхат!$C:$C,$B126,Рўйхат!J:J) | J126: =+SUMIF(Рўйхат!$C:$C,$B126,Рўйхат!K:K) | K126: =+SUMIF(Рўйхат!$C:$C,$B126,Рўйхат!L:L) | L126: =+SUMIF(Рўйхат!$C:$C,$B126,Рўйхат!M:M) | M126: =+SUMIF(Рўйхат!$C:$C,$B126,Рўйхат!N:N) | N126: =+SUMIF(Рўйхат!$C:$C,$B126,Рўйхат!O:O) | O126: =+SUMIF(Рўйхат!$C:$C,$B126,Рўйхат!P:P) | P126: =+SUMIF(Рўйхат!$C:$C,$B126,Рўйхат!Q:Q) | Q126: =+SUMIF(Рўйхат!$C:$C,$B126,Рўйхат!R:R) | R126: =+SUMIF(Рўйхат!$C:$C,$B126,Рўйхат!S:S) | S126: =+SUMIF(Рўйхат!$C:$C,$B126,Рўйхат!T:T) | T126: =+SUMIF(Рўйхат!$C:$C,$B126,Рўйхат!U:U) | U126: =+SUMIF(Рўйхат!$C:$C,$B126,Рўйхат!V:V) | V126: =+SUMIF(Рўйхат!$C:$C,$B126,Рўйхат!W:W) | W126: =+SUMIF(Рўйхат!$C:$C,$B126,Рўйхат!X:X) | X126: =+SUMIF(Рўйхат!$C:$C,$B126,Рўйхат!Y:Y) | Y126: =+SUMIF(Рўйхат!$C:$C,$B126,Рўйхат!Z:Z) | Z126: =+SUMIF(Рўйхат!$C:$C,$B126,Рўйхат!AA:AA) | AA126: =+SUMIF(Рўйхат!$C:$C,$B126,Рўйхат!AB:AB) | AB126: =+SUMIF(Рўйхат!$C:$C,$B126,Рўйхат!AC:AC) | AC126: =+SUMIF(Рўйхат!$C:$C,$B126,Рўйхат!AD:AD) | AD126: =+SUMIF(Рўйхат!$C:$C,$B126,Рўйхат!AE:AE) | AE126: =+SUMIF(Рўйхат!$C:$C,$B126,Рўйхат!AF:AF) | AF126: =+SUMIF(Рўйхат!$C:$C,$B126,Рўйхат!AG:AG) | AG126: =+SUMIF(Рўйхат!$C:$C,$B126,Рўйхат!AH:AH) | AH126: =+SUMIF(Рўйхат!$C:$C,$B126,Рўйхат!AI:AI) | AI126: =+SUMIF(Рўйхат!$C:$C,$B126,Рўйхат!AJ:AJ)
A127: 122 | B127: Ўзбекистон Республикаси Олий суди | C127: =IF(IFERROR(VLOOKUP(B127,Рўйхат!C:E,2,0),"")="[NULL]","",IFERROR(VLOOKUP(B127,Рўйхат!C:E,2,0),"")) | E127: =+SUMIF(Рўйхат!$C:$C,$B127,Рўйхат!G:G) | F127: =+SUMIF(Рўйхат!$C:$C,$B127,Рўйхат!H:H) | G127: =M127 | H127: =R127+W127+AB127+AG127 | I127: =+SUMIF(Рўйхат!$C:$C,$B127,Рўйхат!J:J) | J127: =+SUMIF(Рўйхат!$C:$C,$B127,Рўйхат!K:K) | K127: =+SUMIF(Рўйхат!$C:$C,$B127,Рўйхат!L:L) | L127: =+SUMIF(Рўйхат!$C:$C,$B127,Рўйхат!M:M) | M127: =+SUMIF(Рўйхат!$C:$C,$B127,Рўйхат!N:N) | N127: =+SUMIF(Рўйхат!$C:$C,$B127,Рўйхат!O:O) | O127: =+SUMIF(Рўйхат!$C:$C,$B127,Рўйхат!P:P) | P127: =+SUMIF(Рўйхат!$C:$C,$B127,Рўйхат!Q:Q) | Q127: =+SUMIF(Рўйхат!$C:$C,$B127,Рўйхат!R:R) | R127: =+SUMIF(Рўйхат!$C:$C,$B127,Рўйхат!S:S) | S127: =+SUMIF(Рўйхат!$C:$C,$B127,Рўйхат!T:T) | T127: =+SUMIF(Рўйхат!$C:$C,$B127,Рўйхат!U:U) | U127: =+SUMIF(Рўйхат!$C:$C,$B127,Рўйхат!V:V) | V127: =+SUMIF(Рўйхат!$C:$C,$B127,Рўйхат!W:W) | W127: =+SUMIF(Рўйхат!$C:$C,$B127,Рўйхат!X:X) | X127: =+SUMIF(Рўйхат!$C:$C,$B127,Рўйхат!Y:Y) | Y127: =+SUMIF(Рўйхат!$C:$C,$B127,Рўйхат!Z:Z) | Z127: =+SUMIF(Рўйхат!$C:$C,$B127,Рўйхат!AA:AA) | AA127: =+SUMIF(Рўйхат!$C:$C,$B127,Рўйхат!AB:AB) | AB127: =+SUMIF(Рўйхат!$C:$C,$B127,Рўйхат!AC:AC) | AC127: =+SUMIF(Рўйхат!$C:$C,$B127,Рўйхат!AD:AD) | AD127: =+SUMIF(Рўйхат!$C:$C,$B127,Рўйхат!AE:AE) | AE127: =+SUMIF(Рўйхат!$C:$C,$B127,Рўйхат!AF:AF) | AF127: =+SUMIF(Рўйхат!$C:$C,$B127,Рўйхат!AG:AG) | AG127: =+SUMIF(Рўйхат!$C:$C,$B127,Рўйхат!AH:AH) | AH127: =+SUMIF(Рўйхат!$C:$C,$B127,Рўйхат!AI:AI) | AI127: =+SUMIF(Рўйхат!$C:$C,$B127,Рўйхат!AJ:AJ)
A128: 123 | B128: Андижон биокимё заводи АЖ | C128: =IF(IFERROR(VLOOKUP(B128,Рўйхат!C:E,2,0),"")="[NULL]","",IFERROR(VLOOKUP(B128,Рўйхат!C:E,2,0),"")) | E128: =+SUMIF(Рўйхат!$C:$C,$B128,Рўйхат!G:G) | F128: =+SUMIF(Рўйхат!$C:$C,$B128,Рўйхат!H:H) | G128: =M128 | H128: =R128+W128+AB128+AG128 | I128: =+SUMIF(Рўйхат!$C:$C,$B128,Рўйхат!J:J) | J128: =+SUMIF(Рўйхат!$C:$C,$B128,Рўйхат!K:K) | K128: =+SUMIF(Рўйхат!$C:$C,$B128,Рўйхат!L:L) | L128: =+SUMIF(Рўйхат!$C:$C,$B128,Рўйхат!M:M) | M128: =+SUMIF(Рўйхат!$C:$C,$B128,Рўйхат!N:N) | N128: =+SUMIF(Рўйхат!$C:$C,$B128,Рўйхат!O:O) | O128: =+SUMIF(Рўйхат!$C:$C,$B128,Рўйхат!P:P) | P128: =+SUMIF(Рўйхат!$C:$C,$B128,Рўйхат!Q:Q) | Q128: =+SUMIF(Рўйхат!$C:$C,$B128,Рўйхат!R:R) | R128: =+SUMIF(Рўйхат!$C:$C,$B128,Рўйхат!S:S) | S128: =+SUMIF(Рўйхат!$C:$C,$B128,Рўйхат!T:T) | T128: =+SUMIF(Рўйхат!$C:$C,$B128,Рўйхат!U:U) | U128: =+SUMIF(Рўйхат!$C:$C,$B128,Рўйхат!V:V) | V128: =+SUMIF(Рўйхат!$C:$C,$B128,Рўйхат!W:W) | W128: =+SUMIF(Рўйхат!$C:$C,$B128,Рўйхат!X:X) | X128: =+SUMIF(Рўйхат!$C:$C,$B128,Рўйхат!Y:Y) | Y128: =+SUMIF(Рўйхат!$C:$C,$B128,Рўйхат!Z:Z) | Z128: =+SUMIF(Рўйхат!$C:$C,$B128,Рўйхат!AA:AA) | AA128: =+SUMIF(Рўйхат!$C:$C,$B128,Рўйхат!AB:AB) | AB128: =+SUMIF(Рўйхат!$C:$C,$B128,Рўйхат!AC:AC) | AC128: =+SUMIF(Рўйхат!$C:$C,$B128,Рўйхат!AD:AD) | AD128: =+SUMIF(Рўйхат!$C:$C,$B128,Рўйхат!AE:AE) | AE128: =+SUMIF(Рўйхат!$C:$C,$B128,Рўйхат!AF:AF) | AF128: =+SUMIF(Рўйхат!$C:$C,$B128,Рўйхат!AG:AG) | AG128: =+SUMIF(Рўйхат!$C:$C,$B128,Рўйхат!AH:AH) | AH128: =+SUMIF(Рўйхат!$C:$C,$B128,Рўйхат!AI:AI) | AI128: =+SUMIF(Рўйхат!$C:$C,$B128,Рўйхат!AJ:AJ)
A129: 124 | B129: Ўзбекистон Республикаси Ҳисоб Палатаси | C129: =IF(IFERROR(VLOOKUP(B129,Рўйхат!C:E,2,0),"")="[NULL]","",IFERROR(VLOOKUP(B129,Рўйхат!C:E,2,0),"")) | E129: =+SUMIF(Рўйхат!$C:$C,$B129,Рўйхат!G:G) | F129: =+SUMIF(Рўйхат!$C:$C,$B129,Рўйхат!H:H) | G129: =M129 | H129: =R129+W129+AB129+AG129 | I129: =+SUMIF(Рўйхат!$C:$C,$B129,Рўйхат!J:J) | J129: =+SUMIF(Рўйхат!$C:$C,$B129,Рўйхат!K:K) | K129: =+SUMIF(Рўйхат!$C:$C,$B129,Рўйхат!L:L) | L129: =+SUMIF(Рўйхат!$C:$C,$B129,Рўйхат!M:M) | M129: =+SUMIF(Рўйхат!$C:$C,$B129,Рўйхат!N:N) | N129: =+SUMIF(Рўйхат!$C:$C,$B129,Рўйхат!O:O) | O129: =+SUMIF(Рўйхат!$C:$C,$B129,Рўйхат!P:P) | P129: =+SUMIF(Рўйхат!$C:$C,$B129,Рўйхат!Q:Q) | Q129: =+SUMIF(Рўйхат!$C:$C,$B129,Рўйхат!R:R) | R129: =+SUMIF(Рўйхат!$C:$C,$B129,Рўйхат!S:S) | S129: =+SUMIF(Рўйхат!$C:$C,$B129,Рўйхат!T:T) | T129: =+SUMIF(Рўйхат!$C:$C,$B129,Рўйхат!U:U) | U129: =+SUMIF(Рўйхат!$C:$C,$B129,Рўйхат!V:V) | V129: =+SUMIF(Рўйхат!$C:$C,$B129,Рўйхат!W:W) | W129: =+SUMIF(Рўйхат!$C:$C,$B129,Рўйхат!X:X) | X129: =+SUMIF(Рўйхат!$C:$C,$B129,Рўйхат!Y:Y) | Y129: =+SUMIF(Рўйхат!$C:$C,$B129,Рўйхат!Z:Z) | Z129: =+SUMIF(Рўйхат!$C:$C,$B129,Рўйхат!AA:AA) | AA129: =+SUMIF(Рўйхат!$C:$C,$B129,Рўйхат!AB:AB) | AB129: =+SUMIF(Рўйхат!$C:$C,$B129,Рўйхат!AC:AC) | AC129: =+SUMIF(Рўйхат!$C:$C,$B129,Рўйхат!AD:AD) | AD129: =+SUMIF(Рўйхат!$C:$C,$B129,Рўйхат!AE:AE) | AE129: =+SUMIF(Рўйхат!$C:$C,$B129,Рўйхат!AF:AF) | AF129: =+SUMIF(Рўйхат!$C:$C,$B129,Рўйхат!AG:AG) | AG129: =+SUMIF(Рўйхат!$C:$C,$B129,Рўйхат!AH:AH) | AH129: =+SUMIF(Рўйхат!$C:$C,$B129,Рўйхат!AI:AI) | AI129: =+SUMIF(Рўйхат!$C:$C,$B129,Рўйхат!AJ:AJ)
A130: 125 | B130: UzGasTrade АЖ | C130: =IF(IFERROR(VLOOKUP(B130,Рўйхат!C:E,2,0),"")="[NULL]","",IFERROR(VLOOKUP(B130,Рўйхат!C:E,2,0),"")) | E130: =+SUMIF(Рўйхат!$C:$C,$B130,Рўйхат!G:G) | F130: =+SUMIF(Рўйхат!$C:$C,$B130,Рўйхат!H:H) | G130: =M130 | H130: =R130+W130+AB130+AG130 | I130: =+SUMIF(Рўйхат!$C:$C,$B130,Рўйхат!J:J) | J130: =+SUMIF(Рўйхат!$C:$C,$B130,Рўйхат!K:K) | K130: =+SUMIF(Рўйхат!$C:$C,$B130,Рўйхат!L:L) | L130: =+SUMIF(Рўйхат!$C:$C,$B130,Рўйхат!M:M) | M130: =+SUMIF(Рўйхат!$C:$C,$B130,Рўйхат!N:N) | N130: =+SUMIF(Рўйхат!$C:$C,$B130,Рўйхат!O:O) | O130: =+SUMIF(Рўйхат!$C:$C,$B130,Рўйхат!P:P) | P130: =+SUMIF(Рўйхат!$C:$C,$B130,Рўйхат!Q:Q) | Q130: =+SUMIF(Рўйхат!$C:$C,$B130,Рўйхат!R:R) | R130: =+SUMIF(Рўйхат!$C:$C,$B130,Рўйхат!S:S) | S130: =+SUMIF(Рўйхат!$C:$C,$B130,Рўйхат!T:T) | T130: =+SUMIF(Рўйхат!$C:$C,$B130,Рўйхат!U:U) | U130: =+SUMIF(Рўйхат!$C:$C,$B130,Рўйхат!V:V) | V130: =+SUMIF(Рўйхат!$C:$C,$B130,Рўйхат!W:W) | W130: =+SUMIF(Рўйхат!$C:$C,$B130,Рўйхат!X:X) | X130: =+SUMIF(Рўйхат!$C:$C,$B130,Рўйхат!Y:Y) | Y130: =+SUMIF(Рўйхат!$C:$C,$B130,Рўйхат!Z:Z) | Z130: =+SUMIF(Рўйхат!$C:$C,$B130,Рўйхат!AA:AA) | AA130: =+SUMIF(Рўйхат!$C:$C,$B130,Рўйхат!AB:AB) | AB130: =+SUMIF(Рўйхат!$C:$C,$B130,Рўйхат!AC:AC) | AC130: =+SUMIF(Рўйхат!$C:$C,$B130,Рўйхат!AD:AD) | AD130: =+SUMIF(Рўйхат!$C:$C,$B130,Рўйхат!AE:AE) | AE130: =+SUMIF(Рўйхат!$C:$C,$B130,Рўйхат!AF:AF) | AF130: =+SUMIF(Рўйхат!$C:$C,$B130,Рўйхат!AG:AG) | AG130: =+SUMIF(Рўйхат!$C:$C,$B130,Рўйхат!AH:AH) | AH130: =+SUMIF(Рўйхат!$C:$C,$B130,Рўйхат!AI:AI) | AI130: =+SUMIF(Рўйхат!$C:$C,$B130,Рўйхат!AJ:AJ)
A131: 126 | B131: “УзАссетс Инвестиция Компанияси” АЖ | C131: =IF(IFERROR(VLOOKUP(B131,Рўйхат!C:E,2,0),"")="[NULL]","",IFERROR(VLOOKUP(B131,Рўйхат!C:E,2,0),"")) | E131: =+SUMIF(Рўйхат!$C:$C,$B131,Рўйхат!G:G) | F131: =+SUMIF(Рўйхат!$C:$C,$B131,Рўйхат!H:H) | G131: =M131 | H131: =R131+W131+AB131+AG131 | I131: =+SUMIF(Рўйхат!$C:$C,$B131,Рўйхат!J:J) | J131: =+SUMIF(Рўйхат!$C:$C,$B131,Рўйхат!K:K) | K131: =+SUMIF(Рўйхат!$C:$C,$B131,Рўйхат!L:L) | L131: =+SUMIF(Рўйхат!$C:$C,$B131,Рўйхат!M:M) | M131: =+SUMIF(Рўйхат!$C:$C,$B131,Рўйхат!N:N) | N131: =+SUMIF(Рўйхат!$C:$C,$B131,Рўйхат!O:O) | O131: =+SUMIF(Рўйхат!$C:$C,$B131,Рўйхат!P:P) | P131: =+SUMIF(Рўйхат!$C:$C,$B131,Рўйхат!Q:Q) | Q131: =+SUMIF(Рўйхат!$C:$C,$B131,Рўйхат!R:R) | R131: =+SUMIF(Рўйхат!$C:$C,$B131,Рўйхат!S:S) | S131: =+SUMIF(Рўйхат!$C:$C,$B131,Рўйхат!T:T) | T131: =+SUMIF(Рўйхат!$C:$C,$B131,Рўйхат!U:U) | U131: =+SUMIF(Рўйхат!$C:$C,$B131,Рўйхат!V:V) | V131: =+SUMIF(Рўйхат!$C:$C,$B131,Рўйхат!W:W) | W131: =+SUMIF(Рўйхат!$C:$C,$B131,Рўйхат!X:X) | X131: =+SUMIF(Рўйхат!$C:$C,$B131,Рўйхат!Y:Y) | Y131: =+SUMIF(Рўйхат!$C:$C,$B131,Рўйхат!Z:Z) | Z131: =+SUMIF(Рўйхат!$C:$C,$B131,Рўйхат!AA:AA) | AA131: =+SUMIF(Рўйхат!$C:$C,$B131,Рўйхат!AB:AB) | AB131: =+SUMIF(Рўйхат!$C:$C,$B131,Рўйхат!AC:AC) | AC131: =+SUMIF(Рўйхат!$C:$C,$B131,Рўйхат!AD:AD) | AD131: =+SUMIF(Рўйхат!$C:$C,$B131,Рўйхат!AE:AE) | AE131: =+SUMIF(Рўйхат!$C:$C,$B131,Рўйхат!AF:AF) | AF131: =+SUMIF(Рўйхат!$C:$C,$B131,Рўйхат!AG:AG) | AG131: =+SUMIF(Рўйхат!$C:$C,$B131,Рўйхат!AH:AH) | AH131: =+SUMIF(Рўйхат!$C:$C,$B131,Рўйхат!AI:AI) | AI131: =+SUMIF(Рўйхат!$C:$C,$B131,Рўйхат!AJ:AJ)
A132: 127 | B132: Бошқалар | C132: =IF(IFERROR(VLOOKUP(B132,Рўйхат!C:E,2,0),"")="[NULL]","",IFERROR(VLOOKUP(B132,Рўйхат!C:E,2,0),"")) | D132: =IFERROR(VLOOKUP(B132,Рўйхат!C:E,3,0),"") | E132: =+SUMIF(Рўйхат!$C:$C,$B132,Рўйхат!G:G) | F132: =+SUMIF(Рўйхат!$C:$C,$B132,Рўйхат!H:H) | G132: =M132 | H132: =R132+W132+AB132+AG132 | I132: =+SUMIF(Рўйхат!$C:$C,$B132,Рўйхат!J:J) | J132: =+SUMIF(Рўйхат!$C:$C,$B132,Рўйхат!K:K) | K132: =+SUMIF(Рўйхат!$C:$C,$B132,Рўйхат!L:L) | L132: =+SUMIF(Рўйхат!$C:$C,$B132,Рўйхат!M:M) | M132: =+SUMIF(Рўйхат!$C:$C,$B132,Рўйхат!N:N) | N132: =+SUMIF(Рўйхат!$C:$C,$B132,Рўйхат!O:O) | O132: =+SUMIF(Рўйхат!$C:$C,$B132,Рўйхат!P:P) | P132: =+SUMIF(Рўйхат!$C:$C,$B132,Рўйхат!Q:Q) | Q132: =+SUMIF(Рўйхат!$C:$C,$B132,Рўйхат!R:R) | R132: =+SUMIF(Рўйхат!$C:$C,$B132,Рўйхат!S:S) | S132: =+SUMIF(Рўйхат!$C:$C,$B132,Рўйхат!T:T) | T132: =+SUMIF(Рўйхат!$C:$C,$B132,Рўйхат!U:U) | U132: =+SUMIF(Рўйхат!$C:$C,$B132,Рўйхат!V:V) | V132: =+SUMIF(Рўйхат!$C:$C,$B132,Рўйхат!W:W) | W132: =+SUMIF(Рўйхат!$C:$C,$B132,Рўйхат!X:X) | X132: =+SUMIF(Рўйхат!$C:$C,$B132,Рўйхат!Y:Y) | Y132: =+SUMIF(Рўйхат!$C:$C,$B132,Рўйхат!Z:Z) | Z132: =+SUMIF(Рўйхат!$C:$C,$B132,Рўйхат!AA:AA) | AA132: =+SUMIF(Рўйхат!$C:$C,$B132,Рўйхат!AB:AB) | AB132: =+SUMIF(Рўйхат!$C:$C,$B132,Рўйхат!AC:AC) | AC132: =+SUMIF(Рўйхат!$C:$C,$B132,Рўйхат!AD:AD) | AD132: =+SUMIF(Рўйхат!$C:$C,$B132,Рўйхат!AE:AE) | AE132: =+SUMIF(Рўйхат!$C:$C,$B132,Рўйхат!AF:AF) | AF132: =+SUMIF(Рўйхат!$C:$C,$B132,Рўйхат!AG:AG) | AG132: =+SUMIF(Рўйхат!$C:$C,$B132,Рўйхат!AH:AH) | AH132: =+SUMIF(Рўйхат!$C:$C,$B132,Рўйхат!AI:AI) | AI132: =+SUMIF(Рўйхат!$C:$C,$B132,Рўйхат!AJ:AJ)

Sheet Ходимлар кесимида
A1: "Масофавий аудит" ААТ томонидан аниқланган риск ҳолатларини назоратга олиш ҳамда уларни бартараф этилиши тўғрисида "Масофавий назорат" маркази ходимлари кесимида маълумот
A3: № | B3: Масъул ходим | C3: Жами (тизим ишга тушгандан) | I3: Охирги 16 кунликда
C4: Аниқланган | D4: Назоратга олинмаган | E4: Назоратга олинган | F4: Назоратга олинган лекин ижроси таъминланмаган | G4: Шундан назоратдан ечиш учун юборилган | H4: Назоратдан ечилган | I4: Аниқланган | J4: Назоратга олинмаган | K4: Назоратга олинган | L4: Шундан назоратдан ечиш учун юборилган | M4: Назоратдан ечилган | O4: Аниқланган | P4: Назоратга олинмаган | Q4: Назоратга олинган | R4: Шундан назоратдан ечиш учун юборилган | S4: Назоратдан ечилган
B5: Жами | C5: =SUM(C6:C11) | D5: =SUM(D6:D11) | E5: =SUM(E6:E11) | F5: =SUM(F6:F11) | G5: =SUM(G6:G11) | H5: =SUM(H6:H11) | I5: =SUM(I6:I11) | J5: =SUM(J6:J11) | ... M5: =SUM(M6:M11)
A6: 1 | B6: ATAXODJAYEV MUZAFFARXON BAXODIRXONOVICH | C6: =+SUMIF(Рўйхат!$E:$E,$B6,Рўйхат!G:G) | D6: =+SUMIF(Рўйхат!$E:$E,$B6,Рўйхат!H:H) | E6: =K6 | F6: =F16+K16+F26+K26 | G6: =+SUMIF(Рўйхат!$E:$E,$B6,Рўйхат!J:J) | H6: =+SUMIF(Рўйхат!$E:$E,$B6,Рўйхат!K:K) | I6: =+SUMIF(Рўйхат!$E:$E,$B6,Рўйхат!L:L) | J6: =+SUMIF(Рўйхат!$E:$E,$B6,Рўйхат!M:M) | K6: =+SUMIF(Рўйхат!$E:$E,$B6,Рўйхат!N:N) | L6: =+SUMIF(Рўйхат!$E:$E,$B6,Рўйхат!O:O) | M6: =+SUMIF(Рўйхат!$E:$E,$B6,Рўйхат!P:P) | O6: =C6-I6-C16-I16-C26-I26 | P6: =D6-J6-D16-J16-D26-J26 | R6: =F6-N6-F16-K16-F26-L26 | S6: =G6-L6-G16-L16-G26-L26
A7: 2 | B7: NOROV AKBAR RUZIMAMATOVICH | C7: =+SUMIF(Рўйхат!$E:$E,$B7,Рўйхат!G:G) | D7: =+SUMIF(Рўйхат!$E:$E,$B7,Рўйхат!H:H) | E7: =K7 | F7: =F17+K17+F27+K27 | G7: =+SUMIF(Рўйхат!$E:$E,$B7,Рўйхат!J:J) | H7: =+SUMIF(Рўйхат!$E:$E,$B7,Рўйхат!K:K) | I7: =+SUMIF(Рўйхат!$E:$E,$B7,Рўйхат!L:L) | J7: =+SUMIF(Рўйхат!$E:$E,$B7,Рўйхат!M:M) | K7: =+SUMIF(Рўйхат!$E:$E,$B7,Рўйхат!N:N) | L7: =+SUMIF(Рўйхат!$E:$E,$B7,Рўйхат!O:O) | M7: =+SUMIF(Рўйхат!$E:$E,$B7,Рўйхат!P:P) | O7: =C7-I7-C17-I17-C27-I27 | P7: =D7-J7-D17-J17-D27-J27 | R7: =F7-N7-F17-K17-F27-L27 | S7: =G7-L7-G17-L17-G27-L27
A8: 3 | B8: KARIMOV ANVAR JONAZOQOVICH | C8: =+SUMIF(Рўйхат!$E:$E,$B8,Рўйхат!G:G) | D8: =+SUMIF(Рўйхат!$E:$E,$B8,Рўйхат!H:H) | E8: =K8 | F8: =F18+K18+F28+K28 | G8: =+SUMIF(Рўйхат!$E:$E,$B8,Рўйхат!J:J) | H8: =+SUMIF(Рўйхат!$E:$E,$B8,Рўйхат!K:K) | I8: =+SUMIF(Рўйхат!$E:$E,$B8,Рўйхат!L:L) | J8: =+SUMIF(Рўйхат!$E:$E,$B8,Рўйхат!M:M) | K8: =+SUMIF(Рўйхат!$E:$E,$B8,Рўйхат!N:N) | L8: =+SUMIF(Рўйхат!$E:$E,$B8,Рўйхат!O:O) | M8: =+SUMIF(Рўйхат!$E:$E,$B8,Рўйхат!P:P) | O8: =C8-I8-C18-I18-C28-I28 | P8: =D8-J8-D18-J18-D28-J28 | R8: =F8-N8-F18-K18-F28-L28 | S8: =G8-L8-G18-L18-G28-L28
A9: 4 | B9: SATTAROV XUDOYBERDI PALVANNAZAR O‘G‘LI | C9: =+SUMIF(Рўйхат!$E:$E,$B9,Рўйхат!G:G) | D9: =+SUMIF(Рўйхат!$E:$E,$B9,Рўйхат!H:H) | E9: =K9 | F9: =F19+K19+F29+K29 | G9: =+SUMIF(Рўйхат!$E:$E,$B9,Рўйхат!J:J) | H9: =+SUMIF(Рўйхат!$E:$E,$B9,Рўйхат!K:K) | I9: =+SUMIF(Рўйхат!$E:$E,$B9,Рўйхат!L:L) | J9: =+SUMIF(Рўйхат!$E:$E,$B9,Рўйхат!M:M) | K9: =+SUMIF(Рўйхат!$E:$E,$B9,Рўйхат!N:N) | L9: =+SUMIF(Рўйхат!$E:$E,$B9,Рўйхат!O:O) | M9: =+SUMIF(Рўйхат!$E:$E,$B9,Рўйхат!P:P) | O9: =C9-I9-C19-I19-C29-I29 | P9: =D9-J9-D19-J19-D29-J29 | R9: =F9-N9-F19-K19-F29-L29 | S9: =G9-L9-G19-L19-G29-L29
A10: 5 | B10: TANGRIYEV UMIDJON UKTAMJONOVICH | C10: =+SUMIF(Рўйхат!$E:$E,$B10,Рўйхат!G:G) | D10: =+SUMIF(Рўйхат!$E:$E,$B10,Рўйхат!H:H) | E10: =K10 | F10: =F20+K20+F30+K30 | G10: =+SUMIF(Рўйхат!$E:$E,$B10,Рўйхат!J:J) | H10: =+SUMIF(Рўйхат!$E:$E,$B10,Рўйхат!K:K) | I10: =+SUMIF(Рўйхат!$E:$E,$B10,Рўйхат!L:L) | J10: =+SUMIF(Рўйхат!$E:$E,$B10,Рўйхат!M:M) | K10: =+SUMIF(Рўйхат!$E:$E,$B10,Рўйхат!N:N) | L10: =+SUMIF(Рўйхат!$E:$E,$B10,Рўйхат!O:O) | M10: =+SUMIF(Рўйхат!$E:$E,$B10,Рўйхат!P:P) | O10: =C10-I10-C20-I20-C30-I30 | P10: =D10-J10-D20-J20-D30-J30 | R10: =F10-N10-F20-K20-F30-L30 | S10: =G10-L10-G20-L20-G30-L30
A11: 6 | B11: QOSIMOV MIRAGZAM XALIL OGLI | C11: =+SUMIF(Рўйхат!$E:$E,$B11,Рўйхат!G:G) | D11: =+SUMIF(Рўйхат!$E:$E,$B11,Рўйхат!H:H) | E11: =K11 | F11: =F21+K21+F31+K31 | G11: =+SUMIF(Рўйхат!$E:$E,$B11,Рўйхат!J:J) | H11: =+SUMIF(Рўйхат!$E:$E,$B11,Рўйхат!K:K) | I11: =+SUMIF(Рўйхат!$E:$E,$B11,Рўйхат!L:L) | J11: =+SUMIF(Рўйхат!$E:$E,$B11,Рўйхат!M:M) | K11: =+SUMIF(Рўйхат!$E:$E,$B11,Рўйхат!N:N) | L11: =+SUMIF(Рўйхат!$E:$E,$B11,Рўйхат!O:O) | M11: =+SUMIF(Рўйхат!$E:$E,$B11,Рўйхат!P:P) | O11: =C11-I11-C21-I21-C31-I31 | P11: =D11-J11-D21-J21-D31-J31 | R11: =F11-N11-F21-K21-F31-L31 | S11: =G11-L11-G21-L21-G31-L31
A13: № | B13: Масъул ходим | C13: Охирги 16 - 30 кунликда | I13: Охирги 1 - 6 ойгача
C14: Аниқланган | D14: Назоратга олинмаган | F14: Назоратга олинган лекин ижроси таъминланмаган | G14: Шундан назоратдан ечиш учун юборилган | H14: Назоратдан ечилган | I14: Аниқланган | J14: Назоратга олинмаган | K14: Назоратга олинган лекин ижроси таъминланмаган | L14: Шундан назоратдан ечиш учун юборилган | M14: Назоратдан ечилган
B15: Жами | C15: =SUM(C16:C21) | D15: =SUM(D16:D21) | F15: =SUM(F16:F21) | G15: =SUM(G16:G21) | H15: =SUM(H16:H21) | I15: =SUM(I16:I21) | J15: =SUM(J16:J21) | K15: =SUM(K16:K21) | L15: =SUM(L16:L21) | M15: =SUM(M16:M21)
A16: 1 | B16: ATAXODJAYEV MUZAFFARXON BAXODIRXONOVICH | C16: =+SUMIF(Рўйхат!$E:$E,$B6,Рўйхат!Q:Q) | D16: =+SUMIF(Рўйхат!$E:$E,$B6,Рўйхат!R:R) | F16: =+SUMIF(Рўйхат!$E:$E,$B6,Рўйхат!S:S) | G16: =+SUMIF(Рўйхат!$E:$E,$B6,Рўйхат!T:T) | H16: =+SUMIF(Рўйхат!$E:$E,$B6,Рўйхат!U:U) | I16: =+SUMIF(Рўйхат!$E:$E,$B6,Рўйхат!V:V) | J16: =+SUMIF(Рўйхат!$E:$E,$B6,Рўйхат!W:W) | K16: =+SUMIF(Рўйхат!$E:$E,$B6,Рўйхат!X:X) | L16: =+SUMIF(Рўйхат!$E:$E,$B6,Рўйхат!Y:Y) | M16: =+SUMIF(Рўйхат!$E:$E,$B6,Рўйхат!Z:Z)
A17: 2 | B17: USMANOV AKMAL YAXYOYEVICH | C17: =+SUMIF(Рўйхат!$E:$E,$B7,Рўйхат!Q:Q) | D17: =+SUMIF(Рўйхат!$E:$E,$B7,Рўйхат!R:R) | F17: =+SUMIF(Рўйхат!$E:$E,$B7,Рўйхат!S:S) | G17: =+SUMIF(Рўйхат!$E:$E,$B7,Рўйхат!T:T) | H17: =+SUMIF(Рўйхат!$E:$E,$B7,Рўйхат!U:U) | I17: =+SUMIF(Рўйхат!$E:$E,$B7,Рўйхат!V:V) | J17: =+SUMIF(Рўйхат!$E:$E,$B7,Рўйхат!W:W) | K17: =+SUMIF(Рўйхат!$E:$E,$B7,Рўйхат!X:X) | L17: =+SUMIF(Рўйхат!$E:$E,$B7,Рўйхат!Y:Y) | M17: =+SUMIF(Рўйхат!$E:$E,$B7,Рўйхат!Z:Z)
A18: 3 | B18: KARIMOV ANVAR JONAZOQOVICH | C18: =+SUMIF(Рўйхат!$E:$E,$B8,Рўйхат!Q:Q) | D18: =+SUMIF(Рўйхат!$E:$E,$B8,Рўйхат!R:R) | F18: =+SUMIF(Рўйхат!$E:$E,$B8,Рўйхат!S:S) | G18: =+SUMIF(Рўйхат!$E:$E,$B8,Рўйхат!T:T) | H18: =+SUMIF(Рўйхат!$E:$E,$B8,Рўйхат!U:U) | I18: =+SUMIF(Рўйхат!$E:$E,$B8,Рўйхат!V:V) | J18: =+SUMIF(Рўйхат!$E:$E,$B8,Рўйхат!W:W) | K18: =+SUMIF(Рўйхат!$E:$E,$B8,Рўйхат!X:X) | L18: =+SUMIF(Рўйхат!$E:$E,$B8,Рўйхат!Y:Y) | M18: =+SUMIF(Рўйхат!$E:$E,$B8,Рўйхат!Z:Z)
A19: 4 | B19: SATTAROV XUDOYBERDI PALVANNAZAR O‘G‘LI | C19: =+SUMIF(Рўйхат!$E:$E,$B9,Рўйхат!Q:Q) | D19: =+SUMIF(Рўйхат!$E:$E,$B9,Рўйхат!R:R) | F19: =+SUMIF(Рўйхат!$E:$E,$B9,Рўйхат!S:S) | G19: =+SUMIF(Рўйхат!$E:$E,$B9,Рўйхат!T:T) | H19: =+SUMIF(Рўйхат!$E:$E,$B9,Рўйхат!U:U) | I19: =+SUMIF(Рўйхат!$E:$E,$B9,Рўйхат!V:V) | J19: =+SUMIF(Рўйхат!$E:$E,$B9,Рўйхат!W:W) | K19: =+SUMIF(Рўйхат!$E:$E,$B9,Рўйхат!X:X) | L19: =+SUMIF(Рўйхат!$E:$E,$B9,Рўйхат!Y:Y) | M19: =+SUMIF(Рўйхат!$E:$E,$B9,Рўйхат!Z:Z)
A20: 5 | B20: TANGRIYEV UMIDJON UKTAMJONOVICH | C20: =+SUMIF(Рўйхат!$E:$E,$B10,Рўйхат!Q:Q) | D20: =+SUMIF(Рўйхат!$E:$E,$B10,Рўйхат!R:R) | F20: =+SUMIF(Рўйхат!$E:$E,$B10,Рўйхат!S:S) | G20: =+SUMIF(Рўйхат!$E:$E,$B10,Рўйхат!T:T) | H20: =+SUMIF(Рўйхат!$E:$E,$B10,Рўйхат!U:U) | I20: =+SUMIF(Рўйхат!$E:$E,$B10,Рўйхат!V:V) | J20: =+SUMIF(Рўйхат!$E:$E,$B10,Рўйхат!W:W) | K20: =+SUMIF(Рўйхат!$E:$E,$B10,Рўйхат!X:X) | L20: =+SUMIF(Рўйхат!$E:$E,$B10,Рўйхат!Y:Y) | M20: =+SUMIF(Рўйхат!$E:$E,$B10,Рўйхат!Z:Z)
A21: 6 | B21: QOSIMOV MIRAGZAM XALIL OGLI | C21: =+SUMIF(Рўйхат!$E:$E,$B11,Рўйхат!Q:Q) | D21: =+SUMIF(Рўйхат!$E:$E,$B11,Рўйхат!R:R) | F21: =+SUMIF(Рўйхат!$E:$E,$B11,Рўйхат!S:S) | G21: =+SUMIF(Рўйхат!$E:$E,$B11,Рўйхат!T:T) | H21: =+SUMIF(Рўйхат!$E:$E,$B11,Рўйхат!U:U) | I21: =+SUMIF(Рўйхат!$E:$E,$B11,Рўйхат!V:V) | J21: =+SUMIF(Рўйхат!$E:$E,$B11,Рўйхат!W:W) | K21: =+SUMIF(Рўйхат!$E:$E,$B11,Рўйхат!X:X) | L21: =+SUMIF(Рўйхат!$E:$E,$B11,Рўйхат!Y:Y) | M21: =+SUMIF(Рўйхат!$E:$E,$B11,Рўйхат!Z:Z)
A23: № | B23: Масъул ходим | C23: Охирги 6 - 12 ойгача | I23: 1 йилдан ортиқ
C24: Аниқланган | D24: Назоратга олинмаган | F24: Назоратга олинган лекин ижроси таъминланмаган | G24: Шундан назоратдан ечиш учун юборилган | H24: Назоратдан ечилган | I24: Аниқланган | J24: Назоратга олинмаган | K24: Назоратга олинган лекин ижроси таъминланмаган | L24: Шундан назоратдан ечиш учун юборилган | M24: Назоратдан ечилган
B25: Жами | C25: =SUM(C26:C31) | D25: =SUM(D26:D31) | F25: =SUM(F26:F31) | G25: =SUM(G26:G31) | H25: =SUM(H26:H31) | I25: =SUM(I26:I31) | J25: =SUM(J26:J31) | K25: =SUM(K26:K31) | L25: =SUM(L26:L31) | M25: =SUM(M26:M31)
A26: 1 | B26: ATAXODJAYEV MUZAFFARXON BAXODIRXONOVICH | C26: =+SUMIF(Рўйхат!$E:$E,$B6,Рўйхат!AA:AA) | D26: =+SUMIF(Рўйхат!$E:$E,$B6,Рўйхат!AB:AB) | F26: =+SUMIF(Рўйхат!$E:$E,$B6,Рўйхат!AC:AC) | G26: =+SUMIF(Рўйхат!$E:$E,$B6,Рўйхат!AD:AD) | H26: =+SUMIF(Рўйхат!$E:$E,$B6,Рўйхат!AE:AE) | I26: =+SUMIF(Рўйхат!$E:$E,$B6,Рўйхат!AF:AF) | J26: =+SUMIF(Рўйхат!$E:$E,$B6,Рўйхат!AG:AG) | K26: =+SUMIF(Рўйхат!$E:$E,$B6,Рўйхат!AH:AH) | L26: =+SUMIF(Рўйхат!$E:$E,$B6,Рўйхат!AI:AI) | M26: =+SUMIF(Рўйхат!$E:$E,$B6,Рўйхат!AJ:AJ)
A27: 2 | B27: USMANOV AKMAL YAXYOYEVICH | C27: =+SUMIF(Рўйхат!$E:$E,$B7,Рўйхат!AA:AA) | D27: =+SUMIF(Рўйхат!$E:$E,$B7,Рўйхат!AB:AB) | F27: =+SUMIF(Рўйхат!$E:$E,$B7,Рўйхат!AC:AC) | G27: =+SUMIF(Рўйхат!$E:$E,$B7,Рўйхат!AD:AD) | H27: =+SUMIF(Рўйхат!$E:$E,$B7,Рўйхат!AE:AE) | I27: =+SUMIF(Рўйхат!$E:$E,$B7,Рўйхат!AF:AF) | J27: =+SUMIF(Рўйхат!$E:$E,$B7,Рўйхат!AG:AG) | K27: =+SUMIF(Рўйхат!$E:$E,$B7,Рўйхат!AH:AH) | L27: =+SUMIF(Рўйхат!$E:$E,$B7,Рўйхат!AI:AI) | M27: =+SUMIF(Рўйхат!$E:$E,$B7,Рўйхат!AJ:AJ)
A28: 3 | B28: KARIMOV ANVAR JONAZOQOVICH | C28: =+SUMIF(Рўйхат!$E:$E,$B8,Рўйхат!AA:AA) | D28: =+SUMIF(Рўйхат!$E:$E,$B8,Рўйхат!AB:AB) | F28: =+SUMIF(Рўйхат!$E:$E,$B8,Рўйхат!AC:AC) | G28: =+SUMIF(Рўйхат!$E:$E,$B8,Рўйхат!AD:AD) | H28: =+SUMIF(Рўйхат!$E:$E,$B8,Рўйхат!AE:AE) | I28: =+SUMIF(Рўйхат!$E:$E,$B8,Рўйхат!AF:AF) | J28: =+SUMIF(Рўйхат!$E:$E,$B8,Рўйхат!AG:AG) | K28: =+SUMIF(Рўйхат!$E:$E,$B8,Рўйхат!AH:AH) | L28: =+SUMIF(Рўйхат!$E:$E,$B8,Рўйхат!AI:AI) | M28: =+SUMIF(Рўйхат!$E:$E,$B8,Рўйхат!AJ:AJ)
A29: 4 | B29: SATTAROV XUDOYBERDI PALVANNAZAR O‘G‘LI | C29: =+SUMIF(Рўйхат!$E:$E,$B9,Рўйхат!AA:AA) | D29: =+SUMIF(Рўйхат!$E:$E,$B9,Рўйхат!AB:AB) | F29: =+SUMIF(Рўйхат!$E:$E,$B9,Рўйхат!AC:AC) | G29: =+SUMIF(Рўйхат!$E:$E,$B9,Рўйхат!AD:AD) | H29: =+SUMIF(Рўйхат!$E:$E,$B9,Рўйхат!AE:AE) | I29: =+SUMIF(Рўйхат!$E:$E,$B9,Рўйхат!AF:AF) | J29: =+SUMIF(Рўйхат!$E:$E,$B9,Рўйхат!AG:AG) | K29: =+SUMIF(Рўйхат!$E:$E,$B9,Рўйхат!AH:AH) | L29: =+SUMIF(Рўйхат!$E:$E,$B9,Рўйхат!AI:AI) | M29: =+SUMIF(Рўйхат!$E:$E,$B9,Рўйхат!AJ:AJ)
A30: 5 | B30: TANGRIYEV UMIDJON UKTAMJONOVICH | C30: =+SUMIF(Рўйхат!$E:$E,$B10,Рўйхат!AA:AA) | D30: =+SUMIF(Рўйхат!$E:$E,$B10,Рўйхат!AB:AB) | F30: =+SUMIF(Рўйхат!$E:$E,$B10,Рўйхат!AC:AC) | G30: =+SUMIF(Рўйхат!$E:$E,$B10,Рўйхат!AD:AD) | H30: =+SUMIF(Рўйхат!$E:$E,$B10,Рўйхат!AE:AE) | I30: =+SUMIF(Рўйхат!$E:$E,$B10,Рўйхат!AF:AF) | J30: =+SUMIF(Рўйхат!$E:$E,$B10,Рўйхат!AG:AG) | K30: =+SUMIF(Рўйхат!$E:$E,$B10,Рўйхат!AH:AH) | L30: =+SUMIF(Рўйхат!$E:$E,$B10,Рўйхат!AI:AI) | M30: =+SUMIF(Рўйхат!$E:$E,$B10,Рўйхат!AJ:AJ)
A31: 6 | B31: QOSIMOV MIRAGZAM XALIL OGLI | C31: =+SUMIF(Рўйхат!$E:$E,$B11,Рўйхат!AA:AA) | D31: =+SUMIF(Рўйхат!$E:$E,$B11,Рўйхат!AB:AB) | F31: =+SUMIF(Рўйхат!$E:$E,$B11,Рўйхат!AC:AC) | G31: =+SUMIF(Рўйхат!$E:$E,$B11,Рўйхат!AD:AD) | H31: =+SUMIF(Рўйхат!$E:$E,$B11,Рўйхат!AE:AE) | I31: =+SUMIF(Рўйхат!$E:$E,$B11,Рўйхат!AF:AF) | J31: =+SUMIF(Рўйхат!$E:$E,$B11,Рўйхат!AG:AG) | K31: =+SUMIF(Рўйхат!$E:$E,$B11,Рўйхат!AH:AH) | L31: =+SUMIF(Рўйхат!$E:$E,$B11,Рўйхат!AI:AI) | M31: =+SUMIF(Рўйхат!$E:$E,$B11,Рўйхат!AJ:AJ)

Sheet Рўйхат
G1: =+SUM(G3:G9999)
A2: risk_name | B2: vaz_code | C2: vaz_name | D2: foydalanuvchi_soni | E2: user_fio | F2: oxitgi_ishlagan | G2: aniqlangan | H2: nazoratga_olinmagan | I2: nazoratga_olingan | J2: nazoratdan_echishga_kelgan | K2: nazoratdan_echilgan | L2: aniqlangan_16 | M2: nazoratga_olinmagan_16 | N2: nazoratga_olingan_16 | O2: nazoratdan_echishga_kelgan_16 | P2: nazoratdan_echilgan_16 | Q2: aniqlangan_10_30 | R2: nazoratga_olinmagan_10_30 | S2: nazoratga_olingan_10_30 | T2: nazoratdan_echishga_kelgan_10_30 | U2: nazoratdan_echilgan_10_30 | V2: aniqlangan_30_180 | W2: nazoratga_olinmagan_30_180 | X2: nazoratga_olingan_30_180 | Y2: nazoratdan_echishga_kelgan_30_180 | Z2: nazoratdan_echilgan_30_180 | AA2: aniqlangan_180_365 | AB2: nazoratga_olinmagan_180_365 | AC2: nazoratga_olingan_180_365 | AD2: nazoratdan_echishga_kelgan_180_365 | AE2: nazoratdan_echilgan_180_365 | AF2: aniqlangan_365 | AG2: nazoratga_olinmagan_365 | AH2: nazoratga_olingan_365 | AI2: nazoratdan_echishga_kelgan_365 | AJ2: nazoratdan_echilgan_365
